Workbook

Sheet Beranda
A1: Link | B1: Fungsi
A2: =HYPERLINK("https://docs.google.com/spreadsheets/d/1ESni1h-9NP1dVdHaEILuc6WWv_P8-mWX3jXPRX9GysM/edit#gid=1979551602","BisaStok") -> BisaStok | B2: Menuliskan pembelian stok dari Kas ITBisa
A3: =HYPERLINK("https://docs.google.com/spreadsheets/d/1ESni1h-9NP1dVdHaEILuc6WWv_P8-mWX3jXPRX9GysM/edit#gid=533652570","BisaPerlengkapan") -> BisaPerlengkapan | B3: Menuliskan perlengkapan yang berhubungan dengan penjualan
A4: =HYPERLINK("https://docs.google.com/spreadsheets/d/1ESni1h-9NP1dVdHaEILuc6WWv_P8-mWX3jXPRX9GysM/edit#gid=1164177046","BisaHitungImpor") -> BisaHitungImpor
A5: =HYPERLINK("https://docs.google.com/spreadsheets/d/1ESni1h-9NP1dVdHaEILuc6WWv_P8-mWX3jXPRX9GysM/edit#gid=90517666","BisaEksporBisaJual") -> BisaEksporBisaJual
A6: =HYPERLINK("https://docs.google.com/spreadsheets/d/1ESni1h-9NP1dVdHaEILuc6WWv_P8-mWX3jXPRX9GysM/edit#gid=171163769","BisaHilang") -> BisaHilang
A7: =HYPERLINK("https://docs.google.com/spreadsheets/d/1ESni1h-9NP1dVdHaEILuc6WWv_P8-mWX3jXPRX9GysM/edit#gid=1152745648","BisaJualBukalapak") -> BisaJualBukalapak | B7: Menuliskan semua transaksi barang dari Bukalapak
A8: =HYPERLINK("https://docs.google.com/spreadsheets/d/1ESni1h-9NP1dVdHaEILuc6WWv_P8-mWX3jXPRX9GysM/edit#gid=1873910816","BisaJualTokopedia") -> BisaJualTokopedia | B8: Menuliskan semua transaksi barang dari Tokopedia
A9: =HYPERLINK("https://docs.google.com/spreadsheets/d/1ESni1h-9NP1dVdHaEILuc6WWv_P8-mWX3jXPRX9GysM/edit#gid=1921632670","BisaJualBliBli") -> BisaJualBliBli
A10: =HYPERLINK("https://docs.google.com/spreadsheets/d/1ESni1h-9NP1dVdHaEILuc6WWv_P8-mWX3jXPRX9GysM/edit#gid=1461742550","BisaJualWeb") -> BisaJualWeb
A11: =HYPERLINK("https://docs.google.com/spreadsheets/d/1ESni1h-9NP1dVdHaEILuc6WWv_P8-mWX3jXPRX9GysM/edit#gid=526519451","BisaJualCOD") -> BisaJualCOD
A12: =HYPERLINK("https://docs.google.com/spreadsheets/d/1ESni1h-9NP1dVdHaEILuc6WWv_P8-mWX3jXPRX9GysM/edit#gid=716139622","BisaSEO") -> BisaSEO

Sheet BisaStok
A1: c | D1: Pengiriman | F1: Pembelian | J1: Data Invoice | R1: USD | X1: Rp | AD1: Penjualan
A2: SKU | B2: Tanggal Bayar | C2: Tanggal Sampai | D2: Alamat Pengiriman | E2: Luar Negeri? | F2: Toko | G2: URL Beli | H2: Keterangan Pembelian | I2: Score (0 - 5) | J2: Banyak Lot | K2: Pcs per Lot | L2: HPP per Lot (USD) | M2: Ongkos Kirim (USD) | N2: Diskon Barang (USD) | O2: Diskon Ongkos Kirim (USD) | P2: Konversi USD ke Rupiah | Q2: {={"Banyak Barang (Buah)";IF(J3:J1026*K3:K1026=0,,J3:J1026*K3:K1026)}} -> Banyak Barang (Buah) | R2: {={"Total Harga Lot (USD)";IF(J3:J1026*L3:L1026=0,,J3:J1026*L3:L1026)}} -> Total Harga Lot (USD) | S2: {={"Ongkos Kirim (USD)";IF(M3:M1026=0,,M3:M1026)}} -> Ongkos Kirim (USD) | T2: {={"Diskon Barang (USD)";IF(N3:N1026=0,,N3:N1026)}} -> Diskon Barang (USD) | U2: {={"Diskon Ongkos Kirim (USD)";IF(O3:O1026=0,,O3:O1026)}} -> Diskon Ongkos Kirim (USD) | V2: {={"Total HPP (USD)";IF(R3:R1026+M3:M1026-N3:N1026-O3:O1026=0,,R3:R1026+M3:M1026-N3:N1026-O3:O1026)}} -> Total HPP (USD) | W2: {={"HPP per Buah (USD)";IF(V3:V1026=0,,V3:V1026/Q3:Q1026)}} -> HPP per Buah (USD) | X2: {={"Total Harga Lot (Rp)";IF(R3:R1026=0,,R3:R1026*P3:P1026)}} -> Total Harga Lot (Rp) | Y2: {={"Ongkos Kirim (Rp)";IF(S3:S1026*$P$3:$P1026=0,,S3:S1026*$P$3:$P1026)}} -> Ongkos Kirim (Rp) | Z2: {={"Diskon Barang (Rp)";IF(T3:T1026*$P$3:$P1026=0,,T3:T1026*$P$3:$P1026)}} -> Diskon Barang (Rp) | AA2: {={"Diskon Ongkos Kirim (Rp)";IF(U3:U1026*$P$3:$P1026=0,,U3:U1026*$P$3:$P1026)}} -> Diskon Ongkos Kirim (Rp) | AB2: {={"Total HPP (Rp)";IF(V3:V1026*$P$3:$P1026=0,,V3:V1026*$P$3:$P1026)}} -> Total HPP (Rp) | AC2: {={"HPP per Buah (Rp)";IF(AB3:AB1026=0,,AB3:AB1026/Q3:Q1026)}} -> HPP per Buah (Rp) | AD2: Harga Online/ Dropshipper (Rp) | AE2: Harga Offline (Rp) | AF2: Lain-Lain
A4: ITBISA-7SEGMENT-ANODE-RED-0.56-1BIT | B4: 45957.562 | C4: 46003.61 | D4: KYAI KONTONG | E4: TRUE | F4: Ocistok/Martkita | G4: https://detail.1688.com/offer/554814591930.html | H4: Ocistok / Martkita 302177 (0.23 RMB) | I4: 5 | J4: 7500 | K4: 1 | L4: =(672)/P4 -> 672 | M4: =(5076186 - 5040000)/P4 -> 36186 | N4: 0 | O4: =(27000/4)/P4 -> 6750 | P4: 1 | Q4: 7500 | R4: 5040000 | S4: 36186 | U4: 6750 | V4: 5069436 | W4: 675.9248 | X4: 5040000 | Y4: 36186 | AA4: 6750 | AB4: 5069436 | AC4: 675.9248
A5: ITBISA-7SEGMENT-ANODE-RED-0.56-1BIT | B5: 45858.145 | C5: 45862.567 | D5: KERTASARI CIAMIS | E5: FALSE | F5: Tokopedia | G5: Aisyah Arduino Bandung | H5: Tokopedia Anggi 2523 | I5: 5 | J5: 95 | K5: 1 | L5: =(1300)/P5 -> 0.079268293 | M5: =(1000)/P5 -> 0.06097561 | N5: =(9880 + 3137)/P5 -> 0.79371951 | O5: 0 | P5: 16400 | Q5: 95 | R5: 7.5304878 | S5: 0.06097561 | T5: 0.79371951 | V5: 6.7977439 | W5: 0.071555199 | X5: 123500 | Y5: 1000 | Z5: 13017 | AB5: 111483 | AC5: 1173.5053
A6: ITBISA-7SEGMENT-ANODE-RED-0.56-1BIT | B6: 45858.142 | C6: 45862.406 | D6: KERTASARI CIAMIS | E6: FALSE | F6: Tokopedia | G6: Aisyah Arduino Bandung | H6: Tokopedia Anggi 4347 | I6: 5 | J6: 210 | K6: 1 | L6: =(1300)/P6 -> 0.079268293 | M6: =(1000)/P6 -> 0.06097561 | N6: =(13650 + 12968)/P6 -> 1.6230488 | O6: 0 | P6: 16400 | Q6: 210 | R6: 16.646341 | S6: 0.06097561 | T6: 1.6230488 | V6: 15.084268 | W6: 0.071829849 | X6: 273000 | Y6: 1000 | Z6: 26618 | AB6: 247382 | AC6: 1178.0095
A7: ITBISA-7SEGMENT-ANODE-RED-0.56-1BIT | B7: 45374.679 | C7: 45472.771 | D7: KYAI KONTONG | E7: TRUE | F7: Ocistok/Martkita | G7: https://detail.1688.com/offer/666573965265.html | H7: Ocistok 187962 (0.24 RMB) | I7: 5 | J7: 5000 | K7: 1 | L7: =(684)/P7 -> 0.043776 | M7: 0 | N7: 0 | O7: 0 | P7: 15625 | Q7: 5000 | R7: 218.88 | V7: 218.88 | W7: 0.043776 | X7: 3420000 | AB7: 3420000 | AC7: 684
A8: ITBISA-7SEGMENT-ANODE-RED-0.56-1BIT | B8: 45371.749 | C8: 45376.653 | D8: KERTASARI CIAMIS | E8: FALSE | F8: Tokopedia | G8: Tokopedia Joko | H8: Tokopedia Joko | I8: 5 | J8: 260 | K8: 1 | L8: =(1250)/P8 -> 0.079390283 | M8: =(1000)/P8 -> 0.063512226 | N8: =(3250)/P8 -> 0.20641473 | O8: 0 | P8: 15745 | Q8: 260 | R8: 20.641473 | S8: 0.063512226 | T8: 0.20641473 | V8: 20.498571 | W8: 0.078840658 | X8: 325000 | Y8: 1000 | Z8: 3250 | AB8: 322750 | AC8: 1241.3462
A9: ITBISA-7SEGMENT-ANODE-RED-0.56-1BIT | B9: 45371.747 | C9: 45376.653 | D9: KERTASARI CIAMIS | E9: FALSE | F9: Tokopedia | G9: Tokopedia Joko | H9: Tokopedia Joko | I9: 5 | J9: 260 | K9: 1 | L9: =(1250)/P9 -> 0.079390283 | M9: =(1000)/P9 -> 0.063512226 | N9: =(5000)/P9 -> 0.31756113 | O9: 0 | P9: 15745 | Q9: 260 | R9: 20.641473 | S9: 0.063512226 | T9: 0.31756113 | V9: 20.387425 | W9: 0.078413171 | X9: 325000 | Y9: 1000 | Z9: 5000 | AB9: 321000 | AC9: 1234.6154
A10: ITBISA-7SEGMENT-ANODE-RED-0.56-1BIT | B10: 45371.745 | C10: 45376.653 | D10: KERTASARI CIAMIS | E10: FALSE | F10: Tokopedia | G10: Tokopedia Joko | H10: Tokopedia Joko | I10: 5 | J10: 260 | K10: 1 | L10: =(1250)/P10 -> 0.079390283 | M10: =(1000)/P10 -> 0.063512226 | N10: =(3250 + 5000)/P10 -> 0.52397587 | O10: 0 | P10: 15745 | Q10: 260 | R10: 20.641473 | S10: 0.063512226 | T10: 0.52397587 | V10: 20.18101 | W10: 0.077619269 | X10: 325000 | Y10: 1000 | Z10: 8250 | AB10: 317750 | AC10: 1222.1154
A11: ITBISA-7SEGMENT-ANODE-RED-0.56-1BIT | B11: 45371.744 | C11: 45376.653 | D11: KERTASARI CIAMIS | E11: FALSE | F11: Tokopedia | G11: Tokopedia Joko | H11: Tokopedia Joko | I11: 5 | J11: 260 | K11: 1 | L11: =(1250)/P11 -> 0.079390283 | M11: =(1000)/P11 -> 0.063512226 | N11: =(5000 + 12633)/P11 -> 1.1199111 | O11: 0 | P11: 15745 | Q11: 260 | R11: 20.641473 | S11: 0.063512226 | T11: 1.1199111 | V11: 19.585075 | W11: 0.07532721 | X11: 325000 | Y11: 1000 | Z11: 17633 | AB11: 308367 | AC11: 1186.0269
A12: ITBISA-7SEGMENT-ANODE-RED-0.56-1BIT | B12: 45367.612 | C12: 45371.365 | D12: KERTASARI CIAMIS | E12: FALSE | F12: Tokopedia | G12: Tokopedia Joko | H12: Tokopedia Joko | I12: 5 | J12: 260 | K12: 1 | L12: =(1240)/P12 -> 0.079283887 | M12: =(1000)/P12 -> 0.063938619 | N12: =(1612 + 12896)/P12 -> 0.92762148 | O12: 0 | P12: 15640 | Q12: 260 | R12: 20.613811 | S12: 0.063938619 | T12: 0.92762148 | V12: 19.750128 | W12: 0.07596203 | X12: 322400 | Y12: 1000 | Z12: 14508 | AB12: 308892 | AC12: 1188.0462
A13: ITBISA-7SEGMENT-ANODE-RED-0.56-1BIT | B13: 45348.692 | C13: 45350.482 | D13: KERTASARI CIAMIS | E13: FALSE | F13: Tokopedia | G13: Tokopedia Joko | H13: Tokopedia Joko | I13: 5 | J13: 450 | K13: 1 | L13: =(1240)/P13 -> 0.079299098 | M13: =(1000)/P13 -> 0.063950886 | N13: =(5580)/P13 -> 0.35684594 | O13: 0 | P13: 15637 | Q13: 450 | R13: 35.684594 | S13: 0.063950886 | T13: 0.35684594 | V13: 35.391699 | W13: 0.07864822 | X13: 558000 | Y13: 1000 | Z13: 5580 | AB13: 553420 | AC13: 1229.8222
A14: ITBISA-7SEGMENT-ANODE-RED-0.56-1BIT | B14: 45334.477 | C14: 45413.611 | D14: KYAI KONTONG | E14: TRUE | F14: Ocistok/Martkita | G14: Ocistok | I14: 5 | J14: 3000 | K14: 1 | L14: =(657)/P14 -> 0.041764668 | M14: 0 | N14: 0 | O14: 0 | P14: 15731 | Q14: 3000 | R14: 125.29401 | V14: 125.29401 | W14: 0.041764668 | X14: 1971000 | AB14: 1971000 | AC14: 657
A15: ITBISA-7SEGMENT-ANODE-RED-0.56-1BIT | B15: 45013 | C15: 45061 | D15: KYAI KONTONG | E15: TRUE | F15: Jasa Impor Tiongkok | G15: Jasa Impor Tiongkok | I15: 5 | J15: 10050 | K15: 1 | L15: =731/P15 -> 0.048519846 | M15: 0 | N15: 0 | O15: 0 | P15: 15066 | Q15: 10050 | R15: 487.62445 | V15: 487.62445 | W15: 0.048519846 | X15: 7346550 | AB15: 7346550 | AC15: 731
A16: ITBISA-7SEGMENT-ANODE-RED-0.56-1BIT | B16: 44990.805 | C16: 45361.511 | D16: KERTASARI CIAMIS | E16: FALSE | F16: Tokopedia | G16: Tokopedia Joko | H16: Tokopedia Joko | I16: 5 | J16: 260 | K16: 1 | L16: =(1240)/P16 -> 0.078730159 | M16: =(1000)/P16 -> 0.063492063 | N16: =(3224 + 1612)/P16 -> 0.30704762 | O16: 0 | P16: 15750 | Q16: 260 | R16: 20.469841 | S16: 0.063492063 | T16: 0.30704762 | V16: 20.226286 | W16: 0.077793407 | X16: 322400 | Y16: 1000 | Z16: 4836 | AB16: 318564 | AC16: 1225.2462
A17: ITBISA-7SEGMENT-ANODE-RED-0.56-1BIT | B17: 44990.802 | C17: 45361.511 | D17: KERTASARI CIAMIS | E17: FALSE | F17: Tokopedia | G17: Tokopedia Joko | H17: Tokopedia Joko | I17: 5 | J17: 260 | K17: 1 | L17: =(1240)/P17 -> 0.078730159 | M17: =(1000)/P17 -> 0.063492063 | N17: =(3224 + 5000 + 1595)/P17 -> 0.62342857 | O17: 0 | P17: 15750 | Q17: 260 | R17: 20.469841 | S17: 0.063492063 | T17: 0.62342857 | V17: 19.909905 | W17: 0.076576557 | X17: 322400 | Y17: 1000 | Z17: 9819 | AB17: 313581 | AC17: 1206.0808
A18: ITBISA-7SEGMENT-ANODE-RED-0.56-1BIT | B18: 44839 | C18: 44889 | D18: KYAI KONTONG | E18: TRUE | F18: Jasa Impor Tiongkok | G18: Jasa Impor Tiongkok | H18: Tokopedia Furqonajiy | I18: 5 | J18: 37 | K18: 150 | L18: =(1731600+6926400)/2/37/P18 -> 7.8 | M18: =1000/P18 -> 0.066666667 | N18: =(51948+500000-112525-1000)/2/P18 -> 14.6141 | O18: 0 | P18: 15000 | Q18: 5550 | R18: 288.6 | S18: 0.066666667 | T18: 14.6141 | V18: 274.05257 | W18: 0.049378841 | X18: 4329000 | Y18: 1000 | Z18: 219211.5 | AB18: 4110788.5 | AC18: 740.68261
A19: ITBISA-7SEGMENT-ANODE-RED-0.56-1BIT | B19: 44008 | C19: 44022 | D19: KAETOBO RESIDENCE | E19: TRUE | F19: Shopee | G19: https://shopee.co.id/product/36506495/7612131078 | H19: Shopee Furqonajiy 200626RH03BEN5 | I19: 4 | J19: 20 | K19: 10 | L19: =13908/P19 -> 1.3908 | M19: =12000/P19 -> 1.2 | O19: =M19 -> 1.2 | P19: 10000 | Q19: 200 | R19: 27.816 | S19: 1.2 | U19: 1.2 | V19: 27.816 | W19: 0.13908 | X19: 278160 | Y19: 12000 | AA19: 12000 | AB19: 278160 | AC19: 1390.8
A20: ITBISA-7SEGMENT-ANODE-RED-0.56-1BIT | B20: 44008 | C20: 44020 | D20: KAETOBO RESIDENCE | E20: TRUE | F20: Shopee | G20: https://shopee.co.id/product/240782907/4328806797 | H20: Shopee Furqonajiy 200626RHJJNQ1R | I20: 5 | J20: 50 | K20: 10 | L20: =13997/P20 -> 1.3997 | M20: =12000/P20 -> 1.2 | P20: 10000 | Q20: 500 | R20: 69.985 | S20: 1.2 | V20: 71.185 | W20: 0.14237 | X20: 699850 | Y20: 12000 | AB20: 711850 | AC20: 1423.7
A21: ITBISA-7SEGMENT-ANODE-RED-0.56-1BIT | B21: 43971 | C21: 43980 | D21: KAETOBO RESIDENCE | E21: TRUE | F21: Shopee | G21: https://shopee.co.id/product/240782907/4328806797?smtt=0.0.9 | H21: Shopee Furqonajiy 200428N62SUQV8 | I21: 5 | J21: 50 | K21: 10 | L21: =13997/P21 -> 1.3997 | M21: =12000/P21 -> 1.2 | P21: 10000 | Q21: 500 | R21: 69.985 | S21: 1.2 | V21: 71.185 | W21: 0.14237 | X21: 699850 | Y21: 12000 | AB21: 711850 | AC21: 1423.7
A22: ITBISA-7SEGMENT-ANODE-RED-0.56-1BIT | B22: 43887 | C22: 43987 | D22: RUMAH MUZAKKI | E22: TRUE | F22: AliExpress | G22: https://www.Aliexpress.com/item/32262476520.html?spm | H22: Aliexpress Furqonajiy 8011001562654116 | J22: 15 | K22: 50 | L22: 4.21 | P22: =899572/(4.21*15) -> 14245.004 | Q22: 750 | R22: 63.15 | V22: 63.15 | W22: 0.0842 | X22: 899572 | AB22: 899572 | AC22: 1199.4293
A23: ITBISA-7SEGMENT-ANODE-RED-0.56-1BIT | B23: 43798 | C23: 43829 | D23: RUMAH MUZAKKI | E23: TRUE | F23: AliExpress | G23: https://www.Aliexpress.com/item/50pcs-1bit-1-bit-Common-Anode-Positive-Digital-Tube-0-56-0-56in-Red-LED-Digit/32262476520.html?spm=a2g0s.9042311.0.0.334d4c4d1XLiYh | H23: Aliexpress Furqonajiy 8007001849904116 | J23: 12 | K23: 50 | L23: 4.21 | N23: 5 | P23: =1309247/(91.04) -> 14381.008 | Q23: 600 | R23: 50.52 | T23: 5 | V23: 45.52 | W23: 0.075866667 | X23: 726528.54 | Z23: 71905.042 | AB23: 654623.5 | AC23: 1091.0392
A24: ITBISA-7SEGMENT-ANODE-RED-0.56-1BIT | B24: 43782 | C24: 43810 | D24: RUMAH MUZAKKI | E24: TRUE | F24: AliExpress | G24: https://www.Aliexpress.com/item/50pcs-1bit-1-bit-Common-Anode-Positive-Digital-Tube-0-56-0-56in-Red-LED-Digit/32262476520.html?spm=a2g0s.9042311.0.0.334d4c4d1XLiYh | H24: Aliexpress Furqonajiy 8006178019124116 8006223027484116 | J24: 10 | K24: 50 | L24: 4.16 | M24: =10000/P24 -> 0.69734996 | N24: 1 | P24: =(1014125+269592)/(12*4.16+10*4.16-2) -> 14340.002 | Q24: 500 | R24: 41.6 | S24: 0.69734996 | T24: 1 | V24: 41.29735 | W24: 0.0825947 | X24: 596544.09 | Y24: 10000 | Z24: 14340.002 | AB24: 592204.09 | AC24: 1184.4082
A25: ITBISA-7SEGMENT-ANODE-RED-0.56-1BIT | B25: 43719 | C25: 43749.797 | D25: RUMAH MUZAKKI | E25: TRUE | F25: AliExpress | G25: ="https://www.aliexpress.com/item/20pcs-bag-Red-bright-LED-red-0-5-0-56-inches-a-common-cathode-shell-12/32262476520.html?spm=2114.search0104.3.136.695b58f9P8tLRf&ws_ab_test=searchweb0_0,searchweb201602_5_10065_10068_5734615_319_317_10696_453_10084_10924_45"&"4_10083_10618_10920_10921_10307_10922_537_536_10059_10884_10887_100031_321_322_10103_5734515,searchweb201603_1,ppcSwitch_0&algo_expid=ec02fe65-0b12-4543-bfac-829a7f0163f6-20&algo_pvid=ec02fe65-0b12-4543-bfac-829a7f0163f6" -> https://www.aliexpress.com/item/20pcs-bag-Red-bright-LED-red-0-5-0-56-inches-a-common-cathode-shell-12/32262476520.html?spm=2114.search0104.3.136.695b58f9P8tLRf&ws_ab_test=searchweb0_0,searchweb201602_5_10065_10068_5734615_319_317_10696_453_10084_10924_454_10083_10618_10920_10921_10307_10922_537_536_10059_10884_10887_100031_321_322_10103_5734515,searchweb201603_1,ppcSwitch_0&algo_expid=ec02fe65-0b12-4543-bfac-829a7f0163f6-20&algo_pvid=ec02fe65-0b12-4543-bfac-829a7f0163f6 | H25: Aliexpress Furqonajiy 8001779903204116 Resi EX211568265SG | J25: 12 | K25: 50 | L25: 4.35 | M25: =(20000/P25)/2+10000/P25 -> 1.3943108 | P25: =748757/(4.35*12) -> 14344.004 | Q25: 600 | R25: 52.2 | S25: 1.3943108 | V25: 53.594311 | W25: 0.089323851 | X25: 748757 | Y25: 20000 | AB25: 768757 | AC25: 1281.2617 | AE25: 1500
A26: ITBISA-7SEGMENT-ANODE-RED-0.56-1BIT | B26: 43617.966 | C26: 43639.949 | D26: RUMAH MUZAKKI | E26: TRUE | F26: AliExpress | G26: https://www.Aliexpress.com/item/50pcs-1bit-1-bit-Common-Anode-Positive-Digital-Tube-0-56-0-56in-Red-LED-Digit/32262476520.html?spm=a2g0s.9042311.0.0.3da24c4dThHZe2 | H26: Aliexpress Furqonajiy 102437170834116 Resi RP598310436CN | J26: 12 | K26: 50 | L26: 4.12 | P26: =732477/49.92 -> 14673.017 | Q26: 600 | R26: 49.44 | V26: 49.44 | W26: 0.0824 | X26: 725433.95 | AB26: 725433.95 | AC26: 1209.0566 | AD26: 1500 | AE26: 1500
A27: ITBISA-7SEGMENT-ANODE-RED-0.56-1BIT | B27: 43581 | C27: =B27 -> 43581 | D27: AVRG ITB | E27: FALSE | F27: URO Shop | G27: URO Shop | H27: URO Shop | J27: 100 | K27: 1 | L27: =1300/P27 -> 0.13 | P27: 10000 | Q27: 100 | R27: 13 | V27: 13 | W27: 0.13 | X27: 130000 | AB27: 130000 | AC27: 1300 | AE27: 1500
A28: ITBISA-7SEGMENT-ANODE-RED-0.56-1BIT | B28: 43572 | C28: 43596 | D28: RUMAH SYAFIRA | E28: TRUE | F28: AliExpress | G28: ="https://www.aliexpress.com/item/20pcs-bag-Red-bright-LED-red-0-5-0-56-inches-a-common-cathode-shell-12/32262476520.html?spm=a2g0s.12269583.0.0.109b57f2T8L4qD" -> https://www.aliexpress.com/item/20pcs-bag-Red-bright-LED-red-0-5-0-56-inches-a-common-cathode-shell-12/32262476520.html?spm=a2g0s.12269583.0.0.109b57f2T8L4qD | H28: Aliexpress Furqonajiy 100739640614116 Resi RP540582475CN | J28: 10 | K28: 50 | L28: 4.3 | M28: 0 | N28: 0 | O28: 0 | P28: =616921/(4.3*10) -> 14347 | Q28: 500 | R28: 43 | V28: 43 | W28: 0.086 | X28: 616921 | AB28: 616921 | AC28: 1233.842 | AD28: 1400 | AE28: 1500
A29: ITBISA-7SEGMENT-ANODE-RED-0.56-1BIT | B29: 43570.434 | C29: =B29 -> 43570.434 | D29: AVRG ITB | E29: FALSE | F29: URO Shop | G29: URO Shop | H29: URO Shop | J29: 160 | K29: 1 | L29: =1300/P29 -> 0.13 | M29: 0 | N29: 0 | O29: 0 | P29: 10000 | Q29: 160 | R29: 20.8 | V29: 20.8 | W29: 0.13 | X29: 208000 | AB29: 208000 | AC29: 1300 | AD29: 1400 | AE29: 1500
A30: ITBISA-7SEGMENT-ANODE-RED-0.56-1BIT | B30: 43536.484 | C30: =B30 -> 43536.484 | D30: AVRG ITB | E30: FALSE | F30: URO Shop | G30: URO Shop | H30: URO Shop | J30: 90 | K30: 1 | L30: =1300/P30 -> 0.13 | M30: 0 | P30: 10000 | Q30: 90 | R30: 11.7 | V30: 11.7 | W30: 0.13 | X30: 117000 | AB30: 117000 | AC30: 1300 | AD30: 1400 | AE30: 1500
A31: ITBISA-7SEGMENT-ANODE-RED-0.56-1BIT | B31: 43535.646 | C31: =B31 -> 43535.646 | D31: AVRG ITB | E31: FALSE | F31: URO Shop | G31: URO Shop | H31: URO Shop | J31: 25 | K31: 1 | L31: =1300/P31 -> 0.13 | M31: 0 | P31: 10000 | Q31: 25 | R31: 3.25 | V31: 3.25 | W31: 0.13 | X31: 32500 | AB31: 32500 | AC31: 1300 | AD31: 1400 | AE31: 1500
A32: ITBISA-7SEGMENT-ANODE-RED-0.56-1BIT | B32: 43530.663 | C32: 43550 | D32: RUMAH SYAFIRA | E32: TRUE | F32: AliExpress | G32: ="https://www.aliexpress.com/item/20pcs-bag-Red-bright-LED-red-0-5-0-56-inches-a-common-cathode-shell-12/32262476520.html?spm=2114.search0104.3.136.695b58f9P8tLRf&ws_ab_test=searchweb0_0,searchweb201602_5_10065_10068_5734615_319_317_10696_453_10084_10924_45"&"4_10083_10618_10920_10921_10307_10922_537_536_10059_10884_10887_100031_321_322_10103_5734515,searchweb201603_1,ppcSwitch_0&algo_expid=ec02fe65-0b12-4543-bfac-829a7f0163f6-20&algo_pvid=ec02fe65-0b12-4543-bfac-829a7f0163f6" -> https://www.aliexpress.com/item/20pcs-bag-Red-bright-LED-red-0-5-0-56-inches-a-common-cathode-shell-12/32262476520.html?spm=2114.search0104.3.136.695b58f9P8tLRf&ws_ab_test=searchweb0_0,searchweb201602_5_10065_10068_5734615_319_317_10696_453_10084_10924_454_10083_10618_10920_10921_10307_10922_537_536_10059_10884_10887_100031_321_322_10103_5734515,searchweb201603_1,ppcSwitch_0&algo_expid=ec02fe65-0b12-4543-bfac-829a7f0163f6-20&algo_pvid=ec02fe65-0b12-4543-bfac-829a7f0163f6 | H32: Aliexpress Furqonajiy 99320493804116 Resi RX470050702CN | J32: 8 | K32: 50 | L32: 4.3 | M32: 0 | N32: 0 | O32: 0 | P32: =991477/(8*4.3 + 8*4.3) -> 14411.003 | Q32: 400 | R32: 34.4 | V32: 34.4 | W32: 0.086 | X32: 495738.5 | AB32: 495738.5 | AC32: 1239.3463 | AD32: 1400 | AE32: 1500
A33: ITBISA-7SEGMENT-ANODE-RED-0.56-1BIT | B33: 43428 | C33: 43432 | D33: RUMAH SYAFIRA | E33: TRUE | F33: AliExpress | G33: ="https://www.aliexpress.com/item/20pcs-bag-Red-bright-LED-red-0-5-0-56-inches-a-common-cathode-shell-12/32262476520.html?spm=2114.search0104.3.136.695b58f9P8tLRf&ws_ab_test=searchweb0_0,searchweb201602_5_10065_10068_5734615_319_317_10696_453_10084_10924_45"&"4_10083_10618_10920_10921_10307_10922_537_536_10059_10884_10887_100031_321_322_10103_5734515,searchweb201603_1,ppcSwitch_0&algo_expid=ec02fe65-0b12-4543-bfac-829a7f0163f6-20&algo_pvid=ec02fe65-0b12-4543-bfac-829a7f0163f6" -> https://www.aliexpress.com/item/20pcs-bag-Red-bright-LED-red-0-5-0-56-inches-a-common-cathode-shell-12/32262476520.html?spm=2114.search0104.3.136.695b58f9P8tLRf&ws_ab_test=searchweb0_0,searchweb201602_5_10065_10068_5734615_319_317_10696_453_10084_10924_454_10083_10618_10920_10921_10307_10922_537_536_10059_10884_10887_100031_321_322_10103_5734515,searchweb201603_1,ppcSwitch_0&algo_expid=ec02fe65-0b12-4543-bfac-829a7f0163f6-20&algo_pvid=ec02fe65-0b12-4543-bfac-829a7f0163f6 | H33: Aliexpress Syafirapr 96593938411876 Resi UN582235825CN | J33: 2 | K33: 50 | L33: 4.25 | N33: 4 | O33: 0 | P33: =66794/(4.25*2 - 4) -> 14843.111 | Q33: 100 | R33: 8.5 | T33: 4 | V33: 4.5 | W33: 0.045 | X33: 126166.44 | Z33: 59372.444 | AB33: 66794 | AC33: 667.94 | AD33: 1300 | AE33: 1500
A34: ITBISA-7SEGMENT-ANODE-RED-0.56-1BIT | B34: 43428 | C34: 43446 | D34: RUMAH SYAFIRA | E34: TRUE | F34: AliExpress | G34: ="https://www.aliexpress.com/item/20pcs-bag-Red-bright-LED-red-0-5-0-56-inches-a-common-cathode-shell-12/32262476520.html?spm=2114.search0104.3.136.695b58f9P8tLRf&ws_ab_test=searchweb0_0,searchweb201602_5_10065_10068_5734615_319_317_10696_453_10084_10924_45"&"4_10083_10618_10920_10921_10307_10922_537_536_10059_10884_10887_100031_321_322_10103_5734515,searchweb201603_1,ppcSwitch_0&algo_expid=ec02fe65-0b12-4543-bfac-829a7f0163f6-20&algo_pvid=ec02fe65-0b12-4543-bfac-829a7f0163f6" -> https://www.aliexpress.com/item/20pcs-bag-Red-bright-LED-red-0-5-0-56-inches-a-common-cathode-shell-12/32262476520.html?spm=2114.search0104.3.136.695b58f9P8tLRf&ws_ab_test=searchweb0_0,searchweb201602_5_10065_10068_5734615_319_317_10696_453_10084_10924_454_10083_10618_10920_10921_10307_10922_537_536_10059_10884_10887_100031_321_322_10103_5734515,searchweb201603_1,ppcSwitch_0&algo_expid=ec02fe65-0b12-4543-bfac-829a7f0163f6-20&algo_pvid=ec02fe65-0b12-4543-bfac-829a7f0163f6 | H34: Aliexpress Syafirapr 96811194361876 Resi RY427709390CN | J34: 2 | K34: 50 | L34: 4.25 | N34: =2.05/2 -> 1.025 | O34: 0 | P34: =693911/(30.5*1 + (4.25*3 + 4.25*2) - 5) -> 14843.016 | Q34: 100 | R34: 8.5 | T34: 1.025 | V34: 7.475 | W34: 0.07475 | X34: 126165.64 | Z34: 15214.091 | AB34: 110951.54 | AC34: 1109.5154 | AD34: 1300 | AE34: 1500
A35: ITBISA-7SEGMENT-ANODE-RED-1.00-1BIT | B35: 45374.679 | C35: 45477.917 | D35: KYAI KONTONG | E35: TRUE | F35: Ocistok/Martkita | G35: https://detail.1688.com/offer/678795685587.html | H35: Ocistok 187963 (0.85 RMB) | I35: 5 | J35: 3000 | K35: 1 | L35: =(2000)/P35 -> 0.128 | M35: 0 | N35: 0 | O35: 0 | P35: 15625 | Q35: 3000 | R35: 384 | V35: 384 | W35: 0.128 | X35: 6000000 | AB35: 6000000 | AC35: 2000
A36: ITBISA-7SEGMENT-ANODE-RED-1.00-1BIT | B36: 45202.354 | C36: 45232.639 | D36: KYAI KONTONG | E36: TRUE | F36: Jasa Impor Tiongkok | H36: Jasa Impor Tiongkok | I36: 5 | J36: 1000 | K36: 1 | L36: =2049/P36 -> 0.13122838 | M36: 0 | N36: 0 | O36: 0 | P36: 15614 | Q36: 1000 | R36: 131.22838 | V36: 131.22838 | W36: 0.13122838 | X36: 2049000 | AB36: 2049000 | AC36: 2049
A37: ITBISA-7SEGMENT-ANODE-RED-1.20-1BIT | B37: 45863.007 | C37: 45865.733 | D37: KERTASARI CIAMIS | E37: FALSE | F37: Shopee | G37: Shiryu Store | H37: Shopee Aji 5XV6 | I37: 5 | J37: 1 | K37: 750 | L37: =(3060000)/P37 -> 187.73006 | M37: =(25000 + 1000)/P37 -> 1.595092 | N37: =(X37*12%)/P37 -> 22.527607 | O37: =(10000)/P37 -> 0.61349693 | P37: 16300 | Q37: 750 | R37: 187.73006 | S37: 1.595092 | T37: 22.527607 | U37: 0.61349693 | V37: 166.18405 | W37: 0.22157873 | X37: 3060000 | Y37: 26000 | Z37: 367200 | AA37: 10000 | AB37: 2708800 | AC37: 3611.7333
A38: ITBISA-7SEGMENT-ANODE-RED-1.20-1BIT | B38: 45772.02 | C38: 45775.468 | D38: KERTASARI CIAMIS | E38: FALSE | F38: Shopee | G38: Shiryu Store | H38: Shopee Anggi AVDN | I38: 5 | J38: 1 | K38: 750 | L38: =(3060000)/P38 -> 182.2622 | M38: =(27904 + 736)/P38 -> 1.7058788 | N38: =(X38*12%)/P38 -> 21.871463 | O38: =(20000)/P38 -> 1.1912562 | P38: 16789 | Q38: 750 | R38: 182.2622 | S38: 1.7058788 | T38: 21.871463 | U38: 1.1912562 | V38: 160.90535 | W38: 0.21454047 | X38: 3060000 | Y38: 28640 | Z38: 367200 | AA38: 20000 | AB38: 2701440 | AC38: 3601.92
A39: ITBISA-7SEGMENT-ANODE-RED-1.20-1BIT | B39: 45690.176 | C39: 45694.254 | D39: KERTASARI CIAMIS | E39: FALSE | F39: Shopee | G39: Shiryu Store | H39: Shopee Anggi DWXE | I39: 5 | J39: 1 | K39: 750 | L39: =(3060000)/P39 -> 187.73006 | M39: =(736)/P39 -> 0.045153374 | N39: =(X39*12%)/P39 -> 22.527607 | O39: 0 | P39: 16300 | Q39: 750 | R39: 187.73006 | S39: 0.045153374 | T39: 22.527607 | V39: 165.24761 | W39: 0.22033014 | X39: 3060000 | Y39: 736 | Z39: 367200 | AB39: 2693536 | AC39: 3591.3813
A40: ITBISA-7SEGMENT-ANODE-RED-1.20-1BIT | B40: 45607.757 | C40: 45611.458 | D40: KYAI KONTONG | E40: FALSE | F40: Shopee | G40: Shiryu Store | H40: Shopee Aji JNM6 | I40: 5 | J40: 1 | K40: 1700 | L40: =(6936000)/P40 -> 439.96194 | M40: =(834)/P40 -> 0.052901998 | N40: =(832320)/P40 -> 52.795433 | O40: 0 | P40: 15765 | Q40: 1700 | R40: 439.96194 | S40: 0.052901998 | T40: 52.795433 | V40: 387.21941 | W40: 0.22777612 | X40: 6936000 | Y40: 834 | Z40: 832320 | AB40: 6104514 | AC40: 3590.8906
A41: ITBISA-7SEGMENT-ANODE-RED-1.20-1BIT | B41: 45605.176 | C41: 45607.572 | D41: KYAI KONTONG | E41: FALSE | F41: Shopee | G41: Shiryu Store | H41: Shopee Aji HRK6 | I41: 5 | J41: 1 | K41: 750 | L41: =(3060000)/P41 -> 195.32746 | M41: =(694)/P41 -> 0.044299757 | N41: =(244800)/P41 -> 15.626197 | O41: 0 | P41: 15666 | Q41: 750 | R41: 195.32746 | S41: 0.044299757 | T41: 15.626197 | V41: 179.74556 | W41: 0.23966075 | X41: 3060000 | Y41: 694 | Z41: 244800 | AB41: 2815894 | AC41: 3754.5253
A42: ITBISA-7SEGMENT-ANODE-RED-1.20-1BIT | B42: 45590.007 | C42: 45593.469 | D42: KERTASARI CIAMIS | E42: FALSE | F42: Shopee | G42: Shiryu Store | H42: Shopee Aji 2MM5 | I42: 5 | J42: 1 | K42: 800 | L42: =(3264000)/P42 -> 207.96432 | M42: =(792)/P42 -> 0.050461931 | N42: =(391680)/P42 -> 24.955718 | O42: 0 | P42: 15695 | Q42: 800 | R42: 207.96432 | S42: 0.050461931 | T42: 24.955718 | V42: 183.05906 | W42: 0.22882383 | X42: 3264000 | Y42: 792 | Z42: 391680 | AB42: 2873112 | AC42: 3591.39
A43: ITBISA-7SEGMENT-ANODE-RED-1.20-1BIT | B43: 45514.621 | C43: 45515.706 | D43: KERTASARI CIAMIS | E43: FALSE | F43: Shopee | G43: PegazusStore | H43: Shopee Aji K51T | I43: 5 | J43: 9 | K43: 10 | L43: =(41750)/P43 -> 2.617719 | M43: =(1000)/P43 -> 0.062699856 | N43: =(7515)/P43 -> 0.47118942 | O43: 0 | P43: 15949 | Q43: 90 | R43: 23.559471 | S43: 0.062699856 | T43: 0.47118942 | V43: 23.150981 | W43: 0.25723313 | X43: 375750 | Y43: 1000 | Z43: 7515 | AB43: 369235 | AC43: 4102.6111
A44: ITBISA-7SEGMENT-ANODE-RED-1.20-1BIT | B44: 45514.61 | C44: 45516.529 | D44: KYAI KONTONG | E44: FALSE | F44: Shopee | G44: PegazusStore | H44: Shopee Aji 5JX2 | I44: 5 | J44: 60 | K44: 10 | L44: =(40750)/P44 -> 2.5550191 | M44: =(1000)/P44 -> 0.062699856 | N44: =(97800)/P44 -> 6.1320459 | O44: 0 | P44: 15949 | Q44: 600 | R44: 153.30115 | S44: 0.062699856 | T44: 6.1320459 | V44: 147.2318 | W44: 0.24538634 | X44: 2445000 | Y44: 1000 | Z44: 97800 | AB44: 2348200 | AC44: 3913.6667
A45: ITBISA-7SEGMENT-ANODE-RED-1.20-1BIT | B45: 45514.608 | C45: 45517.509 | D45: KERTASARI CIAMIS | E45: FALSE | F45: Shopee | G45: PegazusStore | H45: Shopee Aji 8T4V | I45: 5 | J45: 100 | K45: 10 | L45: =(40000)/P45 -> 2.5079942 | M45: =(1000)/P45 -> 0.062699856 | N45: =(120000)/P45 -> 7.5239827 | O45: 0 | P45: 15949 | Q45: 1000 | R45: 250.79942 | S45: 0.062699856 | T45: 7.5239827 | V45: 243.33814 | W45: 0.24333814 | X45: 4000000 | Y45: 1000 | Z45: 120000 | AB45: 3881000 | AC45: 3881
A46: ITBISA-7SEGMENT-ANODE-RED-1.20-1BIT | B46: 45417.756 | C46: 45417.756 | D46: KERTASARI CIAMIS | E46: FALSE | F46: Shopee | G46: Shopee Aji RAFM | H46: Shopee Aji RAFM | I46: 5 | J46: 10 | K46: 100 | L46: =(360000)/P46 -> 22.543678 | M46: =(960)/P46 -> 0.060116476 | N46: =(288000)/P46 -> 18.034943 | O46: 0 | P46: 15969 | Q46: 1000 | R46: 225.43678 | S46: 0.060116476 | T46: 18.034943 | V46: 207.46196 | W46: 0.20746196 | X46: 3600000 | Y46: 960 | Z46: 288000 | AB46: 3312960 | AC46: 3312.96
A47: ITBISA-7SEGMENT-ANODE-RED-1.20-1BIT | B47: 45354.034 | C47: 45363.741 | D47: KYAI KONTONG | E47: FALSE | F47: Shopee | G47: Shopee Aji | H47: Shopee Aji | I47: 5 | J47: 11 | K47: 100 | L47: =(360000)/P47 -> 22.928476 | M47: =(1000)/P47 -> 0.063690211 | N47: =(198000)/P47 -> 12.610662 | O47: 0 | P47: 15701 | Q47: 1100 | R47: 252.21323 | S47: 0.063690211 | T47: 12.610662 | V47: 239.66626 | W47: 0.21787842 | X47: 3960000 | Y47: 1000 | Z47: 198000 | AB47: 3763000 | AC47: 3420.9091
A48: ITBISA-7SEGMENT-ANODE-RED-1.20-1BIT | B48: 45347.915 | C48: 45353.71 | D48: KERTASARI CIAMIS | E48: FALSE | F48: Shopee | G48: Shopee Aji | H48: Shopee Aji | I48: 5 | J48: 10 | K48: 100 | L48: =(360000)/P48 -> 23.085802 | M48: =(1000)/P48 -> 0.064127228 | N48: =(180000)/P48 -> 11.542901 | O48: 0 | P48: 15594 | Q48: 1000 | R48: 230.85802 | S48: 0.064127228 | T48: 11.542901 | V48: 219.37925 | W48: 0.21937925 | X48: 3600000 | Y48: 1000 | Z48: 180000 | AB48: 3421000 | AC48: 3421
A49: ITBISA-7SEGMENT-ANODE-RED-1.20-1BIT | B49: 45202.354 | C49: 45232.639 | D49: KYAI KONTONG | E49: TRUE | F49: Jasa Impor Tiongkok | H49: Jasa Impor Tiongkok | I49: 5 | J49: 3000 | K49: 1 | L49: =2756/P49 -> 0.17650826 | M49: 0 | N49: 0 | O49: 0 | P49: 15614 | Q49: 3000 | R49: 529.52479 | V49: 529.52479 | W49: 0.17650826 | X49: 8268000 | AB49: 8268000 | AC49: 2756
A50: ITBISA-7SEGMENT-ANODE-RED-1.20-1BIT | B50: 45002 | C50: 45085 | D50: KYAI KONTONG | E50: TRUE | F50: Jasa Impor Tiongkok | G50: Jasa Impor Tiongkok | I50: 5 | J50: 1000 | K50: 1 | L50: =2893/P50 -> 0.1881626 | M50: 0 | N50: 0 | O50: 0 | P50: 15375 | Q50: 1000 | R50: 188.1626 | V50: 188.1626 | W50: 0.1881626 | X50: 2893000 | AB50: 2893000 | AC50: 2893
A51: ITBISA-7SEGMENT-ANODE-RED-2.30-1BIT | B51: 45265.69 | C51: 45341.64 | D51: KYAI KONTONG | E51: TRUE | F51: Ocistok/Martkita | G51: Ocistok | I51: 5 | J51: 500 | K51: 1 | L51: =6028/P51 -> 0.38922968 | M51: 0 | N51: 0 | O51: 0 | P51: 15487 | Q51: 500 | R51: 194.61484 | V51: 194.61484 | W51: 0.38922968 | X51: 3014000 | AB51: 3014000 | AC51: 6028
A52: ITBISA-7SEGMENT-ANODE-RED-2.30-1BIT | B52: 43607.637 | C52: 43607.638 | D52: AVRG ITB | E52: FALSE | F52: URO Shop | G52: URO Shop | H52: URO Shop | J52: 10 | K52: 1 | L52: 1.5 | P52: 10000 | Q52: 10 | R52: 15 | V52: 15 | W52: 1.5 | X52: 150000 | AB52: 150000 | AC52: 15000
A53: ITBISA-7SEGMENT-ANODE-RED-2.30-1BIT | B53: 43554 | C53: 43563 | D53: RUMAH MUZAKKI | E53: FALSE | F53: Bukalapak | G53: ="https://www.bukalapak.com/p/elektronik/komponen-elektronik/ck5cxm-jual-hs-23101bs-2-2-inch-single-anode-merah?from=list-product&funnel=omnisearch&product_owner=normal_seller&pos=0&cf=1&sort_origin=relevansi&search_sort_default=true&promoted=0" -> https://www.bukalapak.com/p/elektronik/komponen-elektronik/ck5cxm-jual-hs-23101bs-2-2-inch-single-anode-merah?from=list-product&funnel=omnisearch&product_owner=normal_seller&pos=0&cf=1&sort_origin=relevansi&search_sort_default=true&promoted=0 | H53: Bukalapak Furqonajiy 191865788977 | J53: 10 | K53: 1 | L53: =14000/P53 -> 1.4 | M53: =7000/P53 -> 0.7 | P53: 10000 | Q53: 10 | R53: 14 | S53: 0.7 | V53: 14.7 | W53: 1.47 | X53: 140000 | Y53: 7000 | AB53: 147000 | AC53: 14700 | AD53: 15000 | AE53: 15000
A54: ITBISA-7SEGMENT-CATHODE-RED-0.56-1BIT | B54: 45013 | C54: 45061 | D54: KYAI KONTONG | E54: TRUE | F54: Jasa Impor Tiongkok | G54: Jasa Impor Tiongkok | I54: 5 | J54: 10050 | K54: 1 | L54: =731/P54 -> 0.048519846 | M54: 0 | N54: 0 | O54: 0 | P54: 15066 | Q54: 10050 | R54: 487.62445 | V54: 487.62445 | W54: 0.048519846 | X54: 7346550 | AB54: 7346550 | AC54: 731
A55: ITBISA-7SEGMENT-CATHODE-RED-0.56-1BIT | B55: 44839 | C55: 44889 | D55: KYAI KONTONG | E55: TRUE | F55: Jasa Impor Tiongkok | G55: Jasa Impor Tiongkok | H55: Tokopedia Furqonajiy | I55: 5 | J55: 37 | K55: 150 | L55: =(1731600+6926400)/2/37/P55 -> 7.8 | M55: =1000/P55 -> 0.066666667 | N55: =(51948+500000-112525-1000)/2/P55 -> 14.6141 | O55: 0 | P55: 15000 | Q55: 5550 | R55: 288.6 | S55: 0.066666667 | T55: 14.6141 | V55: 274.05257 | W55: 0.049378841 | X55: 4329000 | Y55: 1000 | Z55: 219211.5 | AB55: 4110788.5 | AC55: 740.68261
A56: ITBISA-7SEGMENT-CATHODE-RED-0.56-1BIT | B56: 43798 | C56: 43829 | D56: RUMAH MUZAKKI | E56: TRUE | F56: AliExpress | G56: https://www.Aliexpress.com/item/50pcs-1lot-1-bit-Common-Cathode-Digital-Tube-0-56-0-56in-Red-LED-Digit-7/32701379925.html?spm=a2g0s.9042311.0.0.334d4c4d1XLiYh | H56: Aliexpress Furqonajiy 8007001849904116 | J56: 12 | K56: 50 | L56: 4.21 | N56: 5 | P56: =1309247/(91.04) -> 14381.008 | Q56: 600 | R56: 50.52 | T56: 5 | V56: 45.52 | W56: 0.075866667 | X56: 726528.54 | Z56: 71905.042 | AB56: 654623.5 | AC56: 1091.0392
A57: ITBISA-7SEGMENT-CATHODE-RED-0.56-1BIT | B57: 43782 | C57: 43810 | D57: RUMAH MUZAKKI | E57: TRUE | F57: AliExpress | G57: https://www.Aliexpress.com/item/50pcs-1lot-1-bit-Common-Cathode-Digital-Tube-0-56-0-56in-Red-LED-Digit-7/32701379925.html?spm=a2g0s.9042311.0.0.334d4c4d1XLiYh | H57: Aliexpress Furqonajiy 8006178019124116 8006223027484116 | J57: 12 | K57: 50 | L57: 4.16 | M57: =10000/P57 -> 0.69734996 | N57: 1 | P57: =(1014125+269592)/(12*4.16+10*4.16-2) -> 14340.002 | Q57: 600 | R57: 49.92 | S57: 0.69734996 | T57: 1 | V57: 49.61735 | W57: 0.082695583 | X57: 715852.91 | Y57: 10000 | Z57: 14340.002 | AB57: 711512.91 | AC57: 1185.8548
A58: ITBISA-7SEGMENT-CATHODE-RED-0.56-1BIT | B58: 43719 | C58: 43749.797 | D58: RUMAH MUZAKKI | E58: TRUE | F58: AliExpress | G58: ="https://www.aliexpress.com/item/1-3-Inch-Blue-I2C-IIC-Serial-128X64-OLED-LCD-LED-Display-Module-for-51-MSP420/32701379925.html?spm=2114.search0104.3.129.695b58f9P8tLRf&ws_ab_test=searchweb0_0,searchweb201602_5_10065_10068_5734615_319_317_10696_453_10084_1"&"0924_454_10083_10618_10920_10921_10307_10922_537_536_10059_10884_10887_100031_321_322_10103_5734515,searchweb201603_1,ppcSwitch_0&algo_expid=ec02fe65-0b12-4543-bfac-829a7f0163f6-19&algo_pvid=ec02fe65-0b12-4543-bfac-829a7f0163f6" -> https://www.aliexpress.com/item/1-3-Inch-Blue-I2C-IIC-Serial-128X64-OLED-LCD-LED-Display-Module-for-51-MSP420/32701379925.html?spm=2114.search0104.3.129.695b58f9P8tLRf&ws_ab_test=searchweb0_0,searchweb201602_5_10065_10068_5734615_319_317_10696_453_10084_10924_454_10083_10618_10920_10921_10307_10922_537_536_10059_10884_10887_100031_321_322_10103_5734515,searchweb201603_1,ppcSwitch_0&algo_expid=ec02fe65-0b12-4543-bfac-829a7f0163f6-19&algo_pvid=ec02fe65-0b12-4543-bfac-829a7f0163f6 | H58: Aliexpress Furqonajiy 8001811557214116 Resi EX211568265SG | J58: 12 | K58: 50 | L58: 4.35 | M58: =(20000/P58)/2+10000/P58 -> 1.3943108 | N58: =14122/P58 -> 0.98452288 | P58: =748757/(4.35*12) -> 14344.004 | Q58: 600 | R58: 52.2 | S58: 1.3943108 | T58: 0.98452288 | V58: 52.609788 | W58: 0.08768298 | X58: 748757 | Y58: 20000 | Z58: 14122 | AB58: 754635 | AC58: 1257.725 | AE58: 1500
A59: ITBISA-7SEGMENT-CATHODE-RED-0.56-1BIT | B59: 43581 | C59: 43589 | D59: RUMAH SYAFIRA | E59: TRUE | F59: Shopee | G59: ="https://shopee.co.id/10Pcs-Anoda-Display-LED-1bit-7-Segment-0.5-Warna-Merah-i.119360657.1867222172" -> https://shopee.co.id/10Pcs-Anoda-Display-LED-1bit-7-Segment-0.5-Warna-Merah-i.119360657.1867222172 | H59: Shopee Furqonajiy 190426193570Y33 | J59: 20 | K59: 10 | L59: =13893/P59 -> 1.3893 | M59: =10000/P59 -> 1 | N59: 0 | O59: =10000/P59 -> 1 | P59: 10000 | Q59: 200 | R59: 27.786 | S59: 1 | U59: 1 | V59: 27.786 | W59: 0.13893 | X59: 277860 | Y59: 10000 | AA59: 10000 | AB59: 277860 | AC59: 1389.3 | AD59: 1500 | AE59: 1500
A60: ITBISA-7SEGMENT-CATHODE-RED-0.56-1BIT | B60: 43572 | C60: 43602.038 | D60: RUMAH MUZAKKI | E60: TRUE | F60: AliExpress | G60: ="https://www.aliexpress.com/item/1-3-Inch-Blue-I2C-IIC-Serial-128X64-OLED-LCD-LED-Display-Module-for-51-MSP420/32701379925.html?spm=a2g0s.12269583.0.0.e9ff58aci800B3" -> https://www.aliexpress.com/item/1-3-Inch-Blue-I2C-IIC-Serial-128X64-OLED-LCD-LED-Display-Module-for-51-MSP420/32701379925.html?spm=a2g0s.12269583.0.0.e9ff58aci800B3 | H60: Aliexpress Furqonajiy 100739401884116 Resi RP540584564CN | J60: 10 | K60: 50 | L60: 4.3 | M60: 0 | N60: 0 | O60: 0 | P60: =616921/(4.3*10) -> 14347 | Q60: 500 | R60: 43 | V60: 43 | W60: 0.086 | X60: 616921 | AB60: 616921 | AC60: 1233.842 | AD60: 1500 | AE60: 1500
A61: ITBISA-7SEGMENT-CATHODE-RED-0.56-1BIT | B61: 43569 | C61: =B61 -> 43569 | D61: AVRG ITB | E61: FALSE | F61: URO Shop | G61: URO Shop | H61: URO Shop | J61: 100 | K61: 1 | L61: =1300/P61 -> 0.13 | P61: 10000 | Q61: 100 | R61: 13 | V61: 13 | W61: 0.13 | X61: 130000 | AB61: 130000 | AC61: 1300 | AD61: 1400 | AE61: 1500
A62: ITBISA-7SEGMENT-CATHODE-RED-0.56-1BIT | B62: 43530.663 | C62: 43550 | D62: RUMAH SYAFIRA | E62: TRUE | F62: AliExpress | G62: ="https://www.aliexpress.com/item/1-3-Inch-Blue-I2C-IIC-Serial-128X64-OLED-LCD-LED-Display-Module-for-51-MSP420/32701379925.html?tt=LINE&aff_platform=default&cpt=1543021930032&sk=ioVTkeG&aff_trace_key=8c94b152e33040f387341e43a2a9292c-1543021930032-08877-ioV"&"TkeG&terminal_id=a4f07686fa4c4be491c0b99934cb2c24" -> https://www.aliexpress.com/item/1-3-Inch-Blue-I2C-IIC-Serial-128X64-OLED-LCD-LED-Display-Module-for-51-MSP420/32701379925.html?tt=LINE&aff_platform=default&cpt=1543021930032&sk=ioVTkeG&aff_trace_key=8c94b152e33040f387341e43a2a9292c-1543021930032-08877-ioVTkeG&terminal_id=a4f07686fa4c4be491c0b99934cb2c24 | H62: Aliexpress Furqonajiy 99320493804116 Resi RX470050702CN | J62: 8 | K62: 50 | L62: 4.3 | M62: 0 | N62: 0 | O62: 0 | P62: =991477/(8*4.3 + 8*4.3) -> 14411.003 | Q62: 400 | R62: 34.4 | V62: 34.4 | W62: 0.086 | X62: 495738.5 | AB62: 495738.5 | AC62: 1239.3463 | AD62: 1400 | AE62: 1500
A63: ITBISA-7SEGMENT-CATHODE-RED-0.56-1BIT | B63: 43483.679 | C63: 43495 | D63: WARUNG IBU | E63: TRUE | F63: AliExpress | G63: ="https://www.aliexpress.com/item/1-3-Inch-Blue-I2C-IIC-Serial-128X64-OLED-LCD-LED-Display-Module-for-51-MSP420/32701379925.html?tt=LINE&aff_platform=default&cpt=1543021930032&sk=ioVTkeG&aff_trace_key=8c94b152e33040f387341e43a2a9292c-1543021930032-08877-ioV"&"TkeG&terminal_id=a4f07686fa4c4be491c0b99934cb2c24" -> https://www.aliexpress.com/item/1-3-Inch-Blue-I2C-IIC-Serial-128X64-OLED-LCD-LED-Display-Module-for-51-MSP420/32701379925.html?tt=LINE&aff_platform=default&cpt=1543021930032&sk=ioVTkeG&aff_trace_key=8c94b152e33040f387341e43a2a9292c-1543021930032-08877-ioVTkeG&terminal_id=a4f07686fa4c4be491c0b99934cb2c24 | H63: Aliexpress Furqonajiy 97958978564116 Resi RY499883755CN | J63: 3 | K63: 50 | L63: 4.78 | M63: 0 | N63: 0 | O63: 0 | P63: =977545/(3*4.78 + 4*13.31) -> 14465.004 | Q63: 150 | R63: 14.34 | V63: 14.34 | W63: 0.0956 | X63: 207428.16 | AB63: 207428.16 | AC63: 1382.8544 | AD63: 1400 | AE63: 1500 | AF63: M
A64: ITBISA-7SEGMENT-CATHODE-RED-0.56-1BIT | B64: 43428 | C64: 43446 | D64: RUMAH SYAFIRA | E64: TRUE | F64: AliExpress | G64: ="https://www.aliexpress.com/item/1-3-Inch-Blue-I2C-IIC-Serial-128X64-OLED-LCD-LED-Display-Module-for-51-MSP420/32701379925.html?tt=LINE&aff_platform=default&cpt=1543021930032&sk=ioVTkeG&aff_trace_key=8c94b152e33040f387341e43a2a9292c-1543021930032-08877-ioV"&"TkeG&terminal_id=a4f07686fa4c4be491c0b99934cb2c24" -> https://www.aliexpress.com/item/1-3-Inch-Blue-I2C-IIC-Serial-128X64-OLED-LCD-LED-Display-Module-for-51-MSP420/32701379925.html?tt=LINE&aff_platform=default&cpt=1543021930032&sk=ioVTkeG&aff_trace_key=8c94b152e33040f387341e43a2a9292c-1543021930032-08877-ioVTkeG&terminal_id=a4f07686fa4c4be491c0b99934cb2c24 | H64: Aliexpress Syafirapr 96811194361876 Resi RY427709390CN | J64: 3 | K64: 50 | L64: 4.25 | N64: =2.05/2 -> 1.025 | O64: 0 | P64: =693911/(30.5*1 + (4.25*3 + 4.25*2) - 5) -> 14843.016 | Q64: 150 | R64: 12.75 | T64: 1.025 | V64: 11.725 | W64: 0.078166667 | X64: 189248.45 | Z64: 15214.091 | AB64: 174034.36 | AC64: 1160.2291 | AD64: 1400 | AE64: 1500
A65: ITBISA-7SEGMENT-CATHODE-RED-1.20-1BIT | B65: 45202.354 | C65: 45232.639 | D65: KYAI KONTONG | E65: TRUE | F65: Jasa Impor Tiongkok | H65: Jasa Impor Tiongkok | I65: 5 | J65: 2000 | K65: 1 | L65: =2756/P65 -> 0.17650826 | M65: 0 | N65: 0 | O65: 0 | P65: 15614 | Q65: 2000 | R65: 353.01652 | V65: 353.01652 | W65: 0.17650826 | X65: 5512000 | AB65: 5512000 | AC65: 2756
A66: ITBISA-7SEGMENT-CATHODE-RED-1.20-1BIT | B66: 45002 | C66: 45085 | D66: KYAI KONTONG | E66: TRUE | F66: Jasa Impor Tiongkok | G66: Jasa Impor Tiongkok | I66: 5 | J66: 1000 | K66: 1 | L66: =2893/P66 -> 0.1881626 | M66: 0 | N66: 0 | O66: 0 | P66: 15375 | Q66: 1000 | R66: 188.1626 | V66: 188.1626 | W66: 0.1881626 | X66: 2893000 | AB66: 2893000 | AC66: 2893
A67: ITBISA-7SEGMENT-CATHODE-RED-2.30-1BIT | B67: 45265.69 | C67: 45341.64 | D67: KYAI KONTONG | E67: TRUE | F67: Ocistok/Martkita | G67: Ocistok | I67: 5 | J67: 500 | K67: 1 | L67: =6028/P67 -> 0.38922968 | M67: 0 | N67: 0 | O67: 0 | P67: 15487 | Q67: 500 | R67: 194.61484 | V67: 194.61484 | W67: 0.38922968 | X67: 3014000 | AB67: 3014000 | AC67: 6028
A68: ITBISA-ABC-BATERAI-9V-POWER | B68: 45802.656 | C68: 45811.417 | D68: KYAI KONTONG | E68: FALSE | F68: PT Arta Boga | G68: PT Arta Boga | H68: PT Arta Boga | I68: 5 | J68: 1 | K68: 12 | L68: =(134532)/P68 -> 8.2646517 | M68: 0 | N68: 0 | O68: 0 | P68: 16278 | Q68: 12 | R68: 8.2646517 | V68: 8.2646517 | W68: 0.68872097 | X68: 134532 | AB68: 134532 | AC68: 11211
A69: ITBISA-ABC-BATERAI-9V-POWER | B69: 45587.533 | C69: 45589.916 | D69: KYAI KONTONG | E69: FALSE | F69: PT Arta Boga | G69: PT Arta Boga | H69: PT Arta Boga | I69: 5 | J69: 2 | K69: 12 | L69: =(134500)/P69 -> 8.6295393 | M69: 0 | N69: 0 | O69: 0 | P69: 15586 | Q69: 24 | R69: 17.259079 | V69: 17.259079 | W69: 0.71912828 | X69: 269000 | AB69: 269000 | AC69: 11208.333
A70: ITBISA-ABC-BATERAI-9V-POWER | B70: 45484.339 | C70: 45484.504 | D70: KYAI KONTONG | E70: FALSE | F70: Shopee | G70: ADITAMA ELECTRIC | H70: Shopee Aji RYAN | I70: 5 | J70: 2 | K70: 12 | L70: =(319200/2)/P70 -> 9.9062752 | M70: =(65000 + 1000)/P70 -> 4.09658 | N70: =(9576)/P70 -> 0.59437651 | O70: =(50000)/P70 -> 3.1034697 | P70: 16111 | Q70: 24 | R70: 19.81255 | S70: 4.09658 | T70: 0.59437651 | U70: 3.1034697 | V70: 20.211284 | W70: 0.84213684 | X70: 319200 | Y70: 66000 | Z70: 9576 | AA70: 50000 | AB70: 325624 | AC70: 13567.667
A71: ITBISA-ABC-BATERAI-9V-POWER | B71: 45418.268 | C71: 45420.769 | D71: KYAI KONTONG | E71: FALSE | F71: Shopee | G71: Shopee Aji F8CK | H71: Shopee Aji F8CK | I71: 5 | J71: 1 | K71: 1 | L71: =(9000)/P71 -> 0.56144729 | M71: =(1000)/P71 -> 0.062383032 | N71: 0 | O71: 0 | P71: 16030 | Q71: 1 | R71: 0.56144729 | S71: 0.062383032 | V71: 0.62383032 | W71: 0.62383032 | X71: 9000 | Y71: 1000 | AB71: 10000 | AC71: 10000
A72: ITBISA-ABC-BATERAI-9V-POWER | B72: 45235 | C72: 45236.484 | D72: KYAI KONTONG | E72: FALSE | F72: PT Arta Boga | G72: PT Arta Boga | H72: PT Arta Boga | I72: 5 | J72: 3 | K72: 12 | L72: =(124500)/P72 -> 8.0177743 | M72: 0 | N72: 0 | O72: 0 | P72: 15528 | Q72: 36 | R72: 24.053323 | V72: 24.053323 | W72: 0.66814786 | X72: 373500 | AB72: 373500 | AC72: 10375
A73: ITBISA-ABC-BATERAI-9V-POWER | B73: 45216 | C73: 45218.872 | D73: KYAI KONTONG | E73: FALSE | F73: PT Arta Boga | G73: PT Arta Boga | H73: PT Arta Boga | I73: 5 | J73: 2 | K73: 12 | L73: =(124500)/P73 -> 7.8548896 | M73: 0 | N73: 0 | O73: 0 | P73: 15850 | Q73: 24 | R73: 15.709779 | V73: 15.709779 | W73: 0.65457413 | X73: 249000 | AB73: 249000 | AC73: 10375
A74: ITBISA-ABC-BATERAI-9V-POWER | B74: 45091 | C74: 45092 | D74: KYAI KONTONG | E74: FALSE | F74: PT Arta Boga | G74: PT Arta Boga | H74: PT Arta Boga | I74: 5 | J74: 2 | K74: 12 | L74: =(124500)/P74 -> 8.3260884 | M74: 0 | N74: 0 | O74: 0 | P74: 14953 | Q74: 24 | R74: 16.652177 | V74: 16.652177 | W74: 0.6938407 | X74: 249000 | AB74: 249000 | AC74: 10375
A75: ITBISA-ABC-BATERAI-AA-ALKALINE | B75: 45756.654 | C75: 45772.5 | D75: KYAI KONTONG | E75: FALSE | F75: PT Arta Boga | G75: PT Arta Boga | H75: PT Arta Boga | I75: 5 | J75: 2 | K75: =(36*8) -> 288 | L75: =(1578420)/P75 -> 93.925617 | M75: =0 -> 0 | N75: =(200000 + 741857)/P75 -> 56.046236 | O75: 0 | P75: 16805 | Q75: 576 | R75: 187.85123 | T75: 56.046236 | V75: 131.805 | W75: 0.22882812 | X75: 3156840 | Z75: 941857 | AB75: 2214983 | AC75: 3845.4566
A76: ITBISA-ABC-BATERAI-AA-ALKALINE | B76: 45684.176 | C76: 45690.474 | D76: KERTASARI CIAMIS | E76: FALSE | F76: Shopee | G76: Gading Murni Official Shop | H76: Shopee Aji 0APT | I76: 5 | J76: 43 | K76: 6 | L76: =(28000)/P76 -> 1.7313876 | M76: =(1000)/P76 -> 0.061835271 | N76: =(299750 + 5000)/P76 -> 18.844299 | O76: 0 | P76: 16172 | Q76: 258 | R76: 74.449666 | S76: 0.061835271 | T76: 18.844299 | V76: 55.667203 | W76: 0.21576435 | X76: 1204000 | Y76: 1000 | Z76: 304750 | AB76: 900250 | AC76: 3489.3411
A77: ITBISA-ABC-BATERAI-AA-ALKALINE | B77: 45679.604 | C77: 45681.604 | D77: KYAI KONTONG | E77: FALSE | F77: PT Arta Boga | G77: PT Arta Boga | H77: PT Arta Boga | I77: 5 | J77: 2 | K77: 288 | L77: =(1578420)/P77 -> 96.687289 | M77: 0 | N77: =(200000 + 741857)/P77 -> 57.69415 | O77: 0 | P77: 16325 | Q77: 576 | R77: 193.37458 | T77: 57.69415 | V77: 135.68043 | W77: 0.2355563 | X77: 3156840 | Z77: 941857 | AB77: 2214983 | AC77: 3845.4566
A78: ITBISA-ABC-BATERAI-AA-ALKALINE | B78: 45666.772 | C78: 45671.581 | D78: KERTASARI CIAMIS | E78: FALSE | F78: Shopee | G78: Gading Murni Official Shop | H78: Shopee Aji XVDQ | I78: 5 | J78: 20 | K78: 6 | L78: =(28000)/P78 -> 1.7282884 | M78: =(1900)/P78 -> 0.11727671 | N78: =(99900 + 5000)/P78 -> 6.474909 | O78: 0 | P78: 16201 | Q78: 120 | R78: 34.565768 | S78: 0.11727671 | T78: 6.474909 | V78: 28.208135 | W78: 0.23506779 | X78: 560000 | Y78: 1900 | Z78: 104900 | AB78: 457000 | AC78: 3808.3333
A79: ITBISA-ABC-BATERAI-AA-ALKALINE | B79: 45647.482 | C79: 45652.51 | D79: KYAI KONTONG | E79: FALSE | F79: Shopee | G79: Gading Murni Official Shop | H79: Shopee ITBisa E1JD | I79: 5 | J79: 43 | K79: 6 | L79: =(28000)/P79 -> 1.7361111 | M79: 0 | N79: =(299750 + 5000)/P79 -> 18.895709 | O79: 0 | P79: 16128 | Q79: 258 | R79: 74.652778 | T79: 18.895709 | V79: 55.757068 | W79: 0.21611267 | X79: 1204000 | Z79: 304750 | AB79: 899250 | AC79: 3485.4651
A80: ITBISA-ABC-BATERAI-AA-ALKALINE | B80: 45643.621 | C80: 45645.949 | D80: KYAI KONTONG | E80: FALSE | F80: Shopee | G80: Gading Murni Official Shop | H80: Shopee ITBisa 1G7Y | I80: 5 | J80: 1 | K80: 6 | L80: =(28000)/P80 -> 1.7361111 | M80: 0 | N80: =(5000)/P80 -> 0.31001984 | O80: 0 | P80: 16128 | Q80: 6 | R80: 1.7361111 | T80: 0.31001984 | V80: 1.4260913 | W80: 0.23768188 | X80: 28000 | Z80: 5000 | AB80: 23000 | AC80: 3833.3333
A81: ITBISA-ABC-BATERAI-AA-ALKALINE | B81: 45643.619 | C81: 45645.899 | D81: KYAI KONTONG | E81: FALSE | F81: Shopee | G81: Gading Murni Official Shop | H81: Shopee ITBisa 7XHV | I81: 5 | J81: 43 | K81: 6 | L81: =(28000)/P81 -> 1.7361111 | M81: 0 | N81: =(299750 + 5000)/P81 -> 18.895709 | O81: 0 | P81: 16128 | Q81: 258 | R81: 74.652778 | T81: 18.895709 | V81: 55.757068 | W81: 0.21611267 | X81: 1204000 | Z81: 304750 | AB81: 899250 | AC81: 3485.4651
A82: ITBISA-ABC-BATERAI-AA-ALKALINE | B82: 45591.397 | C82: 45593.306 | D82: KERTASARI CIAMIS | E82: FALSE | F82: Shopee | G82: Kirana Shop Cimahi | H82: Shopee Anggi YTEP | I82: 5 | J82: 1 | K82: 432 | L82: =(1975000)/P82 -> 125.83625 | M82: =(1000)/P82 -> 0.063714559 | N82: =(296250)/P82 -> 18.875438 | O82: 0 | P82: 15695 | Q82: 432 | R82: 125.83625 | S82: 0.063714559 | T82: 18.875438 | V82: 107.02453 | W82: 0.24774197 | X82: 1975000 | Y82: 1000 | Z82: 296250 | AB82: 1679750 | AC82: 3888.3102
A83: ITBISA-ABC-BATERAI-AA-ALKALINE | B83: 45584.033 | C83: 45589.61 | D83: KYAI KONTONG | E83: FALSE | F83: Shopee | G83: LOUIS ELECTRONIC | H83: Shopee Aji 8HVH | I83: 5 | J83: 1 | K83: =(72*6) -> 432 | L83: =(1850000)/P83 -> 119.62496 | M83: =(91001 + 633)/P83 -> 5.9252506 | N83: =(185000)/P83 -> 11.962496 | O83: 0 | P83: 15465 | Q83: 432 | R83: 119.62496 | S83: 5.9252506 | T83: 11.962496 | V83: 113.58771 | W83: 0.26293452 | X83: 1850000 | Y83: 91634 | Z83: 185000 | AB83: 1756634 | AC83: 4066.2824
A84: ITBISA-ABC-BATERAI-AA-ALKALINE | B84: 45580.567 | C84: 45580.653 | D84: KYAI KONTONG | E84: FALSE | F84: PT Arta Boga | G84: PT Arta Boga | H84: PT Arta Boga | I84: 5 | J84: 36 | K84: 8 | L84: =(43750)/P84 -> 2.7987462 | M84: 0 | N84: =(100000 + 370125)/P84 -> 30.074527 | O84: 0 | P84: 15632 | Q84: 288 | R84: 100.75486 | T84: 30.074527 | V84: 70.680335 | W84: 0.24541783 | X84: 1575000 | Z84: 470125 | AB84: 1104875 | AC84: 3836.3715
A85: ITBISA-ABC-BATERAI-AA-ALKALINE | B85: 45560.682 | C85: 45565.707 | D85: KYAI KONTONG | E85: FALSE | F85: Shopee | G85: LOUIS ELECTRONIC | H85: Shopee Aji D289 | I85: 5 | J85: 1 | K85: 432 | L85: =(1800000)/P85 -> 119.03975 | M85: =(91001+1000)/P85 -> 6.0843198 | N85: =(180000)/P85 -> 11.903975 | O85: 0 | P85: 15121 | Q85: 432 | R85: 119.03975 | S85: 6.0843198 | T85: 11.903975 | V85: 113.22009 | W85: 0.26208354 | X85: 1800000 | Y85: 92001 | Z85: 180000 | AB85: 1712001 | AC85: 3962.9653
A86: ITBISA-ABC-BATERAI-AA-ALKALINE | B86: 45527.433 | C86: 45575.576 | D86: KYAI KONTONG | E86: FALSE | F86: PT Arta Boga | G86: PT Arta Boga | H86: PT Arta Boga | I86: 5 | J86: 36 | K86: 8 | L86: =(43750)/P86 -> 2.8167654 | M86: 0 | N86: =(100000 + 370125)/P86 -> 30.268156 | O86: 0 | P86: 15532 | Q86: 288 | R86: 101.40355 | T86: 30.268156 | V86: 71.135398 | W86: 0.24699791 | X86: 1575000 | Z86: 470125 | AB86: 1104875 | AC86: 3836.3715
A87: ITBISA-ABC-BATERAI-AA-ALKALINE | B87: 45502.562 | C87: 45509.553 | D87: KYAI KONTONG | E87: FALSE | F87: PT Arta Boga | G87: PT Arta Boga | H87: PT Arta Boga | I87: 5 | J87: 36 | K87: 8 | L87: =(43750)/P87 -> 2.7047913 | M87: 0 | N87: =(100000 + 370125)/P87 -> 29.064915 | O87: 0 | P87: 16175 | Q87: 288 | R87: 97.372488 | T87: 29.064915 | V87: 68.307573 | W87: 0.23717907 | X87: 1575000 | Z87: 470125 | AB87: 1104875 | AC87: 3836.3715
A88: ITBISA-ABC-BATERAI-AA-ALKALINE | B88: 45489.417 | C88: 45491.69 | D88: KYAI KONTONG | E88: FALSE | F88: PT Arta Boga | G88: PT Arta Boga | H88: PT Arta Boga | I88: 5 | J88: 36 | K88: 8 | L88: =(43750)/P88 -> 2.7047913 | M88: 0 | N88: =(100000 + 370125)/P88 -> 29.064915 | O88: 0 | P88: 16175 | Q88: 288 | R88: 97.372488 | T88: 29.064915 | V88: 68.307573 | W88: 0.23717907 | X88: 1575000 | Z88: 470125 | AB88: 1104875 | AC88: 3836.3715
A89: ITBISA-ABC-BATERAI-AA-ALKALINE | B89: 45481.553 | C89: 45481.583 | D89: KYAI KONTONG | E89: FALSE | F89: Shopee | G89: ACME 88 | H89: Shopee Aji Y4AC | I89: 5 | J89: 20 | K89: 8 | L89: =(36988)/P89 -> 2.2701774 | M89: =(1000)/P89 -> 0.061376051 | N89: =(29591)/P89 -> 1.8161787 | O89: 0 | P89: 16293 | Q89: 160 | R89: 45.403548 | S89: 0.061376051 | T89: 1.8161787 | V89: 43.648745 | W89: 0.27280466 | X89: 739760 | Y89: 1000 | Z89: 29591 | AB89: 711169 | AC89: 4444.8062
A90: ITBISA-ABC-BATERAI-AA-ALKALINE | B90: 45450.292 | C90: 45450.45 | D90: KYAI KONTONG | E90: FALSE | F90: PT Arta Boga | G90: PT Arta Boga | H90: PT Arta Boga | I90: 5 | J90: 36 | K90: 8 | L90: =(43750)/P90 -> 2.6967885 | M90: 0 | N90: =(100000 + 370125)/P90 -> 28.978919 | O90: 0 | P90: 16223 | Q90: 288 | R90: 97.084386 | T90: 28.978919 | V90: 68.105468 | W90: 0.23647732 | X90: 1575000 | Z90: 470125 | AB90: 1104875 | AC90: 3836.3715
A91: ITBISA-ABC-BATERAI-AA-ALKALINE | B91: 45446.997 | C91: 45448.589 | D91: KYAI KONTONG | E91: FALSE | F91: Shopee | G91: ABC Official Shop | H91: Shopee Aji MJ61 | I91: 5 | J91: 1 | K91: =(72*6) -> 432 | L91: =(1800000)/P91 -> 111.04257 | M91: =(1000)/P91 -> 0.061690315 | N91: =(144000)/P91 -> 8.8834053 | O91: 0 | P91: 16210 | Q91: 432 | R91: 111.04257 | S91: 0.061690315 | T91: 8.8834053 | V91: 102.22085 | W91: 0.23662234 | X91: 1800000 | Y91: 1000 | Z91: 144000 | AB91: 1657000 | AC91: 3835.6481
A92: ITBISA-ABC-BATERAI-AA-ALKALINE | B92: 45445.86 | C92: 45447.833 | D92: KYAI KONTONG | E92: FALSE | F92: Shopee | G92: SarangBaterai | H92: Shopee Anggi JNPQ | I92: 5 | J92: 2 | K92: 6 | L92: =(26000)/P92 -> 1.5995078 | M92: =(1000)/P92 -> 0.061519532 | N92: =(10000)/P92 -> 0.61519532 | O92: 0 | P92: 16255 | Q92: 12 | R92: 3.1990157 | S92: 0.061519532 | T92: 0.61519532 | V92: 2.6453399 | W92: 0.22044499 | X92: 52000 | Y92: 1000 | Z92: 10000 | AB92: 43000 | AC92: 3583.3333
A93: ITBISA-ABC-BATERAI-AA-ALKALINE | B93: 45444.015 | C93: 45450.519 | D93: KERTASARI CIAMIS | E93: FALSE | F93: Shopee | G93: ABC Official Shop | H93: Shopee Aji V29H | I93: 5 | J93: 1 | K93: =(72*6) -> 432 | L93: =(1800000)/P93 -> 110.73516 | M93: =(1000)/P93 -> 0.061519532 | N93: =(100000)/P93 -> 6.1519532 | O93: 0 | P93: 16255 | Q93: 432 | R93: 110.73516 | S93: 0.061519532 | T93: 6.1519532 | V93: 104.64472 | W93: 0.24223316 | X93: 1800000 | Y93: 1000 | Z93: 100000 | AB93: 1701000 | AC93: 3937.5
A94: ITBISA-ABC-BATERAI-AA-ALKALINE | B94: 45441.647 | C94: 45441.647 | D94: KYAI KONTONG | E94: FALSE | F94: Shopee | G94: Surya Mas Ateka | H94: Shopee Aji DS12 | I94: 5 | J94: 72 | K94: 6 | L94: =(26000)/P94 -> 1.6068228 | M94: =(1000)/P94 -> 0.061800878 | N94: =(56160)/P94 -> 3.4707373 | O94: 0 | P94: 16181 | Q94: 432 | R94: 115.69124 | S94: 0.061800878 | T94: 3.4707373 | V94: 112.28231 | W94: 0.25991275 | X94: 1872000 | Y94: 1000 | Z94: 56160 | AB94: 1816840 | AC94: 4205.6481
A95: ITBISA-ABC-BATERAI-AA-ALKALINE | B95: 45441.49 | C95: 45441.642 | D95: KYAI KONTONG | E95: FALSE | F95: Shopee | G95: Toys Lifestyle | H95: Shopee Aji YER4 | I95: 5 | J95: 96 | K95: 6 | L95: =(26500)/P95 -> 1.6377233 | M95: =(1000 + 53000)/P95 -> 3.3372474 | N95: =(100000)/P95 -> 6.1800878 | O95: =(50000)/P95 -> 3.0900439 | P95: 16181 | Q95: 576 | R95: 157.22143 | S95: 3.3372474 | T95: 6.1800878 | U95: 3.0900439 | V95: 151.28855 | W95: 0.26265373 | X95: 2544000 | Y95: 54000 | Z95: 100000 | AA95: 50000 | AB95: 2448000 | AC95: 4250
A96: ITBISA-ABC-BATERAI-AA-ALKALINE | B96: 45441.49 | C96: 45441.582 | D96: KYAI KONTONG | E96: FALSE | F96: Shopee | G96: Surya Mas Ateka | H96: Shopee Dwi XWYM | I96: 5 | J96: 80 | K96: 6 | L96: =(26000)/P96 -> 1.6068228 | M96: =(1000)/P96 -> 0.061800878 | N96: =(83200)/P96 -> 5.141833 | O96: 0 | P96: 16181 | Q96: 480 | R96: 128.54583 | S96: 0.061800878 | T96: 5.141833 | V96: 123.46579 | W96: 0.2572204 | X96: 2080000 | Y96: 1000 | Z96: 83200 | AB96: 1997800 | AC96: 4162.0833
A97: ITBISA-ABC-BATERAI-AA-ALKALINE | B97: 45432.96 | C97: 45435.497 | D97: KYAI KONTONG | E97: FALSE | F97: Shopee | G97: thrift889 | H97: Shopee Anggi UEXM | I97: 5 | J97: 35 | K97: 6 | L97: =(822500/35)/P97 -> 1.4684747 | M97: =(368)/P97 -> 0.022995688 | N97: =(32900)/P97 -> 2.0558645 | O97: 0 | P97: 16003 | Q97: 210 | R97: 51.396613 | S97: 0.022995688 | T97: 2.0558645 | V97: 49.363744 | W97: 0.23506545 | X97: 822500 | Y97: 368 | Z97: 32900 | AB97: 789968 | AC97: 3761.7524
A98: ITBISA-ABC-BATERAI-AA-ALKALINE | B98: 45426.999 | C98: 45427.733 | D98: KYAI KONTONG | E98: FALSE | F98: Shopee | G98: Arsyila shop 03 | H98: Shopee Aji F1PN | I98: 5 | J98: 11 | K98: 6 | L98: =(23000)/P98 -> 1.429104 | M98: =(153)/P98 -> 0.0095066484 | N98: =(12650)/P98 -> 0.78600721 | O98: 0 | P98: 16094 | Q98: 66 | R98: 15.720144 | S98: 0.0095066484 | T98: 0.78600721 | V98: 14.943644 | W98: 0.22641884 | X98: 253000 | Y98: 153 | Z98: 12650 | AB98: 240503 | AC98: 3643.9848
A99: ITBISA-ABC-BATERAI-AA-ALKALINE | B99: 45409.328 | C99: 45413.417 | D99: KERTASARI CIAMIS | E99: FALSE | F99: Tokopedia | G99: Tokopedia Anggi 9438 | H99: Tokopedia Anggi 9438 | I99: 5 | J99: 12 | K99: 6 | L99: =(23999)/P99 -> 1.4776799 | M99: =(1900 + 1000/2)/P99 -> 0.14777415 | N99: =(14399)/P99 -> 0.88658334 | O99: 0 | P99: 16241 | Q99: 72 | R99: 17.732159 | S99: 0.14777415 | T99: 0.88658334 | V99: 16.99335 | W99: 0.23601875 | X99: 287988 | Y99: 2400 | Z99: 14399 | AB99: 275989 | AC99: 3833.1806
A100: ITBISA-ABC-BATERAI-AA-ALKALINE | B100: 45409.046 | C100: 45411.675 | D100: KERTASARI CIAMIS | E100: FALSE | F100: Shopee | G100: Shopee Aji HK1B0 | H100: Shopee Aji HK1B0 | I100: 5 | J100: 10 | K100: 6 | L100: =(230000/10)/P100 -> 1.416169 | M100: =(1000)/P100 -> 0.061572563 | N100: 0 | O100: 0 | P100: 16241 | Q100: 60 | R100: 14.16169 | S100: 0.061572563 | V100: 14.223262 | W100: 0.23705437 | X100: 230000 | Y100: 1000 | AB100: 231000 | AC100: 3850
A101: ITBISA-ABC-BATERAI-AA-ALKALINE | B101: 45409.014 | C101: 45411.424 | D101: KYAI KONTONG | E101: FALSE | F101: Shopee | G101: Shopee Aji CUK9 | H101: Shopee Aji CUK9 | I101: 5 | J101: 4 | K101: 6 | L101: =(103996/4)/P101 -> 1.6008251 | M101: =(1000)/P101 -> 0.061572563 | N101: =(10000)/P101 -> 0.61572563 | O101: 0 | P101: 16241 | Q101: 24 | R101: 6.4033003 | S101: 0.061572563 | T101: 0.61572563 | V101: 5.8491472 | W101: 0.24371447 | X101: 103996 | Y101: 1000 | Z101: 10000 | AB101: 94996 | AC101: 3958.1667
...

Sheet BisaHilang
A1: Tanggal Pengecekan Kehilangan | B1: SKU | C1: Banyak Ketemu | D1: Nilai Ketemu | E1: Banyak Hilang | F1: Nilai Hilang | G1: Lokasi Gudang | H1: Keterangan
A3: 43515.59 | B3: ITBISA-IC-NE555P-DIP8 | E3: 130 | F3: =E3*385.058418171057 -> 50057.594 | G3: AVRG ITB
A5: 43550 | B5: ITBISA-JUMPER-FF-10CM | E5: 220 | F5: =E5*263.610082277654 -> 57994.218 | G5: AVRG ITB
A6: 43550.8 | B6: ITBISA-IC-NE555P-DIP8 | C6: 76 | D6: =C6*386.176666666667 -> 29349.427 | G6: AVRG ITB
A7: 43550.813 | B7: ITBISA-SOCKET-IC-DIP8-NARROW | C7: 15 | D7: =C7*279.488315084029 -> 4192.3247 | G7: AVRG ITB
A8: 43550.814 | B8: ITBISA-NPN-2N2222-TO92 | E8: 12 | F8: =E8*106.611587323364 -> 1279.339 | G8: AVRG ITB
A9: 43550.815 | B9: ITBISA-JUMPER-MF-10CM | E9: 20 | F9: =E9*263.610082277654 -> 5272.2016 | G9: AVRG ITB
A10: 43552 | B10: ITBISA-ARDUINO-UNO-R3-CLONE-CABLE30CM | E10: 1 | F10: =E10*42471.2827548361 -> 42471.283 | G10: RUMAH MUZAKKI
A11: 43552 | B11: ITBISA-ARDUINO-UNO-R3-328P-SMD | C11: 1 | D11: =C11*(42471.2827548361-5000) -> 37471.283 | G11: RUMAH MUZAKKI
A12: 43552 | B12: ITBISA-USB-A-TO-B-30CM | C12: 1 | D12: =C12*5000 -> 5000 | G12: RUMAH MUZAKKI
A13: 43552 | B13: ITBISA-ARDUINO-UNO-R3-CLONE-CABLE30CM | E13: 1 | F13: =E13*44927.11 -> 44927.11 | G13: RUMAH MUZAKKI
A14: 43552 | B14: ITBISA-ARDUINO-UNO-R3-328P-SMD | C14: 1 | D14: =C14*(44927.11-5000) -> 39927.11 | G14: RUMAH MUZAKKI
A15: 43552 | B15: ITBISA-USB-A-TO-B-30CM | C15: 1 | D15: =C15*5000 -> 5000 | G15: RUMAH MUZAKKI
A17: 43559 | B17: ITBISA-ARDUINO-UNO-R3-CLONE-CABLE30CM | E17: 1 | F17: =E17*46371.7066813006 -> 46371.707 | G17: RUMAH MUZAKKI
A18: 43559 | B18: ITBISA-ARDUINO-UNO-R3-328P-SMD | C18: 1 | D18: =C18*(46371.7066813006-5000) -> 41371.707 | G18: RUMAH MUZAKKI
A19: 43559 | B19: ITBISA-USB-A-TO-B-30CM | C19: 1 | D19: =C19*5000 -> 5000 | G19: RUMAH MUZAKKI
A20: 43563 | B20: ITBISA-ARDUINO-UNO-R3-CLONE-CABLE50CM | E20: 13 | F20: =E20*39217.1538461538 -> 509823 | G20: RUMAH MUZAKKI
A21: 43563 | B21: ITBISA-ARDUINO-UNO-R3-328P-SMD | C21: 13 | D21: =C21*(39217.1538461538-5000) -> 444823 | G21: RUMAH MUZAKKI
A22: 43563 | B22: ITBISA-USB-A-TO-B-50CM | C22: 13 | D22: =C22*5000 -> 65000 | G22: RUMAH MUZAKKI
A23: 43571 | B23: ITBISA-ARDUINO-UNO-R3-CLONE-CABLE30CM | E23: 7 | F23: =E23*38232.1428571429 -> 267625 | G23: RUMAH SYAFIRA
A24: 43571 | B24: ITBISA-ARDUINO-UNO-R3-328P-SMD | C24: 7 | D24: =C24*(38232.1428571429-5000) -> 232625 | G24: RUMAH MUZAKKI
A25: 43571 | B25: ITBISA-USB-A-TO-B-30CM | C25: 7 | D25: =C25*5000 -> 35000 | G25: RUMAH MUZAKKI
A26: 43573.954 | B26: ITBISA-JUMPER-MF-10CM | E26: 31 | F26: =E26*263.610082277654 -> 8171.9126 | G26: AVRG ITB
A27: 43573.954 | B27: ITBISA-JUMPER-FF-10CM | E27: 26 | F27: =E27*263.610082277654 -> 6853.8621 | G27: AVRG ITB
A28: 43573.955 | B28: ITBISA-IC-NE555P-DIP8 | C28: 201 | D28: =C28*376.321111111111 -> 75640.543 | G28: AVRG ITB
A30: 43617.526 | B30: ITBISA-7SEGMENT-ANODE-RED-0.56-1BIT | E30: 10 | F30: =E30*1233.842 -> 12338.42 | G30: AVRG ITB
A31: 43617.527 | B31: ITBISA-7SEGMENT-CATHODE-RED-0.56-1BIT | E31: 90 | F31: =E31*1233.842 -> 111045.78 | G31: AVRG ITB
A32: 43617.527 | B32: ITBISA-7SEGMENT-CATHODE-RED-0.56-1BIT | E32: 10 | F32: =E32*1233.842 -> 12338.42 | G32: RUMAH MUZAKKI
A33: 43617.528 | B33: ITBISA-ABC-BATERAI-D-POWER | C33: 8 | D33: =C33*3650 -> 29200 | G33: AVRG ITB
A34: 43617.529 | B34: ITBISA-USB-A-TO-B-30CM | C34: 3 | D34: =C34*5000 -> 15000 | G34: RUMAH MUZAKKI
A35: 43617.529 | B35: ITBISA-IC-NE555P-DIP8 | E35: 134 | F35: =E35*376.321111111111 -> 50427.029 | G35: AVRG ITB
A36: 43617.53 | B36: ITBISA-IC-UA741CN-DIP8 | E36: 19 | F36: =E36*688 -> 13072 | G36: AVRG ITB
A37: 43617.531 | B37: ITBISA-JUMPER-FF-10CM | C37: 80 | D37: =C37*152.785222260732 -> 12222.818 | G37: AVRG ITB
A38: 43617.531 | B38: ITBISA-JUMPER-MF-10CM | E38: 47 | F38: =E38*160.403626904782 -> 7538.9705 | G38: AVRG ITB
A39: 43617.532 | B39: ITBISA-JUMPER-FF-10CM | C39: 160 | D39: =C39*152.785222260732 -> 24445.636 | G39: RUMAH MUZAKKI
A40: 43617.533 | B40: ITBISA-JUMPER-MF-10CM | C40: 41 | D40: =C40*160.403626904782 -> 6576.5487 | G40: RUMAH MUZAKKI
A41: 43617.534 | B41: ITBISA-NPN-2N2222-TO92 | E41: 699 | F41: =E41*104.929 -> 73345.371 | G41: AVRG ITB
A42: 43617.535 | B42: ITBISA-SOCKET-IC-DIP8-NARROW | E42: 1 | F42: =E42*300 -> 300 | G42: RUMAH MUZAKKI
A44: 43678 | B44: ITBISA-TIGERHEAD-SENTER-KUNING-FT300 | C44: 2 | D44: =C44*13100 -> 26200 | G44: RUMAH MUZAKKI
A46: 43834 | B46: ITBISA-IC-NE555P-DIP8 | E46: 19 | F46: =E46*343.532091698318 -> 6527.1097 | G46: AVRG ITB
A47: 43834 | B47: ITBISA-SOCKET-IC-DIP8-NARROW | C47: 70 | D47: =C47*188.062908301682 -> 13164.404 | G47: AVRG ITB
A49: 43872 | B49: ITBISA-USB-A-TO-B-50CM | C49: 1 | D49: =C49*5000 -> 5000 | G49: RUMAH MUZAKKI
A51: 43877 | B51: ITBISA-7SEGMENT-ANODE-RED-0.56-1BIT | C51: 1 | D51: =C51*1091.03916666667 -> 1091.0392 | G51: AVRG ITB
A52: 43877 | B52: ITBISA-ARDUINO-UNO-R3-328P-SMD | C52: 3 | D52: =C52*(39217.1538461538-5000) -> 102651.46 | G52: RUMAH MUZAKKI
A53: 43877 | B53: ITBISA-MOTORDRIVER-L298N-WITH-HEATSINK | C53: 2 | D53: =C53*16320 -> 32640 | G53: RUMAH MUZAKKI
A54: 43877.851 | B54: ITBISA-7SEGMENT-ANODE-RED-2.30-1BIT | C54: 2 | D54: =C54*14700 -> 29400 | G54: RUMAH MUZAKKI
A56: 43878 | B56: ITBISA-7SEGMENT-ANODE-RED-0.56-1BIT | C56: 2 | D56: =C56*1091.03916666667 -> 2182.0783 | G56: RUMAH MUZAKKI
A57: 43878 | B57: ITBISA-7SEGMENT-CATHODE-RED-0.56-1BIT | C57: 11 | D57: =C57*1091.03916666667 -> 12001.431 | G57: RUMAH MUZAKKI
A58: 43878 | B58: ITBISA-JUMPER-FF-10CM | E58: 350 | F58: =E58*179.012653374233 -> 62654.429 | G58: RUMAH MUZAKKI
A59: 43878 | B59: ITBISA-JUMPER-MF-10CM | E59: 342 | F59: =E59*179.012653374233 -> 61222.327 | G59: RUMAH MUZAKKI
A60: 43878 | B60: ITBISA-JUMPER-MM-10CM | C60: 40 | D60: =C60*196.941666666667 -> 7877.6667 | G60: RUMAH MUZAKKI
A62: 43923.84 | B62: ITBISA-PCB-5X7-COPPER-SINGLE-SIDE | C62: 2 | D62: =C62*1272.24242424242 -> 2544.4848 | G62: AVRG ITB
A63: 43923.862 | B63: ITBISA-IC-NE555P-DIP8 | E63: 18 | F63: =E63*338.937857142857 -> 6100.8814 | G63: AVRG ITB
A64: 43923.872 | B64: ITBISA-IC-UA741CN-DIP8 | C64: 21 | D64: =C64*817.850183957219 -> 17174.854 | G64: KAETOBO RESIDENCE
A66: 43927 | B66: ITBISA-RAPID-BOHLAM-E10-2.5V-SCREW | C66: 1 | D66: =C66*700 -> 700 | G66: KAETOBO RESIDENCE
A68: 43940 | B68: ITBISA-VYBA-SENTER-KUNING-FT300 | C68: 3 | D68: =C68*12500 -> 37500 | G68: KAETOBO RESIDENCE
A70: 43949 | B70: ITBISA-VYBA-SENTER-KUNING-FT300 | C70: 3 | D70: =C70*12500 -> 37500 | G70: KAETOBO RESIDENCE
A72: 43955 | B72: ITBISA-VYBA-SENTER-KUNING-FT300 | C72: 3 | D72: =C72*12500 -> 37500 | G72: KAETOBO RESIDENCE
A74: 43973.918 | B74: ITBISA-7SEGMENT-CATHODE-RED-0.56-1BIT | E74: 100 | F74: =E74*1091.03916666667 -> 109103.92 | G74: KAETOBO RESIDENCE
A75: 43973.932 | B75: ITBISA-JUMPER-MF-10CM | C75: 24 | D75: =C75*179.012653374233 -> 4296.3037 | G75: KAETOBO RESIDENCE
A77: 43986 | B77: ITBISA-NPN-2N2222-TO92 | C77: 665 | D77: =C77*104.929 -> 69777.785 | G77: KAETOBO RESIDENCE
A79: 43988 | B79: ITBISA-JUMPER-FF-20CM | C79: 40 | D79: =C79*210.041513292434 -> 8401.6605 | G79: KAETOBO RESIDENCE
A80: 43988 | B80: ITBISA-JUMPER-MF-20CM | C80: 80 | D80: =C80*210.041513292434 -> 16803.321 | G80: KAETOBO RESIDENCE
A81: 43988 | B81: ITBISA-JUMPER-MM-20CM | C81: 40 | D81: =C81*210.041513292434 -> 8401.6605 | G81: KAETOBO RESIDENCE
A82: 43988 | B82: ITBISA-7SEGMENT-ANODE-RED-0.56-1BIT | E82: 750 | F82: 899752 | G82: RUMAH MUZAKKI
A84: 43994 | B84: ITBISA-IC-78L05-TO92 | E84: 150 | F84: =E84*211.4625 -> 31719.375 | G84: KAETOBO RESIDENCE
A85: 43994.884 | B85: ITBISA-NPN-2N2222-TO92 | C85: 295 | D85: =C85*132.946 -> 39219.07 | G85: KAETOBO RESIDENCE
A87: 44003 | B87: ITBISA-JUMPER-FF-10CM | E87: 20 | F87: =E87*198.35 -> 3967 | G87: KAETOBO RESIDENCE
A89: 44008 | B89: ITBISA-SOCKET-IC-DIP8-NARROW | C89: 50 | D89: 14220.206 | G89: KAETOBO RESIDENCE
A90: 44008 | B90: ITBISA-NPN-2N2222-TO92 | C90: 50 | D90: 6647.3 | G90: KAETOBO RESIDENCE
A91: 44008 | B91: ITBISA-IC-UA741CN-DIP8 | C91: 50 | D91: 34400 | G91: KAETOBO RESIDENCE
A92: 44008 | B92: ITBISA-ABC-BATERAI-D-POWER | C92: 5 | D92: 17500 | G92: KAETOBO RESIDENCE
A93: 44008 | B93: ITBISA-RESISTOR-22K-1/4W | C93: 50 | D93: 1050 | G93: KAETOBO RESIDENCE
A94: 44008 | B94: ITBISA-RESISTOR-4K7-1/4W | C94: 50 | D94: 1050 | G94: KAETOBO RESIDENCE
A95: 44008 | B95: ITBISA-RESISTOR-3K3-1/4W | C95: 50 | D95: 1050 | G95: KAETOBO RESIDENCE
A96: 44008 | B96: ITBISA-RESISTOR-100K-1/4W | C96: 50 | D96: 1050 | G96: KAETOBO RESIDENCE
A97: 44008 | B97: ITBISA-RESISTOR-2K2-1/4W | C97: 50 | D97: 1050 | G97: KAETOBO RESIDENCE
A98: 44008 | B98: ITBISA-RESISTOR-10K-1/4W | C98: 50 | D98: 1050 | G98: KAETOBO RESIDENCE
A99: 44008 | B99: ITBISA-JUMPER-MF-20CM | C99: 400 | D99: 106020 | G99: KAETOBO RESIDENCE
A100: 44008 | B100: ITBISA-JUMPER-FF-10CM | C100: 400 | D100: 79340 | G100: KAETOBO RESIDENCE
... A123: 44008 | B123: ITBISA-RESISTOR-2K2-1/4W | C123: 50 | D123: 1050 | G123: KAETOBO RESIDENCE
A125: 44038 | B125: ITBISA-IC-78L05-TO92 | C125: 6 | D125: =C125*141.94 -> 851.64 | G125: KOST SRITUNGGAL
A127: 44050 | B127: ITBISA-NPN-2N2222-TO92 | E127: 1 | F127: 132.946 | G127: KAETOBO RESIDENCE
A128: 44050 | B128: ITBISA-RAPID-BOHLAM-E10-2.5V-SCREW | E128: 4 | F128: 700 | G128: KAETOBO RESIDENCE
A130: 44104 | B130: ITBISA-JUMPER-FF-10CM | C130: 546 | D130: =C130*198.35 -> 108299.1 | G130: AVRG ITB
A131: 44104 | B131: ITBISA-JUMPER-FF-10CM | C131: 390 | D131: =C131*198.35 -> 77356.5 | G131: KAETOBO RESIDENCE
A132: 44104 | B132: ITBISA-JUMPER-MF-10CM | C132: 702 | D132: =C132*198.35 -> 139241.7 | G132: AVRG ITB
A134: 44105 | B134: ITBISA-PSU-S4012-12V-3A | C134: 12 | D134: 0 | G134: RUMAH MUZAKKI
A135: 44105 | B135: ITBISA-EMLOCK-ACM-Y180 | C135: 2 | D135: 0 | G135: RUMAH MUZAKKI
A136: 44105 | B136: ITBISA-JUMPER-MF-20CM | C136: 390 | D136: 103369.5 | G136: KAETOBO RESIDENCE
A138: 44158.918 | B138: ITBISA-SYAL | E138: 29 | F138: 298700 | G138: KOST RUMAHUMI
A139: 44158.918 | B139: ITBISA-KUPLUK-HITAM | E139: 26 | F139: 226600 | G139: KOST RUMAHUMI
A140: 44158.918 | B140: ITBISA-PONCO-GAJAH | E140: 13 | F140: 234000 | G140: KOST RUMAHUMI
A141: 44158.92 | B141: ITBISA-SARUNG-TANGAN-SPANDEX | E141: 44 | F141: 281300 | G141: KOST RUMAHUMI
A142: 44158.92 | B142: ITBISA-SARUNG-TANGAN-KATUN | E142: 70 | F142: 206000 | G142: KOST RUMAHUMI
A144: 44174.759 | B144: ITBISA-ABC-BATERAI-D-POWER | E144: 4 | F144: =E144*3500 -> 14000 | G144: KOST RUMAHUMI
A146: 44793 | B146: ITBISA-TIGERHEAD-SENTER-KUNING-FT300 | C146: 1 | D146: =C146*13100 -> 13100 | G146: RUMAH MUZAKKI
A148: 44810 | B148: ITBISA-IC-NE555P-DIP8 | E148: =262-113-110 -> 39 | F148: =E148*550 -> 21450 | G148: KYAI KONTONG
A150: 44826 | B150: ITBISA-SOCKET-IC-DIP8-NARROW | E150: 48 | F150: =E150*236.67 -> 11360.16 | G150: KYAI KONTONG
A152: 44835 | B152: ITBISA-NPN-2N2222-TO92 | C152: 7 | D152: =C152*132.946 -> 930.622 | G152: KYAI KONTONG
...

Sheet BisaRekapBarang
D1: TRUE | E1: FALSE | F1: FALSE | G1: FALSE | H1: FALSE | I1: FALSE | J1: FALSE | K1: FALSE | L1: FALSE | M1: FALSE | N1: FALSE | O1: FALSE | P1: FALSE | Q1: FALSE | R1: FALSE | S1: FALSE | T1: FALSE | U1: FALSE | V1: FALSE | W1: FALSE | X1: FALSE | Y1: FALSE
A2: {={BisaRekapBarangBackend!A1:C1;SORT(IF(BisaRekapBarangBackend!B2:B145<1,,BisaRekapBarangBackend!A2:C145),1,TRUE)}} -> #VALUE! | D2: {={BisaRekapBarangBackend!D1:O1; SORT(IF( (BisaRekapBarangBackend!D2:D145="ITBISA-KODE-UNIK")+(BisaRekapBarangBackend!H2:H145=0),,BisaRekapBarangBackend!D2:O145), IF(D1=TRUE,1, IF(E1=TRUE,2, IF(F1=TRUE,3, IF(G1=TRUE,4, IF(H1=TRUE,5, IF(I1=TRUE,6, IF(J1=TRUE,7, IF(K1=TRUE,8, IF(L1=TRUE,9, IF(M1=TRUE,10, IF(N1=TRUE,11, IF(#REF!=TRUE,12,1)))))))))))), IF(D1=TRUE,TRUE, IF(E1=TRUE,TRUE, IF(F1=TRUE,TRUE, IF(G1=TRUE,FALSE, IF(H1=TRUE,FALSE, IF(I1=TRUE,FALSE, IF(J1=TRUE,FALSE, IF(K1=TRUE,FALSE, IF(L1=TRUE,FALSE, IF(M1=TRUE,FALSE, IF(N1=TRUE,FALSE, IF(#REF!=TRUE,FALSE)))))))))))), 1,TRUE)}} -> SKU | E2: Tanggal Pesan Terakhir | F2: HPP Terakhir | G2: HPP Belum Terjual | H2: Total Stok | I2: 1/2 Total Stok | J2: 1/3 Total Stok | K2: 40% Total Stok | L2: 20% Total Stok | M2: KERTASARI CIAMIS | N2: KYAI KONTONG
D3: ITBISA-7SEGMENT-ANODE-RED-0.56-1BIT | E3: 46014 | F3: 675.9248 | G3: 4937630.7 | H3: 7305 | I3: 3652 | J3: 2435 | K3: 2922 | L3: 1461 | M3: 255 | N3: 7050
D4: ITBISA-7SEGMENT-ANODE-RED-1.00-1BIT | E4: 46003 | F4: 2000 | G4: 4318000 | H4: 2159 | I4: 1079 | J4: 719 | K4: 863 | L4: 431 | M4: 519 | N4: 1640
D5: ITBISA-7SEGMENT-ANODE-RED-1.20-1BIT | E5: 46006 | F5: 3611.7333 | G5: 7646039.5 | H5: 2117 | I5: 1058 | J5: 705 | K5: 846 | L5: 423 | M5: 782 | N5: 1335
D6: ITBISA-7SEGMENT-CATHODE-RED-0.56-1BIT | E6: 46020 | F6: 731 | G6: 2095046 | H6: 2866 | I6: 1433 | J6: 955 | K6: 1146 | L6: 573 | M6: 1752 | N6: 1114
D7: ITBISA-7SEGMENT-CATHODE-RED-1.20-1BIT | E7: 46000 | F7: 2756 | G7: 1113424 | H7: 404 | I7: 202 | J7: 134 | K7: 161 | L7: 80 | M7: 87 | N7: 317
D8: ITBISA-7SEGMENT-CATHODE-RED-2.30-1BIT | E8: 46022 | F8: 6028 | G8: 361680 | H8: 60 | I8: 30 | J8: 20 | K8: 24 | L8: 12 | M8: 8 | N8: 52
D9: ITBISA-ABC-BATERAI-9V-POWER | E9: 46019 | F9: 11211 | G9: 100899 | H9: 9 | I9: 4 | J9: 3 | K9: 3 | L9: 1 | M9: 8 | N9: 1
D10: ITBISA-ABC-BATERAI-AA-ALKALINE | E10: 46022 | F10: 3845.4566 | G10: 4014656.7 | H10: 1044 | I10: 522 | J10: 348 | K10: 417 | L10: 208 | M10: 250 | N10: 794
D11: ITBISA-ABC-BATERAI-AAA-ALKALINE | E11: 46020 | F11: 3612.5312 | G11: 5086444 | H11: 1408 | I11: 704 | J11: 469 | K11: 563 | L11: 281 | M11: 35 | N11: 1373
D12: ITBISA-ABC-BATERAI-D-POWER | E12: 45841 | F12: 5166.6667 | G12: 5166.6667 | H12: 1 | I12: 0 | J12: 0 | K12: 0 | L12: 0 | N12: 1
D13: ITBISA-ARDUINO-UNO-R3-328P-SMD | E13: 45997 | F13: 37978.259 | G13: 9912325.7 | H13: 261 | I13: 130 | J13: 87 | K13: 104 | L13: 52 | M13: 221 | N13: 40
D14: ITBISA-BLUETOOTH-MODULE-HC05 | E14: 46011 | F14: 29027.08 | G14: 1277191.5 | H14: 44 | I14: 22 | J14: 14 | K14: 17 | L14: 8 | M14: 6 | N14: 38
D15: ITBISA-BREADBOARD-830HOLE-MB102 | E15: 46015 | F15: 7000 | G15: 203000 | H15: 29 | I15: 14 | J15: 9 | K15: 11 | L15: 5 | M15: 24 | N15: 5
D16: ITBISA-BUBBLE-WRAP | E16: 46000 | G16: 0 | H16: -13 | I16: -6 | J16: -4 | K16: -5 | L16: -2 | M16: -11 | N16: -2
D17: ITBISA-BUZZER-ACTIVE-5V | E17: 46019 | F17: 1170.311 | G17: 3715737.4 | H17: 3175 | I17: 1587 | J17: 1058 | K17: 1270 | L17: 635 | M17: 1037 | N17: 2138
D18: ITBISA-CHIP-ESP32-WROOM | E18: 46016 | F18: 23076 | G18: 392292 | H18: 17 | I18: 8 | J18: 5 | K18: 6 | L18: 3 | M18: 22 | N18: -5
D19: ITBISA-CHIP-ESP32-WROOM-ANTENNA | F19: 24820 | G19: 198560 | H19: 8 | I19: 4 | J19: 2 | K19: 3 | L19: 1 | N19: 8
D20: ITBISA-CHIP-ESP8266-ESP12F | E20: 45981 | F20: 13937.05 | G20: 1951187 | H20: 140 | I20: 70 | J20: 46 | K20: 56 | L20: 28 | M20: 138 | N20: 2
D21: ITBISA-DC-TO-DC-STEPDOWN-LM2596 | E21: 46015 | F21: 4973.93 | G21: 1124108.2 | H21: 226 | I21: 113 | J21: 75 | K21: 90 | L21: 45 | M21: 101 | N21: 125
D22: ITBISA-DC-TO-DC-STEPDOWN-XL4005 | E22: 46000 | F22: 8461.025 | G22: 1167621.4 | H22: 138 | I22: 69 | J22: 46 | K22: 55 | L22: 27 | M22: 67 | N22: 71
D23: ITBISA-DC-TO-DC-STEPDOWN-XL4015 | E23: 46015 | F23: 8384.9833 | G23: 1442217.1 | H23: 172 | I23: 86 | J23: 57 | K23: 68 | L23: 34 | M23: 119 | N23: 53
D24: ITBISA-DC-TO-DC-STEPUP-XL6009 | E24: 46022 | F24: 6910.9 | G24: 1921230.2 | H24: 278 | I24: 139 | J24: 92 | K24: 111 | L24: 55 | M24: 186 | N24: 92
D25: ITBISA-I2C-IIC-LCD | E25: 46022 | F25: 5617.6 | G25: 381996.8 | H25: 68 | I25: 34 | J25: 22 | K25: 27 | L25: 13 | M25: 31 | N25: 37
D26: ITBISA-IC-74HC595N-DIP16 | E26: 46022 | F26: 639.424 | G26: 2611407.6 | H26: 4084 | I26: 2042 | J26: 1361 | K26: 1633 | L26: 816 | M26: 14 | N26: 4070
D27: ITBISA-IC-ATMEGA328P-DIP28 | E27: 46015 | F27: 27318.462 | G27: 5190507.7 | H27: 190 | I27: 95 | J27: 63 | K27: 76 | L27: 38 | M27: 159 | N27: 31
D28: ITBISA-IC-CD4017BE-DIP16 | E28: 46016 | F28: 727.964 | G28: 3760662 | H28: 5166 | I28: 2583 | J28: 1722 | K28: 2066 | L28: 1033 | N28: 5166
D29: ITBISA-IC-CD4094BE-DIP16 | E29: 45709 | F29: 779.544 | G29: 7795440 | H29: 10000 | I29: 5000 | J29: 3333 | K29: 4000 | L29: 2000 | N29: 10000
D30: ITBISA-IC-CD4094BM-SMD-SOP16 | E30: 46020 | F30: 874.83483 | G30: 762855.98 | H30: 872 | I30: 436 | J30: 290 | K30: 348 | L30: 174 | M30: 494 | N30: 378
D31: ITBISA-IC-JRC4558D-DIP8 | E31: 46017 | F31: 552.98952 | G31: 1498048.6 | H31: 2709 | I31: 1354 | J31: 903 | K31: 1083 | L31: 541 | M31: 1000 | N31: 1709
D32: ITBISA-IC-L7805CV-TO220 | E32: 46013 | F32: 1140.7243 | G32: 5168622 | H32: 4531 | I32: 2265 | J32: 1510 | K32: 1812 | L32: 906 | M32: 932 | N32: 3599
D33: ITBISA-IC-L7812CV-TO220 | E33: 46019 | F33: 1057 | G33: 1144731 | H33: 1083 | I33: 541 | J33: 361 | K33: 433 | L33: 216 | M33: 802 | N33: 281
D34: ITBISA-IC-LM741CN-DIP8 | E34: 45965 | F34: 1291.1 | G34: 27113.1 | H34: 21 | I34: 10 | J34: 7 | K34: 8 | L34: 4 | N34: 21
D35: ITBISA-IC-NE555P-DIP8 | E35: 46022 | F35: 288.887 | G35: 1521567.8 | H35: 5267 | I35: 2633 | J35: 1755 | K35: 2106 | L35: 1053 | M35: 2992 | N35: 2275
D36: ITBISA-IC-PC817-DIP4 | E36: 46022 | F36: 340.3485 | G36: 1347099.4 | H36: 3958 | I36: 1979 | J36: 1319 | K36: 1583 | L36: 791 | M36: 1748 | N36: 2210
D37: ITBISA-IC-UA741CN-DIP8 | E37: 46022 | F37: 572 | G37: 2864004 | H37: 5007 | I37: 2503 | J37: 1669 | K37: 2002 | L37: 1001 | M37: 4619 | N37: 388
D38: ITBISA-IC-ULN2003AN-DIP16 | E38: 46021 | F38: 855.5 | G38: 2073732 | H38: 2424 | I38: 1212 | J38: 808 | K38: 969 | L38: 484 | M38: 1214 | N38: 1210
D39: ITBISA-IC-ULN2803APG-DIP18 | E39: 46021 | F39: 1018 | G39: 1344778 | H39: 1321 | I39: 660 | J39: 440 | K39: 528 | L39: 264 | M39: 423 | N39: 898
D40: ITBISA-IDC-2X5-AMPHENOL-FEMALE | E40: 46016 | F40: 730 | G40: 886950 | H40: 1215 | I40: 607 | J40: 405 | K40: 486 | L40: 243 | M40: 1021 | N40: 194
D41: ITBISA-IDC-2X5-AMPHENOL-MALE | E41: 46019 | F41: 585.402 | G41: 525105.59 | H41: 897 | I41: 448 | J41: 299 | K41: 358 | L41: 179 | M41: 412 | N41: 485
D42: ITBISA-INFRARED-1838 | E42: 46022 | F42: 607.75 | G42: 677641.25 | H42: 1115 | I42: 557 | J42: 371 | K42: 446 | L42: 223 | M42: 552 | N42: 563
D43: ITBISA-JACK-DC-005-FEMALE | E43: 46021 | F43: 325.97464 | G43: 828627.52 | H43: 2542 | I43: 1271 | J43: 847 | K43: 1016 | L43: 508 | M43: 344 | N43: 2198
D44: ITBISA-JUMPER-FF-10CM | E44: 46001 | F44: 165.045 | G44: 1201527.6 | H44: 7280 | I44: 3640 | J44: 2426 | K44: 2912 | L44: 1456 | M44: 5600 | N44: 1680
D45: ITBISA-JUMPER-FF-20CM | E45: 46002 | F45: 165.05558 | G45: 1188400.2 | H45: 7200 | I45: 3600 | J45: 2400 | K45: 2880 | L45: 1440 | M45: 3120 | N45: 4080
D46: ITBISA-JUMPER-MF-10CM | E46: 46017 | F46: 165.0465 | G46: 1366585 | H46: 8280 | I46: 4140 | J46: 2760 | K46: 3312 | L46: 1656 | M46: 5240 | N46: 3040
... D49: ITBISA-JUMPER-MM-20CM | E49: 46010 | F49: 187.38487 | G49: 989392.11 | H49: 5280 | I49: 2640 | J49: 1760 | K49: 2112 | L49: 1056 | M49: 2600 | N49: 2680
D50: ITBISA-KAPASITOR-ELCO-2200UF-25V | E50: 46011 | F50: 829.248 | G50: 386429.57 | H50: 466 | I50: 233 | J50: 155 | K50: 186 | L50: 93 | N50: 466
D51: ITBISA-LCD-16X2-BLUE | E51: 45994 | F51: 9482.4778 | G51: 1081002.5 | H51: 114 | I51: 57 | J51: 38 | K51: 45 | L51: 22 | M51: 23 | N51: 91
D52: ITBISA-LCD-16X2-GREEN | E52: 46019 | F52: 11443.12 | G52: 961222.08 | H52: 84 | I52: 42 | J52: 28 | K52: 33 | L52: 16 | M52: 24 | N52: 60
D53: ITBISA-LDR-GL5516 | E53: 45995 | F53: 285.14019 | G53: 145136.36 | H53: 509 | I53: 254 | J53: 169 | K53: 203 | L53: 101 | M53: 109 | N53: 400
D54: ITBISA-LED-MAX7219-4IN1-GAP | E54: 45505 | F54: 36500 | G54: 182500 | H54: 5 | I54: 2 | J54: 1 | K54: 2 | L54: 1 | M54: 5
D55: ITBISA-LED-MAX7219-4IN1-TIGHT | E55: 45970 | F55: 35799.38 | G55: 3257743.6 | H55: 91 | I55: 45 | J55: 30 | K55: 36 | L55: 18 | M55: 62 | N55: 29
D56: ITBISA-LED-SUPERBRIGHT-5MM-BLUE | E56: 46022 | F56: 58.82 | G56: 314510.54 | H56: 5347 | I56: 2673 | J56: 1782 | K56: 2138 | L56: 1069 | M56: 2690 | N56: 2657
D57: ITBISA-LED-SUPERBRIGHT-5MM-GREEN | E57: 46020 | F57: 64.35 | G57: 65379.6 | H57: 1016 | I57: 508 | J57: 338 | K57: 406 | L57: 203 | M57: 964 | N57: 52
D58: ITBISA-LED-SUPERBRIGHT-5MM-RED | E58: 46021 | F58: 52.64 | G58: 298942.56 | H58: 5679 | I58: 2839 | J58: 1893 | K58: 2271 | L58: 1135 | M58: 983 | N58: 4696
D59: ITBISA-LED-SUPERBRIGHT-5MM-WHITE | E59: 46022 | F59: 76.625 | G59: 221293 | H59: 2888 | I59: 1444 | J59: 962 | K59: 1155 | L59: 577 | M59: 2525 | N59: 363
D60: ITBISA-LED-SUPERBRIGHT-5MM-YELLOW | E60: 46021 | F60: 66.666667 | G60: 53733.333 | H60: 806 | I60: 403 | J60: 268 | K60: 322 | L60: 161 | M60: 490 | N60: 316
D61: ITBISA-NODEMCU-V3-CH340G-ESP8266-MICRO | E61: 46000 | F61: 23261.029 | G61: 7210918.9 | H61: 310 | I61: 155 | J61: 103 | K61: 124 | L61: 62 | M61: 119 | N61: 191
D62: ITBISA-NPN-2N2222-TO92 | E62: 46008 | F62: 106.37111 | G62: 1076369.3 | H62: 10119 | I62: 5059 | J62: 3373 | K62: 4047 | L62: 2023 | M62: 1825 | N62: 8294
D63: ITBISA-NPN-2N3904-TO92 | E63: 45858 | F63: 106.34091 | G63: 240330.45 | H63: 2260 | I63: 1130 | J63: 753 | K63: 904 | L63: 452 | M63: 1070 | N63: 1190
D64: ITBISA-NPN-2N5551-TO92 | F64: 106.43167 | G64: 127718 | H64: 1200 | I64: 600 | J64: 400 | K64: 480 | L64: 240 | M64: 200 | N64: 1000
D65: ITBISA-NPN-BC337-TO92 | E65: 45846 | F65: 106.44013 | G65: 236616.42 | H65: 2223 | I65: 1111 | J65: 741 | K65: 889 | L65: 444 | M65: 1490 | N65: 733
D66: ITBISA-NPN-BC547-TO92 | E66: 46013 | F66: 106.34091 | G66: 387612.61 | H66: 3645 | I66: 1822 | J66: 1215 | K66: 1458 | L66: 729 | M66: 1804 | N66: 1841
D67: ITBISA-NPN-BC548-TO92 | E67: 45735 | F67: 110.3035 | G67: 135673.3 | H67: 1230 | I67: 615 | J67: 410 | K67: 492 | L67: 246 | M67: 1080 | N67: 150
D68: ITBISA-NPN-S9013-TO92 | F68: 106.34091 | G68: 106340.91 | H68: 1000 | I68: 500 | J68: 333 | K68: 400 | L68: 200 | N68: 1000
D69: ITBISA-PCB-5X7-COPPER-SINGLE-SIDE | E69: 46020 | F69: 969.334 | G69: 451709.64 | H69: 466 | I69: 233 | J69: 155 | K69: 186 | L69: 93 | M69: 75 | N69: 391
D70: ITBISA-PIN-HEADER-MALE-1X40PIN-L-SAMA | E70: 45953 | F70: 726.09333 | G70: 12343.587 | H70: 17 | I70: 8 | J70: 5 | K70: 6 | L70: 3 | M70: 17
D71: ITBISA-PIN-HEADER-MALE-1X40PIN-LURUS | E71: 46010 | F71: 315 | G71: 460845 | H71: 1463 | I71: 731 | J71: 487 | K71: 585 | L71: 292 | M71: 794 | N71: 669
D72: ITBISA-PNP-2N3906-TO92 | E72: 45947 | F72: 106.34091 | G72: 126013.98 | H72: 1185 | I72: 592 | J72: 395 | K72: 474 | L72: 237 | M72: 90 | N72: 1095
D73: ITBISA-PNP-2N5401-TO92 | F73: 106.28633 | G73: 175372.45 | H73: 1650 | I73: 825 | J73: 550 | K73: 660 | L73: 330 | M73: 1000 | N73: 650
D74: ITBISA-PNP-A1015-TO92 | F74: 106.28633 | G74: 212572.67 | H74: 2000 | I74: 1000 | J74: 666 | K74: 800 | L74: 400 | M74: 1000 | N74: 1000
D75: ITBISA-PNP-BC557-TO92 | E75: 45830 | F75: 106.34091 | G75: 219913 | H75: 2068 | I75: 1034 | J75: 689 | K75: 827 | L75: 413 | M75: 1000 | N75: 1068
D76: ITBISA-PNP-BC558-TO92 | E76: 46013 | F76: 106.32267 | G76: 157357.55 | H76: 1480 | I76: 740 | J76: 493 | K76: 592 | L76: 296 | M76: 480 | N76: 1000
D77: ITBISA-PNP-S8550-TO92 | E77: 45981 | F77: 106.34083 | G77: 145686.94 | H77: 1370 | I77: 685 | J77: 456 | K77: 548 | L77: 274 | M77: 400 | N77: 970
D78: ITBISA-PNP-S9012-TO92 | E78: 45958 | F78: 106.34091 | G78: 85072.727 | H78: 800 | I78: 400 | J78: 266 | K78: 320 | L78: 160 | N78: 800
D79: ITBISA-RAPID-BOHLAM-E10-2.5V-SCREW | E79: 46021 | F79: 640.66667 | G79: 784176 | H79: 1224 | I79: 612 | J79: 408 | K79: 489 | L79: 244 | M79: 103 | N79: 1121
D80: ITBISA-RAPID-BOHLAM-E10-3.8V-SCREW | E80: 46022 | F80: 559.962 | G80: 461408.69 | H80: 824 | I80: 412 | J80: 274 | K80: 329 | L80: 164 | N80: 824
D81: ITBISA-RELAY-12V-4PIN-BLUE | E81: 46019 | F81: 1637 | G81: 482915 | H81: 295 | I81: 147 | J81: 98 | K81: 118 | L81: 59 | M81: 295
D82: ITBISA-RELAY-12V-5PIN-BLUE | E82: 46016 | F82: 1980.5 | G82: 340646 | H82: 172 | I82: 86 | J82: 57 | K82: 68 | L82: 34 | M82: 171 | N82: 1
D83: ITBISA-RELAY-5V-1CHANNEL-BLUE-LOW-TRIGGER | E83: 46017 | F83: 4252.52 | G83: 229636.08 | H83: 54 | I83: 27 | J83: 18 | K83: 21 | L83: 10 | M83: 47 | N83: 7
D84: ITBISA-RELAY-5V-4PIN-BLUE | E84: 46022 | F84: 1637 | G84: 2617563 | H84: 1599 | I84: 799 | J84: 533 | K84: 639 | L84: 319 | M84: 1254 | N84: 345
D85: ITBISA-RELAY-5V-5PIN-BLUE | E85: 46021 | F85: 1980.3073 | G85: 3756642.9 | H85: 1897 | I85: 948 | J85: 632 | K85: 758 | L85: 379 | M85: 930 | N85: 967
D86: ITBISA-RESISTOR-100K-1/4W | E86: 46002 | F86: 19.957222 | G86: 142973.54 | H86: 7164 | I86: 3582 | J86: 2388 | K86: 2865 | L86: 1432 | M86: 900 | N86: 6264
D87: ITBISA-RESISTOR-10K-1/4W | E87: 46018 | F87: 19.957222 | G87: 87272.933 | H87: 4373 | I87: 2186 | J87: 1457 | K87: 1749 | L87: 874 | M87: 1585 | N87: 2788
D88: ITBISA-RESISTOR-120K-1/4W | F88: 17.44 | G88: 17440 | H88: 1000 | I88: 500 | J88: 333 | K88: 400 | L88: 200 | M88: 1000
D89: ITBISA-RESISTOR-12K-1/4W | F89: 17.44 | G89: 17440 | H89: 1000 | I89: 500 | J89: 333 | K89: 400 | L89: 200 | M89: 1000
D90: ITBISA-RESISTOR-150K-1/4W | F90: 15.589875 | G90: 15589.875 | H90: 1000 | I90: 500 | J90: 333 | K90: 400 | L90: 200 | M90: 1000
D91: ITBISA-RESISTOR-15K-1/4W | E91: 45997 | F91: 15.589875 | G91: 87428.019 | H91: 5608 | I91: 2804 | J91: 1869 | K91: 2243 | L91: 1121 | M91: 1890 | N91: 3718
D92: ITBISA-RESISTOR-18K-1/4W | E92: 45965 | F92: 19.957222 | G92: 79629.317 | H92: 3990 | I92: 1995 | J92: 1330 | K92: 1596 | L92: 798 | M92: 1000 | N92: 2990
D93: ITBISA-RESISTOR-1K-1/4W | E93: 46006 | F93: 17.44 | G93: 40984 | H93: 2350 | I93: 1175 | J93: 783 | K93: 940 | L93: 470 | M93: 1270 | N93: 1080
D94: ITBISA-RESISTOR-1M-1/4W | F94: 17.44 | G94: 17440 | H94: 1000 | I94: 500 | J94: 333 | K94: 400 | L94: 200 | M94: 1000
D95: ITBISA-RESISTOR-220-1/4W | E95: 46015 | F95: 21.1651 | G95: 96047.224 | H95: 4538 | I95: 2269 | J95: 1512 | K95: 1815 | L95: 907 | M95: 4562 | N95: -24
D96: ITBISA-RESISTOR-22K-1/4W | E96: 46017 | F96: 15.589875 | G96: 123440.63 | H96: 7918 | I96: 3959 | J96: 2639 | K96: 3167 | L96: 1583 | M96: 1960 | N96: 5958
D97: ITBISA-RESISTOR-270-1/4W | E97: 45957 | F97: 21.1651 | G97: 105719.67 | H97: 4995 | I97: 2497 | J97: 1665 | K97: 1998 | L97: 999 | M97: 4995
D98: ITBISA-RESISTOR-270K-1/4W | E98: 46002 | F98: 15.589875 | G98: 61969.753 | H98: 3975 | I98: 1987 | J98: 1325 | K98: 1590 | L98: 795 | M98: 1000 | N98: 2975
D99: ITBISA-RESISTOR-27K-1/4W | E99: 45991 | F99: 19.957222 | G99: 89687.757 | H99: 4494 | I99: 2247 | J99: 1498 | K99: 1797 | L99: 898 | M99: 1000 | N99: 3494
D100: ITBISA-RESISTOR-2K2-1/4W | E100: 46017 | F100: 17.6305 | G100: 89016.395 | H100: 5049 | I100: 2524 | J100: 1683 | K100: 2019 | L100: 1009 | M100: 870 | N100: 4179
D101: ITBISA-RESISTOR-2K7-1/4W | E101: 45987 | F101: 15.589875 | G101: 77481.679 | H101: 4970 | I101: 2485 | J101: 1656 | K101: 1988 | L101: 994 | M101: 1980 | N101: 2990
D102: ITBISA-RESISTOR-330-1/4W | E102: 45997 | F102: 21.726667 | G102: 92533.873 | H102: 4259 | I102: 2129 | J102: 1419 | K102: 1703 | L102: 851 | M102: 1289 | N102: 2970
...

Sheet BisaPindahBarang
A1: Tanggal | B1: SKU | C1: Lokasi Penambahan Barang | D1: Lokasi Pengurangan Barang | E1: Banyak Barang | F1: Keterangan
A3: 43595 | B3: ITBISA-7SEGMENT-ANODE-RED-0.56-1BIT | C3: AVRG ITB | D3: RUMAH SYAFIRA | E3: 1100
A4: 43595 | B4: ITBISA-7SEGMENT-ANODE-RED-2.30-1BIT | C4: AVRG ITB | D4: RUMAH MUZAKKI | E4: 10
A5: 43595 | B5: ITBISA-7SEGMENT-CATHODE-RED-0.56-1BIT | C5: AVRG ITB | D5: RUMAH SYAFIRA | E5: 750
A6: 43595 | B6: ITBISA-7SEGMENT-CATHODE-RED-0.56-1BIT | C6: AVRG ITB | D6: WARUNG IBU | E6: 150
A7: 43595 | B7: ITBISA-ABC-BATERAI-D-BIRU | C7: AVRG ITB | E7: 60
A8: 43595 | B8: ITBISA-ABC-BATERAI-D-POWER | C8: AVRG ITB | D8: RUMAH MUZAKKI | E8: 40
A9: 43595 | B9: ITBISA-ABC-BATERAI-D-POWER | C9: AVRG ITB | D9: WARUNG IBU | E9: 60
A10: 43595 | B10: ITBISA-ARDUINO-UNO-R3-328P-SMD | C10: AVRG ITB | D10: RUMAH MUZAKKI | E10: 7
A11: 43595 | B11: ITBISA-USB-A-TO-B-30CM | C11: AVRG ITB | D11: RUMAH MUZAKKI | E11: 7
A12: 43595 | B12: ITBISA-ARDUINO-UNO-R3-328P-SMD | C12: AVRG ITB | D12: RUMAH MUZAKKI | E12: 3
A13: 43595 | B13: ITBISA-USB-A-TO-B-30CM | C13: AVRG ITB | D13: RUMAH MUZAKKI | E13: 3
A14: 43595 | B14: ITBISA-ARDUINO-UNO-R3-328P-SMD | C14: AVRG ITB | D14: RUMAH MUZAKKI | E14: 13
A15: 43595 | B15: ITBISA-USB-A-TO-B-50CM | C15: AVRG ITB | D15: RUMAH MUZAKKI | E15: 13
A16: 43595 | B16: ITBISA-EPSON-L310 | C16: AVRG ITB | D16: RUMAH MUZAKKI | E16: 1
A17: 43595 | B17: ITBISA-IC-NE555P-DIP8 | C17: AVRG ITB | D17: WARUNG IBU | E17: 4900
A18: 43595 | B18: ITBISA-IC-NE555P-DIP8 | C18: AVRG ITB | D18: RUMAH MUZAKKI | E18: 1500
A19: 43595 | B19: ITBISA-IC-UA741CN-DIP8 | C19: AVRG ITB | D19: RUMAH SYAFIRA | E19: 1500
... A254: 45004 | B254: ITBISA-IC-CD4017BE-DIP16 | C254: KERTASARI CIAMIS | D254: KYAI KONTONG | E254: 1000
A255: 45004 | B255: ITBISA-7SEGMENT-ANODE-RED-0.56-1BIT | C255: KERTASARI CIAMIS | D255: KYAI KONTONG | E255: =5*150 -> 750
A256: 45004 | B256: ITBISA-7SEGMENT-CATHODE-RED-0.56-1BIT | C256: KERTASARI CIAMIS | D256: KYAI KONTONG | E256: =7*150 -> 1050
A257: 45004 | B257: ITBISA-IC-L7805CV-TO220 | C257: KERTASARI CIAMIS | D257: KYAI KONTONG | E257: 1000
A258: 45050 | B258: ITBISA-7SEGMENT-CATHODE-RED-0.56-1BIT | C258: KYAI KONTONG | D258: KERTASARI CIAMIS | E258: 4
A259: 45056 | B259: ITBISA-IC-CD4017BE-DIP16 | C259: KYAI KONTONG | D259: KERTASARI CIAMIS | E259: 100
A260: 45058 | B260: ITBISA-IC-NE555P-DIP8 | C260: KYAI KONTONG | D260: KERTASARI CIAMIS | E260: 100
A261: 45058 | B261: ITBISA-IC-CD4017BE-DIP16 | C261: KYAI KONTONG | D261: KERTASARI CIAMIS | E261: 100
A262: 45081 | B262: ITBISA-IC-CD4017BE-DIP16 | C262: KYAI KONTONG | D262: KERTASARI CIAMIS | E262: 23
A263: 45081 | B263: ITBISA-IC-NE555P-DIP8 | C263: KYAI KONTONG | D263: KERTASARI CIAMIS | E263: 100
A264: 45122 | B264: ITBISA-7SEGMENT-CATHODE-RED-0.56-1BIT | C264: KYAI KONTONG | D264: KERTASARI CIAMIS | E264: 60
A265: 45146 | B265: ITBISA-SOCKET-IC-DIP8-NARROW | C265: KYAI KONTONG | D265: KERTASARI CIAMIS | E265: 17
A266: 45192 | B266: ITBISA-IC-CD4094BE-DIP16 | C266: KERTASARI CIAMIS | D266: KYAI KONTONG | E266: 1000
A268: 45201.625 | B268: ITBISA-IC-NE555P-DIP8 | C268: KYAI KONTONG | D268: KERTASARI CIAMIS | E268: 50
A269: 45201.625 | B269: ITBISA-IC-74HC595N-DIP16 | C269: KYAI KONTONG | D269: KERTASARI CIAMIS | E269: 75
... A272: 45201.625 | B272: ITBISA-7SEGMENT-ANODE-RED-0.56-1BIT | C272: KERTASARI CIAMIS | D272: KYAI KONTONG | E272: 118
A273: 45203.751 | B273: ITBISA-IC-74HC245N-DIP20 | C273: KERTASARI CIAMIS | D273: KYAI KONTONG | E273: 720 | F273: INV/20231004/MPL/3492512198 Pindah 720 x 74HC245N ke Ciamis
A274: 45203.754 | B274: ITBISA-IC-UA741CN-DIP8 | C274: KERTASARI CIAMIS | D274: KYAI KONTONG | E274: 2000 | F274: INV/20231004/MPL/3492517923 Pindah 2000 x UA741CN ke Ciamis
A275: 45215.532 | B275: ITBISA-IC-74HC595N-DIP16 | C275: KYAI KONTONG | D275: KERTASARI CIAMIS | E275: 670 | F275: 2310163W3KVQHW Pengiriman 670 x 74HC595N ke Irkham Elektronik
A276: 45227.589 | B276: ITBISA-IC-CD4094BM-SMD-SOP16 | C276: KERTASARI CIAMIS | D276: KYAI KONTONG | E276: 2500
A277: 45227.589 | B277: ITBISA-7SEGMENT-ANODE-RED-0.56-1BIT | C277: KERTASARI CIAMIS | D277: KYAI KONTONG | E277: 300
A278: 45228.85 | B278: ITBISA-7SEGMENT-ANODE-RED-0.56-1BIT | C278: KERTASARI CIAMIS | D278: KYAI KONTONG | E278: 450
A280: 45241.739 | B280: ITBISA-NPN-2N2222-TO92 | C280: KERTASARI CIAMIS | D280: KYAI KONTONG | E280: 10000 | F280: INV/20231111/MPL/3559874484 - 10000 x 2N2222 - ITBisa Jakarta - ITBisa Ciamis
A281: 45241.739 | B281: ITBISA-IC-74HC595N-DIP16 | C281: KERTASARI CIAMIS | D281: KYAI KONTONG | E281: 1000 | F281: INV/20231111/MPL/3559916808 - 1000 x 74HC595N - ITBisa Jakarta - ITBisa Ciamis
A282: 45241.739 | B282: ITBISA-IC-74HC595N-DIP16 | C282: KERTASARI CIAMIS | D282: KYAI KONTONG | E282: 57 | F282: INV/20231111/MPL/3560075456 - 57 x 74HC595N - Jakarta - Fajar Yunianto - Yogya
A283: 45241.739 | B283: ITBISA-ABC-BATERAI-AAA-ALKALINE | C283: KERTASARI CIAMIS | D283: KYAI KONTONG | E283: =1*6*12 -> 72 | F283: INV/20231111/MPL/3560086461 - 72 PCS ABC Alkaline AA + 72PCS ABC Alkaline AAA - ITBisa Jakarta - ITBisa Ciamis
A284: 45241.739 | B284: ITBISA-ABC-BATERAI-AA-ALKALINE | C284: KERTASARI CIAMIS | D284: KYAI KONTONG | E284: 144 | F284: INV/20231111/MPL/3560096132 - 72 PCS ABC Alkaline AA + 12 Baterai 9V - ITBisa Jakarta - ITBisa Ciamis
A285: 45241.739 | B285: ITBISA-ABC-BATERAI-9V-POWER | C285: KERTASARI CIAMIS | D285: KYAI KONTONG | E285: =1*12 -> 12 | F285: INV/20231111/MPL/3560096132 - 72 PCS ABC Alkaline AA + 12 Baterai 9V - ITBisa Jakarta - ITBisa Ciamis
A287: 45252.447 | B287: ITBISA-7SEGMENT-ANODE-RED-1.20-1BIT | C287: KERTASARI CIAMIS | D287: KYAI KONTONG | E287: =3*100*3 -> 900 | F287: INV/20231120/MPL/3575727611 - 900 x 1.2 Inch CA + 594 x 1.2 Inch CC - ITBisa Jakarta - ITBisa Ciamis
A288: 45252.447 | B288: ITBISA-7SEGMENT-CATHODE-RED-1.20-1BIT | C288: KERTASARI CIAMIS | D288: KYAI KONTONG | E288: =3*99*2 -> 594 | F288: INV/20231120/MPL/3575727611 - 900 x 1.2 Inch CA + 594 x 1.2 Inch CC - ITBisa Jakarta - ITBisa Ciamis
A290: 45266.451 | B290: ITBISA-7SEGMENT-ANODE-RED-0.56-1BIT | C290: KERTASARI CIAMIS | D290: KYAI KONTONG | E290: 1350
A291: 45266.452 | B291: ITBISA-7SEGMENT-CATHODE-RED-0.56-1BIT | C291: KERTASARI CIAMIS | D291: KYAI KONTONG | E291: 1350
A292: 45266.452 | B292: ITBISA-ABC-BATERAI-9V-POWER | C292: KERTASARI CIAMIS | D292: KYAI KONTONG | E292: 24
A293: 45266.452 | B293: ITBISA-ARDUINO-UNO-R3-328P-SMD | C293: KERTASARI CIAMIS | D293: KYAI KONTONG | E293: 21
A294: 45271.731 | B294: ITBISA-IC-L7805CV-TO220 | C294: KERTASARI CIAMIS | D294: KYAI KONTONG | E294: 2000
A295: 45271.731 | B295: ITBISA-IC-CD4017BE-DIP16 | C295: KERTASARI CIAMIS | D295: KYAI KONTONG | E295: 3000
A296: 45290.438 | B296: ITBISA-ARDUINO-UNO-R3-328P-SMD | C296: KERTASARI CIAMIS | D296: KYAI KONTONG | E296: 49
A297: 45290.438 | B297: ITBISA-USB-A-TO-B-30CM | C297: KERTASARI CIAMIS | D297: KYAI KONTONG | E297: 100
A298: 45290.438 | B298: ITBISA-IC-L7812CV-TO220 | C298: KERTASARI CIAMIS | D298: KYAI KONTONG | E298: 1000
A299: 45290.438 | B299: ITBISA-IC-L7805CV-TO220 | C299: KERTASARI CIAMIS | D299: KYAI KONTONG | E299: 2000
A300: 45290.438 | B300: ITBISA-IC-CD4094BE-DIP16 | C300: KERTASARI CIAMIS | D300: KYAI KONTONG | E300: 1000
A302: 45308.708 | B302: ITBISA-IC-74HC245N-DIP20 | C302: RANCAEKEK ESTU | D302: KYAI KONTONG | E302: =4*720 -> 2880
A303: 45308.708 | B303: ITBISA-IC-UA741CN-DIP8 | C303: RANCAEKEK ESTU | D303: KYAI KONTONG | E303: 4000
A304: 45308.708 | B304: ITBISA-IC-CD4017BE-DIP16 | C304: RANCAEKEK ESTU | D304: KYAI KONTONG | E304: 4000
A305: 45308.708 | B305: ITBISA-7SEGMENT-CATHODE-RED-0.56-1BIT | C305: RANCAEKEK ESTU | D305: KYAI KONTONG | E305: =42*150 -> 6300
A306: 45311.417 | B306: ITBISA-SERVO-SG90-180DEG | C306: KERTASARI CIAMIS | D306: KYAI KONTONG | E306: 75
A307: 45311.417 | B307: ITBISA-SERVO-SG90-360DEG | C307: KERTASARI CIAMIS | D307: KYAI KONTONG | E307: 75
A308: 45311.417 | B308: ITBISA-BREADBOARD-830HOLE-MB102 | C308: KERTASARI CIAMIS | D308: KYAI KONTONG | E308: 83
A309: 45311.417 | B309: ITBISA-RTC-DS3231SN | C309: KERTASARI CIAMIS | D309: KYAI KONTONG | E309: 100
A310: 45311.417 | B310: ITBISA-7SEGMENT-ANODE-RED-1.20-1BIT | C310: KERTASARI CIAMIS | D310: KYAI KONTONG | E310: 256
A311: 45311.417 | B311: ITBISA-ABC-BATERAI-AA-ALKALINE | C311: KERTASARI CIAMIS | D311: KYAI KONTONG | E311: 192
A313: 45318.675 | B313: ITBISA-7SEGMENT-ANODE-RED-0.56-1BIT | C313: KERTASARI CIAMIS | D313: KYAI KONTONG | E313: 3 | F313: Adjustment
A314: 45318.675 | B314: ITBISA-IC-74HC595N-DIP16 | C314: KERTASARI CIAMIS | D314: KYAI KONTONG | E314: 700 | F314: Adjustment
A315: 45318.675 | B315: ITBISA-IC-L7805CV-TO220 | C315: KYAI KONTONG | D315: KERTASARI CIAMIS | E315: 100 | F315: Adjustment
A316: 45319.687 | B316: ITBISA-IC-74HC595N-DIP16 | C316: KERTASARI CIAMIS | D316: KYAI KONTONG | E316: 50 | F316: INV/20240128/MPL/3705906481 Fajar 50 x 74HC595N dari Jakarta
A318: 45329.596 | B318: ITBISA-SOCKET-IC-DIP8-NARROW | C318: RANCAEKEK ESTU | D318: KYAI KONTONG | E318: =5*6*60 -> 1800
A319: 45329.845 | B319: ITBISA-NPN-2N2222-TO92 | C319: RANCAEKEK ESTU | D319: KYAI KONTONG | E319: 8000
A320: 45329.644 | B320: ITBISA-SOCKET-IC-DIP8-NARROW | C320: KERTASARI CIAMIS | D320: KYAI KONTONG | E320: =43*60 -> 2580
A321: 45329.644 | B321: ITBISA-7SEGMENT-ANODE-RED-1.00-1BIT | C321: KERTASARI CIAMIS | D321: KYAI KONTONG | E321: 450
A323: 45334.452 | B323: ITBISA-IC-UA741CN-DIP8 | C323: KERTASARI CIAMIS | D323: KYAI KONTONG | E323: 2000
A324: 45334.452 | B324: ITBISA-IC-NE555P-DIP8 | C324: KERTASARI CIAMIS | D324: KYAI KONTONG | E324: 5000
A325: 45334.452 | B325: ITBISA-IC-ULN2003AN-DIP16 | C325: KERTASARI CIAMIS | D325: KYAI KONTONG | E325: 1000
A326: 45334.452 | B326: ITBISA-IC-L7812CV-TO220 | C326: KERTASARI CIAMIS | D326: KYAI KONTONG | E326: 1000
A327: 45334.452 | B327: ITBISA-IC-CD4094BE-DIP16 | C327: KERTASARI CIAMIS | D327: KYAI KONTONG | E327: 1000
A328: 45334.452 | B328: ITBISA-7SEGMENT-ANODE-RED-0.56-1BIT | C328: KERTASARI CIAMIS | D328: KYAI KONTONG | E328: 150
A329: 45334.452 | B329: ITBISA-BREADBOARD-830HOLE-MB102 | C329: KERTASARI CIAMIS | D329: KYAI KONTONG | E329: 47
A330: 45338.625 | B330: ITBISA-ABC-BATERAI-D-POWER | C330: RANCAEKEK ESTU | D330: KYAI KONTONG | E330: 52
A331: 45338.625 | B331: ITBISA-IC-CD4017BE-DIP16 | C331: RANCAEKEK ESTU | D331: KYAI KONTONG | E331: 6000
A332: 45338.625 | B332: ITBISA-7SEGMENT-ANODE-RED-0.56-1BIT | C332: RANCAEKEK ESTU | D332: KYAI KONTONG | E332: 300
A333: 45338.625 | B333: ITBISA-BREADBOARD-830HOLE-MB102 | C333: RANCAEKEK ESTU | D333: KYAI KONTONG | E333: 30
... A335: 45338.625 | B335: ITBISA-ARDUINO-UNO-R3-328P-SMD | C335: RANCAEKEK ESTU | D335: KYAI KONTONG | E335: 10
A337: 45350.482 | B337: ITBISA-7SEGMENT-ANODE-RED-0.56-1BIT | C337: RANCAEKEK ESTU | D337: KERTASARI CIAMIS | E337: 300 | F337: INV/20240228/MPL/3763634991 Pengiriman 300 x CA 0.56 ke Moreno
A339: 45357.596 | B339: ITBISA-7SEGMENT-ANODE-RED-2.30-1BIT | C339: KERTASARI CIAMIS | D339: KYAI KONTONG | E339: 45
A340: 45357.596 | B340: ITBISA-7SEGMENT-CATHODE-RED-2.30-1BIT | C340: KERTASARI CIAMIS | D340: KYAI KONTONG | E340: 45
A341: 45357.596 | B341: ITBISA-ARDUINO-UNO-R3-328P-SMD | C341: KERTASARI CIAMIS | D341: KYAI KONTONG | E341: 97
A342: 45357.596 | B342: ITBISA-SERVO-SG90-180DEG | C342: KERTASARI CIAMIS | D342: KYAI KONTONG | E342: 75
A343: 45357.596 | B343: ITBISA-NODEMCU-V3-CH340G-ESP8266-MICRO | C343: KERTASARI CIAMIS | D343: KYAI KONTONG | E343: 80
A344: 45357.596 | B344: ITBISA-IC-L7805CV-TO220 | C344: KERTASARI CIAMIS | D344: KYAI KONTONG | E344: 1300
A345: 45369.697 | B345: ITBISA-ARDUINO-UNO-R3-328P-SMD | C345: RANCAEKEK ESTU | D345: KYAI KONTONG | E345: 50
A346: 45370.697 | B346: ITBISA-BREADBOARD-830HOLE-MB102 | C346: RANCAEKEK ESTU | D346: KERTASARI CIAMIS | E346: 8 | F346: 240319FQJRW4SQ Pengiriman 17 x Bandung + 8 x Ciamis
A348: 45389.5 | B348: ITBISA-USB-A-TO-B-30CM | C348: KERTASARI CIAMIS | D348: KYAI KONTONG | E348: 150 | F348: INV/20240407/MPL/3845895568 Pengiriman USB A to B 30 cm ke Ciamis
A349: 45389.502 | B349: ITBISA-TIGERHEAD-SENTER-KUNING-FT300 | C349: KERTASARI CIAMIS | D349: KYAI KONTONG | E349: 24 | F349: INV/20240407/MPL/3845898382 Pengiriman Senter Kuning Tigerhead ke Ciamis
...

Sheet BisaSEO
A1: SKU | B1: Kata Kunci Utama | C1: Jenis Barang | D1: Keterangan Barang (Ukuran, Warna) | E1: Fungsi Barang (Opsional) | F1: Typo | G1: BisaDivisi | H1: Massa (g) | I1: Tagar | J1: {={"Hitung Tagar";IF(I2:I974="",,LEN(I2:I974)-LEN(SUBSTITUTE(I2:I974,"#","")))}} -> Hitung Tagar | K1: {={"Nama Lengkap";IF(G2:G974="",, TRIM("ITBisa - "&IF(B2:B974="",,B2:B974)&" "&IF(C2:C974="",,C2:C974 )&" "&IF(D2:D974="",,D2:D974)& " "&IF(E2:E974="",,E2:E974)&" "&IF(F2:F974="",,F2:F974)))}} -> Nama Lengkap | L1: {={"Nama Tokopedia (70 Karakter)";IF(K2:K974="",,LEFT(TRIM(K2:K974),70))}} -> Nama Tokopedia (70 Karakter) | M1: {={"Nama Bukalapak (150 Karakter)";IF(K2:K974="",,LEFT(TRIM(K2:K974),150))}} -> Nama Bukalapak (150 Karakter) | N1: {={"Nama Shopee (255 Karakter)";IF(K2:K974="",,LEFT(TRIM(K2:K974),255))}} -> Nama Shopee (255 Karakter) | O1: Link Bukalapak | P1: Link Tokopedia | Q1: Link Shopee
A2: ITBISA-7SEGMENT-ANODE-RED-0.56-1BIT | B2: Seven 7 Segment | C2: CA Common Anode | D2: 0.56 Inch Red 1BIT | E2: LED Merah Display Jam Digital Nilai Sensor | F2: 7-Segment Anoda 0,56" Inci 0.56" 0.56inch 1 BIT | G2: BisaElektronika - BisaSegment | H2: 3 | I2: #ITBisa #BisaElektronika #BisaSegment #7Segment #Segment #CA #CC #Anode #Cathode #0.56 #LED #1BIT #Red #Arduino #Counter #Digital #IC #Mikrokontroler #Timer #Clock | J2: 20 | K2: ITBisa - Seven 7 Segment CA Common Anode 0.56 Inch Red 1BIT LED Merah Display Jam Digital Nilai Sensor 7-Segment Anoda 0,56" Inci 0.56" 0.56inch 1 BIT | L2: ITBisa - Seven 7 Segment CA Common Anode 0.56 Inch Red 1BIT LED Merah | M2: ITBisa - Seven 7 Segment CA Common Anode 0.56 Inch Red 1BIT LED Merah Display Jam Digital Nilai Sensor 7-Segment Anoda 0,56" Inci 0.56" 0.56inch 1 BIT | N2: ITBisa - Seven 7 Segment CA Common Anode 0.56 Inch Red 1BIT LED Merah Display Jam Digital Nilai Sensor 7-Segment Anoda 0,56" Inci 0.56" 0.56inch 1 BIT | O2: https://www.bukalapak.com/p/elektronik/komponen-elektronik/12cm7sr-jual-itbisa-7-segment-cc-common-katoda-0-56-inci-merah-1-bit-led-display-jam-digital-nilai-sensor-7-segment-seven-red-cathode-0-56inch-inch-1bit | P2: https://tokopedia.com/itbisa/itbisa-seven-7-segment-cc-common-cathode-0-56-inch-red-1bit-merah
A3: ITBISA-7SEGMENT-ANODE-RED-1.00-1BIT | B3: Seven 7 Segment | C3: CA Common Anode | D3: 1 Inch Red 1BIT | E3: LED Merah Display Jam Digital Nilai Sensor | F3: 7-Segment Anoda 1" Inch 1inch BIT | G3: BisaElektronika - BisaSegment | H3: 3 | K3: ITBisa - Seven 7 Segment CA Common Anode 1 Inch Red 1BIT LED Merah Display Jam Digital Nilai Sensor 7-Segment Anoda 1" Inch 1inch BIT | L3: ITBisa - Seven 7 Segment CA Common Anode 1 Inch Red 1BIT LED Merah Dis | M3: ITBisa - Seven 7 Segment CA Common Anode 1 Inch Red 1BIT LED Merah Display Jam Digital Nilai Sensor 7-Segment Anoda 1" Inch 1inch BIT | N3: ITBisa - Seven 7 Segment CA Common Anode 1 Inch Red 1BIT LED Merah Display Jam Digital Nilai Sensor 7-Segment Anoda 1" Inch 1inch BIT | O3: https://www.bukalapak.com/p/elektronik/komponen-elektronik/12cn11o-jual-itbisa-ic-ua741cn-dip-8-op-amp-filter-penguat-lpf-hpf-bpf-integrated-circuit-ua-741-ua741-op-amp-opamp-8-pin-kaki-dip8-8dip
A4: ITBISA-7SEGMENT-ANODE-RED-1.20-1BIT | B4: Seven 7 Segment | C4: CA Common Anode | D4: 1.2 Inch Red 1BIT | E4: LED Merah Display Jam Digital Nilai Sensor | F4: 7-Segment Anoda 1,2" Inci 1.2" 1.2inch 1 BIT | G4: BisaElektronika - BisaSegment | H4: 3 | I4: #ITBisa #BisaElektronika #BisaSegment #7Segment #Segment #CA #CC #Anode #Cathode #0.56 #LED #1BIT #Red #Arduino #Counter #Digital #IC #Mikrokontroler #Timer #Clock | J4: 20 | K4: ITBisa - Seven 7 Segment CA Common Anode 1.2 Inch Red 1BIT LED Merah Display Jam Digital Nilai Sensor 7-Segment Anoda 1,2" Inci 1.2" 1.2inch 1 BIT | L4: ITBisa - Seven 7 Segment CA Common Anode 1.2 Inch Red 1BIT LED Merah D | M4: ITBisa - Seven 7 Segment CA Common Anode 1.2 Inch Red 1BIT LED Merah Display Jam Digital Nilai Sensor 7-Segment Anoda 1,2" Inci 1.2" 1.2inch 1 BIT | N4: ITBisa - Seven 7 Segment CA Common Anode 1.2 Inch Red 1BIT LED Merah Display Jam Digital Nilai Sensor 7-Segment Anoda 1,2" Inci 1.2" 1.2inch 1 BIT
A5: ITBISA-7SEGMENT-ANODE-RED-2.30-1BIT | B5: Seven 7 Segment | C5: HS 23101 BS CA Anode Jam Masjid | D5: 2.30 Inch Red 1BIT | E5: LED Display Digital | F5: 7-Segment Anoda 2,3" Inci 2.3" 2.3inch 1 BIT | G5: BisaElektronika - BisaSegment | I5: #ITBisa #BisaElektronika #BisaSegment #7Segment #Segment #CA #CC #Anode #Cathode #0.56 #LED #1BIT #Red #Arduino #Counter #Digital #IC #Mikrokontroler #Timer #Clock | J5: 20 | K5: ITBisa - Seven 7 Segment HS 23101 BS CA Anode Jam Masjid 2.30 Inch Red 1BIT LED Display Digital 7-Segment Anoda 2,3" Inci 2.3" 2.3inch 1 BIT | L5: ITBisa - Seven 7 Segment HS 23101 BS CA Anode Jam Masjid 2.30 Inch Red | M5: ITBisa - Seven 7 Segment HS 23101 BS CA Anode Jam Masjid 2.30 Inch Red 1BIT LED Display Digital 7-Segment Anoda 2,3" Inci 2.3" 2.3inch 1 BIT | N5: ITBisa - Seven 7 Segment HS 23101 BS CA Anode Jam Masjid 2.30 Inch Red 1BIT LED Display Digital 7-Segment Anoda 2,3" Inci 2.3" 2.3inch 1 BIT
A6: ITBISA-7SEGMENT-CATHODE-RED-0.56-1BIT | B6: Seven 7 Segment | C6: CC Common Cathode | D6: 0.56 Inch Red 1BIT | E6: LED Merah Display Jam Digital Nilai Sensor | F6: 7-Segment Katoda 0,56" Inci 0.56" 0.56inch 1 BIT | G6: BisaElektronika - BisaSegment | H6: 3 | I6: #ITBisa #BisaElektronika #BisaSegment #7Segment #Segment #CA #CC #Anode #Cathode #0.56 #LED #1BIT #Red #Arduino #Counter #Digital #IC #Mikrokontroler #Timer #Clock | J6: 20 | K6: ITBisa - Seven 7 Segment CC Common Cathode 0.56 Inch Red 1BIT LED Merah Display Jam Digital Nilai Sensor 7-Segment Katoda 0,56" Inci 0.56" 0.56inch 1 BIT | L6: ITBisa - Seven 7 Segment CC Common Cathode 0.56 Inch Red 1BIT LED Mera | M6: ITBisa - Seven 7 Segment CC Common Cathode 0.56 Inch Red 1BIT LED Merah Display Jam Digital Nilai Sensor 7-Segment Katoda 0,56" Inci 0.56" 0.56inch 1 | N6: ITBisa - Seven 7 Segment CC Common Cathode 0.56 Inch Red 1BIT LED Merah Display Jam Digital Nilai Sensor 7-Segment Katoda 0,56" Inci 0.56" 0.56inch 1 BIT
A7: ITBISA-7SEGMENT-CATHODE-RED-1.00-1BIT | B7: Seven 7 Segment | C7: CC Common Cathode | D7: 1 Inch Red 1BIT | E7: LED Merah Display Jam Digital Nilai Sensor | F7: 7-Segment Katoda 1" Inch 1inch BIT | G7: BisaElektronika - BisaSegment | H7: 3 | K7: ITBisa - Seven 7 Segment CC Common Cathode 1 Inch Red 1BIT LED Merah Display Jam Digital Nilai Sensor 7-Segment Katoda 1" Inch 1inch BIT | L7: ITBisa - Seven 7 Segment CC Common Cathode 1 Inch Red 1BIT LED Merah D | M7: ITBisa - Seven 7 Segment CC Common Cathode 1 Inch Red 1BIT LED Merah Display Jam Digital Nilai Sensor 7-Segment Katoda 1" Inch 1inch BIT | N7: ITBisa - Seven 7 Segment CC Common Cathode 1 Inch Red 1BIT LED Merah Display Jam Digital Nilai Sensor 7-Segment Katoda 1" Inch 1inch BIT
A8: ITBISA-7SEGMENT-CATHODE-RED-1.20-1BIT | B8: Seven 7 Segment | C8: CC Common Cathode | D8: 1.2 Inch Red 1BIT | E8: LED Merah Display Jam Digital Nilai Sensor | F8: 7-Segment Katoda 1,2" Inci 1.2" 1.2inch 1 BIT | G8: BisaElektronika - BisaSegment | H8: 3 | I8: #ITBisa #BisaElektronika #BisaSegment #7Segment #Segment #CA #CC #Anode #Cathode #0.56 #LED #1BIT #Red #Arduino #Counter #Digital #IC #Mikrokontroler #Timer #Clock | J8: 20 | K8: ITBisa - Seven 7 Segment CC Common Cathode 1.2 Inch Red 1BIT LED Merah Display Jam Digital Nilai Sensor 7-Segment Katoda 1,2" Inci 1.2" 1.2inch 1 BIT | L8: ITBisa - Seven 7 Segment CC Common Cathode 1.2 Inch Red 1BIT LED Merah | M8: ITBisa - Seven 7 Segment CC Common Cathode 1.2 Inch Red 1BIT LED Merah Display Jam Digital Nilai Sensor 7-Segment Katoda 1,2" Inci 1.2" 1.2inch 1 BIT | N8: ITBisa - Seven 7 Segment CC Common Cathode 1.2 Inch Red 1BIT LED Merah Display Jam Digital Nilai Sensor 7-Segment Katoda 1,2" Inci 1.2" 1.2inch 1 BIT
A9: ITBISA-7SEGMENT-CATHODE-RED-2.30-1BIT
A10: ITBISA-ABC-BATERAI-9V-ALKALINE
A11: ITBISA-ABC-BATERAI-9V-POWER
A12: ITBISA-ABC-BATERAI-AA-ALKALINE
A13: ITBISA-ABC-BATERAI-AAA-ALKALINE
A14: ITBISA-ABC-BATERAI-D-ALKALINE
A15: ITBISA-ABC-BATERAI-D-BIRU | B15: Baterai ABC | C15: Standar 1,5 V | D15: Size D Biru | F15: Batre Biasa 1,5V 1.5V 1.5 Volt Ukuran D Warna Blue | G15: BisaOspek | H15: 100 | I15: #ITBisa #BisaOspek #BisaBaterai #Ospek #Baterai #ABC #D #Size #1.5V #Volt #Senter #Big #Jumbo #Power #Alkaline #Carbon #Zinc #Karbon #Galon #Jumbo | J15: 20 | K15: ITBisa - Baterai ABC Standar 1,5 V Size D Biru Batre Biasa 1,5V 1.5V 1.5 Volt Ukuran D Warna Blue | L15: ITBisa - Baterai ABC Standar 1,5 V Size D Biru Batre Biasa 1,5V 1.5V 1 | M15: ITBisa - Baterai ABC Standar 1,5 V Size D Biru Batre Biasa 1,5V 1.5V 1.5 Volt Ukuran D Warna Blue | N15: ITBisa - Baterai ABC Standar 1,5 V Size D Biru Batre Biasa 1,5V 1.5V 1.5 Volt Ukuran D Warna Blue | O15: https://www.bukalapak.com/p/elektronik/komponen-elektronik/163beu6-jual-itbisa-40pcs-kabel-jumper-10-cm-male-to-female-m-f-2-54-mm-merk-dupont-arduino-breadboard-40-pcs-buah-mf-m-f-pin-2-54mm-10cm-cable | P15: https://www.tokopedia.com/itbisa/itbisa-40pcs-kabel-jumper-10-cm-male-to-female-m-f-2-54-mm-mf-10cm | Q15: https://shopee.co.id/product/80492423/2291036855/
A16: ITBISA-ABC-BATERAI-D-POWER | B16: Baterai ABC Size D | C16: Super Power Heavy Duty DR20P | D16: 1.5V Jumbo Carbon Zinc Hitam | E16: Senter Pompa Galon | F16: Batre Jumbo Karbon Tipe D R20P Besar 1,5V 1.5V 1.5 Volt Type Ukuran D Warna Black | G16: BisaOspek | H16: 100 | I16: #ITBisa #BisaOspek #BisaBaterai #Ospek #Baterai #ABC #D #Size #1.5V #Volt #Senter #Big #Jumbo #Power #Alkaline #Carbon #Zinc #Karbon #Galon #Jumbo | J16: 20 | K16: ITBisa - Baterai ABC Size D Super Power Heavy Duty DR20P 1.5V Jumbo Carbon Zinc Hitam Senter Pompa Galon Batre Jumbo Karbon Tipe D R20P Besar 1,5V 1.5V 1.5 Volt Type Ukuran D Warna Black | L16: ITBisa - Baterai ABC Size D Super Power Heavy Duty DR20P 1.5V Jumbo Ca | M16: ITBisa - Baterai ABC Size D Super Power Heavy Duty DR20P 1.5V Jumbo Carbon Zinc Hitam Senter Pompa Galon Batre Jumbo Karbon Tipe D R20P Besar 1,5V 1.5 | N16: ITBisa - Baterai ABC Size D Super Power Heavy Duty DR20P 1.5V Jumbo Carbon Zinc Hitam Senter Pompa Galon Batre Jumbo Karbon Tipe D R20P Besar 1,5V 1.5V 1.5 Volt Type Ukuran D Warna Black | O16: https://www.bukalapak.com/p/elektronik/komponen-elektronik/1b2qbb9-jual-itbisa-transistor-bjt-npn-2n2222a-h331-to92-0-6a-30v-penguat-switch-transistors-2n2222-2n-2222-a-to-92-h-331-0-6-op-amp-switching-30-v-30volt | P16: https://www.tokopedia.com/itbisa/itbisa-transistor-bjt-npn-2n2222-a-2n2222a-h331-penguat-switch-to92 | Q16: https://shopee.co.id/product/80492423/2291143520/
A17: ITBISA-ABC-SENTER-LED-ALKALINE | B17: Senter ABC Alkaline | C17: LED Multifungsi | E17: Emergency Light | F17: Multifunction LED Lights | G17: BisaSenter | H17: 300 | I17: #ITBisa #BisaOspek #BisaSenter #Ospek #Baterai #ABC #AAA | J17: 7 | K17: ITBisa - Senter ABC Alkaline LED Multifungsi Emergency Light Multifunction LED Lights | L17: ITBisa - Senter ABC Alkaline LED Multifungsi Emergency Light Multifunc | M17: ITBisa - Senter ABC Alkaline LED Multifungsi Emergency Light Multifunction LED Lights | N17: ITBisa - Senter ABC Alkaline LED Multifungsi Emergency Light Multifunction LED Lights
A18: ITBISA-ARDUINO-UNO-R3-328P-SMD | B18: Arduino | C18: UNO R3 CH340G SMD ATMega328P | D18: Clone Only No Cable | E18: Mikrokontroler | F18: Tanpa Kabel USB ATMega328 AT Mega Kloning Duplikat Microcontroller | G18: BisaElektronika | K18: ITBisa - Arduino UNO R3 CH340G SMD ATMega328P Clone Only No Cable Mikrokontroler Tanpa Kabel USB ATMega328 AT Mega Kloning Duplikat Microcontroller | L18: ITBisa - Arduino UNO R3 CH340G SMD ATMega328P Clone Only No Cable Mikr | M18: ITBisa - Arduino UNO R3 CH340G SMD ATMega328P Clone Only No Cable Mikrokontroler Tanpa Kabel USB ATMega328 AT Mega Kloning Duplikat Microcontroller | N18: ITBisa - Arduino UNO R3 CH340G SMD ATMega328P Clone Only No Cable Mikrokontroler Tanpa Kabel USB ATMega328 AT Mega Kloning Duplikat Microcontroller
A19: ITBISA-ARDUINO-UNO-R3-CLONE-CABLE30CM | B19: Arduino | C19: UNO R3 CH340G SMD | D19: Clone Plus + USB Kabel 30CM Cable 30 CM ATMega328P | E19: Mikrokontroler | F19: ATMega328 AT Mega 328 P + Cable Kloning Duplikat Microcontroller | G19: BisaElektronika | K19: ITBisa - Arduino UNO R3 CH340G SMD Clone Plus + USB Kabel 30CM Cable 30 CM ATMega328P Mikrokontroler ATMega328 AT Mega 328 P + Cable Kloning Duplikat Microcontroller | L19: ITBisa - Arduino UNO R3 CH340G SMD Clone Plus + USB Kabel 30CM Cable 3 | M19: ITBisa - Arduino UNO R3 CH340G SMD Clone Plus + USB Kabel 30CM Cable 30 CM ATMega328P Mikrokontroler ATMega328 AT Mega 328 P + Cable Kloning Duplikat | N19: ITBisa - Arduino UNO R3 CH340G SMD Clone Plus + USB Kabel 30CM Cable 30 CM ATMega328P Mikrokontroler ATMega328 AT Mega 328 P + Cable Kloning Duplikat Microcontroller
A20: ITBISA-ARDUINO-UNO-R3-CLONE-CABLE50CM | B20: Arduino | C20: UNO R3 CH340G ATMega328P SMD | D20: Clone Plus USB Kabel 50CM | E20: Mikrokontroler | F20: ATMega328 AT Mega 328 P + Cable 50 cm Kloning Duplikat Microcontroller | G20: BisaElektronika | K20: ITBisa - Arduino UNO R3 CH340G ATMega328P SMD Clone Plus USB Kabel 50CM Mikrokontroler ATMega328 AT Mega 328 P + Cable 50 cm Kloning Duplikat Microcontroller | L20: ITBisa - Arduino UNO R3 CH340G ATMega328P SMD Clone Plus USB Kabel 50C | M20: ITBisa - Arduino UNO R3 CH340G ATMega328P SMD Clone Plus USB Kabel 50CM Mikrokontroler ATMega328 AT Mega 328 P + Cable 50 cm Kloning Duplikat Microcon | N20: ITBisa - Arduino UNO R3 CH340G ATMega328P SMD Clone Plus USB Kabel 50CM Mikrokontroler ATMega328 AT Mega 328 P + Cable 50 cm Kloning Duplikat Microcontroller
A21: ITBISA-BLUETOOTH-MODULE-HC05
A22: ITBISA-BREADBOARD-830HOLE-MB102
A23: ITBISA-BUBBLE-WRAP | O23: https://www.bukalapak.com/p/elektronik/komponen-elektronik/1p5d40c-jual-itbisa-40pcs-kabel-jumper-10-cm-female-to-female-f-f-2-54-mm-merk-dupont-arduino-breadboard-40-pcs-buah-ff-f-f-pin-2-54mm-10cm-cable | P23: https://www.tokopedia.com/itbisa/itbisa-40pcs-kabel-jumper-10-cm-female-to-female-f-f-2-54-mm-ff-10cm | Q23: https://shopee.co.id/product/80492423/2287703561/
A24: ITBISA-BUKAEMAS | O24: https://www.bukalapak.com/p/elektronik/komponen-elektronik/2aposh9-jual-itbisa-socket-ic-dip-8-2x4-narrow-soket-integrated-circuit-8-pin-kaki-lubang-datar-dip8-8dip | P24: https://tokopedia.com/itbisa/itbisa-socket-ic-dip-8-2x4-narrow-soket-dip8-8dip-8-dip-pin-kaki | Q24: https://shopee.co.id/product/80492423/2287659492/
A25: ITBISA-BUKAREKSA-BAHANA-MES-SYARIAH
A26: ITBISA-BUKAREKSA-CIMB-PRINCIPAL-PASAR-UANG
A27: ITBISA-BUKAREKSA-CIPTA-SYARIAH-BALANCE
A28: ITBISA-BUKAREKSA-MANDIRI-INVESTA-DANA-SYARIAH | O28: https://www.bukalapak.com/p/elektronik/komponen-elektronik/3ge7cl1-jual-itbisa-socket-ic-dip16-2x8-narrow-dip-16-pin-16p-soket-dip-16-2-54mm-2-54-mm-dudukan-16-lubang-16-dip-integrated-integrate-circuit-2-x-8-8x2-8-x-2 | P28: https://tokopedia.com/itbisa/itbisa-socket-ic-dip16-2x8-narrow-dip-16-pin-16p-soket-dip-16-2-54mm
A29: ITBISA-BUKAREKSA-MANDIRI-INVESTA-PASAR-UANG | O29: https://www.bukalapak.com/p/elektronik/komponen-elektronik/3t18497-jual-itbisa-40pcs-kabel-jumper-20-cm-male-to-male-m-m-mm-m-m-2-54mm-arduino-breadboard-40-pcs-20cm-buah-pin-2-54-mm-wire-cable-rainbow-pelangi-sensor | P29: https://tokopedia.com/itbisa/itbisa-40pcs-kabel-jumper-20-cm-male-to-male-m-m-2-54-mm-mm-m-m-20cm | Q29: https://shopee.co.id/product/80492423/4855244491/
A30: ITBISA-BUKAREKSA-SUCORINVEST-SHARIA-EQUITY-FUND | O30: https://www.bukalapak.com/p/elektronik/komponen-elektronik/3t187p8-jual-itbisa-40pcs-kabel-jumper-20-cm-female-to-female-f-f-ff-f-f-2-54mm-arduino-breadboard-40-pcs-20cm-buah-pin-2-54-mm-wire-cable-rainbow-pelangi-sensor | P30: https://www.tokopedia.com/itbisa/itbisa-40pcs-kabel-jumper-20-cm-female-to-female-f-f-2-54-mm-ff-20cm | Q30: https://shopee.co.id/product/80492423/5655241072/
A31: ITBISA-BUKAREKSA-SYARIAH-MANDIRI-PASAR-UANG | O31: https://www.bukalapak.com/p/elektronik/komponen-elektronik/vbuzpu-jual-itbisa-40pcs-kabel-jumper-10-cm-male-to-male-m-m-2-54-mm-merk-dupont-arduino-breadboard-40-pcs-buah-mm-m-m-pin-2-54mm-10cm-cable | P31: https://www.tokopedia.com/itbisa/itbisa-40pcs-kabel-jumper-10-cm-male-to-male-m-m-2-54-mm-mm-m-m-10cm | Q31: https://shopee.co.id/product/80492423/2291050648/
A32: ITBISA-BUZZER-ACTIVE-5V
A33: ITBISA-CHIP-ESP32-WROOM
A34: ITBISA-CHIP-ESP32-WROOM-ANTENNA
A35: ITBISA-CHIP-ESP8266-ESP12F
A36: ITBISA-CORSAIR-VENGEANCE-K66
A37: ITBISA-DC-TO-DC-STEPDOWN-LM2596 | P37: https://www.tokopedia.com/itbisa/itbisa-seven-7-segment-ca-common-anode-0-56-inch-red-1bit-led-merah
A38: ITBISA-DC-TO-DC-STEPDOWN-XL4005
A39: ITBISA-DC-TO-DC-STEPDOWN-XL4015
A40: ITBISA-DC-TO-DC-STEPUP-XL6009 | P40: https://tokopedia.com/itbisa/itbisa-baterai-abc-super-power-1-5-v-volt-size-d-hitam-carbon-zinc
A41: ITBISA-DIODE-1N4007
A42: ITBISA-EMLOCK-ACM-Y180
A43: ITBISA-EPSON-L310
A44: ITBISA-I2C-IIC-LCD
A45: ITBISA-IC-4N35-DIP6-BLACK | B45: IC 4N35 | C45: DIP-6 | D45: Black | E45: Optocoupler Photocoupler | F45: Phototransistor Optotransistor Putih DIP6 6DIP 6 Pin Kaki | G45: BisaElektronika - BisaIC | H45: 1 | I45: #ITBisa #BisaElektronika #BisaIC #Socket #IC #Switch #Transistor #LED #Sensor #Timer #Osilator #FlipFlop #DIP6 #DIP8 #DIP16 #Arduino #Breadboard #Mikrokontroler #Sensor #PCB | J45: 20 | K45: ITBisa - IC 4N35 DIP-6 Black Optocoupler Photocoupler Phototransistor Optotransistor Putih DIP6 6DIP 6 Pin Kaki | L45: ITBisa - IC 4N35 DIP-6 Black Optocoupler Photocoupler Phototransistor | M45: ITBisa - IC 4N35 DIP-6 Black Optocoupler Photocoupler Phototransistor Optotransistor Putih DIP6 6DIP 6 Pin Kaki | N45: ITBisa - IC 4N35 DIP-6 Black Optocoupler Photocoupler Phototransistor Optotransistor Putih DIP6 6DIP 6 Pin Kaki
A46: ITBISA-IC-4N35-DIP6-WHITE | B46: IC 4N35 | C46: DIP-6 | D46: White | E46: Optocoupler Photocoupler | F46: Phototransistor Optotransistor DIP6 6DIP 6 Pin Kaki | G46: BisaElektronika - BisaIC | H46: 1 | I46: #ITBisa #BisaElektronika #BisaIC #Socket #IC #Switch #Transistor #LED #Sensor #Timer #Osilator #FlipFlop #DIP6 #DIP8 #DIP16 #Arduino #Breadboard #Mikrokontroler #Sensor #PCB | J46: 20 | K46: ITBisa - IC 4N35 DIP-6 White Optocoupler Photocoupler Phototransistor Optotransistor DIP6 6DIP 6 Pin Kaki | L46: ITBisa - IC 4N35 DIP-6 White Optocoupler Photocoupler Phototransistor | M46: ITBisa - IC 4N35 DIP-6 White Optocoupler Photocoupler Phototransistor Optotransistor DIP6 6DIP 6 Pin Kaki | N46: ITBisa - IC 4N35 DIP-6 White Optocoupler Photocoupler Phototransistor Optotransistor DIP6 6DIP 6 Pin Kaki
A47: ITBISA-IC-74HC245N-DIP20 | B47: IC HC245N | C47: SN74HC245N | D47: DIP-20 | E47: Octal Bus Transceiver | F47: SN 74HC245N 74HC245 DIP20 20P 20 Pin Kaki Digital Buffer Parallel Data Transfer Transmission | G47: BisaElektronika - BisaIC | H47: 2 | I47: #ITBisa #BisaElektronika #BisaIC #Socket #IC #Shifter #Shift #Register #7Segment #Segment #LED #Counter #DIP6 #DIP8 #DIP16 #Arduino #Breadboard #Mikrokontroler #Sensor #PCB | J47: 20 | K47: ITBisa - IC HC245N SN74HC245N DIP-20 Octal Bus Transceiver SN 74HC245N 74HC245 DIP20 20P 20 Pin Kaki Digital Buffer Parallel Data Transfer Transmission | L47: ITBisa - IC HC245N SN74HC245N DIP-20 Octal Bus Transceiver SN 74HC245N | M47: ITBisa - IC HC245N SN74HC245N DIP-20 Octal Bus Transceiver SN 74HC245N 74HC245 DIP20 20P 20 Pin Kaki Digital Buffer Parallel Data Transfer Transmissio | N47: ITBisa - IC HC245N SN74HC245N DIP-20 Octal Bus Transceiver SN 74HC245N 74HC245 DIP20 20P 20 Pin Kaki Digital Buffer Parallel Data Transfer Transmission
A48: ITBISA-IC-74HC595N-DIP16 | B48: IC HC595N | C48: SN74HC595N | D48: DIP-16 | E48: 8 Stage Serial Shift Register | F48: SN 74HC595N 74HC595 DIP16 16P 16 Pin Kaki Serial to Parallel Paralel Conversion Output Latch | G48: BisaElektronika - BisaIC | H48: 2 | K48: ITBisa - IC HC595N SN74HC595N DIP-16 8 Stage Serial Shift Register SN 74HC595N 74HC595 DIP16 16P 16 Pin Kaki Serial to Parallel Paralel Conversion Output Latch | L48: ITBisa - IC HC595N SN74HC595N DIP-16 8 Stage Serial Shift Register SN | M48: ITBisa - IC HC595N SN74HC595N DIP-16 8 Stage Serial Shift Register SN 74HC595N 74HC595 DIP16 16P 16 Pin Kaki Serial to Parallel Paralel Conversion Out | N48: ITBisa - IC HC595N SN74HC595N DIP-16 8 Stage Serial Shift Register SN 74HC595N 74HC595 DIP16 16P 16 Pin Kaki Serial to Parallel Paralel Conversion Output Latch
A49: ITBISA-IC-78L05-TO92 | B49: IC 78L05 | C49: 7805 | D49: TO92 | E49: Positive Voltage Regulator 5V 0.1A | F49: L78L05 Positif 100mA TO 92 TO-92 5V 0.1 A 3 Terminal | G49: BisaElektronika - BisaIC | H49: 1 | I49: #ITBisa #BisaElektronika #BisaIC #Regulator #Voltage | J49: 5 | K49: ITBisa - IC 78L05 7805 TO92 Positive Voltage Regulator 5V 0.1A L78L05 Positif 100mA TO 92 TO-92 5V 0.1 A 3 Terminal | L49: ITBisa - IC 78L05 7805 TO92 Positive Voltage Regulator 5V 0.1A L78L05 | M49: ITBisa - IC 78L05 7805 TO92 Positive Voltage Regulator 5V 0.1A L78L05 Positif 100mA TO 92 TO-92 5V 0.1 A 3 Terminal | N49: ITBisa - IC 78L05 7805 TO92 Positive Voltage Regulator 5V 0.1A L78L05 Positif 100mA TO 92 TO-92 5V 0.1 A 3 Terminal
A50: ITBISA-IC-ATMEGA328P-DIP28
A51: ITBISA-IC-CD4017BE-DIP16 | B51: IC 4017 | C51: CD4017 CD4017BE | D51: DIP-16 | E51: Decade Counter Divider Digital | F51: DIP16 16P 16 Pin Kaki CMOS Latch CD 4017 BE Shifter Switch Clock Running LED Text | G51: BisaElektronika - BisaIC | H51: 2 | I51: #ITBisa #BisaElektronika #BisaIC #Socket #IC #Decade #Counter #Divider #Digital #Shifter #LED #CMOS #DIP6 #DIP8 #DIP16 #Arduino #Breadboard #Mikrokontroler #Sensor #PCB | J51: 20 | K51: ITBisa - IC 4017 CD4017 CD4017BE DIP-16 Decade Counter Divider Digital DIP16 16P 16 Pin Kaki CMOS Latch CD 4017 BE Shifter Switch Clock Running LED Text | L51: ITBisa - IC 4017 CD4017 CD4017BE DIP-16 Decade Counter Divider Digital | M51: ITBisa - IC 4017 CD4017 CD4017BE DIP-16 Decade Counter Divider Digital DIP16 16P 16 Pin Kaki CMOS Latch CD 4017 BE Shifter Switch Clock Running LED Te | N51: ITBisa - IC 4017 CD4017 CD4017BE DIP-16 Decade Counter Divider Digital DIP16 16P 16 Pin Kaki CMOS Latch CD 4017 BE Shifter Switch Clock Running LED Text
A52: ITBISA-IC-CD4094BE-DIP16 | B52: IC 4094 | C52: CD4094 BE CD4094BE | D52: DIP-16 | E52: Shift Register | F52: DIP16 16P 16 Pin Kaki 7 Segment 8 BIT 8BIT CD 4094 BE LED 7-Segment Latch CMOS 3 State Counter Output | G52: BisaElektronika - BisaIC | H52: 2 | I52: #ITBisa #BisaElektronika #BisaIC #Socket #IC #Shifter #Shift #Register #7Segment #Segment #LED #Counter #DIP6 #DIP8 #DIP16 #Arduino #Breadboard #Mikrokontroler #Sensor #PCB | J52: 20 | K52: ITBisa - IC 4094 CD4094 BE CD4094BE DIP-16 Shift Register DIP16 16P 16 Pin Kaki 7 Segment 8 BIT 8BIT CD 4094 BE LED 7-Segment Latch CMOS 3 State Counter Output | L52: ITBisa - IC 4094 CD4094 BE CD4094BE DIP-16 Shift Register DIP16 16P 16 | M52: ITBisa - IC 4094 CD4094 BE CD4094BE DIP-16 Shift Register DIP16 16P 16 Pin Kaki 7 Segment 8 BIT 8BIT CD 4094 BE LED 7-Segment Latch CMOS 3 State Count | N52: ITBisa - IC 4094 CD4094 BE CD4094BE DIP-16 Shift Register DIP16 16P 16 Pin Kaki 7 Segment 8 BIT 8BIT CD 4094 BE LED 7-Segment Latch CMOS 3 State Counter Output
A53: ITBISA-IC-CD4094BM-SMD-SOP16 | B53: IC 4094 | C53: SMD CD4094 BM CD4094BM | D53: SOP-16 | E53: Shift Register | F53: SOP16 16P 16 Pin Kaki 7 Segment 8 BIT 8BIT CD 4094 BM LED 7-Segment Latch CMOS 3 State Counter Output | G53: BisaElektronika - BisaIC | H53: 2 | I53: #ITBisa #BisaElektronika #BisaIC #Socket #IC #Shifter #Shift #Register #7Segment #Segment #LED #Counter #SOP6 #SOP8 #SOP16 #Arduino #Breadboard #Mikrokontroler #Sensor #PCB | J53: 20 | K53: ITBisa - IC 4094 SMD CD4094 BM CD4094BM SOP-16 Shift Register SOP16 16P 16 Pin Kaki 7 Segment 8 BIT 8BIT CD 4094 BM LED 7-Segment Latch CMOS 3 State Counter Output | L53: ITBisa - IC 4094 SMD CD4094 BM CD4094BM SOP-16 Shift Register SOP16 16 | M53: ITBisa - IC 4094 SMD CD4094 BM CD4094BM SOP-16 Shift Register SOP16 16P 16 Pin Kaki 7 Segment 8 BIT 8BIT CD 4094 BM LED 7-Segment Latch CMOS 3 State C | N53: ITBisa - IC 4094 SMD CD4094 BM CD4094BM SOP-16 Shift Register SOP16 16P 16 Pin Kaki 7 Segment 8 BIT 8BIT CD 4094 BM LED 7-Segment Latch CMOS 3 State Counter Output
A54: ITBISA-IC-CD4511BE-DIP16
A55: ITBISA-IC-JRC4558D-DIP8
A56: ITBISA-IC-L7805CV-TO220 | B56: IC L7805CV | C56: L7805 7805 CV 7805CV | D56: 3 Terminal TO-220 | E56: Linear Voltage Regulator 5V | F56: 5Volt 5 Volt Linier IC Power Supply Stabilizer TO220 TO 220 | G56: BisaElektronika - BisaIC | H56: 2 | I56: #ITBisa #BisaElektronika #BisaIC #Socket #IC #Shifter #Shift #Register #7Segment #Segment #LED #Counter #DIP6 #DIP8 #DIP16 #Arduino #Breadboard #Mikrokontroler #Sensor #PCB | J56: 20 | K56: ITBisa - IC L7805CV L7805 7805 CV 7805CV 3 Terminal TO-220 Linear Voltage Regulator 5V 5Volt 5 Volt Linier IC Power Supply Stabilizer TO220 TO 220 | L56: ITBisa - IC L7805CV L7805 7805 CV 7805CV 3 Terminal TO-220 Linear Volt | M56: ITBisa - IC L7805CV L7805 7805 CV 7805CV 3 Terminal TO-220 Linear Voltage Regulator 5V 5Volt 5 Volt Linier IC Power Supply Stabilizer TO220 TO 220 | N56: ITBisa - IC L7805CV L7805 7805 CV 7805CV 3 Terminal TO-220 Linear Voltage Regulator 5V 5Volt 5 Volt Linier IC Power Supply Stabilizer TO220 TO 220
A57: ITBISA-IC-L7809CV-TO220 | B57: IC L7809CV | C57: L7809 7809 CV 7809CV | D57: 3 Terminal TO-220 | E57: Linear Voltage Regulator 5V | F57: 5Volt 5 Volt Linier IC Power Supply Stabilizer TO220 TO 220 | G57: BisaElektronika - BisaIC | H57: 2 | I57: #ITBisa #BisaElektronika #BisaIC #Socket #IC #Shifter #Shift #Register #7Segment #Segment #LED #Counter #DIP6 #DIP8 #DIP16 #Arduino #Breadboard #Mikrokontroler #Sensor #PCB | J57: 20 | K57: ITBisa - IC L7809CV L7809 7809 CV 7809CV 3 Terminal TO-220 Linear Voltage Regulator 5V 5Volt 5 Volt Linier IC Power Supply Stabilizer TO220 TO 220 | L57: ITBisa - IC L7809CV L7809 7809 CV 7809CV 3 Terminal TO-220 Linear Volt | M57: ITBisa - IC L7809CV L7809 7809 CV 7809CV 3 Terminal TO-220 Linear Voltage Regulator 5V 5Volt 5 Volt Linier IC Power Supply Stabilizer TO220 TO 220 | N57: ITBisa - IC L7809CV L7809 7809 CV 7809CV 3 Terminal TO-220 Linear Voltage Regulator 5V 5Volt 5 Volt Linier IC Power Supply Stabilizer TO220 TO 220
A58: ITBISA-IC-L7812CV-TO220 | B58: IC L7812CV | C58: L7812 7812 CV 7812CV | D58: 3 Terminal TO-220 | E58: Linear Voltage Regulator 12V | F58: 12Volt 12 Volt Linier IC Power Supply Stabilizer TO220 TO 220 | G58: BisaElektronika - BisaIC | H58: 2 | I58: #ITBisa #BisaElektronika #BisaIC #Socket #IC #Shifter #Shift #Register #7Segment #Segment #LED #Counter #DIP6 #DIP8 #DIP16 #Arduino #Breadboard #Mikrokontroler #Sensor #PCB | J58: 20 | K58: ITBisa - IC L7812CV L7812 7812 CV 7812CV 3 Terminal TO-220 Linear Voltage Regulator 12V 12Volt 12 Volt Linier IC Power Supply Stabilizer TO220 TO 220 | L58: ITBisa - IC L7812CV L7812 7812 CV 7812CV 3 Terminal TO-220 Linear Volt | M58: ITBisa - IC L7812CV L7812 7812 CV 7812CV 3 Terminal TO-220 Linear Voltage Regulator 12V 12Volt 12 Volt Linier IC Power Supply Stabilizer TO220 TO 220 | N58: ITBisa - IC L7812CV L7812 7812 CV 7812CV 3 Terminal TO-220 Linear Voltage Regulator 12V 12Volt 12 Volt Linier IC Power Supply Stabilizer TO220 TO 220
A59: ITBISA-IC-L7815CV-TO220 | B59: IC L7815CV | C59: L7815 7815 CV 7815CV | D59: 3 Terminal TO-220 | E59: Linear Voltage Regulator 15V | F59: 15Volt 15 Volt Linier IC Power Supply Stabilizer TO220 TO 220 | G59: BisaElektronika - BisaIC | H59: 2 | I59: #ITBisa #BisaElektronika #BisaIC #Socket #IC #Shifter #Shift #Register #7Segment #Segment #LED #Counter #DIP6 #DIP8 #DIP16 #Arduino #Breadboard #Mikrokontroler #Sensor #PCB | J59: 20 | K59: ITBisa - IC L7815CV L7815 7815 CV 7815CV 3 Terminal TO-220 Linear Voltage Regulator 15V 15Volt 15 Volt Linier IC Power Supply Stabilizer TO220 TO 220 | L59: ITBisa - IC L7815CV L7815 7815 CV 7815CV 3 Terminal TO-220 Linear Volt | M59: ITBisa - IC L7815CV L7815 7815 CV 7815CV 3 Terminal TO-220 Linear Voltage Regulator 15V 15Volt 15 Volt Linier IC Power Supply Stabilizer TO220 TO 220 | N59: ITBisa - IC L7815CV L7815 7815 CV 7815CV 3 Terminal TO-220 Linear Voltage Regulator 15V 15Volt 15 Volt Linier IC Power Supply Stabilizer TO220 TO 220
A60: ITBISA-IC-LM741CN-DIP8 | B60: IC 741 | C60: LM741CN | D60: DIP-8 | E60: Op-Amp Filter Penguat LPF HPF BPF | F60: Integrated Circuit LM 741 LM741 Op Amp OpAmp 8 Pin Kaki DIP8 8DIP | G60: BisaElektronika - BisaIC | H60: 1 | I60: #ITBisa #BisaElektronika #BisaIC #Socket #IC #OpAmp #HPF #LPF #BPF #Filter #Amplifier #Inverting #DIP6 #DIP8 #DIP16 #Arduino #Breadboard #Mikrokontroler #Sensor #PCB | J60: 20 | K60: ITBisa - IC 741 LM741CN DIP-8 Op-Amp Filter Penguat LPF HPF BPF Integrated Circuit LM 741 LM741 Op Amp OpAmp 8 Pin Kaki DIP8 8DIP | L60: ITBisa - IC 741 LM741CN DIP-8 Op-Amp Filter Penguat LPF HPF BPF Integr | M60: ITBisa - IC 741 LM741CN DIP-8 Op-Amp Filter Penguat LPF HPF BPF Integrated Circuit LM 741 LM741 Op Amp OpAmp 8 Pin Kaki DIP8 8DIP | N60: ITBisa - IC 741 LM741CN DIP-8 Op-Amp Filter Penguat LPF HPF BPF Integrated Circuit LM 741 LM741 Op Amp OpAmp 8 Pin Kaki DIP8 8DIP
A61: ITBISA-IC-NE555P-DIP8 | B61: IC NE 555 | C61: NE555P | D61: DIP 8 Pin Kaki DIP-8 DIP8 8DIP | E61: Timer Osilator Flip Flop DIP-8 | F61: Oscillator Flip-Flop Integrated Circuit 8 Kaki | G61: BisaElektronika - BisaIC | H61: 1 | I61: #ITBisa #BisaElektronika #BisaIC #Socket #IC #Switch #Transistor #LED #Sensor #Timer #Osilator #FlipFlop #DIP6 #DIP8 #DIP16 #Arduino #Breadboard #Mikrokontroler #Sensor #PCB | J61: 20 | K61: ITBisa - IC NE 555 NE555P DIP 8 Pin Kaki DIP-8 DIP8 8DIP Timer Osilator Flip Flop DIP-8 Oscillator Flip-Flop Integrated Circuit 8 Kaki | L61: ITBisa - IC NE 555 NE555P DIP 8 Pin Kaki DIP-8 DIP8 8DIP Timer Osilato | M61: ITBisa - IC NE 555 NE555P DIP 8 Pin Kaki DIP-8 DIP8 8DIP Timer Osilator Flip Flop DIP-8 Oscillator Flip-Flop Integrated Circuit 8 Kaki | N61: ITBisa - IC NE 555 NE555P DIP 8 Pin Kaki DIP-8 DIP8 8DIP Timer Osilator Flip Flop DIP-8 Oscillator Flip-Flop Integrated Circuit 8 Kaki
A62: ITBISA-IC-PC817-DIP4
A63: ITBISA-IC-UA741CN-DIP8 | B63: IC UA 741 CN | C63: UA741CN | D63: 8 Pin DIP8 | E63: Op Amp Filter Penguat LPF HPF BPF DIP-8 | F63: 8 Kaki UA741 OpAmp Op-Amp Integrated Circuit | G63: BisaElektronika - BisaIC | H63: 1 | I63: #ITBisa #BisaElektronika #BisaIC #Socket #IC #OpAmp #HPF #LPF #BPF #Filter #Amplifier #Inverting #DIP6 #DIP8 #DIP16 #Arduino #Breadboard #Mikrokontroler #Sensor #PCB | J63: 20 | K63: ITBisa - IC UA 741 CN UA741CN 8 Pin DIP8 Op Amp Filter Penguat LPF HPF BPF DIP-8 8 Kaki UA741 OpAmp Op-Amp Integrated Circuit | L63: ITBisa - IC UA 741 CN UA741CN 8 Pin DIP8 Op Amp Filter Penguat LPF HPF | M63: ITBisa - IC UA 741 CN UA741CN 8 Pin DIP8 Op Amp Filter Penguat LPF HPF BPF DIP-8 8 Kaki UA741 OpAmp Op-Amp Integrated Circuit | N63: ITBisa - IC UA 741 CN UA741CN 8 Pin DIP8 Op Amp Filter Penguat LPF HPF BPF DIP-8 8 Kaki UA741 OpAmp Op-Amp Integrated Circuit
A64: ITBISA-IC-ULN2003AN-DIP16 | B64: IC 2003 | C64: ULN2003AN | D64: DIP16 DIP-16 16 Pin 16P | E64: Kanal Channel Darlington Driver Motor Stepper Control Kontrol | F64: ULN2003 | G64: BisaElektronika - BisaIC | I64: #ITBisa #BisaElektronika #BisaIC #Socket #IC #OpAmp #HPF #LPF #BPF #Filter #Amplifier #Inverting #DIP6 #DIP8 #DIP16 #Arduino #Breadboard #Mikrokontroler #Sensor #PCB | J64: 20 | K64: ITBisa - IC 2003 ULN2003AN DIP16 DIP-16 16 Pin 16P Kanal Channel Darlington Driver Motor Stepper Control Kontrol ULN2003 | L64: ITBisa - IC 2003 ULN2003AN DIP16 DIP-16 16 Pin 16P Kanal Channel Darli | M64: ITBisa - IC 2003 ULN2003AN DIP16 DIP-16 16 Pin 16P Kanal Channel Darlington Driver Motor Stepper Control Kontrol ULN2003 | N64: ITBisa - IC 2003 ULN2003AN DIP16 DIP-16 16 Pin 16P Kanal Channel Darlington Driver Motor Stepper Control Kontrol ULN2003
A65: ITBISA-IC-ULN2803APG-DIP18 | B65: IC 2803 | C65: ULN2803APG | D65: DIP18 DIP-18 18 Pin 18P | E65: Kanal Channel Darlington Driver Motor Stepper Control Kontrol | F65: ULN2803 | G65: BisaElektronika - BisaIC | I65: #ITBisa #BisaElektronika #BisaIC #Socket #IC #OpAmp #HPF #LPF #BPF #Filter #Amplifier #Inverting #DIP6 #DIP8 #DIP16 #DIP18 #Arduino #Breadboard #Mikrokontroler #Sensor #PCB | J65: 21 | K65: ITBisa - IC 2803 ULN2803APG DIP18 DIP-18 18 Pin 18P Kanal Channel Darlington Driver Motor Stepper Control Kontrol ULN2803 | L65: ITBisa - IC 2803 ULN2803APG DIP18 DIP-18 18 Pin 18P Kanal Channel Darl | M65: ITBisa - IC 2803 ULN2803APG DIP18 DIP-18 18 Pin 18P Kanal Channel Darlington Driver Motor Stepper Control Kontrol ULN2803 | N65: ITBisa - IC 2803 ULN2803APG DIP18 DIP-18 18 Pin 18P Kanal Channel Darlington Driver Motor Stepper Control Kontrol ULN2803
A66: ITBISA-IDC-2X5-AMPHENOL-FEMALE
A67: ITBISA-IDC-2X5-AMPHENOL-MALE
A68: ITBISA-IGAME-GTX-1070-8GB-DDR5-X-TOP-TRIPLE-FAN
A69: ITBISA-INFRARED-1838
A70: ITBISA-JACK-DC-005-FEMALE
A71: ITBISA-JUMPER-FF-10CM | B71: 40PCS Kabel Jumper | C71: 10 cm Female to Female F-F FF F F 2.54mm | E71: Arduino Breadboard | F71: 40 PCS 10cm Buah Pin 2.54 mm 2,54 mm 2,54mm Cable Rainbow Pelangi Sensor | G71: BisaElektronika - BisaKabel | H71: 25 | I71: #ITBisa #BisaElektronika #BisaKabel #Kabel #Jumper #40PCS #Male #Female #FF #10cm #20cm #30cm #Arduino #Breadboard #2.54mm #Mikrokontroler #Sensor #Socket #IC #PCB | J71: 20 | K71: ITBisa - 40PCS Kabel Jumper 10 cm Female to Female F-F FF F F 2.54mm Arduino Breadboard 40 PCS 10cm Buah Pin 2.54 mm 2,54 mm 2,54mm Cable Rainbow Pelangi Sensor | L71: ITBisa - 40PCS Kabel Jumper 10 cm Female to Female F-F FF F F 2.54mm A | M71: ITBisa - 40PCS Kabel Jumper 10 cm Female to Female F-F FF F F 2.54mm Arduino Breadboard 40 PCS 10cm Buah Pin 2.54 mm 2,54 mm 2,54mm Cable Rainbow Pela | N71: ITBisa - 40PCS Kabel Jumper 10 cm Female to Female F-F FF F F 2.54mm Arduino Breadboard 40 PCS 10cm Buah Pin 2.54 mm 2,54 mm 2,54mm Cable Rainbow Pelangi Sensor
A72: ITBISA-JUMPER-FF-20CM | B72: 40PCS Kabel Jumper | C72: 20 cm Female to Female F-F FF F F 2.54mm | E72: Arduino Breadboard | F72: 40 PCS 20cm Buah Pin 2.54 mm 2,54 mm 2,54mm Cable Rainbow Pelangi Sensor | G72: BisaElektronika - BisaKabel | H72: 35 | I72: #ITBisa #BisaElektronika #BisaKabel #Kabel #Jumper #40PCS #Male #Female #FF #10cm #20cm #30cm #Arduino #Breadboard #2.54mm #Mikrokontroler #Sensor #Socket #IC #PCB | J72: 20 | K72: ITBisa - 40PCS Kabel Jumper 20 cm Female to Female F-F FF F F 2.54mm Arduino Breadboard 40 PCS 20cm Buah Pin 2.54 mm 2,54 mm 2,54mm Cable Rainbow Pelangi Sensor | L72: ITBisa - 40PCS Kabel Jumper 20 cm Female to Female F-F FF F F 2.54mm A | M72: ITBisa - 40PCS Kabel Jumper 20 cm Female to Female F-F FF F F 2.54mm Arduino Breadboard 40 PCS 20cm Buah Pin 2.54 mm 2,54 mm 2,54mm Cable Rainbow Pela | N72: ITBisa - 40PCS Kabel Jumper 20 cm Female to Female F-F FF F F 2.54mm Arduino Breadboard 40 PCS 20cm Buah Pin 2.54 mm 2,54 mm 2,54mm Cable Rainbow Pelangi Sensor
A73: ITBISA-JUMPER-MF-10CM | B73: 40PCS Kabel Jumper | C73: 10 cm Male to Female M-F MF M F 2.54mm | E73: Arduino Breadboard | F73: 40 PCS 10cm Buah Pin 2.54 mm 2,54 mm 2,54mm Cable Rainbow Pelangi Sensor | G73: BisaElektronika - BisaKabel | H73: 25 | I73: #ITBisa #BisaElektronika #BisaKabel #Kabel #Jumper #40PCS #Male #Female #MF #10cm #20cm #30cm #Arduino #Breadboard #2.54mm #Mikrokontroler #Sensor #Socket #IC #PCB | J73: 20 | K73: ITBisa - 40PCS Kabel Jumper 10 cm Male to Female M-F MF M F 2.54mm Arduino Breadboard 40 PCS 10cm Buah Pin 2.54 mm 2,54 mm 2,54mm Cable Rainbow Pelangi Sensor | L73: ITBisa - 40PCS Kabel Jumper 10 cm Male to Female M-F MF M F 2.54mm Ard | M73: ITBisa - 40PCS Kabel Jumper 10 cm Male to Female M-F MF M F 2.54mm Arduino Breadboard 40 PCS 10cm Buah Pin 2.54 mm 2,54 mm 2,54mm Cable Rainbow Pelang | N73: ITBisa - 40PCS Kabel Jumper 10 cm Male to Female M-F MF M F 2.54mm Arduino Breadboard 40 PCS 10cm Buah Pin 2.54 mm 2,54 mm 2,54mm Cable Rainbow Pelangi Sensor | P73: https://tokopedia.com/itbisa/itbisa-ic-4n35-optocoupler-phototransistor-photocoupler-dip6-6-pin
A74: ITBISA-JUMPER-MF-20CM | B74: 40PCS Kabel Jumper | C74: 20 cm Male to Female M-F MF M F 2.54mm | E74: Arduino Breadboard | F74: 40 PCS 20cm Buah Pin 2.54 mm 2,54 mm 2,54mm Cable Rainbow Pelangi Sensor | G74: BisaElektronika - BisaKabel | H74: 35 | I74: #ITBisa #BisaElektronika #BisaKabel #Kabel #Jumper #40PCS #Male #Female #MF #10cm #20cm #30cm #Arduino #Breadboard #2.54mm #Mikrokontroler #Sensor #Socket #IC #PCB | J74: 20 | K74: ITBisa - 40PCS Kabel Jumper 20 cm Male to Female M-F MF M F 2.54mm Arduino Breadboard 40 PCS 20cm Buah Pin 2.54 mm 2,54 mm 2,54mm Cable Rainbow Pelangi Sensor | L74: ITBisa - 40PCS Kabel Jumper 20 cm Male to Female M-F MF M F 2.54mm Ard | M74: ITBisa - 40PCS Kabel Jumper 20 cm Male to Female M-F MF M F 2.54mm Arduino Breadboard 40 PCS 20cm Buah Pin 2.54 mm 2,54 mm 2,54mm Cable Rainbow Pelang | N74: ITBisa - 40PCS Kabel Jumper 20 cm Male to Female M-F MF M F 2.54mm Arduino Breadboard 40 PCS 20cm Buah Pin 2.54 mm 2,54 mm 2,54mm Cable Rainbow Pelangi Sensor
A75: ITBISA-JUMPER-MM-10CM | B75: 40PCS Kabel Jumper | C75: 10 cm Male to Male M-M MM M M 2.54mm | E75: Arduino Breadboard | F75: 40 PCS 10cm Buah Pin 2.54 mm 2,54 mm 2,54mm Cable Rainbow Pelangi Sensor | G75: BisaElektronika - BisaKabel | H75: 25 | I75: #ITBisa #BisaElektronika #BisaKabel #Kabel #Jumper #40PCS #Male #Female #MM #10cm #20cm #30cm #Arduino #Breadboard #2.54mm #Mikrokontroler #Sensor #Socket #IC #PCB | J75: 20 | K75: ITBisa - 40PCS Kabel Jumper 10 cm Male to Male M-M MM M M 2.54mm Arduino Breadboard 40 PCS 10cm Buah Pin 2.54 mm 2,54 mm 2,54mm Cable Rainbow Pelangi Sensor | L75: ITBisa - 40PCS Kabel Jumper 10 cm Male to Male M-M MM M M 2.54mm Ardui | M75: ITBisa - 40PCS Kabel Jumper 10 cm Male to Male M-M MM M M 2.54mm Arduino Breadboard 40 PCS 10cm Buah Pin 2.54 mm 2,54 mm 2,54mm Cable Rainbow Pelangi | N75: ITBisa - 40PCS Kabel Jumper 10 cm Male to Male M-M MM M M 2.54mm Arduino Breadboard 40 PCS 10cm Buah Pin 2.54 mm 2,54 mm 2,54mm Cable Rainbow Pelangi Sensor
A76: ITBISA-JUMPER-MM-20CM | B76: 40PCS Kabel Jumper | C76: 20 cm Male to Male M-M MM M M 2.54mm | E76: Arduino Breadboard | F76: 40 PCS 20cm Buah Pin 2.54 mm 2,54 mm 2,54mm Cable Rainbow Pelangi Sensor | G76: BisaElektronika - BisaKabel | H76: 35 | I76: #ITBisa #BisaElektronika #BisaKabel #Kabel #Jumper #40PCS #Male #Female #MM #10cm #20cm #30cm #Arduino #Breadboard #2.54mm #Mikrokontroler #Sensor #Socket #IC #PCB | J76: 20 | K76: ITBisa - 40PCS Kabel Jumper 20 cm Male to Male M-M MM M M 2.54mm Arduino Breadboard 40 PCS 20cm Buah Pin 2.54 mm 2,54 mm 2,54mm Cable Rainbow Pelangi Sensor | L76: ITBisa - 40PCS Kabel Jumper 20 cm Male to Male M-M MM M M 2.54mm Ardui | M76: ITBisa - 40PCS Kabel Jumper 20 cm Male to Male M-M MM M M 2.54mm Arduino Breadboard 40 PCS 20cm Buah Pin 2.54 mm 2,54 mm 2,54mm Cable Rainbow Pelangi | N76: ITBisa - 40PCS Kabel Jumper 20 cm Male to Male M-M MM M M 2.54mm Arduino Breadboard 40 PCS 20cm Buah Pin 2.54 mm 2,54 mm 2,54mm Cable Rainbow Pelangi Sensor
A77: ITBISA-KAPASITOR-ELCO-2200UF-25V
A78: ITBISA-KODE-UNIK
A79: ITBISA-KUPLUK-HITAM
A80: ITBISA-LCD-16X2-BLUE
A81: ITBISA-LCD-16X2-GREEN
A82: ITBISA-LDR-GL5516
A83: ITBISA-LED-MAX7219-4IN1-GAP
A84: ITBISA-LED-MAX7219-4IN1-TIGHT
A85: ITBISA-LED-SUPERBRIGHT-5MM-BLUE
A86: ITBISA-LED-SUPERBRIGHT-5MM-GREEN
A87: ITBISA-LED-SUPERBRIGHT-5MM-RED
A88: ITBISA-LED-SUPERBRIGHT-5MM-WHITE
... A91: ITBISA-MICRO-SD-READER-MINI
A92: ITBISA-MOTORDRIVER-L298N-WITH-HEATSINK | B92: Motor Driver Stepper DC | C92: L298N Dual H Bridge | D92: With Heatsink | E92: Module Control Robot Car Arduino | F92: L 298 N Modul Kontrol High Power | G92: BisaElektronika | K92: ITBisa - Motor Driver Stepper DC L298N Dual H Bridge With Heatsink Module Control Robot Car Arduino L 298 N Modul Kontrol High Power | L92: ITBisa - Motor Driver Stepper DC L298N Dual H Bridge With Heatsink Mod | M92: ITBisa - Motor Driver Stepper DC L298N Dual H Bridge With Heatsink Module Control Robot Car Arduino L 298 N Modul Kontrol High Power | N92: ITBisa - Motor Driver Stepper DC L298N Dual H Bridge With Heatsink Module Control Robot Car Arduino L 298 N Modul Kontrol High Power
A93: ITBISA-NODEMCU-ESP32-MICRO
A94: ITBISA-NODEMCU-ESP32-MICRO-30PIN
A95: ITBISA-NODEMCU-ESP32-MICRO-38PIN
A96: ITBISA-NODEMCU-V3-CH340G-ESP8266-MICRO | B96: NodeMCU | C96: V3 CH340G
A97: ITBISA-NPN-2N2222-TO92 | B97: Transistor | C97: BJT NPN 2N2222 A 2N2222A | D97: TO92 0.6A 30V | E97: Penguat Switch | F97: Transistors 2N 2222 TO 92 TO-92 0.6 Ampere 0,6A Op-Amp Op Amp Switching 30 V 30Volt Volt | G97: BisaElektronika - BisaTransistor | H97: 1 | I97: #ITBisa #BisaElektronika #BisaTransistor #IC #Socket #Switch #Penguat #OpAmp #Op-Amp #Amplifier #BJT #MOSFET #NPN #PNP #TO-92 #TO92 #PCB #Arduino #Breadboard #Mikrokontroler | J97: 20 | K97: ITBisa - Transistor BJT NPN 2N2222 A 2N2222A TO92 0.6A 30V Penguat Switch Transistors 2N 2222 TO 92 TO-92 0.6 Ampere 0,6A Op-Amp Op Amp Switching 30 V 30Volt Volt | L97: ITBisa - Transistor BJT NPN 2N2222 A 2N2222A TO92 0.6A 30V Penguat Swi | M97: ITBisa - Transistor BJT NPN 2N2222 A 2N2222A TO92 0.6A 30V Penguat Switch Transistors 2N 2222 TO 92 TO-92 0.6 Ampere 0,6A Op-Amp Op Amp Switching 30 V | N97: ITBisa - Transistor BJT NPN 2N2222 A 2N2222A TO92 0.6A 30V Penguat Switch Transistors 2N 2222 TO 92 TO-92 0.6 Ampere 0,6A Op-Amp Op Amp Switching 30 V 30Volt Volt
A98: ITBISA-NPN-2N3904-TO92
A99: ITBISA-NPN-2N5551-TO92
A100: ITBISA-NPN-BC337-TO92
A101: ITBISA-NPN-BC547A-TO92 | B101: Transistor | C101: BJT NPN BC547 | D101: TO-92 TO92 | E101: Penguat Switch Amplifier | G101: BisaElektronika - BisaTransistor | H101: 1 | I101: #ITBisa #BisaElektronika #BisaTransistor #IC #Socket #Switch #Penguat #OpAmp #Op-Amp #Amplifier #BJT #MOSFET #NPN #PNP #TO-92 #TO92 #PCB #Arduino #Breadboard #Mikrokontroler | J101: 20 | K101: ITBisa - Transistor BJT NPN BC547 TO-92 TO92 Penguat Switch Amplifier | L101: ITBisa - Transistor BJT NPN BC547 TO-92 TO92 Penguat Switch Amplifier | M101: ITBisa - Transistor BJT NPN BC547 TO-92 TO92 Penguat Switch Amplifier | N101: ITBisa - Transistor BJT NPN BC547 TO-92 TO92 Penguat Switch Amplifier
A102: ITBISA-NPN-BC547-TO92 | B102: Transistor | C102: BJT NPN BC547 | D102: TO-92 TO92 | E102: Penguat Switch Amplifier | G102: BisaElektronika - BisaTransistor | H102: 1 | I102: #ITBisa #BisaElektronika #BisaTransistor #IC #Socket #Switch #Penguat #OpAmp #Op-Amp #Amplifier #BJT #MOSFET #NPN #PNP #TO-92 #TO92 #PCB #Arduino #Breadboard #Mikrokontroler | J102: 20 | K102: ITBisa - Transistor BJT NPN BC547 TO-92 TO92 Penguat Switch Amplifier | L102: ITBisa - Transistor BJT NPN BC547 TO-92 TO92 Penguat Switch Amplifier | M102: ITBisa - Transistor BJT NPN BC547 TO-92 TO92 Penguat Switch Amplifier | N102: ITBisa - Transistor BJT NPN BC547 TO-92 TO92 Penguat Switch Amplifier
...

Sheet BisaEtalase
A1: Level 1 | B1: Level 2
A2: Elektronika
B3: IC
B4: Induktor
B5: Kabel
B6: Kapasitor
B7: Lampu
B8: Mikrokontroler
B9: PCB
B10: Resistor
B11: Segment
B12: Socket
B13: Transistor
A14: Ospek
B15: Lampu
B16: Sarung Tangan
B17: Senter
B18: Syal
B19: Baterai

Sheet BisaPerlengkapan
A1: Tanggal Beli | B1: Jenis Transaksi Debit | C1: Jenis Transaksi Kredit | D1: Nominal | E1: Keterangan
A3: 43314.787 | B3: Perlengkapan Tape Cutter | C3: Kas ITBisa | D3: 38800 | E3: Tape Cutter Borma (Mahal?)
A4: 43316 | B4: Perlengkapan Bubble Wrap | C4: Kas ITBisa | D4: =135000+19000 -> 154000 | E4: Bubble Wrap 50cmx1.25m
A5: 43316.631 | B5: Perlengkapan Baterai | C5: Kas ITBisa | D5: 17100 | E5: Aji membeli Baterai ABC Super Power size D, Testing Baterai ABC buat senter
A6: 43422 | B6: Perlengkapan Selotip | C6: Kas ITBisa | D6: 15000 | E6: Selotip Cokelat
A7: 43440 | B7: Perlengkapan Plastik Klip | C7: Kas ITBisa | D7: =1*12000 + 6000 -> 18000 | E7: 1 x 1000 x https://www.tokopedia.com/dwi-jaya/kantong-plastik-klip-3-cm-x-5-cm-isi-1000-pcs
A8: 43477.58 | B8: Perlengkapan Plastik Klip | C8: Kas ITBisa | D8: =8*4300 + 10000 -> 44400 | E8: 800 x https://www.tokopedia.com/jayaplastik/plastik-klip-8x12-cm-termurah
A9: 43516 | B9: Perlengkapan Keresek | C9: Kas ITBisa | D9: 7500 | E9: Beli Keresek/Plastik Hitam
A10: 43516 | B10: Perlengkapan Selotip | C10: Kas ITBisa | D10: 7000 | E10: Beli Solasi/Selotip Bening
A11: 43522.943 | B11: Perlengkapan Bubble Wrap | C11: Kas ITBisa | D11: =129000+36000 -> 165000 | E11: Bubble Wrap 50cmx1.25m
A12: 43543.737 | B12: Perlengkapan Lainnya | C12: Kas ITBisa | D12: 50000 | E12: Aji membeli Arduino dari ITBisa
A13: 43554 | B13: Perlengkapan Selotip | C13: Kas ITBisa | D13: =4*6500 + 5*5000 + 8500 - 8500 -> 51000 | E13: Lakban Bening
A14: 43584.587 | B14: Perlengkapan Gunting | C14: Kas ITBisa | D14: =13000*2 + 7000 -> 33000 | E14: 2x Gunting De Xian
A15: 43584.588 | B15: Perlengkapan Label | C15: Kas ITBisa | D15: =3600*2 + 5000 -> 12200 | E15: 2x1960 Label 113
A16: 43850 | B16: Perlengkapan Plastik Klip | C16: Kas ITBisa | D16: 20000 | E16: 2 x https://www.tokopedia.com/gemilang888/kantong-plastik-klip-uk-10x15-cm-plastik-zipper-lock-plastik-obat
A17: 43881 | B17: Perlengkapan Kardus | C17: Kas ITBisa | D17: 24500 | E17: Kardus Packing https://www.tokopedia.com/zenindah/kardus-karton-box-uk-10-x-10-x-20-cm-untuk-packing
A18: 43881 | B18: Perlengkapan Selotip | C18: Kas ITBisa | D18: 50490 | E18: Lakban Packing https://www.tokopedia.com/murahhematstore/lakban-bening-coklat-super-murah-coklat-promooo-45mm-x50y-rolll-putih
A19: 44043 | B19: Perlengkapan Plastik Klip | C19: Kas ITBisa | D19: =10*2600 + 5*1200 + 1800*10 -> 50000 | E19: 2 x https://www.tokopedia.com/tokopackaging/pe-klip-6x10-kantong-plastik-klip-bening-transparan-kemasan-obat-baju 5 x https://www.tokopedia.com/tokopackaging/pe-klip-4x6-kantong-plastik-klip-bening-transparan-kemasan-obat-zipper 10 x https://www.tokopedia.com/tokopackaging/pe-klip-5x8-kantong-plastik-klip-bening-transparan-kemasan-obat-zipper
A20: 44090 | B20: Perlengkapan Kertas | C20: Kas ITBisa | D20: =2*33000 + 10000-5000 -> 71000 | E20: 2 rim x https://www.tokopedia.com/hqstationary/promo-kertas-hvs-a4-75gsm-ekon-copy-produk-paperone-1-rim
A21: 43927.792 | B21: Perlengkapan Baterai | C21: Kas ITBisa | D21: 15900 | E21: Beli Baterai ABC 2x
A22: 44083 | B22: Perlengkapan Plastik Klip | C22: Kas ITBisa | D22: =3*5000 -> 15000 | E22: 3 x https://shopee.co.id/product/10970573/1853873359
A24: 44247 | B24: Perlengkapan Selotip | C24: Kas ITBisa | D24: =15*8000 -> 120000 | E24: Shopee Serba Fair
A26: 44834 | B26: Perlengkapan Kardus | C26: Kas ITBisa | D26: =25*330 -> 8250 | E26: Ukuran 7x5x8 https://tokopedia.link/XGyG4Ieyfxb
A27: 44834 | B27: Perlengkapan Kardus | C27: Kas ITBisa | D27: =25*230 -> 5750 | E27: Ukuran 4x4x8 https://tokopedia.link/K8AtqJfyfxb
A28: 44834 | B28: Perlengkapan Kardus | C28: Kas ITBisa | D28: =25*430 -> 10750 | E28: Ukuran 10x7x5 https://tokopedia.link/qup9nQgyfxb
A29: 44834 | B29: Perlengkapan Kardus | C29: Kas ITBisa | D29: =25*440 -> 11000 | E29: Ukuran 6x6x12 https://tokopedia.link/6vTecTjyfxb
A31: 44954 | B31: Perlengkapan Cutter | C31: Kas ITBisa | D31: 12500 | E31: 1 x Kenko L500 https://tokopedia.link/fDyHQ37xfxb
A32: 44954 | B32: Perlengkapan Selotip | C32: Kas ITBisa | D32: =5*8000 -> 40000 | E32: 5 x Daimaru Selotip https://tokopedia.link/58XuMW6xfxb
A34: 44965 | B34: Perlengkapan Bubble Wrap | C34: Kas ITBisa | D34: =47000+6500 -> 53500 | E34: 1 x Bubble Wrap 60cm x 50m https://tokopedia.link/eOn43UAyfxb
A35: 44979 | B35: Perlengkapan Baterai | C35: Kas ITBisa | D35: =2*5458 -> 10916 | E35: Beli Baterai ABC D Power 2x
A37: 44984 | B37: Perlengkapan Plastik Klip | C37: Kas ITBisa | D37: =17*1200 + 1000 -> 21400 | E37: 17 x Plastik Klip 4x6 https://tokopedia.link/FKWUltB9Kxb
A39: 45005 | B39: Perlengkapan Selotip | C39: Kas ITBisa | D39: =7*7150 + 1000 -> 51050 | E39: 7 x Daimaru
A40: 45010 | B40: Perlengkapan Bubble Wrap | C40: Kas ITBisa | D40: =47000+6500 -> 53500 | E40: 1 x Bubble Wrap 60cm x 50m https://tokopedia.link/eOn43UAyfxb
A42: 45075 | B42: Perlengkapan Selotip | C42: Kas ITBisa | D42: =5*7300 + 2000 -> 38500 | E42: 5 x Daimaru Bening
A44: 45107.458 | B44: Perlengkapan Kardus | C44: Kas ITBisa | D44: =11500+2000 -> 13500 | E44: Ukuran 4x4x8 https://tokopedia.link/K8AtqJfyfxb
A46: 45151.479 | B46: Perlengkapan Cutter | C46: Kas ITBisa | D46: =2*11999+1000+1000 -> 25998 | E46: 2x Kenko L500
A48: 45178.442 | B48: Perlengkapan Kardus | C48: Kas ITBisa | D48: 21650 | E48: 30 x Kardus 7x5x8 + 25 x Kardus 10x7x5
A49: 45186.521 | B49: Perlengkapan Kardus | C49: Kas ITBisa | D49: 21240 | E49: 46 x Kardus 6x6x12
A51: 45209.625 | B51: Perlengkapan Bubble Wrap | C51: Kas ITBisa | D51: =47000 + 6500 + 1000 -> 54500 | E51: 1 x Bubble Wrap 60cm x 50m https://tokopedia.link/eOn43UAyfxb
A52: 45221.928 | B52: Perlengkapan Kardus | C52: Kas ITBisa | D52: =20*300 + 25*280 + 40*185 + 23000 - 20000 + 300 + 1000 -> 24700 | E52: 20 x 13x4x7.5 + 25 x 10x5x5 + 40 + 9 x 4.5 x 4.5
A54: 45234.956 | B54: Perlengkapan Selotip | C54: Kas ITBisa | D54: =6 * 7300 + 11500 - 11500 + 1000 -> 44800 | E54: 6 Daimaru Cokelat
A56: 45305.506 | B56: Perlengkapan Selotip | C56: Kas ITBisa | D56: =(3*7300) + (3*7300) + 1000 -> 44800 | E56: 3 x Daimaru Bening + 3 x Daimaru Cokelat
A57: 45351.613 | B57: Perlengkapan Selotip | C57: Kas ITBisa | D57: =5*7250 + 5*7250 + 1000 -> 73500 | E57: 5 x Daimaru Bening + 5 x Daimaru Cokelat
A59: 45370.932 | B59: Perlengkapan Bubble Wrap | C59: Kas ITBisa | D59: =(42000 + 19000 - 15000 - 1 + 1000) -> 46999 | E59: 1 x Bubble Wrap 60cm x 50 m Shopee Aji
A60: 45370.946 | B60: Perlengkapan Kardus | C60: Kas ITBisa | D60: =(48*440 + 1000) -> 22120 | E60: 40 8 x 6x6x12
A62: 45409.756 | B62: Perlengkapan Selotip | C62: Kas ITBisa | D62: =(8*7100 + 7*7100) + (34500 - 30000) + (1000) - (6390) -> 105610 | E62: 7 x Daimaru Bening + 8 x Daimaru Cokelat
A63: 45418.451 | B63: Perlengkapan Selotip | C63: Kas ITBisa | D63: =5*7800 + 1*7800 + 1*5000 + 1000 - 15000 -> 37800 | E63: 7 x Darimau Cokelat + 1 x Daimaru Bening + 1 x Daimaru Bening 1 Inch
A65: 45453.511 | B65: Perlengkapan Bubble Wrap | C65: Kas ITBisa | D65: =(44000 + 1000) -> 45000 | E65: 1 x Bubble Wrap 60cm x 50 m Shopee Aji - Ciamis
A66: 45478.677 | B66: Perlengkapan Bubble Wrap | C66: Kas ITBisa | D66: 47000 | E66: 1 x Bubble Wrap 60cm x 50 m Shopee Aji - Cipinang
A68: 45505 | B68: Perlengkapan Selotip | C68: Kas ITBisa | D68: =3*7500 + 1*7500 + 300 - 15000 -> 15300 | E68: 3 x Daimaru Cokelat + 1 x Daimaru Bening - artija Tokopedia
A69: 45523.527 | B69: Perlengkapan Bubble Wrap | C69: Kas ITBisa | D69: =(79900 + 18000 - 15000 + 1000) -> 83900 | E69: 1 x Bubble Wrap 125cm x 50 m Shopee Aji - Ciamis
A71: 45563.559 | B71: Perlengkapan Selotip | C71: Kas ITBisa | D71: =(20*6900 + 10*6900) - 20700 + 81 -> 186381 | E71: 20 x Daimaru Palsu Cokelat + 10 x Daimaru Palsu Bening - TOKO SANDIRA Shopee
A73: 45666.784 | B73: Perlengkapan Bubble Wrap | C73: Kas ITBisa | D73: =(1*82500 - 12375 + 25) -> 70150 | E73: 1 x Bubble Wrap
A74: 45773.734 | B74: Perlengkapan Kertas | C74: Kas ITBisa | D74: =(25000 - 2000 + 45) -> 23045 | E74: 1 Rim A5 x ATKStore Jombang Shopee
A76: 45845.002 | B76: Perlengkapan Selotip | C76: Kas ITBisa | D76: =(15*6900 + 15*6900 - 24840 + 1016) -> 183176 | E76: 15 x Daimaru Cokelat + 15 x Daimaru Bening - TOKO SANDIRA Shopee
A77: 45845.028 | B77: Perlengkapan Selotip | C77: Kas ITBisa | D77: =10*8400 + 9*8400 - 23940 + 1900 -> 137560 | E77: 10 x Daimaru Cokelar + 9 x Daimaru Bening - TOKO SANDIRA Shopee
A79: 45904.538 | B79: Perlengkapan Kertas | C79: Kas ITBisa | D79: =(204999 + 28500 - 20000 - 16400 + 1260) -> 198359 | E79: Kertas HV A4 5 Rim - Jakarta x Nusantara Grosir ATK Shopee
A80: 45918.631 | B80: Perlengkapan Kertas | C80: Kas ITBisa | D80: =197500 + 23500 - 10000 - 19750 + 2000 + (198359) -> 391609 | E80: Kertas HVS 70 Gram A4 5 Rim - Ciamis x Toko Kertas WJP
A82: 45969.651 | B82: Perlengkapan Bubble Wrap | C82: Kas ITBisa | D82: =(113738 - 13647 + 139) -> 100230 | E82: 1 x Bubble Wrap 50m x 125cm
A83: 45969.651 | B83: Perlengkapan Selotip | C83: Kas ITBisa | D83: =(10*7950 + 10 *7950) - 19081 + 193 -> 140112 | E83: 10 x Daimaru Cokelar + 10 x Daimaru Bening - grosiredo Shopee
A85: 45976.719 | B85: Perlengkapan Kardus | C85: Kas ITBisa | D85: =(115*259 - 14983 + 1000) -> 15802 | E85: 115 x Kardus 12x6x6 - KARDUS MOUD Shopee
A87: 46002.682 | B87: Perlengkapan Plastik Klip | C87: Kas ITBisa | D87: =(2*14400 + 6500-6500 - 4000 + 1000) -> 25800 | E87: 2 x Plastik 4x6 - majuplastic Shopee

Sheet BisaJurnal
A1: {={"Tanggal Akun","Akun","Referensi (Kode Transaksi)","Debit","Kredit","Keterangan"; SORT({ IF((BisaStok!B3:B4643<2),,{BisaStok!B3:B4643+0.00001*MOD(ROW(BisaStok!B3:B4643),100), "Piutang "&BisaStok!F3:F4643,IF(BisaStok!B3:B4643<2,,"PIU-BisaStok-"&TEXT(ROW(BisaStok!B3:B4643),"00000")),BisaStok!AB3:AB4643,SUBSTITUTE(BisaStok!B3:B4643,BisaStok!B3:B4643,),BisaStok!H3:H4643}); IF((BisaStok!B3:B4643<2),,{BisaStok!B3:B4643+0.00001*MOD(ROW(BisaStok!B3:B4643),100), " Kas ITBisa"&SUBSTITUTE(BisaStok!B3:B4643,BisaStok!B3:B4643,),IF(BisaStok!B3:B4643<2,,"KAS-BisaStok-"&TEXT(ROW(BisaStok!B3:B4643),"00000")),SUBSTITUTE(BisaStok!B3:B4643,BisaStok!B3:B4643,),BisaStok!AB3:AB4643,BisaStok!H3:H4643}); IF((BisaStok!C3:C4643<2),,{BisaStok!C3:C4643+0.00001*MOD(ROW(BisaStok!C3:C4643),100), "Persediaan "&BisaStok!A3:A4643,IF(BisaStok!B3:B4643<2,,"INV-BisaStok-"&TEXT(ROW(BisaStok!B3:B4643),"00000")),BisaStok!AB3:AB4643,SUBSTITUTE(BisaStok!B3:B4643,BisaStok!B3:B4643,),BisaStok!H3:H4643}); IF((BisaStok!C3:C4643<2),,{BisaStok!C3:C4643+0.00001*MOD(ROW(BisaStok!C3:C4643),100), " Piutang "&BisaStok!F3:F4643,IF(BisaStok!B3:B4643<2,,"PIU-BisaStok-"&TEXT(ROW(BisaStok!B3:B4643),"00000")),SUBSTITUTE(BisaStok!B3:B4643,BisaStok!B3:B4643,),BisaStok!AB3:AB4643,BisaStok!H3:H4643}); "","","","","",""; IF((BisaPerlengkapan!A2:A4643<2),,{BisaPerlengkapan!A2:A4643+0.00001*MOD(ROW(BisaPerlengkapan!A2:A4643),100),BisaPerlengkapan!B2:B4643,"DBT-BisaPerlengkapan-"&TEXT(ROW(BisaPerlengkapan!A2:A4643),"00000"),BisaPerlengkapan!D2:D4643,SUBSTITUTE(BisaPerlengkapan!A2:A4643,BisaPerlengkapan!A2:A4643,),BisaPerlengkapan!E2:E4643}); IF((BisaPerlengkapan!A2:A4643<2),,{BisaPerlengkapan!A2:A4643+0.00001*MOD(ROW(BisaPerlengkapan!A2:A4643),100), " "&BisaPerlengkapan!C2:C4643,"CRT-BisaPerlengkapan-"&TEXT(ROW(BisaPerlengkapan!A2:A4643),"00000"),SUBSTITUTE(BisaPerlengkapan!A2:A4643,BisaPerlengkapan!A2:A4643,),BisaPerlengkapan!D2:D4643,BisaPerlengkapan!E2:E4643}); "","","","","",""; IF((BisaHilang!A2:A4643<2)+(BisaHilang!C2:C4643<1)+(BisaHilang!D2:D4643<1),,{BisaHilang!A2:A4643+0.00001*MOD(ROW(BisaHilang!A2:A4643),100),"Persediaan "&BisaHilang!B2:B4643,"INV-BisaHilang-"&TEXT(ROW(BisaHilang!A2:A4643),"00000"),BisaHilang!D2:D4643,SUBSTITUTE(BisaHilang!A2:A4643,BisaHilang!A2:A4643,),SUBSTITUTE(BisaHilang!A2:A4643,BisaHilang!A2:A4643,)}); IF((BisaHilang!A2:A4643<2)+(BisaHilang!C2:C4643<1)+(BisaHilang!D2:D4643<1),,{BisaHilang!A2:A4643+0.00001*MOD(ROW(BisaHilang!A2:A4643),100)," Bonus "&BisaHilang!B2:B4643,"BNS-BisaHilang-"&TEXT(ROW(BisaHilang!A2:A4643),"00000"),SUBSTITUTE(BisaHilang!A2:A4643,BisaHilang!A2:A4643,),BisaHilang!D2:D4643,SUBSTITUTE(BisaHilang!A2:A4643,BisaHilang!A2:A4643,)}); "","","","","",""; IF((BisaHilang!A2:A4643<2)+(BisaHilang!E2:E4643<1)+(BisaHilang!F2:F4643<1),,{BisaHilang!A2:A4643+0.00001*MOD(ROW(BisaHilang!A2:A4643),100),"Beban Hilang "&BisaHilang!B2:B4643,"BBN-BisaHilang-"&TEXT(ROW(BisaHilang!A2:A4643),"00000"),BisaHilang!F2:F4643,SUBSTITUTE(BisaHilang!A2:A4643,BisaHilang!A2:A4643,),SUBSTITUTE(BisaHilang!A2:A4643,BisaHilang!A2:A4643,)}); IF((BisaHilang!A2:A4643<2)+(BisaHilang!E2:E4643<1)+(BisaHilang!F2:F4643<1),,{BisaHilang!A2:A4643+0.00001*MOD(ROW(BisaHilang!A2:A4643),100)," Persediaan "&BisaHilang!B2:B4643,"INV-BisaHilang-"&TEXT(ROW(BisaHilang!A2:A4643),"00000"),SUBSTITUTE(BisaHilang!A2:A4643,BisaHilang!A2:A4643,),BisaHilang!F2:F4643,SUBSTITUTE(BisaHilang!A2:A4643,BisaHilang!A2:A4643,)}); "","","","","",""},1,TRUE)}} -> Tanggal Akun | B1: Akun | C1: Referensi (Kode Transaksi) | D1: Debit | E1: Kredit | F1: Keterangan
A2: 43271 | B2: Piutang Bukalapak | C2: PIU-BisaStok-00209 | D2: 607316 | F2: BukaEmas Furqonajiy
A3: 43271 | B3: Kas ITBisa | C3: KAS-BisaStok-00209 | E3: 607316 | F3: BukaEmas Furqonajiy
A4: 43271 | B4: Persediaan ITBISA-BUKAEMAS | C4: INV-BisaStok-00209 | D4: 607316 | F4: BukaEmas Furqonajiy
A5: 43271 | B5: Piutang Bukalapak | C5: PIU-BisaStok-00209 | E5: 607316 | F5: BukaEmas Furqonajiy
A6: 43281 | B6: Piutang Bukalapak | C6: PIU-BisaStok-00224 | D6: 150000 | F6: BukaReksa Furqonajiy
A7: 43281 | B7: Kas ITBisa | C7: KAS-BisaStok-00224 | E7: 150000 | F7: BukaReksa Furqonajiy
A8: 43283 | B8: Persediaan ITBISA-BUKAREKSA-SYARIAH-MANDIRI-PASAR-UANG | C8: INV-BisaStok-00224 | D8: 150000 | F8: BukaReksa Furqonajiy
A9: 43283 | B9: Piutang Bukalapak | C9: PIU-BisaStok-00224 | E9: 150000 | F9: BukaReksa Furqonajiy
A10: 43284.001 | B10: Piutang Shopee | C10: PIU-BisaStok-00689 | D10: 234000 | F10: Shopee Furqonajiy 1807030912462JP Resi JNE 120790076724318
A11: 43284.001 | B11: Kas ITBisa | C11: KAS-BisaStok-00689 | E11: 234000 | F11: Shopee Furqonajiy 1807030912462JP Resi JNE 120790076724318
A12: 43286.001 | B12: Persediaan ITBISA-PONCO-GAJAH | C12: INV-BisaStok-00689 | D12: 234000 | F12: Shopee Furqonajiy 1807030912462JP Resi JNE 120790076724318
A13: 43286.001 | B13: Piutang Shopee | C13: PIU-BisaStok-00689 | E13: 234000 | F13: Shopee Furqonajiy 1807030912462JP Resi JNE 120790076724318
A14: 43295 | B14: Piutang Bukalapak | C14: PIU-BisaStok-00208 | D14: 607923 | F14: BukaEmas Furqonajiy
A15: 43295 | B15: Kas ITBisa | C15: KAS-BisaStok-00208 | E15: 607923 | F15: BukaEmas Furqonajiy
A16: 43295 | B16: Persediaan ITBISA-BUKAEMAS | C16: INV-BisaStok-00208 | D16: 607923 | F16: BukaEmas Furqonajiy
A17: 43295 | B17: Piutang Bukalapak | C17: PIU-BisaStok-00208 | E17: 607923 | F17: BukaEmas Furqonajiy
A18: 43295 | B18: Piutang AliExpress | C18: PIU-BisaStok-00517 | D18: 63266.42 | F18: Aliexpress Furqonajiy 93253631544116 Resi UC917272223CN
A19: 43295 | B19: Kas ITBisa | C19: KAS-BisaStok-00517 | E19: 63266.42 | F19: Aliexpress Furqonajiy 93253631544116 Resi UC917272223CN
A20: 43295 | B20: Piutang AliExpress | C20: PIU-BisaStok-00518 | D20: 63266.42 | F20: Aliexpress Furqonajiy 93253631584116 Resi UC917303098CN
A21: 43295 | B21: Kas ITBisa | C21: KAS-BisaStok-00518 | E21: 63266.42 | F21: Aliexpress Furqonajiy 93253631584116 Resi UC917303098CN
A22: 43295 | B22: Piutang AliExpress | C22: PIU-BisaStok-00519 | D22: 66634.771 | F22: Aliexpress Furqonajiy 93253631614116 Resi RY220993442CN
A23: 43295 | B23: Kas ITBisa | C23: KAS-BisaStok-00519 | E23: 66634.771 | F23: Aliexpress Furqonajiy 93253631614116 Resi RY220993442CN
A24: 43295 | B24: Piutang AliExpress | C24: PIU-BisaStok-00520 | D24: 66634.771 | F24: Aliexpress Furqonajiy 93253631654116 Resi UC919314371CN
A25: 43295 | B25: Kas ITBisa | C25: KAS-BisaStok-00520 | E25: 66634.771 | F25: Aliexpress Furqonajiy 93253631654116 Resi UC919314371CN
A26: 43295 | B26: Piutang AliExpress | C26: PIU-BisaStok-00521 | D26: 66634.771 | F26: Aliexpress Furqonajiy 93253631694116 Resi LP113384050SG
A27: 43295 | B27: Kas ITBisa | C27: KAS-BisaStok-00521 | E27: 66634.771 | F27: Aliexpress Furqonajiy 93253631694116 Resi LP113384050SG
A28: 43295 | B28: Piutang AliExpress | C28: PIU-BisaStok-00522 | D28: 69710.222 | F28: Aliexpress Furqonajiy 93253631744116 Resi UC919882942CN
A29: 43295 | B29: Kas ITBisa | C29: KAS-BisaStok-00522 | E29: 69710.222 | F29: Aliexpress Furqonajiy 93253631744116 Resi UC919882942CN
A30: 43295 | B30: Piutang AliExpress | C30: PIU-BisaStok-00523 | D30: 68685.071 | F30: Aliexpress Furqonajiy 93253631754116 Resi UC914481942CN
A31: 43295 | B31: Kas ITBisa | C31: KAS-BisaStok-00523 | E31: 68685.071 | F31: Aliexpress Furqonajiy 93253631754116 Resi UC914481942CN
A32: 43295 | B32: Piutang AliExpress | C32: PIU-BisaStok-00549 | D32: 63266.42 | F32: Aliexpress Furqonajiy 93253631544116 Resi UC917272223CN
A33: 43295 | B33: Kas ITBisa | C33: KAS-BisaStok-00549 | E33: 63266.42 | F33: Aliexpress Furqonajiy 93253631544116 Resi UC917272223CN
A34: 43295.001 | B34: Piutang AliExpress | C34: PIU-BisaStok-00550 | D34: 66634.771 | F34: Aliexpress Furqonajiy 93253631614116 Resi RY220993442CN
A35: 43295.001 | B35: Kas ITBisa | C35: KAS-BisaStok-00550 | E35: 66634.771 | F35: Aliexpress Furqonajiy 93253631614116 Resi RY220993442CN
A36: 43295.001 | B36: Piutang AliExpress | C36: PIU-BisaStok-00551 | D36: 67952.821 | F36: Aliexpress Furqonajiy 93253631654116 Resi UC919314371CN
A37: 43295.001 | B37: Kas ITBisa | C37: KAS-BisaStok-00551 | E37: 67952.821 | F37: Aliexpress Furqonajiy 93253631654116 Resi UC919314371CN
A38: 43295.001 | B38: Piutang AliExpress | C38: PIU-BisaStok-00552 | D38: 68685.071 | F38: Aliexpress Furqonajiy 93253631694116 Resi LP113384050SG
A39: 43295.001 | B39: Kas ITBisa | C39: KAS-BisaStok-00552 | E39: 68685.071 | F39: Aliexpress Furqonajiy 93253631694116 Resi LP113384050SG
A40: 43295.001 | B40: Piutang AliExpress | C40: PIU-BisaStok-00484 | D40: 63266.42 | F40: Aliexpress Furqonajiy 93253631544116 Resi UC917272223CN
A41: 43295.001 | B41: Kas ITBisa | C41: KAS-BisaStok-00484 | E41: 63266.42 | F41: Aliexpress Furqonajiy 93253631544116 Resi UC917272223CN
A42: 43295.001 | B42: Piutang AliExpress | C42: PIU-BisaStok-00485 | D42: 63266.42 | F42: Aliexpress Furqonajiy 93253631584116 Resi UC917303098CN
A43: 43295.001 | B43: Kas ITBisa | C43: KAS-BisaStok-00485 | E43: 63266.42 | F43: Aliexpress Furqonajiy 93253631584116 Resi UC917303098CN
A44: 43295.001 | B44: Piutang AliExpress | C44: PIU-BisaStok-00486 | D44: 66634.771 | F44: Aliexpress Furqonajiy 93253631614116 Resi RY220993442CN
A45: 43295.001 | B45: Kas ITBisa | C45: KAS-BisaStok-00486 | E45: 66634.771 | F45: Aliexpress Furqonajiy 93253631614116 Resi RY220993442CN
A46: 43295.001 | B46: Piutang AliExpress | C46: PIU-BisaStok-00487 | D46: 66634.771 | F46: Aliexpress Furqonajiy 93253631654116 Resi UC919314371CN
A47: 43295.001 | B47: Kas ITBisa | C47: KAS-BisaStok-00487 | E47: 66634.771 | F47: Aliexpress Furqonajiy 93253631654116 Resi UC919314371CN
A48: 43295.001 | B48: Piutang AliExpress | C48: PIU-BisaStok-00488 | D48: 64584.47 | F48: Aliexpress Furqonajiy 93253631694116 Resi LP113384050SG
A49: 43295.001 | B49: Kas ITBisa | C49: KAS-BisaStok-00488 | E49: 64584.47 | F49: Aliexpress Furqonajiy 93253631694116 Resi LP113384050SG
A50: 43295.001 | B50: Piutang AliExpress | C50: PIU-BisaStok-00489 | D50: 65609.62 | F50: Aliexpress Furqonajiy 93253631734116 Resi UC915005176CN
A51: 43295.001 | B51: Kas ITBisa | C51: KAS-BisaStok-00489 | E51: 65609.62 | F51: Aliexpress Furqonajiy 93253631734116 Resi UC915005176CN
A52: 43296 | B52: Piutang Bukalapak | C52: PIU-BisaStok-00223 | D52: 350000 | F52: BukaReksa Furqonajiy
A53: 43296 | B53: Kas ITBisa | C53: KAS-BisaStok-00223 | E53: 350000 | F53: BukaReksa Furqonajiy
A54: 43297 | B54: Persediaan ITBISA-BUKAREKSA-SYARIAH-MANDIRI-PASAR-UANG | C54: INV-BisaStok-00223 | D54: 350000 | F54: BukaReksa Furqonajiy
A55: 43297 | B55: Piutang Bukalapak | C55: PIU-BisaStok-00223 | E55: 350000 | F55: BukaReksa Furqonajiy
A56: 43298 | B56: Piutang AliExpress | C56: PIU-BisaStok-00408 | D56: 864740.37 | F56: Aliexpress Furqonajiy 93056048434116 Resi LP113971280SG
A57: 43298 | B57: Kas ITBisa | C57: KAS-BisaStok-00408 | E57: 864740.37 | F57: Aliexpress Furqonajiy 93056048434116 Resi LP113971280SG
A58: 43298 | B58: Piutang AliExpress | C58: PIU-BisaStok-00949 | D58: 558976.63 | F58: Aliexpress Furqonajiy 93056048424116 Resi RU869777975CN (-) Kaki tidak rapi (-) Packing menggunakan klip dan tidak rapi
A59: 43298 | B59: Kas ITBisa | C59: KAS-BisaStok-00949 | E59: 558976.63 | F59: Aliexpress Furqonajiy 93056048424116 Resi RU869777975CN (-) Kaki tidak rapi (-) Packing menggunakan klip dan tidak rapi
A60: 43299 | B60: Piutang Bukalapak | C60: PIU-BisaStok-00207 | D60: 199486 | F60: BukaEmas ITBisa
A61: 43299 | B61: Kas ITBisa | C61: KAS-BisaStok-00207 | E61: 199486 | F61: BukaEmas ITBisa
A62: 43299 | B62: Persediaan ITBISA-BUKAEMAS | C62: INV-BisaStok-00207 | D62: 199486 | F62: BukaEmas ITBisa
A63: 43299 | B63: Piutang Bukalapak | C63: PIU-BisaStok-00207 | E63: 199486 | F63: BukaEmas ITBisa
A64: 43299 | B64: Piutang Local - Other | C64: PIU-BisaStok-00838 | D64: 100000 | F64: BNI Syariah ITBisa
A65: 43299 | B65: Kas ITBisa | C65: KAS-BisaStok-00838 | E65: 100000 | F65: BNI Syariah ITBisa
A66: 43299 | B66: Persediaan ITBISA-SALDO-KUNCI-BNI-SYARIAH | C66: INV-BisaStok-00838 | D66: 100000 | F66: BNI Syariah ITBisa
A67: 43299 | B67: Piutang Local - Other | C67: PIU-BisaStok-00838 | E67: 100000 | F67: BNI Syariah ITBisa
A68: 43299 | B68: Piutang Local - Other | C68: PIU-BisaStok-00840 | D68: 100000 | F68: Mandiri ITBisa
A69: 43299 | B69: Kas ITBisa | C69: KAS-BisaStok-00840 | E69: 100000 | F69: Mandiri ITBisa
A70: 43299 | B70: Persediaan ITBISA-SALDO-KUNCI-MANDIRI | C70: INV-BisaStok-00840 | D70: 100000 | F70: Mandiri ITBisa
A71: 43299 | B71: Piutang Local - Other | C71: PIU-BisaStok-00840 | E71: 100000 | F71: Mandiri ITBisa
A72: 43300 | B72: Piutang Bukalapak | C72: PIU-BisaStok-00205 | D72: 199821 | F72: BukaEmas ITBisa
A73: 43300 | B73: Kas ITBisa | C73: KAS-BisaStok-00205 | E73: 199821 | F73: BukaEmas ITBisa
A74: 43300 | B74: Persediaan ITBISA-BUKAEMAS | C74: INV-BisaStok-00205 | D74: 199821 | F74: BukaEmas ITBisa
A75: 43300 | B75: Piutang Bukalapak | C75: PIU-BisaStok-00205 | E75: 199821 | F75: BukaEmas ITBisa
A76: 43300 | B76: Piutang Bukalapak | C76: PIU-BisaStok-00206 | D76: 199821 | F76: BukaEmas ITBisa
A77: 43300 | B77: Kas ITBisa | C77: KAS-BisaStok-00206 | E77: 199821 | F77: BukaEmas ITBisa
A78: 43300 | B78: Persediaan ITBISA-BUKAEMAS | C78: INV-BisaStok-00206 | D78: 199821 | F78: BukaEmas ITBisa
A79: 43300 | B79: Piutang Bukalapak | C79: PIU-BisaStok-00206 | E79: 199821 | F79: BukaEmas ITBisa
A80: 43300 | B80: Piutang Bukalapak | C80: PIU-BisaStok-00222 | D80: 750000 | F80: BukaReksa Furqonajiy
A81: 43300 | B81: Kas ITBisa | C81: KAS-BisaStok-00222 | E81: 750000 | F81: BukaReksa Furqonajiy
A82: 43301 | B82: Persediaan ITBISA-BUKAREKSA-SYARIAH-MANDIRI-PASAR-UANG | C82: INV-BisaStok-00222 | D82: 750000 | F82: BukaReksa Furqonajiy
A83: 43301 | B83: Piutang Bukalapak | C83: PIU-BisaStok-00222 | E83: 750000 | F83: BukaReksa Furqonajiy
A84: 43306.001 | B84: Piutang Shopee | C84: PIU-BisaStok-00957 | D84: 393000 | F84: Shopee Furqonajiy 18072514324BUKU Resi JNE MDCAH00175405118
A85: 43306.001 | B85: Kas ITBisa | C85: KAS-BisaStok-00957 | E85: 393000 | F85: Shopee Furqonajiy 18072514324BUKU Resi JNE MDCAH00175405118
A86: 43309.001 | B86: Persediaan ITBISA-TIGERHEAD-SENTER-KUNING-FT300 | C86: INV-BisaStok-00957 | D86: 393000 | F86: Shopee Furqonajiy 18072514324BUKU Resi JNE MDCAH00175405118
A87: 43309.001 | B87: Piutang Shopee | C87: PIU-BisaStok-00957 | E87: 393000 | F87: Shopee Furqonajiy 18072514324BUKU Resi JNE MDCAH00175405118
A88: 43309.001 | B88: Piutang Local - Other | C88: PIU-BisaStok-00563 | F88: ITBisa Web
A89: 43309.001 | B89: Kas ITBisa | C89: KAS-BisaStok-00563 | F89: ITBisa Web
A90: 43309.001 | B90: Persediaan ITBISA-KODE-UNIK | C90: INV-BisaStok-00563 | F90: ITBisa Web
A91: 43309.001 | B91: Piutang Local - Other | C91: PIU-BisaStok-00563 | F91: ITBisa Web
A92: 43313 | B92: Persediaan ITBISA-JUMPER-MF-10CM | C92: INV-BisaStok-00517 | D92: 63266.42 | F92: Aliexpress Furqonajiy 93253631544116 Resi UC917272223CN
A93: 43313 | B93: Piutang AliExpress | C93: PIU-BisaStok-00517 | E93: 63266.42 | F93: Aliexpress Furqonajiy 93253631544116 Resi UC917272223CN
A94: 43313 | B94: Persediaan ITBISA-JUMPER-MF-10CM | C94: INV-BisaStok-00518 | D94: 63266.42 | F94: Aliexpress Furqonajiy 93253631584116 Resi UC917303098CN
A95: 43313 | B95: Piutang AliExpress | C95: PIU-BisaStok-00518 | E95: 63266.42 | F95: Aliexpress Furqonajiy 93253631584116 Resi UC917303098CN
A96: 43313 | B96: Persediaan ITBISA-JUMPER-MF-10CM | C96: INV-BisaStok-00519 | D96: 66634.771 | F96: Aliexpress Furqonajiy 93253631614116 Resi RY220993442CN
A97: 43313 | B97: Piutang AliExpress | C97: PIU-BisaStok-00519 | E97: 66634.771 | F97: Aliexpress Furqonajiy 93253631614116 Resi RY220993442CN
A98: 43313 | B98: Persediaan ITBISA-JUMPER-MF-10CM | C98: INV-BisaStok-00520 | D98: 66634.771 | F98: Aliexpress Furqonajiy 93253631654116 Resi UC919314371CN
A99: 43313 | B99: Piutang AliExpress | C99: PIU-BisaStok-00520 | E99: 66634.771 | F99: Aliexpress Furqonajiy 93253631654116 Resi UC919314371CN
A100: 43313 | B100: Persediaan ITBISA-JUMPER-MF-10CM | C100: INV-BisaStok-00521 | D100: 66634.771 | F100: Aliexpress Furqonajiy 93253631694116 Resi LP113384050SG
...

Sheet BisaRekapBarangBackend
A1: {={"Alamat Penerima"; SORT(IF(UNIQUE(TRIM(UPPER({BisaStok!D3:D1123;BisaPindahBarang!C2:C1123;BisaPindahBarang!D2:D1123;BisaHilang!G2:G1123})))="",,UNIQUE(TRIM(UPPER({BisaStok!D3:D1123;BisaPindahBarang!C2:C1123;BisaPindahBarang!D2:D1123;BisaHilang!G2:G1123})))))}} -> Alamat Penerima | B1: {={"Harga Impor Barang (Rupiah)";IF(A2:A1123="",,IF(SUMIF(BisaStok!D3:D1123&BisaStok!E3:E1123&IF(BisaStok!C3:C1123<2,FALSE,TRUE),A2:A1123&TRUE&FALSE,BisaStok!X3:X1123)<1,,SUMIF(BisaStok!D3:D1123&BisaStok!E3:E1123&IF(BisaStok!C3:C1123<2,FALSE,TRUE),A2:A1123&TRUE&FALSE,BisaStok!X3:X1123)))}} -> Harga Impor Barang (Rupiah) | C1: =IFERROR(__xludf.DUMMYFUNCTION("ARRAYFORMULA({""Harga Impor Barang (USD)"";If(B2:B1123="""",,B2:B1123/GOOGLEFINANCE(""CURRENCY:USDIDR""))})"),"Harga Impor Barang (USD)") -> Harga Impor Barang (USD) | D1: {={"SKU","Tanggal Pesan Terakhir","HPP Terakhir"; SORT({ SORT(UNIQUE(BisaSEO!A2:A1123)),IFERROR(IF(SORT(UNIQUE(BisaSEO!A2:A1123))="",,{ VLOOKUP(SORT(BisaSEO!A2:A1123),SORT({'Import-BisaJual'!A2:A1123,'Import-BisaJual'!B2:B1123},1,TRUE,2,FALSE),2,FALSE), VLOOKUP(SORT(BisaSEO!A2:A1123),SORT({BisaStok!A3:A1123,BisaStok!B3:B1123,BisaStok!AC3:AC1123},1,TRUE,2,FALSE),3,FALSE)}),"") },1,TRUE)}} -> SKU | E1: Tanggal Pesan Terakhir | F1: HPP Terakhir | G1: {={"HPP Belum Terjual";IF(D2:D1123="",,F2:F1123*H2:H1123)}} -> HPP Belum Terjual | H1: {={"Total Stok"; IF(D2:D1123="",,IF(SUMIF(IF(COLUMN(M2:O1123),ROW(M2:O1123)),ROW(M2:O1123),M2:O1123)=0,,SUMIF(IF(COLUMN(M2:O1123),ROW(M2:O1123)),ROW(M2:O1123),M2:O1123)))}} -> Total Stok | I1: {={"1/2 Total Stok"; IF(H2:H1123="",,ROUNDDOWN(H2:H1123/2,0))}} -> 1/2 Total Stok | J1: {={"1/3 Total Stok"; IF(H2:H1123="",,ROUNDDOWN(H2:H1123/3,0))}} -> 1/3 Total Stok | K1: {={"40% Total Stok"; IF(H2:H1123="",,ROUNDDOWN(H2:H1123*40%,0))}} -> 40% Total Stok | L1: {={"20% Total Stok"; IF(H2:H1123="",,ROUNDDOWN(H2:H1123*20%,0))}} -> 20% Total Stok | M1: {=TRANSPOSE(SORT(TRANSPOSE(IF( ABS(BisaRekapGudangBackend!A1:AE1)<0.5 + (BisaRekapGudangBackend!A2:AE2="BCA ITBISA") + (BisaRekapGudangBackend!A2:AE2="BLIBLI ITBISA") + (BisaRekapGudangBackend!A2:AE2="BNI SYARIAH ITBISA") + (BisaRekapGudangBackend!A2:AE2="BRI ITBISA") + (BisaRekapGudangBackend!A2:AE2="MANDIRI ITBISA") ,,{BisaRekapGudangBackend!A2:AE2;IF(ABS(BisaRekapGudangBackend!A3:Y1123)<1,,BisaRekapGudangBackend!A3:Y1123)}))))} -> KERTASARI CIAMIS | N1: KYAI KONTONG
A2: AVRG ITB | D2: ITBISA-7SEGMENT-ANODE-RED-0.56-1BIT | E2: 46014 | F2: 675.9248 | G2: 4937630.7 | H2: 7305 | I2: 3652 | J2: 2435 | K2: 2922 | L2: 1461 | M2: 255 | N2: 7050
A3: BCA ITBISA | D3: ITBISA-7SEGMENT-ANODE-RED-1.00-1BIT | E3: 46003 | F3: 2000 | G3: 4318000 | H3: 2159 | I3: 1079 | J3: 719 | K3: 863 | L3: 431 | M3: 519 | N3: 1640
A4: BLIBLI ITBISA | D4: ITBISA-7SEGMENT-ANODE-RED-1.20-1BIT | E4: 46006 | F4: 3611.7333 | G4: 7646039.5 | H4: 2117 | I4: 1058 | J4: 705 | K4: 846 | L4: 423 | M4: 782 | N4: 1335
A5: BNI SYARIAH ITBISA | D5: ITBISA-7SEGMENT-ANODE-RED-2.30-1BIT | E5: 45715 | F5: 6028 | G5: 0
A6: BRI ITBISA | D6: ITBISA-7SEGMENT-CATHODE-RED-0.56-1BIT | E6: 46020 | F6: 731 | G6: 2095046 | H6: 2866 | I6: 1433 | J6: 955 | K6: 1146 | L6: 573 | M6: 1752 | N6: 1114
A7: BUKAEMAS FURQONAJIY | D7: ITBISA-7SEGMENT-CATHODE-RED-1.00-1BIT | G7: 0
A8: BUKAEMAS ITBISA | D8: ITBISA-7SEGMENT-CATHODE-RED-1.20-1BIT | E8: 46000 | F8: 2756 | G8: 1113424 | H8: 404 | I8: 202 | J8: 134 | K8: 161 | L8: 80 | M8: 87 | N8: 317
A9: BUKAREKSA FURQONAJIY | D9: ITBISA-7SEGMENT-CATHODE-RED-2.30-1BIT | E9: 46022 | F9: 6028 | G9: 361680 | H9: 60 | I9: 30 | J9: 20 | K9: 24 | L9: 12 | M9: 8 | N9: 52
A10: KAETOBO RESIDENCE | D10: ITBISA-ABC-BATERAI-9V-ALKALINE | G10: 0
A11: KERTASARI CIAMIS | D11: ITBISA-ABC-BATERAI-9V-POWER | E11: 46019 | F11: 11211 | G11: 100899 | H11: 9 | I11: 4 | J11: 3 | K11: 3 | L11: 1 | M11: 8 | N11: 1
A12: KOST RUMAHUMI | D12: ITBISA-ABC-BATERAI-AA-ALKALINE | E12: 46022 | F12: 3845.4566 | G12: 4014656.7 | H12: 1044 | I12: 522 | J12: 348 | K12: 417 | L12: 208 | M12: 250 | N12: 794
A13: KOST SRITUNGGAL | D13: ITBISA-ABC-BATERAI-AAA-ALKALINE | E13: 46020 | F13: 3612.5312 | G13: 5086444 | H13: 1408 | I13: 704 | J13: 469 | K13: 563 | L13: 281 | M13: 35 | N13: 1373
A14: KYAI KONTONG | D14: ITBISA-ABC-BATERAI-D-ALKALINE | G14: 0
A15: MANDIRI ITBISA | D15: ITBISA-ABC-BATERAI-D-BIRU | E15: 43362 | F15: 5000 | G15: 0
A16: RANCAEKEK ESTU | D16: ITBISA-ABC-BATERAI-D-POWER | E16: 45841 | F16: 5166.6667 | G16: 5166.6667 | H16: 1 | I16: 0 | J16: 0 | K16: 0 | L16: 0 | N16: 1
A17: RUMAH MUZAKKI | D17: ITBISA-ABC-SENTER-LED-ALKALINE | E17: 45355 | G17: 0
A18: RUMAH SYAFIRA | D18: ITBISA-ARDUINO-UNO-R3-328P-SMD | E18: 45997 | F18: 37978.259 | G18: 9912325.7 | H18: 261 | I18: 130 | J18: 87 | K18: 104 | L18: 52 | M18: 221 | N18: 40
A19: WARUNG IBU | D19: ITBISA-ARDUINO-UNO-R3-CLONE-CABLE30CM | E19: 45200 | F19: 38232.143 | G19: 0
D20: ITBISA-ARDUINO-UNO-R3-CLONE-CABLE50CM | F20: 39217.154 | G20: 0
D21: ITBISA-BLUETOOTH-MODULE-HC05 | E21: 46011 | F21: 29027.08 | G21: 1277191.5 | H21: 44 | I21: 22 | J21: 14 | K21: 17 | L21: 8 | M21: 6 | N21: 38
D22: ITBISA-BREADBOARD-830HOLE-MB102 | E22: 46015 | F22: 7000 | G22: 203000 | H22: 29 | I22: 14 | J22: 9 | K22: 11 | L22: 5 | M22: 24 | N22: 5
D23: ITBISA-BUBBLE-WRAP | E23: 46000 | G23: 0 | H23: -13 | I23: -6 | J23: -4 | K23: -5 | L23: -2 | M23: -11 | N23: -2
D24: ITBISA-BUKAEMAS | E24: 43326 | F24: 611959.37 | G24: 0
D25: ITBISA-BUKAREKSA-BAHANA-MES-SYARIAH | E25: 43326 | F25: 1114.41 | G25: 0
D26: ITBISA-BUKAREKSA-CIMB-PRINCIPAL-PASAR-UANG | E26: 43326 | F26: 1110.3901 | G26: 0
D27: ITBISA-BUKAREKSA-CIPTA-SYARIAH-BALANCE | G27: 0
D28: ITBISA-BUKAREKSA-MANDIRI-INVESTA-DANA-SYARIAH | G28: 0
D29: ITBISA-BUKAREKSA-MANDIRI-INVESTA-PASAR-UANG | E29: 43326 | F29: 1421.4005 | G29: 0
D30: ITBISA-BUKAREKSA-SUCORINVEST-SHARIA-EQUITY-FUND | E30: 43326 | G30: 0
D31: ITBISA-BUKAREKSA-SYARIAH-MANDIRI-PASAR-UANG | E31: 43326 | F31: 1107.9925 | G31: 0
D32: ITBISA-BUZZER-ACTIVE-5V | E32: 46019 | F32: 1170.311 | G32: 3715737.4 | H32: 3175 | I32: 1587 | J32: 1058 | K32: 1270 | L32: 635 | M32: 1037 | N32: 2138
D33: ITBISA-CHIP-ESP32-WROOM | E33: 46016 | F33: 23076 | G33: 392292 | H33: 17 | I33: 8 | J33: 5 | K33: 6 | L33: 3 | M33: 22 | N33: -5
D34: ITBISA-CHIP-ESP32-WROOM-ANTENNA | F34: 24820 | G34: 198560 | H34: 8 | I34: 4 | J34: 2 | K34: 3 | L34: 1 | N34: 8
D35: ITBISA-CHIP-ESP8266-ESP12F | E35: 45981 | F35: 13937.05 | G35: 1951187 | H35: 140 | I35: 70 | J35: 46 | K35: 56 | L35: 28 | M35: 138 | N35: 2
D36: ITBISA-CORSAIR-VENGEANCE-K66 | E36: 43527 | F36: 670000 | G36: 0
D37: ITBISA-DC-TO-DC-STEPDOWN-LM2596 | E37: 46015 | F37: 4973.93 | G37: 1124108.2 | H37: 226 | I37: 113 | J37: 75 | K37: 90 | L37: 45 | M37: 101 | N37: 125
D38: ITBISA-DC-TO-DC-STEPDOWN-XL4005 | E38: 46000 | F38: 8461.025 | G38: 1167621.4 | H38: 138 | I38: 69 | J38: 46 | K38: 55 | L38: 27 | M38: 67 | N38: 71
D39: ITBISA-DC-TO-DC-STEPDOWN-XL4015 | E39: 46015 | F39: 8384.9833 | G39: 1442217.1 | H39: 172 | I39: 86 | J39: 57 | K39: 68 | L39: 34 | M39: 119 | N39: 53
D40: ITBISA-DC-TO-DC-STEPUP-XL6009 | E40: 46022 | F40: 6910.9 | G40: 1921230.2 | H40: 278 | I40: 139 | J40: 92 | K40: 111 | L40: 55 | M40: 186 | N40: 92
D41: ITBISA-DIODE-1N4007 | G41: 0
D42: ITBISA-EMLOCK-ACM-Y180 | E42: 43798 | G42: 0
D43: ITBISA-EPSON-L310 | E43: 43464 | F43: 1293750 | G43: 0
D44: ITBISA-I2C-IIC-LCD | E44: 46022 | F44: 5617.6 | G44: 381996.8 | H44: 68 | I44: 34 | J44: 22 | K44: 27 | L44: 13 | M44: 31 | N44: 37
D45: ITBISA-IC-4N35-DIP6-BLACK | G45: 0
D46: ITBISA-IC-4N35-DIP6-WHITE | E46: 45022 | F46: 9.78 | G46: 0
D47: ITBISA-IC-74HC245N-DIP20 | E47: 45979 | F47: 1339 | G47: 0
D48: ITBISA-IC-74HC595N-DIP16 | E48: 46022 | F48: 639.424 | G48: 2611407.6 | H48: 4084 | I48: 2042 | J48: 1361 | K48: 1633 | L48: 816 | M48: 14 | N48: 4070
D49: ITBISA-IC-78L05-TO92 | E49: 45996 | F49: 161.42 | G49: 0
D50: ITBISA-IC-ATMEGA328P-DIP28 | E50: 46015 | F50: 27318.462 | G50: 5190507.7 | H50: 190 | I50: 95 | J50: 63 | K50: 76 | L50: 38 | M50: 159 | N50: 31
D51: ITBISA-IC-CD4017BE-DIP16 | E51: 46016 | F51: 727.964 | G51: 3760662 | H51: 5166 | I51: 2583 | J51: 1722 | K51: 2066 | L51: 1033 | N51: 5166
D52: ITBISA-IC-CD4094BE-DIP16 | E52: 45709 | F52: 779.544 | G52: 7795440 | H52: 10000 | I52: 5000 | J52: 3333 | K52: 4000 | L52: 2000 | N52: 10000
D53: ITBISA-IC-CD4094BM-SMD-SOP16 | E53: 46020 | F53: 874.83483 | G53: 762855.98 | H53: 872 | I53: 436 | J53: 290 | K53: 348 | L53: 174 | M53: 494 | N53: 378
D54: ITBISA-IC-CD4511BE-DIP16 | E54: 45405 | F54: 2425 | G54: 0
D55: ITBISA-IC-JRC4558D-DIP8 | E55: 46017 | F55: 552.98952 | G55: 1498048.6 | H55: 2709 | I55: 1354 | J55: 903 | K55: 1083 | L55: 541 | M55: 1000 | N55: 1709
D56: ITBISA-IC-L7805CV-TO220 | E56: 46013 | F56: 1140.7243 | G56: 5168622 | H56: 4531 | I56: 2265 | J56: 1510 | K56: 1812 | L56: 906 | M56: 932 | N56: 3599
D57: ITBISA-IC-L7809CV-TO220 | E57: 45527 | F57: 1448.0667 | G57: 0
D58: ITBISA-IC-L7812CV-TO220 | E58: 46019 | F58: 1057 | G58: 1144731 | H58: 1083 | I58: 541 | J58: 361 | K58: 433 | L58: 216 | M58: 802 | N58: 281
D59: ITBISA-IC-L7815CV-TO220 | G59: 0
D60: ITBISA-IC-LM741CN-DIP8 | E60: 45965 | F60: 1291.1 | G60: 27113.1 | H60: 21 | I60: 10 | J60: 7 | K60: 8 | L60: 4 | N60: 21
D61: ITBISA-IC-NE555P-DIP8 | E61: 46022 | F61: 288.887 | G61: 1521567.8 | H61: 5267 | I61: 2633 | J61: 1755 | K61: 2106 | L61: 1053 | M61: 2992 | N61: 2275
D62: ITBISA-IC-PC817-DIP4 | E62: 46022 | F62: 340.3485 | G62: 1347099.4 | H62: 3958 | I62: 1979 | J62: 1319 | K62: 1583 | L62: 791 | M62: 1748 | N62: 2210
D63: ITBISA-IC-UA741CN-DIP8 | E63: 46022 | F63: 572 | G63: 2864004 | H63: 5007 | I63: 2503 | J63: 1669 | K63: 2002 | L63: 1001 | M63: 4619 | N63: 388
D64: ITBISA-IC-ULN2003AN-DIP16 | E64: 46021 | F64: 855.5 | G64: 2073732 | H64: 2424 | I64: 1212 | J64: 808 | K64: 969 | L64: 484 | M64: 1214 | N64: 1210
D65: ITBISA-IC-ULN2803APG-DIP18 | E65: 46021 | F65: 1018 | G65: 1344778 | H65: 1321 | I65: 660 | J65: 440 | K65: 528 | L65: 264 | M65: 423 | N65: 898
D66: ITBISA-IDC-2X5-AMPHENOL-FEMALE | E66: 46016 | F66: 730 | G66: 886950 | H66: 1215 | I66: 607 | J66: 405 | K66: 486 | L66: 243 | M66: 1021 | N66: 194
D67: ITBISA-IDC-2X5-AMPHENOL-MALE | E67: 46019 | F67: 585.402 | G67: 525105.59 | H67: 897 | I67: 448 | J67: 299 | K67: 358 | L67: 179 | M67: 412 | N67: 485
D68: ITBISA-IGAME-GTX-1070-8GB-DDR5-X-TOP-TRIPLE-FAN | E68: 43444 | F68: 7889000 | G68: 0
D69: ITBISA-INFRARED-1838 | E69: 46022 | F69: 607.75 | G69: 677641.25 | H69: 1115 | I69: 557 | J69: 371 | K69: 446 | L69: 223 | M69: 552 | N69: 563
D70: ITBISA-JACK-DC-005-FEMALE | E70: 46021 | F70: 325.97464 | G70: 828627.52 | H70: 2542 | I70: 1271 | J70: 847 | K70: 1016 | L70: 508 | M70: 344 | N70: 2198
D71: ITBISA-JUMPER-FF-10CM | E71: 46001 | F71: 165.045 | G71: 1201527.6 | H71: 7280 | I71: 3640 | J71: 2426 | K71: 2912 | L71: 1456 | M71: 5600 | N71: 1680
D72: ITBISA-JUMPER-FF-20CM | E72: 46002 | F72: 165.05558 | G72: 1188400.2 | H72: 7200 | I72: 3600 | J72: 2400 | K72: 2880 | L72: 1440 | M72: 3120 | N72: 4080
D73: ITBISA-JUMPER-MF-10CM | E73: 46017 | F73: 165.0465 | G73: 1366585 | H73: 8280 | I73: 4140 | J73: 2760 | K73: 3312 | L73: 1656 | M73: 5240 | N73: 3040
D74: ITBISA-JUMPER-MF-20CM | E74: 46010 | F74: 179.24125 | G74: 996581.35 | H74: 5560 | I74: 2780 | J74: 1853 | K74: 2224 | L74: 1112 | M74: 2440 | N74: 3120
D75: ITBISA-JUMPER-MM-10CM | E75: 46017 | F75: 165.0465 | G75: 845038.08 | H75: 5120 | I75: 2560 | J75: 1706 | K75: 2048 | L75: 1024 | M75: 1560 | N75: 3560
D76: ITBISA-JUMPER-MM-20CM | E76: 46010 | F76: 187.38487 | G76: 989392.11 | H76: 5280 | I76: 2640 | J76: 1760 | K76: 2112 | L76: 1056 | M76: 2600 | N76: 2680
D77: ITBISA-KAPASITOR-ELCO-2200UF-25V | E77: 46011 | F77: 829.248 | G77: 386429.57 | H77: 466 | I77: 233 | J77: 155 | K77: 186 | L77: 93 | N77: 466
D78: ITBISA-KODE-UNIK | G78: 0 | H78: 1 | I78: 0 | J78: 0 | K78: 0 | L78: 0 | O78: 1
D79: ITBISA-KUPLUK-HITAM | F79: 8715.3846 | G79: 0
D80: ITBISA-LCD-16X2-BLUE | E80: 45994 | F80: 9482.4778 | G80: 1081002.5 | H80: 114 | I80: 57 | J80: 38 | K80: 45 | L80: 22 | M80: 23 | N80: 91
D81: ITBISA-LCD-16X2-GREEN | E81: 46019 | F81: 11443.12 | G81: 961222.08 | H81: 84 | I81: 42 | J81: 28 | K81: 33 | L81: 16 | M81: 24 | N81: 60
D82: ITBISA-LDR-GL5516 | E82: 45995 | F82: 285.14019 | G82: 145136.36 | H82: 509 | I82: 254 | J82: 169 | K82: 203 | L82: 101 | M82: 109 | N82: 400
D83: ITBISA-LED-MAX7219-4IN1-GAP | E83: 45505 | F83: 36500 | G83: 182500 | H83: 5 | I83: 2 | J83: 1 | K83: 2 | L83: 1 | M83: 5
D84: ITBISA-LED-MAX7219-4IN1-TIGHT | E84: 45970 | F84: 35799.38 | G84: 3257743.6 | H84: 91 | I84: 45 | J84: 30 | K84: 36 | L84: 18 | M84: 62 | N84: 29
D85: ITBISA-LED-SUPERBRIGHT-5MM-BLUE | E85: 46022 | F85: 58.82 | G85: 314510.54 | H85: 5347 | I85: 2673 | J85: 1782 | K85: 2138 | L85: 1069 | M85: 2690 | N85: 2657
D86: ITBISA-LED-SUPERBRIGHT-5MM-GREEN | E86: 46020 | F86: 64.35 | G86: 65379.6 | H86: 1016 | I86: 508 | J86: 338 | K86: 406 | L86: 203 | M86: 964 | N86: 52
D87: ITBISA-LED-SUPERBRIGHT-5MM-RED | E87: 46021 | F87: 52.64 | G87: 298942.56 | H87: 5679 | I87: 2839 | J87: 1893 | K87: 2271 | L87: 1135 | M87: 983 | N87: 4696
D88: ITBISA-LED-SUPERBRIGHT-5MM-WHITE | E88: 46022 | F88: 76.625 | G88: 221293 | H88: 2888 | I88: 1444 | J88: 962 | K88: 1155 | L88: 577 | M88: 2525 | N88: 363
D89: ITBISA-LED-SUPERBRIGHT-5MM-YELLOW | E89: 46021 | F89: 66.666667 | G89: 53733.333 | H89: 806 | I89: 403 | J89: 268 | K89: 322 | L89: 161 | M89: 490 | N89: 316
D90: ITBISA-LOGITECH-F710 | E90: 43458 | F90: 382000 | G90: 0
D91: ITBISA-MICRO-SD-READER-MINI | E91: 45957 | F91: 5500 | G91: 0
D92: ITBISA-MOTORDRIVER-L298N-WITH-HEATSINK | E92: 43925 | F92: 16323.333 | G92: 0
D93: ITBISA-NODEMCU-ESP32-MICRO | E93: 45468 | F93: 45000 | G93: 0
D94: ITBISA-NODEMCU-ESP32-MICRO-30PIN | E94: 45650 | F94: 43320 | G94: 0
D95: ITBISA-NODEMCU-ESP32-MICRO-38PIN | E95: 45523 | F95: 35872.632 | G95: 0
D96: ITBISA-NODEMCU-V3-CH340G-ESP8266-MICRO | E96: 46000 | F96: 23261.029 | G96: 7210918.9 | H96: 310 | I96: 155 | J96: 103 | K96: 124 | L96: 62 | M96: 119 | N96: 191
D97: ITBISA-NPN-2N2222-TO92 | E97: 46008 | F97: 106.37111 | G97: 1076369.3 | H97: 10119 | I97: 5059 | J97: 3373 | K97: 4047 | L97: 2023 | M97: 1825 | N97: 8294
D98: ITBISA-NPN-2N3904-TO92 | E98: 45858 | F98: 106.34091 | G98: 240330.45 | H98: 2260 | I98: 1130 | J98: 753 | K98: 904 | L98: 452 | M98: 1070 | N98: 1190
D99: ITBISA-NPN-2N5551-TO92 | F99: 106.43167 | G99: 127718 | H99: 1200 | I99: 600 | J99: 400 | K99: 480 | L99: 240 | M99: 200 | N99: 1000
D100: ITBISA-NPN-BC337-TO92 | E100: 45846 | F100: 106.44013 | G100: 236616.42 | H100: 2223 | I100: 1111 | J100: 741 | K100: 889 | L100: 444 | M100: 1490 | N100: 733
...

Sheet BisaRekapGudangBackend
A1: {=SUMIF(IF(ROW(A3:Y624),COLUMN(A3:Y624)),COLUMN(A3:Y624),A3:Y624)} -> 0 | B1: 1 | C1: 1 | D1: 1 | E1: 1 | F1: 0 | G1: 0 | H1: 5.6843419e-13 | I1: 0 | J1: 111981 | K1: 0 | L1: 0 | M1: 170326 | N1: 1 | O1: 0 | P1: 0 | Q1: 0 | R1: 0 | S1: 1 | T1: 0 | U1: 0 | V1: 0 | W1: 0 | X1: 0 | Y1: 0
A2: {={TRANSPOSE(UNIQUE(BisaRekapBarangBackend!A2:A624)); IF(BisaRekapBarangBackend!D2:D624="",,0 + SUMIF(BisaStok!A3:A624&BisaStok!D3:D624&(BisaStok!C3:C624>0),BisaRekapBarangBackend!D2:D624&TRANSPOSE(UNIQUE(BisaRekapBarangBackend!A2:A624))&TRUE,BisaStok!Q3:Q624) + SUMIF(BisaPindahBarang!B2:B624&BisaPindahBarang!C2:C624,BisaRekapBarangBackend!D2:D624&TRANSPOSE(UNIQUE(BisaRekapBarangBackend!A2:A624)),BisaPindahBarang!E2:E624) - SUMIF(BisaPindahBarang!B2:B624&BisaPindahBarang!D2:D624,BisaRekapBarangBackend!D2:D624&TRANSPOSE(UNIQUE(BisaRekapBarangBackend!A2:A624)),BisaPindahBarang!E2:E624) - SUMIF('Import-BisaJual'!A2:A624&'Import-BisaJual'!C2:C624,BisaRekapBarangBackend!D2:D624&TRANSPOSE(UNIQUE(BisaRekapBarangBackend!A2:A624)),'Import-BisaJual'!D2:D624) + SUMIF(BisaHilang!B2:B624&BisaHilang!G2:G624,BisaRekapBarangBackend!D2:D624&TRANSPOSE(UNIQUE(BisaRekapBarangBackend!A2:A624)),BisaHilang!C2:C624) - SUMIF(BisaHilang!B2:B624&BisaHilang!G2:G624,BisaRekapBarangBackend!D2:D624&TRANSPOSE(UNIQUE(BisaRekapBarangBackend!A2:A624)),BisaHilang!E2:E624) )}} -> AVRG ITB | B2: BCA ITBISA | C2: BLIBLI ITBISA | D2: BNI SYARIAH ITBISA | E2: BRI ITBISA | F2: BUKAEMAS FURQONAJIY | G2: BUKAEMAS ITBISA | H2: BUKAREKSA FURQONAJIY | I2: KAETOBO RESIDENCE | J2: KERTASARI CIAMIS | K2: KOST RUMAHUMI | L2: KOST SRITUNGGAL | M2: KYAI KONTONG | N2: MANDIRI ITBISA | O2: RANCAEKEK ESTU | P2: RUMAH MUZAKKI | Q2: RUMAH SYAFIRA | R2: WARUNG IBU
A3: 0 | B3: 0 | C3: 0 | D3: 0 | E3: 0 | F3: 0 | G3: 0 | H3: 0 | I3: 0 | J3: 255 | K3: 0 | L3: 0 | M3: 7050 | N3: 0 | O3: 0 | P3: 0 | Q3: 0 | R3: 0 | S3: 0
A4: 0 | B4: 0 | C4: 0 | D4: 0 | E4: 0 | F4: 0 | G4: 0 | H4: 0 | I4: 0 | J4: 519 | K4: 0 | L4: 0 | M4: 1640 | N4: 0 | O4: 0 | P4: 0 | Q4: 0 | R4: 0 | S4: 0
A5: 0 | B5: 0 | C5: 0 | D5: 0 | E5: 0 | F5: 0 | G5: 0 | H5: 0 | I5: 0 | J5: 782 | K5: 0 | L5: 0 | M5: 1335 | N5: 0 | O5: 0 | P5: 0 | Q5: 0 | R5: 0 | S5: 0
A6: 0 | B6: 0 | C6: 0 | D6: 0 | E6: 0 | F6: 0 | G6: 0 | H6: 0 | I6: 0 | J6: 0 | K6: 0 | L6: 0 | M6: 0 | N6: 0 | O6: 0 | P6: 0 | Q6: 0 | R6: 0 | S6: 0
A7: 0 | B7: 0 | C7: 0 | D7: 0 | E7: 0 | F7: 0 | G7: 0 | H7: 0 | I7: 0 | J7: 1752 | K7: 0 | L7: 0 | M7: 1114 | N7: 0 | O7: 0 | P7: -3 | Q7: 0 | R7: 0 | S7: 0
A8: 0 | B8: 0 | C8: 0 | D8: 0 | E8: 0 | F8: 0 | G8: 0 | H8: 0 | I8: 0 | J8: 0 | K8: 0 | L8: 0 | M8: 0 | N8: 0 | O8: 0 | P8: 0 | Q8: 0 | R8: 0 | S8: 0
A9: 0 | B9: 0 | C9: 0 | D9: 0 | E9: 0 | F9: 0 | G9: 0 | H9: 0 | I9: 0 | J9: 87 | K9: 0 | L9: 0 | M9: 317 | N9: 0 | O9: 0 | P9: 0 | Q9: 0 | R9: 0 | S9: 0
A10: 0 | B10: 0 | C10: 0 | D10: 0 | E10: 0 | F10: 0 | G10: 0 | H10: 0 | I10: 0 | J10: 8 | K10: 0 | L10: 0 | M10: 52 | N10: 0 | O10: 0 | P10: 0 | Q10: 0 | R10: 0 | S10: 0
A11: 0 | B11: 0 | C11: 0 | D11: 0 | E11: 0 | F11: 0 | G11: 0 | H11: 0 | I11: 0 | J11: 0 | K11: 0 | L11: 0 | M11: 0 | N11: 0 | O11: 0 | P11: 0 | Q11: 0 | R11: 0 | S11: 0
A12: 0 | B12: 0 | C12: 0 | D12: 0 | E12: 0 | F12: 0 | G12: 0 | H12: 0 | I12: 0 | J12: 8 | K12: 0 | L12: 0 | M12: 1 | N12: 0 | O12: 0 | P12: 0 | Q12: 0 | R12: 0 | S12: 0
A13: 0 | B13: 0 | C13: 0 | D13: 0 | E13: 0 | F13: 0 | G13: 0 | H13: 0 | I13: 0 | J13: 250 | K13: 0 | L13: 0 | M13: 794 | N13: 0 | O13: 0 | P13: 0 | Q13: 0 | R13: 0 | S13: 0
A14: 0 | B14: 0 | C14: 0 | D14: 0 | E14: 0 | F14: 0 | G14: 0 | H14: 0 | I14: 0 | J14: 35 | K14: 0 | L14: 0 | M14: 1373 | N14: 0 | O14: 0 | P14: 0 | Q14: 0 | R14: 0 | S14: 0
... A213: 0 | B213: 0 | C213: 0 | D213: 0 | E213: 0 | F213: 0 | G213: 0 | H213: 0 | I213: 0 | J213: 0 | K213: 0 | L213: 0 | M213: 0 | N213: 0 | O213: 0 | P213: 0 | Q213: 0 | R213: 0 | S213: 0

Sheet Import-BisaJual
A1: =IFERROR(__xludf.DUMMYFUNCTION("ARRAYFORMULA({IF(IMPORTRANGE(""https://docs.google.com/spreadsheets/d/1yismcdwflLF6yw9e2QW1De-YipgifSF_RdHGS-Eh2tk"",""Ekspor-BisaJual-BisaStok!A1:H1"")="""",, IMPORTRANGE(""https://docs.google.com/spreadsheets/d/1yismcdwflLF6yw9e2QW1De-YipgifSF_RdHGS-Eh2"&"tk"",""Ekspor-BisaJual-BisaStok!A1:H1"")); SORT(IF(IMPORTRANGE(""https://docs.google.com/spreadsheets/d/1yismcdwflLF6yw9e2QW1De-YipgifSF_RdHGS-Eh2tk"",""Ekspor-BisaJual-BisaStok!A2:H"")="""",, IMPORTRANGE(""https://docs.google.com/spreadsheets/d/1yismcdwf"&"lLF6yw9e2QW1De-YipgifSF_RdHGS-Eh2tk"",""Ekspor-BisaJual-BisaStok!A2:H"")))})"),"SKU") -> SKU | B1: =IFERROR(__xludf.DUMMYFUNCTION("""COMPUTED_VALUE"""),"Tanggal") -> Tanggal | C1: =IFERROR(__xludf.DUMMYFUNCTION("""COMPUTED_VALUE"""),"Lokasi Gudang") -> Lokasi Gudang | D1: =IFERROR(__xludf.DUMMYFUNCTION("""COMPUTED_VALUE"""),"Banyak Terjual (Buah)") -> Banyak Terjual (Buah)
A2: =IFERROR(__xludf.DUMMYFUNCTION("""COMPUTED_VALUE"""),"ITBISA-7SEGMENT-ANODE-RED-0.56-1BIT") -> ITBISA-7SEGMENT-ANODE-RED-0.56-1BIT | B2: =IFERROR(__xludf.DUMMYFUNCTION("""COMPUTED_VALUE"""),43484.0) -> 43484 | C2: =IFERROR(__xludf.DUMMYFUNCTION("""COMPUTED_VALUE"""),"AVRG ITB") -> AVRG ITB | D2: =IFERROR(__xludf.DUMMYFUNCTION("""COMPUTED_VALUE"""),20.0) -> 20
A3: =IFERROR(__xludf.DUMMYFUNCTION("""COMPUTED_VALUE"""),"ITBISA-7SEGMENT-ANODE-RED-0.56-1BIT") -> ITBISA-7SEGMENT-ANODE-RED-0.56-1BIT | B3: =IFERROR(__xludf.DUMMYFUNCTION("""COMPUTED_VALUE"""),43501.0) -> 43501 | C3: =IFERROR(__xludf.DUMMYFUNCTION("""COMPUTED_VALUE"""),"AVRG ITB") -> AVRG ITB | D3: =IFERROR(__xludf.DUMMYFUNCTION("""COMPUTED_VALUE"""),10.0) -> 10
A4: =IFERROR(__xludf.DUMMYFUNCTION("""COMPUTED_VALUE"""),"ITBISA-7SEGMENT-ANODE-RED-0.56-1BIT") -> ITBISA-7SEGMENT-ANODE-RED-0.56-1BIT | B4: =IFERROR(__xludf.DUMMYFUNCTION("""COMPUTED_VALUE"""),43501.0) -> 43501 | C4: =IFERROR(__xludf.DUMMYFUNCTION("""COMPUTED_VALUE"""),"AVRG ITB") -> AVRG ITB | D4: =IFERROR(__xludf.DUMMYFUNCTION("""COMPUTED_VALUE"""),10.0) -> 10
A5: =IFERROR(__xludf.DUMMYFUNCTION("""COMPUTED_VALUE"""),"ITBISA-7SEGMENT-ANODE-RED-0.56-1BIT") -> ITBISA-7SEGMENT-ANODE-RED-0.56-1BIT | B5: =IFERROR(__xludf.DUMMYFUNCTION("""COMPUTED_VALUE"""),43508.0) -> 43508 | C5: =IFERROR(__xludf.DUMMYFUNCTION("""COMPUTED_VALUE"""),"AVRG ITB") -> AVRG ITB | D5: =IFERROR(__xludf.DUMMYFUNCTION("""COMPUTED_VALUE"""),10.0) -> 10
A6: =IFERROR(__xludf.DUMMYFUNCTION("""COMPUTED_VALUE"""),"ITBISA-7SEGMENT-ANODE-RED-0.56-1BIT") -> ITBISA-7SEGMENT-ANODE-RED-0.56-1BIT | B6: =IFERROR(__xludf.DUMMYFUNCTION("""COMPUTED_VALUE"""),43525.0) -> 43525 | C6: =IFERROR(__xludf.DUMMYFUNCTION("""COMPUTED_VALUE"""),"AVRG ITB") -> AVRG ITB | D6: =IFERROR(__xludf.DUMMYFUNCTION("""COMPUTED_VALUE"""),50.0) -> 50
A7: =IFERROR(__xludf.DUMMYFUNCTION("""COMPUTED_VALUE"""),"ITBISA-7SEGMENT-ANODE-RED-0.56-1BIT") -> ITBISA-7SEGMENT-ANODE-RED-0.56-1BIT | B7: =IFERROR(__xludf.DUMMYFUNCTION("""COMPUTED_VALUE"""),43525.0) -> 43525 | C7: =IFERROR(__xludf.DUMMYFUNCTION("""COMPUTED_VALUE"""),"RUMAH MUZAKKI") -> RUMAH MUZAKKI | D7: =IFERROR(__xludf.DUMMYFUNCTION("""COMPUTED_VALUE"""),50.0) -> 50
A8: =IFERROR(__xludf.DUMMYFUNCTION("""COMPUTED_VALUE"""),"ITBISA-7SEGMENT-ANODE-RED-0.56-1BIT") -> ITBISA-7SEGMENT-ANODE-RED-0.56-1BIT | B8: =IFERROR(__xludf.DUMMYFUNCTION("""COMPUTED_VALUE"""),43528.0) -> 43528 | C8: =IFERROR(__xludf.DUMMYFUNCTION("""COMPUTED_VALUE"""),"AVRG ITB") -> AVRG ITB | D8: =IFERROR(__xludf.DUMMYFUNCTION("""COMPUTED_VALUE"""),20.0) -> 20
A9: =IFERROR(__xludf.DUMMYFUNCTION("""COMPUTED_VALUE"""),"ITBISA-7SEGMENT-ANODE-RED-0.56-1BIT") -> ITBISA-7SEGMENT-ANODE-RED-0.56-1BIT | B9: =IFERROR(__xludf.DUMMYFUNCTION("""COMPUTED_VALUE"""),43528.0) -> 43528 | C9: =IFERROR(__xludf.DUMMYFUNCTION("""COMPUTED_VALUE"""),"AVRG ITB") -> AVRG ITB | D9: =IFERROR(__xludf.DUMMYFUNCTION("""COMPUTED_VALUE"""),20.0) -> 20
A10: =IFERROR(__xludf.DUMMYFUNCTION("""COMPUTED_VALUE"""),"ITBISA-7SEGMENT-ANODE-RED-0.56-1BIT") -> ITBISA-7SEGMENT-ANODE-RED-0.56-1BIT | B10: =IFERROR(__xludf.DUMMYFUNCTION("""COMPUTED_VALUE"""),43533.0) -> 43533 | C10: =IFERROR(__xludf.DUMMYFUNCTION("""COMPUTED_VALUE"""),"AVRG ITB") -> AVRG ITB | D10: =IFERROR(__xludf.DUMMYFUNCTION("""COMPUTED_VALUE"""),25.0) -> 25
A11: =IFERROR(__xludf.DUMMYFUNCTION("""COMPUTED_VALUE"""),"ITBISA-7SEGMENT-ANODE-RED-0.56-1BIT") -> ITBISA-7SEGMENT-ANODE-RED-0.56-1BIT | B11: =IFERROR(__xludf.DUMMYFUNCTION("""COMPUTED_VALUE"""),43536.0) -> 43536 | C11: =IFERROR(__xludf.DUMMYFUNCTION("""COMPUTED_VALUE"""),"AVRG ITB") -> AVRG ITB | D11: =IFERROR(__xludf.DUMMYFUNCTION("""COMPUTED_VALUE"""),50.0) -> 50
A12: =IFERROR(__xludf.DUMMYFUNCTION("""COMPUTED_VALUE"""),"ITBISA-7SEGMENT-ANODE-RED-0.56-1BIT") -> ITBISA-7SEGMENT-ANODE-RED-0.56-1BIT | B12: =IFERROR(__xludf.DUMMYFUNCTION("""COMPUTED_VALUE"""),43536.0) -> 43536 | C12: =IFERROR(__xludf.DUMMYFUNCTION("""COMPUTED_VALUE"""),"AVRG ITB") -> AVRG ITB | D12: =IFERROR(__xludf.DUMMYFUNCTION("""COMPUTED_VALUE"""),50.0) -> 50
A13: =IFERROR(__xludf.DUMMYFUNCTION("""COMPUTED_VALUE"""),"ITBISA-7SEGMENT-ANODE-RED-0.56-1BIT") -> ITBISA-7SEGMENT-ANODE-RED-0.56-1BIT | B13: =IFERROR(__xludf.DUMMYFUNCTION("""COMPUTED_VALUE"""),43556.0) -> 43556 | C13: =IFERROR(__xludf.DUMMYFUNCTION("""COMPUTED_VALUE"""),"AVRG ITB") -> AVRG ITB | D13: =IFERROR(__xludf.DUMMYFUNCTION("""COMPUTED_VALUE"""),115.0) -> 115
A14: =IFERROR(__xludf.DUMMYFUNCTION("""COMPUTED_VALUE"""),"ITBISA-7SEGMENT-ANODE-RED-0.56-1BIT") -> ITBISA-7SEGMENT-ANODE-RED-0.56-1BIT | B14: =IFERROR(__xludf.DUMMYFUNCTION("""COMPUTED_VALUE"""),43562.0) -> 43562 | C14: =IFERROR(__xludf.DUMMYFUNCTION("""COMPUTED_VALUE"""),"AVRG ITB") -> AVRG ITB | D14: =IFERROR(__xludf.DUMMYFUNCTION("""COMPUTED_VALUE"""),10.0) -> 10
A15: =IFERROR(__xludf.DUMMYFUNCTION("""COMPUTED_VALUE"""),"ITBISA-7SEGMENT-ANODE-RED-0.56-1BIT") -> ITBISA-7SEGMENT-ANODE-RED-0.56-1BIT | B15: =IFERROR(__xludf.DUMMYFUNCTION("""COMPUTED_VALUE"""),43568.0) -> 43568 | C15: =IFERROR(__xludf.DUMMYFUNCTION("""COMPUTED_VALUE"""),"AVRG ITB") -> AVRG ITB | D15: =IFERROR(__xludf.DUMMYFUNCTION("""COMPUTED_VALUE"""),200.0) -> 200
A16: =IFERROR(__xludf.DUMMYFUNCTION("""COMPUTED_VALUE"""),"ITBISA-7SEGMENT-ANODE-RED-0.56-1BIT") -> ITBISA-7SEGMENT-ANODE-RED-0.56-1BIT | B16: =IFERROR(__xludf.DUMMYFUNCTION("""COMPUTED_VALUE"""),43568.0) -> 43568 | C16: =IFERROR(__xludf.DUMMYFUNCTION("""COMPUTED_VALUE"""),"AVRG ITB") -> AVRG ITB | D16: =IFERROR(__xludf.DUMMYFUNCTION("""COMPUTED_VALUE"""),200.0) -> 200
A17: =IFERROR(__xludf.DUMMYFUNCTION("""COMPUTED_VALUE"""),"ITBISA-7SEGMENT-ANODE-RED-0.56-1BIT") -> ITBISA-7SEGMENT-ANODE-RED-0.56-1BIT | B17: =IFERROR(__xludf.DUMMYFUNCTION("""COMPUTED_VALUE"""),43581.0) -> 43581 | C17: =IFERROR(__xludf.DUMMYFUNCTION("""COMPUTED_VALUE"""),"AVRG ITB") -> AVRG ITB | D17: =IFERROR(__xludf.DUMMYFUNCTION("""COMPUTED_VALUE"""),16.0) -> 16
A18: =IFERROR(__xludf.DUMMYFUNCTION("""COMPUTED_VALUE"""),"ITBISA-7SEGMENT-ANODE-RED-0.56-1BIT") -> ITBISA-7SEGMENT-ANODE-RED-0.56-1BIT | B18: =IFERROR(__xludf.DUMMYFUNCTION("""COMPUTED_VALUE"""),43589.0) -> 43589 | C18: =IFERROR(__xludf.DUMMYFUNCTION("""COMPUTED_VALUE"""),"AVRG ITB") -> AVRG ITB | D18: =IFERROR(__xludf.DUMMYFUNCTION("""COMPUTED_VALUE"""),100.0) -> 100
A19: =IFERROR(__xludf.DUMMYFUNCTION("""COMPUTED_VALUE"""),"ITBISA-7SEGMENT-ANODE-RED-0.56-1BIT") -> ITBISA-7SEGMENT-ANODE-RED-0.56-1BIT | B19: =IFERROR(__xludf.DUMMYFUNCTION("""COMPUTED_VALUE"""),43602.0) -> 43602 | C19: =IFERROR(__xludf.DUMMYFUNCTION("""COMPUTED_VALUE"""),"AVRG ITB") -> AVRG ITB | D19: =IFERROR(__xludf.DUMMYFUNCTION("""COMPUTED_VALUE"""),100.0) -> 100
A20: =IFERROR(__xludf.DUMMYFUNCTION("""COMPUTED_VALUE"""),"ITBISA-7SEGMENT-ANODE-RED-0.56-1BIT") -> ITBISA-7SEGMENT-ANODE-RED-0.56-1BIT | B20: =IFERROR(__xludf.DUMMYFUNCTION("""COMPUTED_VALUE"""),43604.0) -> 43604 | C20: =IFERROR(__xludf.DUMMYFUNCTION("""COMPUTED_VALUE"""),"AVRG ITB") -> AVRG ITB | D20: =IFERROR(__xludf.DUMMYFUNCTION("""COMPUTED_VALUE"""),225.0) -> 225
A21: =IFERROR(__xludf.DUMMYFUNCTION("""COMPUTED_VALUE"""),"ITBISA-7SEGMENT-ANODE-RED-0.56-1BIT") -> ITBISA-7SEGMENT-ANODE-RED-0.56-1BIT | B21: =IFERROR(__xludf.DUMMYFUNCTION("""COMPUTED_VALUE"""),43604.0) -> 43604 | C21: =IFERROR(__xludf.DUMMYFUNCTION("""COMPUTED_VALUE"""),"RUMAH MUZAKKI") -> RUMAH MUZAKKI | D21: =IFERROR(__xludf.DUMMYFUNCTION("""COMPUTED_VALUE"""),10.0) -> 10
A22: =IFERROR(__xludf.DUMMYFUNCTION("""COMPUTED_VALUE"""),"ITBISA-7SEGMENT-ANODE-RED-0.56-1BIT") -> ITBISA-7SEGMENT-ANODE-RED-0.56-1BIT | B22: =IFERROR(__xludf.DUMMYFUNCTION("""COMPUTED_VALUE"""),43615.0) -> 43615 | C22: =IFERROR(__xludf.DUMMYFUNCTION("""COMPUTED_VALUE"""),"AVRG ITB") -> AVRG ITB | D22: =IFERROR(__xludf.DUMMYFUNCTION("""COMPUTED_VALUE"""),10.0) -> 10
A23: =IFERROR(__xludf.DUMMYFUNCTION("""COMPUTED_VALUE"""),"ITBISA-7SEGMENT-ANODE-RED-0.56-1BIT") -> ITBISA-7SEGMENT-ANODE-RED-0.56-1BIT | B23: =IFERROR(__xludf.DUMMYFUNCTION("""COMPUTED_VALUE"""),43641.0) -> 43641 | C23: =IFERROR(__xludf.DUMMYFUNCTION("""COMPUTED_VALUE"""),"RUMAH MUZAKKI") -> RUMAH MUZAKKI | D23: =IFERROR(__xludf.DUMMYFUNCTION("""COMPUTED_VALUE"""),52.0) -> 52
A24: =IFERROR(__xludf.DUMMYFUNCTION("""COMPUTED_VALUE"""),"ITBISA-7SEGMENT-ANODE-RED-0.56-1BIT") -> ITBISA-7SEGMENT-ANODE-RED-0.56-1BIT | B24: =IFERROR(__xludf.DUMMYFUNCTION("""COMPUTED_VALUE"""),43648.0) -> 43648 | C24: =IFERROR(__xludf.DUMMYFUNCTION("""COMPUTED_VALUE"""),"RUMAH MUZAKKI") -> RUMAH MUZAKKI | D24: =IFERROR(__xludf.DUMMYFUNCTION("""COMPUTED_VALUE"""),19.0) -> 19
A25: =IFERROR(__xludf.DUMMYFUNCTION("""COMPUTED_VALUE"""),"ITBISA-7SEGMENT-ANODE-RED-0.56-1BIT") -> ITBISA-7SEGMENT-ANODE-RED-0.56-1BIT | B25: =IFERROR(__xludf.DUMMYFUNCTION("""COMPUTED_VALUE"""),43650.0) -> 43650 | C25: =IFERROR(__xludf.DUMMYFUNCTION("""COMPUTED_VALUE"""),"RUMAH MUZAKKI") -> RUMAH MUZAKKI | D25: =IFERROR(__xludf.DUMMYFUNCTION("""COMPUTED_VALUE"""),200.0) -> 200
A26: =IFERROR(__xludf.DUMMYFUNCTION("""COMPUTED_VALUE"""),"ITBISA-7SEGMENT-ANODE-RED-0.56-1BIT") -> ITBISA-7SEGMENT-ANODE-RED-0.56-1BIT | B26: =IFERROR(__xludf.DUMMYFUNCTION("""COMPUTED_VALUE"""),43655.0) -> 43655 | C26: =IFERROR(__xludf.DUMMYFUNCTION("""COMPUTED_VALUE"""),"RUMAH MUZAKKI") -> RUMAH MUZAKKI | D26: =IFERROR(__xludf.DUMMYFUNCTION("""COMPUTED_VALUE"""),150.0) -> 150
A27: =IFERROR(__xludf.DUMMYFUNCTION("""COMPUTED_VALUE"""),"ITBISA-7SEGMENT-ANODE-RED-0.56-1BIT") -> ITBISA-7SEGMENT-ANODE-RED-0.56-1BIT | B27: =IFERROR(__xludf.DUMMYFUNCTION("""COMPUTED_VALUE"""),43684.0) -> 43684 | C27: =IFERROR(__xludf.DUMMYFUNCTION("""COMPUTED_VALUE"""),"RUMAH MUZAKKI") -> RUMAH MUZAKKI | D27: =IFERROR(__xludf.DUMMYFUNCTION("""COMPUTED_VALUE"""),100.0) -> 100
A28: =IFERROR(__xludf.DUMMYFUNCTION("""COMPUTED_VALUE"""),"ITBISA-7SEGMENT-ANODE-RED-0.56-1BIT") -> ITBISA-7SEGMENT-ANODE-RED-0.56-1BIT | B28: =IFERROR(__xludf.DUMMYFUNCTION("""COMPUTED_VALUE"""),43694.0) -> 43694 | C28: =IFERROR(__xludf.DUMMYFUNCTION("""COMPUTED_VALUE"""),"RUMAH MUZAKKI") -> RUMAH MUZAKKI | D28: =IFERROR(__xludf.DUMMYFUNCTION("""COMPUTED_VALUE"""),200.0) -> 200
A29: =IFERROR(__xludf.DUMMYFUNCTION("""COMPUTED_VALUE"""),"ITBISA-7SEGMENT-ANODE-RED-0.56-1BIT") -> ITBISA-7SEGMENT-ANODE-RED-0.56-1BIT | B29: =IFERROR(__xludf.DUMMYFUNCTION("""COMPUTED_VALUE"""),43732.0) -> 43732 | C29: =IFERROR(__xludf.DUMMYFUNCTION("""COMPUTED_VALUE"""),"RUMAH MUZAKKI") -> RUMAH MUZAKKI | D29: =IFERROR(__xludf.DUMMYFUNCTION("""COMPUTED_VALUE"""),2.0) -> 2
A30: =IFERROR(__xludf.DUMMYFUNCTION("""COMPUTED_VALUE"""),"ITBISA-7SEGMENT-ANODE-RED-0.56-1BIT") -> ITBISA-7SEGMENT-ANODE-RED-0.56-1BIT | B30: =IFERROR(__xludf.DUMMYFUNCTION("""COMPUTED_VALUE"""),43733.0) -> 43733 | C30: =IFERROR(__xludf.DUMMYFUNCTION("""COMPUTED_VALUE"""),"RUMAH MUZAKKI") -> RUMAH MUZAKKI | D30: =IFERROR(__xludf.DUMMYFUNCTION("""COMPUTED_VALUE"""),1.0) -> 1
A31: =IFERROR(__xludf.DUMMYFUNCTION("""COMPUTED_VALUE"""),"ITBISA-7SEGMENT-ANODE-RED-0.56-1BIT") -> ITBISA-7SEGMENT-ANODE-RED-0.56-1BIT | B31: =IFERROR(__xludf.DUMMYFUNCTION("""COMPUTED_VALUE"""),43753.0) -> 43753 | C31: =IFERROR(__xludf.DUMMYFUNCTION("""COMPUTED_VALUE"""),"RUMAH MUZAKKI") -> RUMAH MUZAKKI | D31: =IFERROR(__xludf.DUMMYFUNCTION("""COMPUTED_VALUE"""),100.0) -> 100
A32: =IFERROR(__xludf.DUMMYFUNCTION("""COMPUTED_VALUE"""),"ITBISA-7SEGMENT-ANODE-RED-0.56-1BIT") -> ITBISA-7SEGMENT-ANODE-RED-0.56-1BIT | B32: =IFERROR(__xludf.DUMMYFUNCTION("""COMPUTED_VALUE"""),43759.0) -> 43759 | C32: =IFERROR(__xludf.DUMMYFUNCTION("""COMPUTED_VALUE"""),"RUMAH MUZAKKI") -> RUMAH MUZAKKI | D32: =IFERROR(__xludf.DUMMYFUNCTION("""COMPUTED_VALUE"""),100.0) -> 100
A33: =IFERROR(__xludf.DUMMYFUNCTION("""COMPUTED_VALUE"""),"ITBISA-7SEGMENT-ANODE-RED-0.56-1BIT") -> ITBISA-7SEGMENT-ANODE-RED-0.56-1BIT | B33: =IFERROR(__xludf.DUMMYFUNCTION("""COMPUTED_VALUE"""),43768.0) -> 43768 | C33: =IFERROR(__xludf.DUMMYFUNCTION("""COMPUTED_VALUE"""),"RUMAH MUZAKKI") -> RUMAH MUZAKKI | D33: =IFERROR(__xludf.DUMMYFUNCTION("""COMPUTED_VALUE"""),6.0) -> 6
A34: =IFERROR(__xludf.DUMMYFUNCTION("""COMPUTED_VALUE"""),"ITBISA-7SEGMENT-ANODE-RED-0.56-1BIT") -> ITBISA-7SEGMENT-ANODE-RED-0.56-1BIT | B34: =IFERROR(__xludf.DUMMYFUNCTION("""COMPUTED_VALUE"""),43771.0) -> 43771 | C34: =IFERROR(__xludf.DUMMYFUNCTION("""COMPUTED_VALUE"""),"RUMAH MUZAKKI") -> RUMAH MUZAKKI | D34: =IFERROR(__xludf.DUMMYFUNCTION("""COMPUTED_VALUE"""),100.0) -> 100
A35: =IFERROR(__xludf.DUMMYFUNCTION("""COMPUTED_VALUE"""),"ITBISA-7SEGMENT-ANODE-RED-0.56-1BIT") -> ITBISA-7SEGMENT-ANODE-RED-0.56-1BIT | B35: =IFERROR(__xludf.DUMMYFUNCTION("""COMPUTED_VALUE"""),43783.0) -> 43783 | C35: =IFERROR(__xludf.DUMMYFUNCTION("""COMPUTED_VALUE"""),"RUMAH MUZAKKI") -> RUMAH MUZAKKI | D35: =IFERROR(__xludf.DUMMYFUNCTION("""COMPUTED_VALUE"""),10.0) -> 10
A36: =IFERROR(__xludf.DUMMYFUNCTION("""COMPUTED_VALUE"""),"ITBISA-7SEGMENT-ANODE-RED-0.56-1BIT") -> ITBISA-7SEGMENT-ANODE-RED-0.56-1BIT | B36: =IFERROR(__xludf.DUMMYFUNCTION("""COMPUTED_VALUE"""),43783.0) -> 43783 | C36: =IFERROR(__xludf.DUMMYFUNCTION("""COMPUTED_VALUE"""),"RUMAH MUZAKKI") -> RUMAH MUZAKKI | D36: =IFERROR(__xludf.DUMMYFUNCTION("""COMPUTED_VALUE"""),144.0) -> 144
A37: =IFERROR(__xludf.DUMMYFUNCTION("""COMPUTED_VALUE"""),"ITBISA-7SEGMENT-ANODE-RED-0.56-1BIT") -> ITBISA-7SEGMENT-ANODE-RED-0.56-1BIT | B37: =IFERROR(__xludf.DUMMYFUNCTION("""COMPUTED_VALUE"""),43797.0) -> 43797 | C37: =IFERROR(__xludf.DUMMYFUNCTION("""COMPUTED_VALUE"""),"RUMAH MUZAKKI") -> RUMAH MUZAKKI | D37: =IFERROR(__xludf.DUMMYFUNCTION("""COMPUTED_VALUE"""),150.0) -> 150
A38: =IFERROR(__xludf.DUMMYFUNCTION("""COMPUTED_VALUE"""),"ITBISA-7SEGMENT-ANODE-RED-0.56-1BIT") -> ITBISA-7SEGMENT-ANODE-RED-0.56-1BIT | B38: =IFERROR(__xludf.DUMMYFUNCTION("""COMPUTED_VALUE"""),43813.0) -> 43813 | C38: =IFERROR(__xludf.DUMMYFUNCTION("""COMPUTED_VALUE"""),"AVRG ITB") -> AVRG ITB | D38: =IFERROR(__xludf.DUMMYFUNCTION("""COMPUTED_VALUE"""),50.0) -> 50
A39: =IFERROR(__xludf.DUMMYFUNCTION("""COMPUTED_VALUE"""),"ITBISA-7SEGMENT-ANODE-RED-0.56-1BIT") -> ITBISA-7SEGMENT-ANODE-RED-0.56-1BIT | B39: =IFERROR(__xludf.DUMMYFUNCTION("""COMPUTED_VALUE"""),43820.0) -> 43820 | C39: =IFERROR(__xludf.DUMMYFUNCTION("""COMPUTED_VALUE"""),"AVRG ITB") -> AVRG ITB | D39: =IFERROR(__xludf.DUMMYFUNCTION("""COMPUTED_VALUE"""),20.0) -> 20
A40: =IFERROR(__xludf.DUMMYFUNCTION("""COMPUTED_VALUE"""),"ITBISA-7SEGMENT-ANODE-RED-0.56-1BIT") -> ITBISA-7SEGMENT-ANODE-RED-0.56-1BIT | B40: =IFERROR(__xludf.DUMMYFUNCTION("""COMPUTED_VALUE"""),43832.0) -> 43832 | C40: =IFERROR(__xludf.DUMMYFUNCTION("""COMPUTED_VALUE"""),"AVRG ITB") -> AVRG ITB | D40: =IFERROR(__xludf.DUMMYFUNCTION("""COMPUTED_VALUE"""),120.0) -> 120
A41: =IFERROR(__xludf.DUMMYFUNCTION("""COMPUTED_VALUE"""),"ITBISA-7SEGMENT-ANODE-RED-0.56-1BIT") -> ITBISA-7SEGMENT-ANODE-RED-0.56-1BIT | B41: =IFERROR(__xludf.DUMMYFUNCTION("""COMPUTED_VALUE"""),43837.0) -> 43837 | C41: =IFERROR(__xludf.DUMMYFUNCTION("""COMPUTED_VALUE"""),"AVRG ITB") -> AVRG ITB | D41: =IFERROR(__xludf.DUMMYFUNCTION("""COMPUTED_VALUE"""),150.0) -> 150
A42: =IFERROR(__xludf.DUMMYFUNCTION("""COMPUTED_VALUE"""),"ITBISA-7SEGMENT-ANODE-RED-0.56-1BIT") -> ITBISA-7SEGMENT-ANODE-RED-0.56-1BIT | B42: =IFERROR(__xludf.DUMMYFUNCTION("""COMPUTED_VALUE"""),43841.0) -> 43841 | C42: =IFERROR(__xludf.DUMMYFUNCTION("""COMPUTED_VALUE"""),"AVRG ITB") -> AVRG ITB | D42: =IFERROR(__xludf.DUMMYFUNCTION("""COMPUTED_VALUE"""),70.0) -> 70
A43: =IFERROR(__xludf.DUMMYFUNCTION("""COMPUTED_VALUE"""),"ITBISA-7SEGMENT-ANODE-RED-0.56-1BIT") -> ITBISA-7SEGMENT-ANODE-RED-0.56-1BIT | B43: =IFERROR(__xludf.DUMMYFUNCTION("""COMPUTED_VALUE"""),43877.0) -> 43877 | C43: =IFERROR(__xludf.DUMMYFUNCTION("""COMPUTED_VALUE"""),"AVRG ITB") -> AVRG ITB | D43: =IFERROR(__xludf.DUMMYFUNCTION("""COMPUTED_VALUE"""),92.0) -> 92
A44: =IFERROR(__xludf.DUMMYFUNCTION("""COMPUTED_VALUE"""),"ITBISA-7SEGMENT-ANODE-RED-0.56-1BIT") -> ITBISA-7SEGMENT-ANODE-RED-0.56-1BIT | B44: =IFERROR(__xludf.DUMMYFUNCTION("""COMPUTED_VALUE"""),43881.0) -> 43881 | C44: =IFERROR(__xludf.DUMMYFUNCTION("""COMPUTED_VALUE"""),"AVRG ITB") -> AVRG ITB | D44: =IFERROR(__xludf.DUMMYFUNCTION("""COMPUTED_VALUE"""),300.0) -> 300
A45: =IFERROR(__xludf.DUMMYFUNCTION("""COMPUTED_VALUE"""),"ITBISA-7SEGMENT-ANODE-RED-0.56-1BIT") -> ITBISA-7SEGMENT-ANODE-RED-0.56-1BIT | B45: =IFERROR(__xludf.DUMMYFUNCTION("""COMPUTED_VALUE"""),43884.0) -> 43884 | C45: =IFERROR(__xludf.DUMMYFUNCTION("""COMPUTED_VALUE"""),"AVRG ITB") -> AVRG ITB | D45: =IFERROR(__xludf.DUMMYFUNCTION("""COMPUTED_VALUE"""),15.0) -> 15
