Workbook

Sheet Beranda
A1: Link | B1: Fungsi
A2: =HYPERLINK("https://docs.google.com/spreadsheets/d/1ESni1h-9NP1dVdHaEILuc6WWv_P8-mWX3jXPRX9GysM/edit#gid=1979551602","BisaStok") -> BisaStok | B2: Menuliskan pembelian stok dari Kas ITBisa
A3: =HYPERLINK("https://docs.google.com/spreadsheets/d/1ESni1h-9NP1dVdHaEILuc6WWv_P8-mWX3jXPRX9GysM/edit#gid=533652570","BisaPerlengkapan") -> BisaPerlengkapan | B3: Menuliskan perlengkapan yang berhubungan dengan penjualan
A4: =HYPERLINK("https://docs.google.com/spreadsheets/d/1ESni1h-9NP1dVdHaEILuc6WWv_P8-mWX3jXPRX9GysM/edit#gid=1164177046","BisaHitungImpor") -> BisaHitungImpor
A5: =HYPERLINK("https://docs.google.com/spreadsheets/d/1ESni1h-9NP1dVdHaEILuc6WWv_P8-mWX3jXPRX9GysM/edit#gid=90517666","BisaEksporBisaJual") -> BisaEksporBisaJual
A6: =HYPERLINK("https://docs.google.com/spreadsheets/d/1ESni1h-9NP1dVdHaEILuc6WWv_P8-mWX3jXPRX9GysM/edit#gid=171163769","BisaHilang") -> BisaHilang
A7: =HYPERLINK("https://docs.google.com/spreadsheets/d/1ESni1h-9NP1dVdHaEILuc6WWv_P8-mWX3jXPRX9GysM/edit#gid=1152745648","BisaJualBukalapak") -> BisaJualBukalapak | B7: Menuliskan semua transaksi barang dari Bukalapak
A8: =HYPERLINK("https://docs.google.com/spreadsheets/d/1ESni1h-9NP1dVdHaEILuc6WWv_P8-mWX3jXPRX9GysM/edit#gid=1873910816","BisaJualTokopedia") -> BisaJualTokopedia | B8: Menuliskan semua transaksi barang dari Tokopedia
A9: =HYPERLINK("https://docs.google.com/spreadsheets/d/1ESni1h-9NP1dVdHaEILuc6WWv_P8-mWX3jXPRX9GysM/edit#gid=1921632670","BisaJualBliBli") -> BisaJualBliBli
A10: =HYPERLINK("https://docs.google.com/spreadsheets/d/1ESni1h-9NP1dVdHaEILuc6WWv_P8-mWX3jXPRX9GysM/edit#gid=1461742550","BisaJualWeb") -> BisaJualWeb
A11: =HYPERLINK("https://docs.google.com/spreadsheets/d/1ESni1h-9NP1dVdHaEILuc6WWv_P8-mWX3jXPRX9GysM/edit#gid=526519451","BisaJualCOD") -> BisaJualCOD
A12: =HYPERLINK("https://docs.google.com/spreadsheets/d/1ESni1h-9NP1dVdHaEILuc6WWv_P8-mWX3jXPRX9GysM/edit#gid=716139622","BisaSEO") -> BisaSEO

Sheet BisaStok
D1: Pengiriman | F1: Pembelian | J1: Data Invoice | R1: USD | X1: Rp | AD1: Penjualan
A2: SKU | B2: Tanggal Bayar | C2: Tanggal Sampai | D2: Alamat Pengiriman | E2: Luar Negeri? | F2: Toko | G2: URL Beli | H2: Keterangan Pembelian | I2: Score (0 - 5) | J2: Banyak Lot | K2: Pcs per Lot | L2: HPP per Lot (USD) | M2: Ongkos Kirim (USD) | N2: Diskon Barang (USD) | O2: Diskon Ongkos Kirim (USD) | P2: Konversi USD ke Rupiah | Q2: {={"Banyak Barang (Buah)";IF(J3:J263*K3:K263=0,,J3:J263*K3:K263)}} -> Banyak Barang (Buah) | R2: {={"Total Harga Lot (USD)";IF(J3:J263*L3:L263=0,,J3:J263*L3:L263)}} -> Total Harga Lot (USD) | S2: {={"Ongkos Kirim (USD)";IF(M3:M263=0,,M3:M263)}} -> Ongkos Kirim (USD) | T2: {={"Diskon Barang (USD)";IF(N3:N263=0,,N3:N263)}} -> Diskon Barang (USD) | U2: {={"Diskon Ongkos Kirim (USD)";IF(O3:O263=0,,O3:O263)}} -> Diskon Ongkos Kirim (USD) | V2: {={"Total HPP (USD)";IF(R3:R263+M3:M263-N3:N263-O3:O263=0,,R3:R263+M3:M263-N3:N263-O3:O263)}} -> Total HPP (USD) | W2: {={"HPP per Buah (USD)";IF(V3:V263=0,,V3:V263/Q3:Q263)}} -> HPP per Buah (USD) | X2: {={"Total Harga Lot (Rp)";IF(R3:R263=0,,R3:R263*P3:P263)}} -> Total Harga Lot (Rp) | Y2: {={"Ongkos Kirim (Rp)";IF(S3:S263*$P$3:$P263=0,,S3:S263*$P$3:$P263)}} -> Ongkos Kirim (Rp) | Z2: {={"Diskon Barang (Rp)";IF(T3:T263*$P$3:$P263=0,,T3:T263*$P$3:$P263)}} -> Diskon Barang (Rp) | AA2: {={"Diskon Ongkos Kirim (Rp)";IF(U3:U263*$P$3:$P263=0,,U3:U263*$P$3:$P263)}} -> Diskon Ongkos Kirim (Rp) | AB2: {={"Total HPP (Rp)";IF(V3:V263*$P$3:$P263=0,,V3:V263*$P$3:$P263)}} -> Total HPP (Rp) | AC2: {={"HPP per Buah (Rp)";IF(AB3:AB263=0,,AB3:AB263/Q3:Q263)}} -> HPP per Buah (Rp) | AD2: Harga Online/ Dropshipper (Rp) | AE2: Harga Offline (Rp) | AF2: Lain-Lain
A4: ITBISA-IC-LM741CN-DIP8 | B4: 43590.408 | C4: 43596 | D4: KYAI KONTONG | E4: FALSE | F4: Migrasi - Shopee | G4: https://shopee.co.id/20pcs-IC-lm741c-lm741cn-DIP-8Pin-UA741CN-Amp-LM741-Amp-i.77214376.1434513222 | H4: Shopee Furqonajiy 19050510476HUJK ( - ) Mahal ( + ) Untuk Testing Darurat Pesan (?) setiap 10 buah diberi strefoam | I4: 5 | J4: 21 | K4: 1 | L4: 1291.1 | M4: 0 | N4: 0 | O4: 0 | P4: 1 | Q4: 21 | R4: 27113.1 | V4: 27113.1 | W4: 1291.1 | X4: 27113.1 | AB4: 27113.1 | AC4: 1291.1
A5: ITBISA-RESISTOR-470K-1/4W | B5: 44032 | C5: 44039 | D5: KYAI KONTONG | E5: FALSE | F5: Migrasi - Tokopedia | G5: https://www.tokopedia.com/multigshop/1000-pcs-resistor-470k-1-4-watt | H5: Tokopedia Furqonajiy | I5: 5 | J5: 980 | K5: 1 | L5: 22.43 | M5: 0 | N5: 0 | O5: 0 | P5: 1 | Q5: 980 | R5: 21981.4 | V5: 21981.4 | W5: 22.43 | X5: 21981.4 | AB5: 21981.4 | AC5: 22.43
A6: ITBISA-RESISTOR-56K-1/4W | B6: 44039 | C6: 44041 | D6: KYAI KONTONG | E6: FALSE | F6: Migrasi - Tokopedia | G6: https://www.tokopedia.com/smartmm/resistor-1-4w-56k-1000biji | H6: Tokopedia Furqonajiy | I6: 5 | J6: 650 | K6: 1 | L6: 20 | M6: 0 | N6: 0 | O6: 0 | P6: 1 | Q6: 650 | R6: 13000 | V6: 13000 | W6: 20 | X6: 13000 | AB6: 13000 | AC6: 20
A7: ITBISA-RAPID-BOHLAM-E10-3.8V-SCREW | B7: 44871 | C7: 44873 | D7: KYAI KONTONG | E7: FALSE | F7: Migrasi - Tokopedia | G7: https://www.tokopedia.com/evelinel/bohlam-e-10-bola-lampu-senter-drat-e10-rapid-isi-50-pcs-kotak?utm_source=whatsapp&utm_medium=share&utm_campaign=PDP-2644979-5342447705-301022-contextual_image | H7: Tokopedia Furqonajiy | I7: 5 | J7: 824 | K7: 1 | L7: 559.96 | M7: 0 | N7: 0 | O7: 0 | P7: 1 | Q7: 824 | R7: 461407.04 | V7: 461407.04 | W7: 559.96 | X7: 461407.04 | AB7: 461407.04 | AC7: 559.96
A8: ITBISA-7SEGMENT-CATHODE-RED-0.56-1BIT | B8: 45013 | C8: 45061 | D8: KYAI KONTONG | E8: FALSE | F8: Migrasi - Jasa Impor Tiongkok | G8: Jasa Impor Tiongkok | I8: 5 | J8: 2866 | K8: 1 | L8: 731 | M8: 0 | N8: 0 | O8: 0 | P8: 1 | Q8: 2866 | R8: 2095046 | V8: 2095046 | W8: 731 | X8: 2095046 | AB8: 2095046 | AC8: 731
A9: ITBISA-IC-UA741CN-DIP8 | B9: 45085 | C9: 45129 | D9: KYAI KONTONG | E9: FALSE | F9: Migrasi - Jasa Impor Tiongkok | G9: Jasa Impor Tiongkok | H9: Tokopedia Furqonajiy 1x Invoice | I9: 5 | J9: 5007 | K9: 1 | L9: 572 | M9: 0 | N9: 0 | O9: 0 | P9: 1 | Q9: 5007 | R9: 2864004 | V9: 2864004 | W9: 572 | X9: 2864004 | AB9: 2864004 | AC9: 572
A10: ITBISA-7SEGMENT-CATHODE-RED-1.20-1BIT | B10: 45202.354 | C10: 45232.639 | D10: KYAI KONTONG | E10: FALSE | F10: Migrasi - Jasa Impor Tiongkok | G10: Jasa Impor Tiongkok | I10: 5 | J10: 404 | K10: 1 | L10: 2756 | M10: 0 | N10: 0 | O10: 0 | P10: 1 | Q10: 404 | R10: 1113424 | V10: 1113424 | W10: 2756 | X10: 1113424 | AB10: 1113424 | AC10: 2756
A11: ITBISA-7SEGMENT-CATHODE-RED-2.30-1BIT | B11: 45265.69 | C11: 45341.64 | D11: KYAI KONTONG | E11: TRUE | F11: Migrasi - Ocistok/Martkita | G11: Ocistok | I11: 5 | J11: 60 | K11: 1 | L11: 6028 | M11: 0 | N11: 0 | O11: 0 | P11: 1 | Q11: 60 | R11: 361680 | V11: 361680 | W11: 6028 | X11: 361680 | AB11: 361680 | AC11: 6028
A12: ITBISA-TIGERHEAD-SENTER-KUNING-FT300 | B12: 45336.46 | C12: 45313.25 | D12: KYAI KONTONG | E12: FALSE | F12: Migrasi - Shopee | G12: Shopee Aji | H12: Shopee Aji | I12: 5 | J12: 1 | K12: 1 | L12: 10607.58 | M12: 0 | N12: 0 | O12: 0 | P12: 1 | Q12: 1 | R12: 10607.58 | V12: 10607.58 | W12: 10607.58 | X12: 10607.58 | AB12: 10607.58 | AC12: 10607.58
A13: ITBISA-LED-MAX7219-4IN1-GAP | B13: 45361.603 | C13: 45365.484 | D13: KYAI KONTONG | E13: FALSE | F13: Migrasi - Art Techno | G13: Art Techno | H13: Art Techno | I13: 5 | J13: 5 | K13: 1 | L13: 36500 | M13: 0 | N13: 0 | O13: 0 | P13: 1 | Q13: 5 | R13: 182500 | V13: 182500 | W13: 36500 | X13: 182500 | AB13: 182500 | AC13: 36500
A14: ITBISA-7SEGMENT-ANODE-RED-1.00-1BIT | B14: 45374.679 | C14: 45477.917 | D14: KYAI KONTONG | E14: TRUE | F14: Migrasi - Ocistok/Martkita | G14: https://detail.1688.com/offer/678795685587.html | H14: MKT-63258 / 187963 (0.85 RMB) | I14: 5 | J14: 2159 | K14: 1 | L14: 2000 | M14: 0 | N14: 0 | O14: 0 | P14: 1 | Q14: 2159 | R14: 4318000 | V14: 4318000 | W14: 2000 | X14: 4318000 | AB14: 4318000 | AC14: 2000
A15: ITBISA-RESISTOR-33K-1/4W | B15: 45381.201 | C15: 45384.568 | D15: KYAI KONTONG | E15: FALSE | F15: Migrasi - Shopee | G15: Shopee Aji GTGD | H15: Shopee Aji GTGD | I15: 5 | J15: 1760 | K15: 1 | L15: 21.75 | M15: 0 | N15: 0 | O15: 0 | P15: 1 | Q15: 1760 | R15: 38280 | V15: 38280 | W15: 21.75 | X15: 38280 | AB15: 38280 | AC15: 21.75
A16: ITBISA-NODEMCU-V3-CH340G-ESP8266-MICRO | B16: 45409.658 | C16: 45411.659 | D16: KYAI KONTONG | E16: FALSE | F16: Migrasi - Tokopedia | G16: Tokopedia Hendang | H16: Tokopedia Hendang | I16: 5 | J16: 310 | K16: 1 | L16: 23261.03 | M16: 0 | N16: 0 | O16: 0 | P16: 1 | Q16: 310 | R16: 7210919.3 | V16: 7210919.3 | W16: 23261.03 | X16: 7210919.3 | AB16: 7210919.3 | AC16: 23261.03
A17: ITBISA-RAPID-BOHLAM-E10-2.5V-SCREW | B17: 45411.511 | C17: 45414.417 | D17: KYAI KONTONG | E17: FALSE | F17: Migrasi - Shopee | G17: Shopee Aji 5E6M | H17: Shopee Aji 5E6M | I17: 5 | J17: 1224 | K17: 1 | L17: 640.67 | M17: 0 | N17: 0 | O17: 0 | P17: 1 | Q17: 1224 | R17: 784180.08 | V17: 784180.08 | W17: 640.67 | X17: 784180.08 | AB17: 784180.08 | AC17: 640.67
A18: ITBISA-ABC-BATERAI-D-POWER | B18: 45414.907 | C18: 45415.655 | D18: KYAI KONTONG | E18: FALSE | F18: Migrasi - Tokopedia | G18: SmartBrain Tokopedia | H18: SmartBrain Tokopedia | I18: 5 | J18: 1 | K18: 1 | L18: 5166.67 | M18: 0 | N18: 0 | O18: 0 | P18: 1 | Q18: 1 | R18: 5166.67 | V18: 5166.67 | W18: 5166.67 | X18: 5166.67 | AB18: 5166.67 | AC18: 5166.67
A19: ITBISA-SENSOR-SUHU-DHT11 | B19: 45417.981 | C19: 45421.604 | D19: KYAI KONTONG | E19: FALSE | F19: Migrasi - Shopee | G19: Shopee Anggi VMGV | H19: Shopee Anggi VMGV | I19: 5 | J19: 36 | K19: 1 | L19: 8283.86 | M19: 0 | N19: 0 | O19: 0 | P19: 1 | Q19: 36 | R19: 298218.96 | V19: 298218.96 | W19: 8283.86 | X19: 298218.96 | AB19: 298218.96 | AC19: 8283.86
A20: ITBISA-RESISTOR-4K7-1/4W | B20: 45421.205 | C20: 45423.626 | D20: KYAI KONTONG | E20: FALSE | F20: Migrasi - Shopee | G20: STARVIS CCTV | H20: Shopee Aji QK45 | I20: 5 | J20: 2873 | K20: 1 | L20: 21.7 | M20: 0 | N20: 0 | O20: 0 | P20: 1 | Q20: 2873 | R20: 62344.1 | V20: 62344.1 | W20: 21.7 | X20: 62344.1 | AB20: 62344.1 | AC20: 21.7
A21: ITBISA-IC-ULN2803APG-DIP18 | B21: 45426.593 | C21: 45493.667 | D21: KYAI KONTONG | E21: TRUE | F21: Migrasi - Ocistok/Martkita | G21: Ocistok | H21: Ocistok 205883 | I21: 5 | J21: 1321 | K21: 1 | L21: 1018 | M21: 0 | N21: 0 | O21: 0 | P21: 1 | Q21: 1321 | R21: 1344778 | V21: 1344778 | W21: 1018 | X21: 1344778 | AB21: 1344778 | AC21: 1018
A22: ITBISA-IC-L7805CV-TO220 | B22: 45426.999 | C22: 45429.457 | D22: KYAI KONTONG | E22: FALSE | F22: Migrasi - Shopee | G22: SukiTech | H22: Shopee Aji F1PM | I22: 5 | J22: 4531 | K22: 1 | L22: 1140.72 | M22: 0 | N22: 0 | O22: 0 | P22: 1 | Q22: 4531 | R22: 5168602.3 | V22: 5168602.3 | W22: 1140.72 | X22: 5168602.3 | AB22: 5168602.3 | AC22: 1140.72
A23: ITBISA-IC-L7812CV-TO220 | B23: 45452.715 | C23: 45456.594 | D23: KYAI KONTONG | E23: FALSE | F23: Migrasi - Shopee | G23: GT Electronik | H23: Shopee Aji F9QB | I23: 5 | J23: 1083 | K23: 1 | L23: 1057 | M23: 0 | N23: 0 | O23: 0 | P23: 1 | Q23: 1083 | R23: 1144731 | V23: 1144731 | W23: 1057 | X23: 1144731 | AB23: 1144731 | AC23: 1057
... A132: ITBISA-WEMOS-D1-MINI-ESP8266 | B132: 46003.633 | C132: 46004.816 | D132: KYAI KONTONG | E132: FALSE | F132: Migrasi - Shopee | G132: IndoTechno New | H132: Shopee Aji VFX9 | I132: 5 | J132: 120 | K132: 1 | L132: 20791.2 | M132: 0 | N132: 0 | O132: 0 | P132: 1 | Q132: 120 | R132: 2494944 | V132: 2494944 | W132: 20791.2 | X132: 2494944 | AB132: 2494944 | AC132: 20791.2
A133: ITBISA-BUBBLE-WRAP | B133: 46022.417 | C133: 46022.458 | D133: KYAI KONTONG | E133: FALSE | F133: Migrasi - Migrasi | G133: Migrasi | I133: 5 | J133: 70 | K133: 1 | M133: 0 | N133: 0 | O133: 0 | P133: 1 | Q133: 70
A134: ITBISA-ABC-BATERAI-9V-POWER | B134: 46024.659 | C134: 46036.749 | D134: KYAI KONTONG | E134: FALSE | F134: PT Arta Boga | G134: PT Arta Boga | H134: PT Arta Boga | I134: 5 | J134: 1 | K134: 144 | L134: =(1614384)/P134 -> 1614384 | M134: 9 | N134: 9 | O134: 9 | P134: 1 | Q134: 144 | R134: 1614384 | S134: 9 | T134: 9 | U134: 9 | V134: 1614375 | W134: 11210.938 | X134: 1614384 | Y134: 9 | Z134: 9 | AA134: 9 | AB134: 1614375 | AC134: 11210.938
A135: ITBISA-JACK-DC-005-FEMALE | B135: 46041.688 | C135: 46047.598 | D135: KERTASARI CIAMIS | E135: FALSE | F135: Shopee | G135: Golden Dream Official Shop | H135: Shopee Aji 47MX | I135: 5 | J135: 99 | K135: 1 | L135: =(380)/P135 -> 380 | M135: =(2000)/P135 -> 2000 | N135: =(15000)/P135 -> 15000 | O135: 0 | P135: 1 | Q135: 99 | R135: 37620 | S135: 2000 | T135: 15000 | V135: 24620 | W135: 248.68687 | X135: 37620 | Y135: 2000 | Z135: 15000 | AB135: 24620 | AC135: 248.68687
A136: ITBISA-ABC-BATERAI-AA-ALKALINE | B136: 46044.458 | C136: 46047.371 | D136: KERTASARI CIAMIS | E136: FALSE | F136: Shopee | G136: Awalia Store | H136: Shopee Aji V92Q | I136: 5 | J136: 5 | K136: 6 | L136: =(28950)/P136 -> 28950 | M136: =(1200)/P136 -> 1200 | N136: =(28950)/P136 -> 28950 | O136: 0 | P136: 1 | Q136: 30 | R136: 144750 | S136: 1200 | T136: 28950 | V136: 117000 | W136: 3900 | X136: 144750 | Y136: 1200 | Z136: 28950 | AB136: 117000 | AC136: 3900
A137: ITBISA-SOCKET-IC-DIP8-NARROW | B137: 46047.995 | C137: 46050.483 | D137: KYAI KONTONG | E137: FALSE | F137: Shopee | G137: ARS AUDIO 226 | H137: Shopee Aji NP55 | I137: 5 | J137: 1020 | K137: 1 | L137: =(210)/P137 -> 210 | M137: =(1200)/P137 -> 1200 | N137: =(32130)/P137 -> 32130 | O137: 0 | P137: 1 | Q137: 1020 | R137: 214200 | S137: 1200 | T137: 32130 | V137: 183270 | W137: 179.67647 | X137: 214200 | Y137: 1200 | Z137: 32130 | AB137: 183270 | AC137: 179.67647
A138: ITBISA-IC-74HC245N-DIP20 | B138: 46052.484 | C138: 46116.701 | D138: KYAI KONTONG | E138: TRUE | F138: Ocistok/Martkita | G138: https://detail.1688.com/offer/679786580432.html | H138: MKT-137391 / 319508 | I138: 5 | J138: 5000 | K138: 1 | L138: =(1435)/P138 -> 1435 | M138: =(25530)/P138 -> 25530 | N138: =(500000)*(R138/50094000) -> 71615.363 | P138: 1 | Q138: 5000 | R138: 7175000 | S138: 25530 | T138: 71615.363 | V138: 7128914.6 | W138: 1425.7829 | X138: 7175000 | Y138: 25530 | Z138: 71615.363 | AB138: 7128914.6 | AC138: 1425.7829
A139: ITBISA-RELAY-5V-4PIN-BLUE | B139: 46052.484 | C139: 46116.701 | D139: KYAI KONTONG | E139: TRUE | F139: Ocistok/Martkita | G139: https://detail.1688.com/offer/775368378784.html | H139: MKT-137392 / 319509 | I139: 5 | J139: 2000 | K139: 1 | L139: =(1781)/P139 -> 1781 | M139: =(233322)*(R139/33839000) -> 24560.211 | N139: =(500000)*(R139/50094000) -> 35553.16 | P139: 1 | Q139: 2000 | R139: 3562000 | S139: 24560.211 | T139: 35553.16 | V139: 3551007.1 | W139: 1775.5035 | X139: 3562000 | Y139: 24560.211 | Z139: 35553.16 | AB139: 3551007.1 | AC139: 1775.5035
A140: ITBISA-RELAY-12V-4PIN-BLUE | B140: 46052.484 | C140: 46116.701 | D140: KYAI KONTONG | E140: TRUE | F140: Ocistok/Martkita | G140: https://detail.1688.com/offer/775368378784.html | H140: MKT-137392 / 319509 | I140: 5 | J140: 5000 | K140: 1 | L140: =(1781)/P140 -> 1781 | M140: =(233322)*(R140/33839000) -> 61400.526 | N140: =(500000)*(R140/50094000) -> 88882.9 | P140: 1 | Q140: 5000 | R140: 8905000 | S140: 61400.526 | T140: 88882.9 | V140: 8877517.6 | W140: 1775.5035 | X140: 8905000 | Y140: 61400.526 | Z140: 88882.9 | AB140: 8877517.6 | AC140: 1775.5035
A141: ITBISA-RELAY-12V-5PIN-BLUE | B141: 46052.484 | C141: 46116.701 | D141: KYAI KONTONG | E141: TRUE | F141: Ocistok/Martkita | G141: https://detail.1688.com/offer/775368378784.html | H141: MKT-137392 / 319509 | I141: 5 | J141: 10000 | K141: 1 | L141: =(1781)/P141 -> 1781 | M141: =(233322)*(R141/33839000) -> 122801.05 | N141: =(500000)*(R141/50094000) -> 177765.8 | P141: 1 | Q141: 10000 | R141: 17810000 | S141: 122801.05 | T141: 177765.8 | V141: 17755035 | W141: 1775.5035 | X141: 17810000 | Y141: 122801.05 | Z141: 177765.8 | AB141: 17755035 | AC141: 1775.5035
A142: ITBISA-RELAY-5V-5PIN-BLUE | B142: 46052.484 | C142: 46116.701 | D142: KYAI KONTONG | E142: TRUE | F142: Ocistok/Martkita | G142: https://detail.1688.com/offer/775368378784.html | H142: MKT-137392 / 319509 | I142: 5 | J142: 2000 | K142: 1 | L142: =(1781)/P142 -> 1781 | M142: =(233322)*(R142/33839000) -> 24560.211 | N142: =(500000)*(R142/50094000) -> 35553.16 | P142: 1 | Q142: 2000 | R142: 3562000 | S142: 24560.211 | T142: 35553.16 | V142: 3551007.1 | W142: 1775.5035 | X142: 3562000 | Y142: 24560.211 | Z142: 35553.16 | AB142: 3551007.1 | AC142: 1775.5035
A143: ITBISA-IC-CD4094BM-SMD-SOP16 | B143: 46052.484 | C143: 46116.701 | D143: KYAI KONTONG | E143: TRUE | F143: Ocistok/Martkita | G143: https://detail.1688.com/offer/575196879958.html | H143: MKT-137393 / 319510 | I143: 5 | J143: 10000 | K143: 1 | L143: =(590)/P143 -> 590 | M143: =(18870)/P143 -> 18870 | N143: =(500000)*(R143/50094000) -> 58889.288 | P143: 1 | Q143: 10000 | R143: 5900000 | S143: 18870 | T143: 58889.288 | V143: 5859980.7 | W143: 585.99807 | X143: 5900000 | Y143: 18870 | Z143: 58889.288 | AB143: 5859980.7 | AC143: 585.99807
A144: ITBISA-IC-NE555P-DIP8 | B144: 46052.484 | C144: 46116.701 | D144: KYAI KONTONG | E144: TRUE | F144: Ocistok/Martkita | G144: https://detail.1688.com/offer/624513627642.html | H144: MKT-137394 / 319511 | I144: 5 | J144: 10000 | K144: 1 | L144: =(318)/P144 -> 318 | M144: =(18870)/P144 -> 18870 | N144: =(500000)*(R144/50094000) -> 31740.328 | P144: 1 | Q144: 10000 | R144: 3180000 | S144: 18870 | T144: 31740.328 | V144: 3167129.7 | W144: 316.71297 | X144: 3180000 | Y144: 18870 | Z144: 31740.328 | AB144: 3167129.7 | AC144: 316.71297
A145: ITBISA-IDC-2X5-AMPHENOL-FEMALE | B145: 46054.205 | C145: 46060.507 | D145: KYAI KONTONG | E145: FALSE | F145: Shopee | G145: Duta Part | H145: Shopee Aji HDC8 | I145: 5 | J145: 27 | K145: 1 | L145: =(750)/P145 -> 750 | M145: =(1000)/P145 -> 1000 | N145: =(4000)/P145 -> 4000 | P145: 1 | Q145: 27 | R145: 20250 | S145: 1000 | T145: 4000 | V145: 17250 | W145: 638.88889 | X145: 20250 | Y145: 1000 | Z145: 4000 | AB145: 17250 | AC145: 638.88889
A146: ITBISA-RELAY-12V-5PIN-BLUE | B146: 46054.216 | C146: 46060.481 | D146: KYAI KONTONG | E146: FALSE | F146: Shopee | G146: Golden Dream Official Shop | H146: Shopee Aji CSTS | I146: 5 | J146: 580 | K146: 1 | L146: =(2300)/P146 -> 2300 | M146: =(3000)/P146 -> 3000 | N146: =(199725 + 2500)/P146 -> 202225 | O146: 0 | P146: 1 | Q146: 580 | R146: 1334000 | S146: 3000 | T146: 202225 | V146: 1134775 | W146: 1956.5086 | X146: 1334000 | Y146: 3000 | Z146: 202225 | AB146: 1134775 | AC146: 1956.5086
A147: ITBISA-CHIP-ESP8266-ESP12F | B147: 46059.84 | C147: 46062.614 | D147: KYAI KONTONG | E147: FALSE | F147: Shopee | G147: CNC Store Jogja | H147: Shopee Aji WYU3 | I147: 5 | J147: 16 | K147: 1 | L147: =(18800)/P147 -> 18800 | M147: =(3000)/P147 -> 3000 | N147: =(99264)/P147 -> 99264 | P147: 1 | Q147: 16 | R147: 300800 | S147: 3000 | T147: 99264 | V147: 204536 | W147: 12783.5 | X147: 300800 | Y147: 3000 | Z147: 99264 | AB147: 204536 | AC147: 12783.5
A148: ITBISA-KAPASITOR-ELCO-2200UF-25V | B148: 46061.835 | C148: 46064.588 | D148: KERTASARI CIAMIS | E148: FALSE | F148: Shopee | G148: NE Elektronik | H148: Shopee Aji SPUV | I148: 5 | J148: 310 | K148: 1 | L148: =(975)/P148 -> 975 | M148: =(3000)/P148 -> 3000 | N148: =(99743)/P148 -> 99743 | P148: 1 | Q148: 310 | R148: 302250 | S148: 3000 | T148: 99743 | V148: 205507 | W148: 662.92581 | X148: 302250 | Y148: 3000 | Z148: 99743 | AB148: 205507 | AC148: 662.92581
A149: ITBISA-IC-PC817-DIP4 | B149: 46061.838 | C149: 46065.319 | D149: KYAI KONTONG | E149: FALSE | F149: Shopee | G149: DN TRONIC | H149: Shopee Anggi R9UK | I149: 5 | J149: 759 | K149: 1 | L149: =(399)/P149 -> 399 | M149: =(3000)/P149 -> 3000 | N149: =(99938)/P149 -> 99938 | P149: 1 | Q149: 759 | R149: 302841 | S149: 3000 | T149: 99938 | V149: 205903 | W149: 271.28195 | X149: 302841 | Y149: 3000 | Z149: 99938 | AB149: 205903 | AC149: 271.28195
A150: ITBISA-SERVO-SG90-180DEG | B150: 46063.835 | C150: 46065.789 | D150: KYAI KONTONG | E150: FALSE | F150: Shopee | G150: Avicena Teknologi Indonesia | H150: Shopee Aji SY6T | I150: 5 | J150: 25 | K150: 1 | L150: =(11852)/P150 -> 11852 | M150: =(2200)/P150 -> 2200 | N150: =(97779)/P150 -> 97779 | P150: 1 | Q150: 25 | R150: 296300 | S150: 2200 | T150: 97779 | V150: 200721 | W150: 8028.84 | X150: 296300 | Y150: 2200 | Z150: 97779 | AB150: 200721 | AC150: 8028.84
A151: ITBISA-JUMPER-MF-20CM | B151: 46064.867 | C151: 46067.506 | D151: KERTASARI CIAMIS | E151: FALSE | F151: Shopee | G151: Avicena Teknologi Indonesia | H151: Shopee Aji 7EPE | I151: 5 | J151: 25 | K151: 40 | L151: =(5875)/P151 -> 5875 | M151: =(2200)/P151 -> 2200 | N151: =(29375)/P151 -> 29375 | P151: 1 | Q151: 1000 | R151: 146875 | S151: 2200 | T151: 29375 | V151: 119700 | W151: 119.7 | X151: 146875 | Y151: 2200 | Z151: 29375 | AB151: 119700 | AC151: 119.7
A152: ITBISA-JUMPER-FF-10CM | B152: 46065.835 | C152: 46067.637 | D152: KYAI KONTONG | E152: FALSE | F152: Shopee | G152: Avicena Teknologi Indonesia | H152: Shopee Aji W1Y5 | I152: 5 | J152: 9 | K152: 40 | L152: =(5315)/P152 -> 5315 | M152: =(2200*(47385/(248786 + 47385)))/P152 -> 351.98247 | N152: =ROUNDDOWN((X152*33%)/P152,0) -> 15785 | P152: 1 | Q152: 360 | R152: 47835 | S152: 351.98247 | T152: 15785 | V152: 32401.982 | W152: 90.005507 | X152: 47835 | Y152: 351.98247 | Z152: 15785 | AB152: 32401.982 | AC152: 90.005507
A153: ITBISA-JUMPER-MM-10CM | B153: 46065.835 | C153: 46067.637 | D153: KYAI KONTONG | E153: FALSE | F153: Shopee | G153: Avicena Teknologi Indonesia | H153: Shopee Aji W1Y5 | I153: 5 | J153: 38 | K153: 40 | L153: =(6547)/P153 -> 6547 | M153: =(2200*(248786/(248786 + 47385)))/P153 -> 1848.0175 | N153: =ROUNDUP((X153*33%)/P153,0) -> 82100 | P153: 1 | Q153: 1520 | R153: 248786 | S153: 1848.0175 | T153: 82100 | V153: 168534.02 | W153: 110.87764 | X153: 248786 | Y153: 1848.0175 | Z153: 82100 | AB153: 168534.02 | AC153: 110.87764
A154: ITBISA-IC-CD4094BM-SMD-SOP16 | B154: 46065.837 | C154: 46067.526 | D154: KERTASARI CIAMIS | E154: FALSE | F154: Shopee | G154: EasyWare Electronics | H154: Shopee Anggi J2KB | I154: 5 | J154: 275 | K154: 1 | L154: =(1100)/P154 -> 1100 | M154: =(3000)/P154 -> 3000 | N154: =(99825)/P154 -> 99825 | P154: 1 | Q154: 275 | R154: 302500 | S154: 3000 | T154: 99825 | V154: 205675 | W154: 747.90909 | X154: 302500 | Y154: 3000 | Z154: 99825 | AB154: 205675 | AC154: 747.90909
A155: ITBISA-RTC-DS3231SN | B155: 46068.023 | C155: 46073.581 | D155: KERTASARI CIAMIS | E155: FALSE | F155: Shopee | G155: DT Production | H155: Shopee Aji XYJ2 | I155: 5 | J155: 2 | K155: 1 | L155: =(23100)/P155 -> 23100 | M155: =(1000)/P155 -> 1000 | N155: =(15000)/P155 -> 15000 | P155: 1 | Q155: 2 | R155: 46200 | S155: 1000 | T155: 15000 | V155: 32200 | W155: 16100 | X155: 46200 | Y155: 1000 | Z155: 15000 | AB155: 32200 | AC155: 16100
A156: ITBISA-RTC-DS3231SN | B156: 46068.024 | C156: 46073.581 | D156: KERTASARI CIAMIS | E156: FALSE | F156: Shopee | G156: DT Production | H156: Shopee Aji 1A50 | I156: 5 | J156: 1 | K156: 1 | L156: =(23100)/P156 -> 23100 | M156: =(1000)/P156 -> 1000 | N156: =(4000)/P156 -> 4000 | P156: 1 | Q156: 1 | R156: 23100 | S156: 1000 | T156: 4000 | V156: 20100 | W156: 20100 | X156: 23100 | Y156: 1000 | Z156: 4000 | AB156: 20100 | AC156: 20100
A157: ITBISA-IC-PC817-DIP4 | B157: 46068.028 | C157: 46071.402 | D157: KYAI KONTONG | E157: FALSE | F157: Shopee | G157: DN TRONIC | H157: Shopee Anggi | I157: 5 | J157: 48 | K157: 1 | L157: =(410)/P157 -> 410 | M157: =(1000)/P157 -> 1000 | N157: =(3936)/P157 -> 3936 | P157: 1 | Q157: 48 | R157: 19680 | S157: 1000 | T157: 3936 | V157: 16744 | W157: 348.83333 | X157: 19680 | Y157: 1000 | Z157: 3936 | AB157: 16744 | AC157: 348.83333
A158: ITBISA-IC-PC817-DIP4 | B158: 46068.029 | C158: 46071.402 | D158: KYAI KONTONG | E158: FALSE | F158: Shopee | G158: DN TRONIC | H158: Shopee Anggi 179Q | I158: 5 | J158: 74 | K158: 1 | L158: =(410)/P158 -> 410 | M158: =(1000)/P158 -> 1000 | N158: =(15000)/P158 -> 15000 | P158: 1 | Q158: 74 | R158: 30340 | S158: 1000 | T158: 15000 | V158: 16340 | W158: 220.81081 | X158: 30340 | Y158: 1000 | Z158: 15000 | AB158: 16340 | AC158: 220.81081
A159: ITBISA-IC-PC817-DIP4 | B159: 46068.042 | C159: 46071.353 | D159: KYAI KONTONG | E159: FALSE | F159: Shopee | G159: Xumo Store | H159: Shopee Aji NQAM | I159: 5 | J159: 116 | K159: 10 | L159: =(4000)/P159 -> 4000 | M159: =(1044)/P159 -> 1044 | N159: =(69600)/P159 -> 69600 | P159: 1 | Q159: 1160 | R159: 464000 | S159: 1044 | T159: 69600 | V159: 395444 | W159: 340.9 | X159: 464000 | Y159: 1044 | Z159: 69600 | AB159: 395444 | AC159: 340.9
A160: ITBISA-IC-PC817-DIP4 | B160: 46068.042 | C160: 46071.651 | D160: KYAI KONTONG | E160: FALSE | F160: Shopee | G160: DN TRONIC | H160: Shopee Aji NQAK | I160: 5 | J160: 2045 | K160: 1 | L160: =(425)/P160 -> 425 | M160: =(1956)/P160 -> 1956 | N160: =(130369)/P160 -> 130369 | P160: 1 | Q160: 2045 | R160: 869125 | S160: 1956 | T160: 130369 | V160: 740712 | W160: 362.20636 | X160: 869125 | Y160: 1956 | Z160: 130369 | AB160: 740712 | AC160: 362.20636
A161: ITBISA-RELAY-12V-5PIN-BLUE | B161: 46068.062 | C161: 46076.558 | D161: KYAI KONTONG | E161: FALSE | F161: Shopee | G161: Toko Golden Dream | H161: Shopee Anggi AYP6 | I161: 5 | J161: 580 | K161: 1 | L161: =(2300)/P161 -> 2300 | M161: =(3000)/P161 -> 3000 | N161: =(200000)/P161 -> 200000 | P161: 1 | Q161: 580 | R161: 1334000 | S161: 3000 | T161: 200000 | V161: 1137000 | W161: 1960.3448 | X161: 1334000 | Y161: 3000 | Z161: 200000 | AB161: 1137000 | AC161: 1960.3448
A162: ITBISA-IC-NE555P-DIP8 | B162: 46069.576 | C162: 46073.803 | D162: KERTASARI CIAMIS | E162: FALSE | F162: Shopee | G162: EasyWare Electronics | H162: Shopee Aji PW65 | I162: 5 | J162: 41 | K162: 1 | L162: =(550)/P162 -> 550 | M162: =(1000)/P162 -> 1000 | N162: =(4000)/P162 -> 4000 | P162: 1 | Q162: 41 | R162: 22550 | S162: 1000 | T162: 4000 | V162: 19550 | W162: 476.82927 | X162: 22550 | Y162: 1000 | Z162: 4000 | AB162: 19550 | AC162: 476.82927
A163: ITBISA-ABC-BATERAI-AA-ALKALINE | B163: 46072.517 | C163: 46079.583 | D163: KYAI KONTONG | E163: FALSE | F163: PT Arta Boga | G163: PT Arta Boga | H163: PT Arta Boga | I163: 5 | J163: 2 | K163: 288 | L163: =(1578420)/P163 -> 1578420 | M163: 0 | N163: =(741857)/P163 -> 741857 | O163: 0 | P163: 1 | Q163: 576 | R163: 3156840 | T163: 741857 | V163: 2414983 | W163: 4192.6788 | X163: 3156840 | Z163: 741857 | AB163: 2414983 | AC163: 4192.6788
A164: ITBISA-RTC-DS3231SN | B164: 46073.815 | C164: 46076.692 | D164: KERTASARI CIAMIS | E164: FALSE | F164: Shopee | G164: Vision Tech | H164: Shopee Aji ASMJ | I164: 5 | J164: 1 | K164: 1 | L164: =(22398)/P164 -> 22398 | M164: =(1000)/P164 -> 1000 | N164: =(4000)/P164 -> 4000 | P164: 1 | Q164: 1 | R164: 22398 | S164: 1000 | T164: 4000 | V164: 19398 | W164: 19398 | X164: 22398 | Y164: 1000 | Z164: 4000 | AB164: 19398 | AC164: 19398
A165: ITBISA-RTC-DS3231SN | B165: 46081.733 | C165: 46085.555 | D165: KERTASARI CIAMIS | E165: FALSE | F165: Shopee | G165: Vision Tech | H165: Shopee Aji NHU3 | I165: 5 | J165: 1 | K165: 1 | L165: =(22398)/P165 -> 22398 | M165: =(1000)/P165 -> 1000 | N165: =(4000)/P165 -> 4000 | P165: 1 | Q165: 1 | R165: 22398 | S165: 1000 | T165: 4000 | V165: 19398 | W165: 19398 | X165: 22398 | Y165: 1000 | Z165: 4000 | AB165: 19398 | AC165: 19398
A166: ITBISA-IC-PC817-DIP4 | B166: 46081.85 | C166: 46088.788 | D166: KERTASARI CIAMIS | E166: FALSE | F166: Shopee | G166: DN TRONIC | H166: Shopee Aji NRPF | I166: 5 | J166: 2000 | K166: 1 | L166: =(410)/P166 -> 410 | M166: =(3000)/P166 -> 3000 | N166: =(X166*12%)/P166 -> 98400 | P166: 1 | Q166: 2000 | R166: 820000 | S166: 3000 | T166: 98400 | V166: 724600 | W166: 362.3 | X166: 820000 | Y166: 3000 | Z166: 98400 | AB166: 724600 | AC166: 362.3
A167: ITBISA-RELAY-12V-5PIN-BLUE | B167: 46082.189 | C167: 46088.812 | D167: KERTASARI CIAMIS | E167: FALSE | F167: Shopee | G167: Toko Golden Dream | H167: Shopee Aji AM7N | I167: 5 | J167: 362 | K167: 1 | L167: =(2300)/P167 -> 2300 | M167: =(3000)/P167 -> 3000 | N167: =(X167*12%)/P167 -> 99912 | P167: 1 | Q167: 362 | R167: 832600 | S167: 3000 | T167: 99912 | V167: 735688 | W167: 2032.2873 | X167: 832600 | Y167: 3000 | Z167: 99912 | AB167: 735688 | AC167: 2032.2873
A168: ITBISA-RTC-DS3231SN | B168: 46084.574 | C168: 46088.453 | D168: KERTASARI CIAMIS | E168: FALSE | F168: Shopee | G168: Vision Tech | H168: Shopee Aji 2F7X | I168: 5 | J168: 1 | K168: 1 | L168: =(22398)/P168 -> 22398 | M168: =(1000)/P168 -> 1000 | N168: =(4000)/P168 -> 4000 | P168: 1 | Q168: 1 | R168: 22398 | S168: 1000 | T168: 4000 | V168: 19398 | W168: 19398 | X168: 22398 | Y168: 1000 | Z168: 4000 | AB168: 19398 | AC168: 19398
A169: ITBISA-RTC-DS3231SN | B169: 46084.601 | C169: 46099.517 | D169: KYAI KONTONG | E169: FALSE | F169: Shopee | G169: DT Production | H169: Shopee Aji JC1F | I169: 5 | J169: 215 | K169: 1 | L169: =(23100)/P169 -> 23100 | M169: =(3000)/P169 -> 3000 | N169: =(X169*15%)/P169 -> 744975 | P169: 1 | Q169: 215 | R169: 4966500 | S169: 3000 | T169: 744975 | V169: 4224525 | W169: 19648.953 | X169: 4966500 | Y169: 3000 | Z169: 744975 | AB169: 4224525 | AC169: 19648.953
A170: ITBISA-BLUETOOTH-MODULE-HC05 | B170: 46088.939 | C170: 46092.8 | D170: KERTASARI CIAMIS | E170: FALSE | F170: Shopee | G170: DA Seller 17 | H170: Shopee Aji 977P | I170: 5 | J170: 100 | K170: 1 | L170: =(25577)/P170 -> 25577 | M170: =(2304)/P170 -> 2304 | N170: =ROUNDUP(X170*15% + 1,0)/P170 -> 383656 | P170: 1 | Q170: 100 | R170: 2557700 | S170: 2304 | T170: 383656 | V170: 2176348 | W170: 21763.48 | X170: 2557700 | Y170: 2304 | Z170: 383656 | AB170: 2176348 | AC170: 21763.48
A171: ITBISA-BREADBOARD-830HOLE-MB102 | B171: 46088.939 | C171: 46092.787 | D171: KERTASARI CIAMIS | E171: FALSE | F171: Shopee | G171: Toko Mitra Abadi Official | H171: Shopee Aji 977M | I171: 5 | J171: 65 | K171: 1 | L171: =(8000)/P171 -> 8000 | M171: =(469)/P171 -> 469 | N171: =ROUNDUP(X171*15% + 1,0)/P171 -> 78001 | P171: 1 | Q171: 65 | R171: 520000 | S171: 469 | T171: 78001 | V171: 442468 | W171: 6807.2 | X171: 520000 | Y171: 469 | Z171: 78001 | AB171: 442468 | AC171: 6807.2
A172: ITBISA-RELAY-5V-1CHANNEL-BLUE-LOW-TRIGGER | B172: 46088.939 | C172: 46092.45 | D172: KERTASARI CIAMIS | E172: FALSE | F172: Shopee | G172: GROWTEC | H172: Shopee Aji 977N | I172: 5 | J172: 50 | K172: 1 | L172: =(5029)/P172 -> 5029 | M172: =(227)/P172 -> 227 | N172: =ROUNDUP(X172*15% - 2,0)/P172 -> 37716 | P172: 1 | Q172: 50 | R172: 251450 | S172: 227 | T172: 37716 | V172: 213961 | W172: 4279.22 | X172: 251450 | Y172: 227 | Z172: 37716 | AB172: 213961 | AC172: 4279.22
A173: ITBISA-BLUETOOTH-MODULE-HC05 | B173: 46088.991 | C173: 46091.512 | D173: KYAI KONTONG | E173: FALSE | F173: Shopee | G173: DA Seller 17 | H173: Shopee Anggi 0Y3Q | I173: 5 | J173: 99 | K173: 1 | L173: =(25577)/P173 -> 25577 | M173: =(3040)/P173 -> 3040 | N173: =ROUNDUP(X173*15%,0)/P173 -> 379819 | P173: 1 | Q173: 99 | R173: 2532123 | S173: 3040 | T173: 379819 | V173: 2155344 | W173: 21771.152 | X173: 2532123 | Y173: 3040 | Z173: 379819 | AB173: 2155344 | AC173: 21771.152
A174: ITBISA-BREADBOARD-830HOLE-MB102 | B174: 46088.991 | C174: 46090.427 | D174: KYAI KONTONG | E174: FALSE | F174: Shopee | G174: Toko Mitra Abadi Official | H174: Shopee Anggi 0Y3P | I174: 5 | J174: 100 | K174: 1 | L174: =(8000)/P174 -> 8000 | M174: =(960)/P174 -> 960 | N174: =ROUNDUP(X174*15%,0)/P174 -> 120000 | P174: 1 | Q174: 100 | R174: 800000 | S174: 960 | T174: 120000 | V174: 680960 | W174: 6809.6 | X174: 800000 | Y174: 960 | Z174: 120000 | AB174: 680960 | AC174: 6809.6
A175: ITBISA-LCD-16X2-GREEN | B175: 46133.54 | C175: 46137.393 | D175: KYAI KONTONG | E175: FALSE | F175: Shopee | G175: dcms.store | H175: Shopee Aji 260421D3A5KBN3 | I175: 5 | J175: 2 | K175: 1 | L175: =(14500)/P175 -> 0.84597433 | M175: =(14300+1000)/P175 -> 0.89264877 | N175: =(4000)/P175 -> 0.23337223 | O175: =(14300)/P175 -> 0.83430572 | P175: 17140 | Q175: 2 | R175: 1.6919487 | S175: 0.89264877 | T175: 0.23337223 | U175: 0.83430572 | V175: 1.5169195 | W175: 0.75845974 | X175: 29000 | Y175: 15300 | Z175: 4000 | AA175: 14300 | AB175: 26000 | AC175: 13000
A176: ITBISA-IDC-2X5-AMPHENOL-FEMALE | B176: 46135.39 | C176: 46136.674 | D176: KYAI KONTONG | E176: FALSE | F176: Shopee | G176: aisyahsyakilaafsheen | H176: Shopee Aji 260423HR76N68R | I176: 5 | J176: 1000 | K176: 1 | L176: =(700)/P176 -> 0.040378403 | M176: =((27200+1377)*700000/1411000)/P176 -> 0.81778429 | N176: =((168720+5000)*700000/1411000)/P176 -> 4.9713226 | O176: =(27200*700000/1411000)/P176 -> 0.77837886 | P176: 17336 | Q176: 1000 | R176: 40.378403 | S176: 0.81778429 | T176: 4.9713226 | U176: 0.77837886 | V176: 35.446486 | W176: 0.035446486 | X176: 700000 | Y176: 14177.108 | Z176: 86182.849 | AA176: 13493.976 | AB176: 614500.28 | AC176: 614.50028
A177: ITBISA-LED-SUPERBRIGHT-5MM-GREEN | B177: 46135.39 | C177: 46136.674 | D177: KYAI KONTONG | E177: FALSE | F177: Shopee | G177: aisyahsyakilaafsheen | H177: Shopee Aji 260423HR76N68R | I177: 5 | J177: 9 | K177: 1000 | L177: =(711000/9)/P177 -> 4.5569912 | M177: =((27200+1377)*711000/1411000)/P177 -> 0.83063518 | N177: =((168720+5000)*711000/1411000)/P177 -> 5.0494434 | O177: =(27200*711000/1411000)/P177 -> 0.79061053 | P177: 17336 | Q177: 9000 | R177: 41.012921 | S177: 0.83063518 | T177: 5.0494434 | U177: 0.79061053 | V177: 36.003502 | W177: 0.0040003891 | X177: 711000 | Y177: 14399.892 | Z177: 87537.151 | AA177: 13706.024 | AB177: 624156.72 | AC177: 69.350746
A178: ITBISA-IC-PC817-DIP4 | B178: 46137.009 | C178: 46139.483 | D178: KYAI KONTONG | E178: FALSE | F178: Shopee | G178: DN TRONIC | H178: Shopee Aji 260425NTF033G4 | I178: 5 | J178: 1000 | K178: 1 | L178: =(425)/P178 -> 0.024535273 | M178: =(8000+1283)/P178 -> 0.53590809 | N178: =(63750)/P178 -> 3.680291 | O178: =(8000)/P178 -> 0.46184043 | P178: 17322 | Q178: 1000 | R178: 24.535273 | S178: 0.53590809 | T178: 3.680291 | U178: 0.46184043 | V178: 20.92905 | W178: 0.02092905 | X178: 425000 | Y178: 9283 | Z178: 63750 | AA178: 8000 | AB178: 362533 | AC178: 362.533
A179: ITBISA-IDC-2X5-AMPHENOL-FEMALE | B179: 46137.009 | C179: 46139.588 | D179: KYAI KONTONG | E179: FALSE | F179: Shopee | G179: 4rduinonan0 | H179: Shopee Aji 260425NTF033G3 | I179: 5 | J179: 900 | K179: 1 | L179: =(1000)/P179 -> 0.057730054 | M179: =(15000+2717)/P179 -> 1.0228034 | N179: =(135000)/P179 -> 7.7935573 | O179: =(15000)/P179 -> 0.86595081 | P179: 17322 | Q179: 900 | R179: 51.957049 | S179: 1.0228034 | T179: 7.7935573 | U179: 0.86595081 | V179: 44.320344 | W179: 0.049244827 | X179: 900000 | Y179: 17717 | Z179: 135000 | AA179: 15000 | AB179: 767717 | AC179: 853.01889
A180: ITBISA-IDC-2X5-AMPHENOL-FEMALE | B180: 46147.01 | C180: 46147.826 | D180: KYAI KONTONG | E180: FALSE | F180: Shopee | G180: aisyah shakila afsheen | H180: Shopee Aji 260505HUTR2945 | I180: 5 | J180: 300 | K180: 1 | L180: =780/P180 -> 0.044967139 | M180: =(17500+151)/P180 -> 1.0175833 | N180: =114/P180 -> 0.0065721204 | O180: =17500/P180 -> 1.0088781 | P180: 17346 | Q180: 300 | R180: 13.490142 | S180: 1.0175833 | T180: 0.0065721204 | U180: 1.0088781 | V180: 13.492275 | W180: 0.04497425 | X180: 234000 | Y180: 17651 | Z180: 114 | AA180: 17500 | AB180: 234037 | AC180: 780.12333
A181: ITBISA-BUZZER-ACTIVE-5V | B181: 46147.01 | C181: 46148.402 | D181: KYAI KONTONG | E181: FALSE | F181: Shopee | G181: DX-Tronics | H181: Shopee Aji 260505HUTR2942 | I181: 5 | J181: 4000 | K181: 1 | L181: =1399/P181 -> 0.0806526 | M181: =((50000+3573)*5596000/6929000)/P181 -> 2.4943292 | N181: =((1385800+2680-649481)*5596000/6929000)/P181 -> 34.407384 | O181: =(50000*5596000/6929000)/P181 -> 2.3279723 | P181: 17346 | Q181: 4000 | R181: 322.6104 | S181: 2.4943292 | T181: 34.407384 | U181: 2.3279723 | V181: 288.36937 | W181: 0.072092343 | X181: 5596000 | Y181: 43266.634 | Z181: 596830.48 | AA181: 40381.007 | AB181: 5002055.1 | AC181: 1250.5138
A182: ITBISA-DC-TO-DC-STEPUP-XL6009 | B182: 46147.01 | C182: 46148.402 | D182: KYAI KONTONG | E182: FALSE | F182: Shopee | G182: DX-Tronics | H182: Shopee Aji 260505HUTR2942 | I182: 5 | J182: 110 | K182: 1 | L182: =8100/P182 -> 0.46696645 | M182: =((50000+3573)*891000/6929000)/P182 -> 0.39714927 | N182: =((1385800+2680-649481)*891000/6929000)/P182 -> 5.4783737 | O182: =(50000*891000/6929000)/P182 -> 0.37066178 | P182: 17346 | Q182: 110 | R182: 51.366309 | S182: 0.39714927 | T182: 5.4783737 | U182: 0.37066178 | V182: 45.914423 | W182: 0.41740385 | X182: 891000 | Y182: 6888.9512 | Z182: 95027.87 | AA182: 6429.4992 | AB182: 796431.58 | AC182: 7240.2871
A183: ITBISA-TERMINAL-BLOCK-KF301-2P-BLUE | B183: 46147.01 | C183: 46148.402 | D183: KYAI KONTONG | E183: FALSE | F183: Shopee | G183: DX-Tronics | H183: Shopee Aji 260505HUTR2942 | I183: 5 | J183: 1000 | K183: 1 | L183: =442/P183 -> 0.025481379 | M183: =((50000+3573)*442000/6929000)/P183 -> 0.19701456 | N183: =((1385800+2680-649481)*442000/6929000)/P183 -> 2.7176668 | O183: =(50000*442000/6929000)/P183 -> 0.18387487 | P183: 17346 | Q183: 1000 | R183: 25.481379 | S183: 0.19701456 | T183: 2.7176668 | U183: 0.18387487 | V183: 22.776852 | W183: 0.022776852 | X183: 442000 | Y183: 3417.4146 | Z183: 47140.649 | AA183: 3189.4934 | AB183: 395087.27 | AC183: 395.08727
A184: ITBISA-IC-PC817-DIP4 | B184: 46147.01 | C184: 46149.56 | D184: KYAI KONTONG | E184: FALSE | F184: Shopee | G184: XUMO STORE | H184: Shopee Aji 260505HUTR2943 | I184: 5 | J184: 20 | K184: 10 | L184: =(85000/20)/P184 -> 0.24501326 | M184: =(8000+44)/P184 -> 0.46373804 | N184: =(17000+31)/P184 -> 0.98184019 | O184: =8000/P184 -> 0.46120143 | P184: 17346 | Q184: 200 | R184: 4.9002652 | S184: 0.46373804 | T184: 0.98184019 | U184: 0.46120143 | V184: 3.9209616 | W184: 0.019604808 | X184: 85000 | Y184: 8044 | Z184: 17031 | AA184: 8000 | AB184: 68013 | AC184: 340.065
A185: ITBISA-IDC-2X5-AMPHENOL-FEMALE | B185: 46150.935 | D185: KYAI KONTONG | E185: TRUE | F185: Ocistok/Martkita | G185: https://detail.1688.com/offer/966411176889.html | H185: MKT-145981 / 335604 | I185: 5 | J185: 20000 | K185: 1 | L185: =368/P185 -> 0.021200599 | M185: =(112110+(200000*7360000/50203000))/P185 -> 8.1478832 | N185: =(700000*7360000/50203000)/P185 -> 5.9121644 | P185: 17358 | Q185: 20000 | R185: 424.01198 | S185: 8.1478832 | T185: 5.9121644 | V185: 426.2477 | W185: 0.021312385 | X185: 7360000 | Y185: 141430.96 | Z185: 102623.35 | AB185: 7398807.6 | AC185: 369.94038
A186: ITBISA-IC-74HC595N-DIP16 | B186: 46150.935 | D186: KYAI KONTONG | E186: TRUE | F186: Ocistok/Martkita | G186: https://detail.1688.com/offer/586404749466.html | H186: MKT-145982 / 335605 | I186: 5 | J186: 20000 | K186: 1 | L186: =773/P186 -> 0.04453278 | M186: =(58830+(200000*15460000/50203000))/P186 -> 6.937432 | N186: =(700000*15460000/50203000)/P186 -> 12.418758 | P186: 17358 | Q186: 20000 | R186: 890.65561 | S186: 6.937432 | T186: 12.418758 | V186: 885.17428 | W186: 0.044258714 | X186: 15460000 | Y186: 120419.94 | Z186: 215564.81 | AB186: 15364855 | AC186: 768.24276
A187: ITBISA-POTENSIO-WH148-B10K-15MM | B187: 46150.935 | D187: KYAI KONTONG | E187: TRUE | F187: Ocistok/Martkita | G187: https://detail.1688.com/offer/1258284723.html | H187: MKT-145983 / 335606 | I187: 5 | J187: 11000 | K187: 1 | L187: =1013/P187 -> 0.058359258 | M187: =(108114+(200000*11143000/50203000))/P187 -> 8.7859068 | N187: =(700000*11143000/50203000)/P187 -> 8.9509847 | P187: 17358 | Q187: 11000 | R187: 641.95184 | S187: 8.7859068 | T187: 8.9509847 | V187: 641.78676 | W187: 0.058344251 | X187: 11143000 | Y187: 152505.77 | Z187: 155371.19 | AB187: 11140135 | AC187: 1012.7395
A188: ITBISA-7SEGMENT-CATHODE-RED-2.30-1BIT | B188: 46150.935 | D188: KYAI KONTONG | E188: TRUE | F188: Ocistok/Martkita | G188: https://detail.1688.com/offer/714453066015.html | H188: MKT-145984 / 335607 | I188: 5 | J188: 500 | K188: 1 | L188: =6496/P188 -> 0.37423666 | M188: =((77478*3248000/16240000)+(200000*3248000/50203000))/P188 -> 1.6381533 | N188: =(700000*3248000/50203000)/P188 -> 2.6090638 | P188: 17358 | Q188: 500 | R188: 187.11833 | S188: 1.6381533 | T188: 2.6090638 | V188: 186.14742 | W188: 0.37229484 | X188: 3248000 | Y188: 28435.066 | Z188: 45288.13 | AB188: 3231146.9 | AC188: 6462.2939
A189: ITBISA-7SEGMENT-ANODE-RED-2.30-1BIT | B189: 46150.935 | D189: KYAI KONTONG | E189: TRUE | F189: Ocistok/Martkita | G189: https://detail.1688.com/offer/714453066015.html | H189: MKT-145984 / 335607 | I189: 5 | J189: 2000 | K189: 1 | L189: =6496/P189 -> 0.37423666 | M189: =((77478*12992000/16240000)+(200000*12992000/50203000))/P189 -> 6.5526134 | N189: =(700000*12992000/50203000)/P189 -> 10.436255 | P189: 17358 | Q189: 2000 | R189: 748.47333 | S189: 6.5526134 | T189: 10.436255 | V189: 744.58968 | W189: 0.37229484 | X189: 12992000 | Y189: 113740.26 | Z189: 181152.52 | AB189: 12924588 | AC189: 6462.2939
A190: ITBISA-SOCKET-IC-DIP8-NARROW | B190: 46154.382 | C190: 46154.614 | D190: KYAI KONTONG | E190: FALSE | F190: Shopee | G190: namoe shop | H190: Shopee Aji 26051279QKQD4V | I190: 5 | J190: 2760 | K190: 1 | L190: =185/P190 -> 0.010559963 | M190: =(17500+3000)/P190 -> 1.1701581 | N190: =10212/P190 -> 0.58290998 | O190: =17500/P190 -> 0.99891546 | P190: 17519 | Q190: 2760 | R190: 29.145499 | S190: 1.1701581 | T190: 0.58290998 | U190: 0.99891546 | V190: 28.733832 | W190: 0.010410809 | X190: 510600 | Y190: 20500 | Z190: 10212 | AA190: 17500 | AB190: 503388 | AC190: 182.38696
A191: ITBISA-I2C-IIC-LCD | B191: 46158.592 | C191: 46163.371 | D191: KYAI KONTONG | E191: FALSE | F191: Shopee | G191: ICHIBOT STORE | H191: Shopee Aji 260516HVJAF930 | I191: 5 | J191: 52 | K191: 1 | L191: =6430/P191 -> 0.36677885 | M191: =(8900+1005)/P191 -> 0.56499914 | N191: =33436/P191 -> 1.90725 | O191: =8900/P191 -> 0.50767212 | P191: 17531 | Q191: 52 | R191: 19.0725 | S191: 0.56499914 | T191: 1.90725 | U191: 0.50767212 | V191: 17.222577 | W191: 0.33120341 | X191: 334360 | Y191: 9905 | Z191: 33436 | AA191: 8900 | AB191: 301929 | AC191: 5806.3269
A192: ITBISA-KAPASITOR-ELCO-47UF-50V | B192: 46158.592 | C192: 46160.509 | D192: KYAI KONTONG | E192: FALSE | F192: Shopee | G192: XUMO STORE | H192: Shopee Aji 260516HVJAE93P | I192: 5 | J192: 2 | K192: 1000 | L192: =244000/2/P192 -> 6.959101 | M192: =((19600+1929)*244000/642000)/P192 -> 0.46673672 | N192: =(64200*244000/642000)/P192 -> 1.3918202 | O192: =(19600*244000/642000)/P192 -> 0.42491707 | P192: 17531 | Q192: 2000 | R192: 13.918202 | S192: 0.46673672 | T192: 1.3918202 | U192: 0.42491707 | V192: 12.568201 | W192: 0.0062841007 | X192: 244000 | Y192: 8182.3614 | Z192: 24400 | AA192: 7449.2212 | AB192: 220333.14 | AC192: 110.16657
A193: ITBISA-KAPASITOR-ELCO-100UF-25V | B193: 46158.592 | C193: 46160.509 | D193: KYAI KONTONG | E193: FALSE | F193: Shopee | G193: XUMO STORE | H193: Shopee Aji 260516HVJAE93P | I193: 5 | J193: 2 | K193: 1000 | L193: =224000/2/P193 -> 6.3886829 | M193: =((19600+1929)*224000/642000)/P193 -> 0.42847961 | N193: =(64200*224000/642000)/P193 -> 1.2777366 | O193: =(19600*224000/642000)/P193 -> 0.3900878 | P193: 17531 | Q193: 2000 | R193: 12.777366 | S193: 0.42847961 | T193: 1.2777366 | U193: 0.3900878 | V193: 11.538021 | W193: 0.0057690105 | X193: 224000 | Y193: 7511.676 | Z193: 22400 | AA193: 6838.6293 | AB193: 202273.05 | AC193: 101.13652
A194: ITBISA-DIODA-1N4007-DO41 | B194: 46158.592 | C194: 46160.509 | D194: KYAI KONTONG | E194: FALSE | F194: Shopee | G194: XUMO STORE | H194: Shopee Aji 260516HVJAE93P | I194: 5 | J194: 2 | K194: 1000 | L194: =174000/2/P194 -> 4.9626376 | M194: =((19600+1929)*174000/642000)/P194 -> 0.33283684 | N194: =(64200*174000/642000)/P194 -> 0.99252752 | O194: =(19600*174000/642000)/P194 -> 0.30301463 | P194: 17531 | Q194: 2000 | R194: 9.9252752 | S194: 0.33283684 | T194: 0.99252752 | U194: 0.30301463 | V194: 8.9625699 | W194: 0.004481285 | X194: 174000 | Y194: 5834.9626 | Z194: 17400 | AA194: 5312.1495 | AB194: 157122.81 | AC194: 78.561407
A195: ITBISA-LCD-16X2-GREEN | B195: 46160.151 | C195: 46162.553 | D195: KYAI KONTONG | E195: FALSE | F195: Shopee | G195: SukiTech | H195: Shopee Aji 260518NT1PTFB9 | I195: 5 | J195: 1 | K195: 1 | L195: =14900/P195 -> 0.84443185 | M195: =(6500+1000)/P195 -> 0.42504959 | N195: =(2215+3828)/P195 -> 0.34247662 | O195: =6500/P195 -> 0.36837631 | P195: 17645 | Q195: 1 | R195: 0.84443185 | S195: 0.42504959 | T195: 0.34247662 | U195: 0.36837631 | V195: 0.55862851 | W195: 0.55862851 | X195: 14900 | Y195: 7500 | Z195: 6043 | AA195: 6500 | AB195: 9857 | AC195: 9857
A196: ITBISA-ABC-BATERAI-AA-ALKALINE | B196: 46162.536 | C196: 46164.677 | D196: KYAI KONTONG | E196: FALSE | F196: Shopee | G196: ElectricalmartID | H196: Shopee Aji 260520USV17BBX | I196: 5 | J196: 1 | K196: 6 | L196: =28278/1/P196 -> 1.6062482 | M196: =(8000+1000)/P196 -> 0.5112184 | N196: =(4000+6583)/P196 -> 0.60113604 | O196: =8000/P196 -> 0.45441636 | P196: 17605 | Q196: 6 | R196: 1.6062482 | S196: 0.5112184 | T196: 0.60113604 | U196: 0.45441636 | V196: 1.0619142 | W196: 0.1769857 | X196: 28278 | Y196: 9000 | Z196: 10583 | AA196: 8000 | AB196: 18695 | AC196: 3115.8333
A197: ITBISA-ABC-BATERAI-AA-ALKALINE | B197: 46162.537 | C197: 46163.453 | D197: KYAI KONTONG | E197: FALSE | F197: Shopee | G197: ElectricalmartID | H197: Shopee Aji 260520USYSCCJM | I197: 5 | J197: 1 | K197: 6 | L197: =29499/1/P197 -> 1.6756035 | M197: =(8000+1000)/P197 -> 0.5112184 | N197: =6783/P197 -> 0.38528827 | O197: =8000/P197 -> 0.45441636 | P197: 17605 | Q197: 6 | R197: 1.6756035 | S197: 0.5112184 | T197: 0.38528827 | U197: 0.45441636 | V197: 1.3471173 | W197: 0.22451955 | X197: 29499 | Y197: 9000 | Z197: 6783 | AA197: 8000 | AB197: 23716 | AC197: 3952.6667
A198: ITBISA-ABC-BATERAI-AA-ALKALINE | B198: 46162.538 | C198: 46165.664 | D198: KYAI KONTONG | E198: FALSE | F198: Shopee | G198: ecommerceemart | H198: Shopee Aji 260520UT2PSXG8 | I198: 5 | J198: 1 | K198: 6 | L198: =29497/1/P198 -> 1.6754899 | M198: =(8000+1000)/P198 -> 0.5112184 | N198: =6572/P198 -> 0.37330304 | O198: =8000/P198 -> 0.45441636 | P198: 17605 | Q198: 6 | R198: 1.6754899 | S198: 0.5112184 | T198: 0.37330304 | U198: 0.45441636 | V198: 1.3589889 | W198: 0.22649815 | X198: 29497 | Y198: 9000 | Z198: 6572 | AA198: 8000 | AB198: 23925 | AC198: 3987.5
A199: ITBISA-ABC-BATERAI-AAA-ALKALINE | B199: 46167.453 | C199: 46168.353 | D199: KYAI KONTONG | E199: FALSE | F199: Shopee | G199: ElectricalmartID | H199: Shopee Aji 260525B1V6VMDE | I199: 5 | J199: 1 | K199: 6 | L199: =28278/1/P199 -> 1.5944742 | M199: =(8000+1000)/P199 -> 0.5074711 | N199: =(4000+6575)/P199 -> 0.59627855 | O199: =8000/P199 -> 0.45108542 | P199: 17735 | Q199: 6 | R199: 1.5944742 | S199: 0.5074711 | T199: 0.59627855 | U199: 0.45108542 | V199: 1.0545813 | W199: 0.17576356 | X199: 28278 | Y199: 9000 | Z199: 10575 | AA199: 8000 | AB199: 18703 | AC199: 3117.1667
A200: ITBISA-IC-CD4017BE-DIP16 | B200: 46169.68 | D200: KYAI KONTONG | E200: TRUE | F200: Ocistok/Martkita | G200: https://detail.1688.com/offer/1010760289214.html | H200: MKT-147173 / 338764 | I200: 5 | J200: 10000 | K200: 1 | L200: =683/P200 -> 0.038605019 | M200: =(18870+(100000*6830000/50300000))/P200 -> 1.8340792 | N200: =(100000*6830000/50300000)/P200 -> 0.76749541 | P200: 17692 | Q200: 10000 | R200: 386.05019 | S200: 1.8340792 | T200: 0.76749541 | V200: 387.11678 | W200: 0.038711678 | X200: 6830000 | Y200: 32448.529 | Z200: 13578.529 | AB200: 6848870 | AC200: 684.887
A201: ITBISA-RELAY-5V-5PIN-BLUE | B201: 46169.68 | D201: KYAI KONTONG | E201: TRUE | F201: Ocistok/Martkita | G201: https://detail.1688.com/offer/775368378784.html | H201: MKT-147174 / 338765 | I201: 5 | J201: 15000 | K201: 1 | L201: =1890/P201 -> 0.10682794 | M201: =((152070*28350000/43470000)+(100000*28350000/50300000))/P201 -> 8.7914264 | N201: =(100000*28350000/50300000)/P201 -> 3.185724 | P201: 17692 | Q201: 15000 | R201: 1602.4192 | S201: 8.7914264 | T201: 3.185724 | V201: 1608.0249 | W201: 0.10720166 | X201: 28350000 | Y201: 155537.92 | Z201: 56361.829 | AB201: 28449176 | AC201: 1896.6117
A202: ITBISA-RELAY-24V-5PIN-BLUE | B202: 46169.68 | D202: KYAI KONTONG | E202: TRUE | F202: Ocistok/Martkita | G202: https://detail.1688.com/offer/775368378784.html | H202: MKT-147174 / 338765 | I202: 5 | J202: 6000 | K202: 1 | L202: =1890/P202 -> 0.10682794 | M202: =((152070*11340000/43470000)+(100000*11340000/50300000))/P202 -> 3.5165706 | N202: =(100000*11340000/50300000)/P202 -> 1.2742896 | P202: 17692 | Q202: 6000 | R202: 640.96767 | S202: 3.5165706 | T202: 1.2742896 | V202: 643.20995 | W202: 0.10720166 | X202: 11340000 | Y202: 62215.166 | Z202: 22544.732 | AB202: 11379670 | AC202: 1896.6117
A203: ITBISA-RELAY-24V-4PIN-BLUE | B203: 46169.68 | D203: KYAI KONTONG | E203: TRUE | F203: Ocistok/Martkita | G203: https://detail.1688.com/offer/775368378784.html | H203: MKT-147174 / 338765 | I203: 5 | J203: 2000 | K203: 1 | L203: =1890/P203 -> 0.10682794 | M203: =((152070*3780000/43470000)+(100000*3780000/50300000))/P203 -> 1.1721902 | N203: =(100000*3780000/50300000)/P203 -> 0.4247632 | P203: 17692 | Q203: 2000 | R203: 213.65589 | S203: 1.1721902 | T203: 0.4247632 | V203: 214.40332 | W203: 0.10720166 | X203: 3780000 | Y203: 20738.389 | Z203: 7514.9105 | AB203: 3793223.5 | AC203: 1896.6117
A204: ITBISA-LCD-16X2-GREEN | B204: 46189.199 | C204: 46190.556 | D204: KYAI KONTONG | E204: FALSE | F204: Shopee Aji | G204: Starlectric | H204: Shopee Aji 2606167HD513P8 | I204: 5 | J204: 1 | K204: 1 | L204: =16500/P204 -> 0.9325195 | M204: =(13980+1000)/P204 -> 0.84661467 | N204: =(2653+3236)/P204 -> 0.33282469 | O204: =13980/P204 -> 0.79009834 | P204: 17694 | Q204: 1 | R204: 0.9325195 | S204: 0.84661467 | T204: 0.33282469 | U204: 0.79009834 | V204: 0.65621115 | W204: 0.65621115 | X204: 16500 | Y204: 14980 | Z204: 5889 | AA204: 13980 | AB204: 11611 | AC204: 11611
A205: ITBISA-LCD-16X2-GREEN | B205: 46186.208 | C205: 46186.533 | D205: KYAI KONTONG | E205: FALSE | F205: Shopee Aji | G205: Starlectric | H205: Shopee Aji 26061300ND0FTY | I205: 5 | J205: 1 | K205: 1 | L205: =16500/P205 -> 0.9233352 | M205: =(13980+1000)/P205 -> 0.83827644 | N205: =(2655+3228)/P205 -> 0.32921097 | O205: =13980/P205 -> 0.78231673 | P205: 17870 | Q205: 1 | R205: 0.9233352 | S205: 0.83827644 | T205: 0.32921097 | U205: 0.78231673 | V205: 0.65008394 | W205: 0.65008394 | X205: 16500 | Y205: 14980 | Z205: 5883 | AA205: 13980 | AB205: 11617 | AC205: 11617
E206: FALSE
E207: FALSE
E208: FALSE
E209: FALSE
...

Sheet BisaHilang
A1: Tanggal Pengecekan Kehilangan | B1: SKU | C1: Banyak Ketemu | D1: Nilai Ketemu | E1: Banyak Hilang | F1: Nilai Hilang | G1: Lokasi Gudang | H1: Keterangan
A3: 46023.042 | B3: ITBISA-BUBBLE-WRAP | C3: 1 | D3: 1 | G3: KYAI KONTONG
A4: 46023.042 | B4: ITBISA-BUBBLE-WRAP | E4: 1 | F4: 1 | G4: KYAI KONTONG
A6: 46044.169 | B6: ITBISA-IC-LM741CN-DIP8 | E6: 20 | F6: =E6*1291.1 -> 25822 | G6: KYAI KONTONG
A7: 46044.169 | B7: ITBISA-IC-UA741CN-DIP8 | C7: 20 | D7: =C7*572 -> 11440 | G7: KYAI KONTONG
A8: 46044.169 | B8: ITBISA-7SEGMENT-CATHODE-RED-1.20-1BIT | C8: =(339 - 292) -> 47 | D8: =C8*2756 -> 129532 | G8: KYAI KONTONG
A9: 46044.169 | B9: ITBISA-7SEGMENT-CATHODE-RED-2.30-1BIT | C9: =(58-42) -> 16 | D9: =C9*6028 -> 96448 | G9: KYAI KONTONG
A10: 46044.169 | B10: ITBISA-BLUETOOTH-MODULE-HC05 | E10: =(27-15) -> 12 | F10: =E10*29027 -> 348324 | G10: KYAI KONTONG
A11: 46044.169 | B11: ITBISA-IC-NE555P-DIP8 | E11: =(825-313) -> 512 | F11: =E11*288.89 -> 147911.68 | G11: KYAI KONTONG
A12: 46044.169 | B12: ITBISA-IC-PC817-DIP4 | E12: =(852-473) -> 379 | F12: =E12*340.35 -> 128992.65 | G12: KYAI KONTONG
A13: 46044.169 | B13: ITBISA-RELAY-5V-1CHANNEL-BLUE-LOW-TRIGGER | E13: =(8-5) -> 3 | F13: =E13*4252.52 -> 12757.56 | G13: KYAI KONTONG
A14: 46044.169 | B14: ITBISA-SERVO-SG90-180DEG | C14: =(13-8) -> 5 | D14: =C14* 10459.32 -> 52296.6 | G14: KYAI KONTONG
A15: 46044.169 | B15: ITBISA-SERVO-SG90-360DEG | C15: =(5-3) -> 2 | D15: =C15* 11352.67 -> 22705.34 | G15: KYAI KONTONG
A16: 46044.169 | B16: ITBISA-SOCKET-IC-DIP14-NARROW | C16: =(123-25) -> 98 | D16: =C16* 222.05 -> 21760.9 | G16: KYAI KONTONG
A17: 46044.169 | B17: ITBISA-CHIP-ESP32-WROOM-ANTENNA | E17: 6 | F17: =E17*24820 -> 148920 | G17: KYAI KONTONG
A19: 46046.137 | B19: ITBISA-7SEGMENT-ANODE-RED-0.56-1BIT | E19: 160 | F19: =E19*675.92 -> 108147.2 | G19: KERTASARI CIAMIS
A20: 46046.137 | B20: ITBISA-IC-CD4094BM-SMD-SOP16 | E20: =494-130 -> 364 | F20: =E20*874.83 -> 318438.12 | G20: KERTASARI CIAMIS
A21: 46046.137 | B21: ITBISA-IC-CD4094BM-SMD-SOP16 | E21: 45 | F21: =E21*874.83 -> 39367.35 | G21: KERTASARI CIAMIS
A22: 46046.137 | B22: ITBISA-7SEGMENT-CATHODE-RED-1.20-1BIT | E22: =(87-52) -> 35 | F22: =E22*2756 -> 96460 | G22: KERTASARI CIAMIS
A23: 46046.137 | B23: ITBISA-7SEGMENT-CATHODE-RED-2.30-1BIT | C23: =(36-8) -> 28 | D23: =C23*6028 -> 168784 | G23: KERTASARI CIAMIS
A24: 46046.137 | B24: ITBISA-ABC-BATERAI-AA-ALKALINE | E24: =(155-94) -> 61 | F24: =E24*3900 -> 237900 | G24: KERTASARI CIAMIS
A25: 46046.137 | B25: ITBISA-ABC-BATERAI-AAA-ALKALINE | C25: =(38-35) -> 3 | D25: =C25*3612.53 -> 10837.59 | G25: KERTASARI CIAMIS
A26: 46046.137 | B26: ITBISA-BREADBOARD-830HOLE-MB102 | C26: =(32-23) -> 9 | D26: =C26*7000 -> 63000 | G26: KERTASARI CIAMIS
A27: 46046.137 | B27: ITBISA-CHIP-ESP32-WROOM | C27: =(21-14) -> 7 | D27: =(C27*23076) -> 161532 | G27: KERTASARI CIAMIS
A28: 46046.137 | B28: ITBISA-I2C-IIC-LCD | C28: =(44-31) -> 13 | D28: =C28*5617.6 -> 73028.8 | G28: KERTASARI CIAMIS
A29: 46046.137 | B29: ITBISA-LDR-GL5516 | E29: =(79-47) -> 32 | F29: =E29*285.14 -> 9124.48 | G29: KERTASARI CIAMIS
A30: 46046.137 | B30: ITBISA-LED-MAX7219-4IN1-TIGHT | E30: 1 | F30: =E30*35799.38 -> 35799.38 | G30: KERTASARI CIAMIS
A31: 46046.137 | B31: ITBISA-PIN-HEADER-MALE-1X40PIN-L-SAMA | E31: 7 | F31: =E31*726.09 -> 5082.63 | G31: KERTASARI CIAMIS
A32: 46046.137 | B32: ITBISA-RELAY-12V-4PIN-BLUE | C32: =(400)-291 -> 109 | D32: =C32*1637 -> 178433 | G32: KERTASARI CIAMIS
A33: 46046.137 | B33: ITBISA-RELAY-12V-5PIN-BLUE | E33: 10 | F33: =E33*1980.5 -> 19805 | G33: KERTASARI CIAMIS
A34: 46046.137 | B34: ITBISA-SERVO-SG90-180DEG | E34: =(56-37) -> 19 | F34: =E34* 10459.32 -> 198727.08 | G34: KERTASARI CIAMIS
A35: 46046.137 | B35: ITBISA-SERVO-SG90-360DEG | E35: =(35-30) -> 5 | F35: =E35* 11352.67 -> 56763.35 | G35: KERTASARI CIAMIS
A36: 46046.137 | B36: ITBISA-SOCKET-IC-DIP20-NARROW | C36: =(103-33) -> 70 | D36: =C36*535 -> 37450 | G36: KERTASARI CIAMIS
A37: 46046.137 | B37: ITBISA-WEMOS-D1-MINI-ESP8266 | E37: 1 | F37: =E37*20791.2 -> 20791.2 | G37: KERTASARI CIAMIS
A38: 46046.137 | B38: ITBISA-IC-NE555P-DIP8 | E38: =(161-58) -> 103 | F38: =E38*316.71 -> 32621.13 | G38: KYAI KONTONG
A40: 46081.674 | B40: ITBISA-CHIP-ESP8266-ESP12F | E40: 17 | F40: =E40*12783.5 -> 217319.5 | G40: KERTASARI CIAMIS
A41: 46081.674 | B41: ITBISA-RTC-DS3231SN | E41: 4 | F41: =E41*19398 -> 77592 | G41: KYAI KONTONG
A42: 46081.674 | B42: ITBISA-SERVO-SG90-360DEG | C42: 3 | D42: =C42* 11352.67 -> 34058.01 | G42: KYAI KONTONG
A43: 46081.674 | B43: ITBISA-CHIP-ESP8266-ESP12F | E43: 3 | F43: =E43*12783.5 -> 38350.5 | G43: KERTASARI CIAMIS
A44: 46081.674 | B44: ITBISA-CHIP-ESP8266-ESP12F | E44: 18 | F44: =E44*12783.5 -> 230103 | G44: KERTASARI CIAMIS
A45: 46081.674 | B45: ITBISA-RELAY-12V-5PIN-BLUE | E45: 10 | F45: =E45*1960.34482758621 -> 19603.448 | G45: KERTASARI CIAMIS
A46: 46081.674 | B46: ITBISA-IC-NE555P-DIP8 | E46: 200 | F46: =E46*476.829268292683 -> 95365.854 | G46: KERTASARI CIAMIS
A48: 46147.542 | B48: ITBISA-RTC-DS3231SN | C48: 18 | D48: =C48*19648.9534883721 -> 353681.16 | G48: KYAI KONTONG
A49: 46147.542 | B49: ITBISA-RTC-DS3231M | E49: 118 | F49: =E49*18007.86 -> 2124927.5 | G49: KYAI KONTONG
A51: 46172.999 | B51: ITBISA-IC-L7812CV-TO220 | E51: =38-12 -> 26 | F51: =E51*1057 -> 27482 | G51: KYAI KONTONG
A52: 46172.999 | B52: ITBISA-IC-ULN2803APG-DIP18 | E52: =283-18 -> 265 | F52: =E52*1018 -> 269770 | G52: KYAI KONTONG
A54: 46178.417 | B54: ITBISA-RELAY-5V-5PIN-BLUE | C54: 20 | D54: 53980 | G54: KYAI KONTONG
A55: 46178.417 | B55: ITBISA-IC-74HC595N-DIP16 | C55: 84 | D55: =C55*768.242756896998 -> 64532.392 | G55: KYAI KONTONG
A56: 46178.417 | B56: ITBISA-IC-CD4017BE-DIP16 | C56: 286 | D56: =C56*684.887 -> 195877.68 | G56: KYAI KONTONG
A58: 46198.592 | B58: ITBISA-7SEGMENT-CATHODE-RED-0.56-1BIT | E58: 312 | F58: 254746 | G58: KYAI KONTONG | H58: Stock opname 2026-06-25 (hitung fisik Shopee+TikTok)
A59: 46198.592 | B59: ITBISA-7SEGMENT-CATHODE-RED-1.20-1BIT | E59: 26 | F59: 72843 | G59: KYAI KONTONG | H59: Stock opname 2026-06-25 (hitung fisik Shopee+TikTok)
A60: 46198.592 | B60: ITBISA-7SEGMENT-CATHODE-RED-2.30-1BIT | C60: 2 | D60: 12490 | G60: KYAI KONTONG | H60: Stock opname 2026-06-25 (hitung fisik Shopee+TikTok)
A61: 46198.592 | B61: ITBISA-BREADBOARD-830HOLE-MB102 | E61: 20 | F61: 129596 | G61: KYAI KONTONG | H61: Stock opname 2026-06-25 (hitung fisik Shopee+TikTok)
A62: 46198.592 | B62: ITBISA-CHIP-ESP32-WROOM-ANTENNA | E62: 1 | F62: 22100 | G62: KYAI KONTONG | H62: Stock opname 2026-06-25 (hitung fisik Shopee+TikTok)
A63: 46198.592 | B63: ITBISA-CHIP-ESP8266-ESP12F | C63: 38 | D63: 535306 | G63: KYAI KONTONG | H63: Stock opname 2026-06-25 (hitung fisik Shopee+TikTok)
A64: 46198.592 | B64: ITBISA-DC-TO-DC-STEPDOWN-LM2596 | E64: 28 | F64: 151500 | G64: KYAI KONTONG | H64: Stock opname 2026-06-25 (hitung fisik Shopee+TikTok)
A65: 46198.592 | B65: ITBISA-DC-TO-DC-STEPDOWN-XL4005 | E65: 5 | F65: 43916 | G65: KYAI KONTONG | H65: Stock opname 2026-06-25 (hitung fisik Shopee+TikTok)
A66: 46198.592 | B66: ITBISA-DC-TO-DC-STEPDOWN-XL4015 | E66: 110 | F66: 955567 | G66: KYAI KONTONG | H66: Stock opname 2026-06-25 (hitung fisik Shopee+TikTok)
A67: 46198.592 | B67: ITBISA-DC-TO-DC-STEPUP-XL6009 | E67: 14 | F67: 98818 | G67: KYAI KONTONG | H67: Stock opname 2026-06-25 (hitung fisik Shopee+TikTok)
A68: 46198.592 | B68: ITBISA-IC-CD4017BE-DIP16 | E68: 1 | F68: 682 | G68: KYAI KONTONG | H68: Stock opname 2026-06-25 (hitung fisik Shopee+TikTok)
A69: 46198.592 | B69: ITBISA-IC-L7805CV-TO220 | E69: 82 | F69: 71870 | G69: KYAI KONTONG | H69: Stock opname 2026-06-25 (hitung fisik Shopee+TikTok)
A70: 46198.592 | B70: ITBISA-INFRARED-1838 | E70: 16 | F70: 9835 | G70: KYAI KONTONG | H70: Stock opname 2026-06-25 (hitung fisik Shopee+TikTok)
A71: 46198.592 | B71: ITBISA-NODEMCU-V3-CH340G-ESP8266-MICRO | E71: 6 | F71: 142717 | G71: KYAI KONTONG | H71: Stock opname 2026-06-25 (hitung fisik Shopee+TikTok)
A72: 46198.592 | B72: ITBISA-WEMOS-D1-MINI-ESP8266 | C72: 2 | D72: 43690 | G72: KYAI KONTONG | H72: Stock opname 2026-06-25 (hitung fisik Shopee+TikTok)
A73: 46198.592 | B73: ITBISA-SOCKET-IC-DIP8-NARROW | E73: 612 | F73: 117309 | G73: KYAI KONTONG | H73: Stock opname 2026-06-25 (hitung fisik Shopee+TikTok)

Sheet BisaRekapBarang
D1: TRUE | E1: FALSE | F1: FALSE | G1: FALSE | H1: FALSE | I1: FALSE | J1: FALSE | K1: FALSE | L1: FALSE | M1: FALSE | N1: FALSE
A2: {={BisaRekapBarangBackend!A1:C1;SORT(IF(BisaRekapBarangBackend!B2:B140<1,,BisaRekapBarangBackend!A2:C140),1,TRUE)}} -> Alamat Penerima | B2: Harga Impor Barang (Rupiah) | C2: Harga Impor Barang (USD) | D2: {={BisaRekapBarangBackend!D1:O1; SORT(IF( (BisaRekapBarangBackend!D2:D140="ITBISA-KODE-UNIK")+(BisaRekapBarangBackend!H2:H140=0),,BisaRekapBarangBackend!D2:O140), IF(D1=TRUE,1, IF(E1=TRUE,2, IF(F1=TRUE,3, IF(G1=TRUE,4, IF(H1=TRUE,5, IF(I1=TRUE,6, IF(J1=TRUE,7, IF(K1=TRUE,8, IF(L1=TRUE,9, IF(M1=TRUE,10, IF(N1=TRUE,11, IF(#REF!=TRUE,12,1)))))))))))), IF(D1=TRUE,TRUE, IF(E1=TRUE,TRUE, IF(F1=TRUE,TRUE, IF(G1=TRUE,FALSE, IF(H1=TRUE,FALSE, IF(I1=TRUE,FALSE, IF(J1=TRUE,FALSE, IF(K1=TRUE,FALSE, IF(L1=TRUE,FALSE, IF(M1=TRUE,FALSE, IF(N1=TRUE,FALSE, IF(#REF!=TRUE,FALSE)))))))))))), 1,TRUE)}} -> SKU | E2: Tanggal Pesan Terakhir | F2: HPP Terakhir | G2: HPP Belum Terjual | H2: Total Stok | I2: 1/2 Total Stok | J2: 1/3 Total Stok | K2: 40% Total Stok | L2: 20% Total Stok | M2: KERTASARI CIAMIS | N2: KYAI KONTONG
A3: KYAI KONTONG | B3: 100503000 | C3: 5600.3009 | D3: ITBISA-7SEGMENT-ANODE-RED-0.56-1BIT | E3: 46197 | F3: 675.92 | G3: 2867252.6 | H3: 4242 | I3: 2121 | J3: 1414 | K3: 1696 | L3: 848 | N3: 4242
D4: ITBISA-7SEGMENT-ANODE-RED-1.00-1BIT | E4: 46197 | F4: 2000 | G4: 4016000 | H4: 2008 | I4: 1004 | J4: 669 | K4: 803 | L4: 401 | N4: 2008
D5: ITBISA-7SEGMENT-ANODE-RED-1.20-1BIT | E5: 46193 | F5: 3611.73 | G5: 2235660.9 | H5: 619 | I5: 309 | J5: 206 | K5: 247 | L5: 123 | N5: 619
D6: ITBISA-7SEGMENT-CATHODE-RED-0.56-1BIT | E6: 46196 | F6: 731 | G6: 3655 | H6: 5 | I6: 2 | J6: 1 | K6: 2 | L6: 1 | N6: 5
D7: ITBISA-7SEGMENT-CATHODE-RED-1.20-1BIT | E7: 46176 | F7: 2756 | G7: 55120 | H7: 20 | I7: 10 | J7: 6 | K7: 8 | L7: 4 | N7: 20
D8: ITBISA-7SEGMENT-CATHODE-RED-2.30-1BIT | E8: 46179 | F8: 6462.2939 | G8: 38773.763 | H8: 6 | I8: 3 | J8: 2 | K8: 2 | L8: 1 | N8: 6
D9: ITBISA-ABC-BATERAI-9V-POWER | E9: 46192 | F9: 11210.938 | G9: 1244414.1 | H9: 111 | I9: 55 | J9: 37 | K9: 44 | L9: 22 | N9: 111
D10: ITBISA-ABC-BATERAI-AA-ALKALINE | E10: 46198 | F10: 3987.5 | G10: 1375687.5 | H10: 345 | I10: 172 | J10: 115 | K10: 138 | L10: 69 | N10: 345
D11: ITBISA-ABC-BATERAI-AAA-ALKALINE | E11: 46198 | F11: 3117.1667 | G11: 1362201.8 | H11: 437 | I11: 218 | J11: 145 | K11: 174 | L11: 87 | N11: 437
D12: ITBISA-ABC-BATERAI-D-POWER | F12: 5166.67 | G12: 5166.67 | H12: 1 | I12: 0 | J12: 0 | K12: 0 | L12: 0 | N12: 1
D13: ITBISA-ARDUINO-UNO-R3-328P-SMD | E13: 46196 | F13: 37978.26 | G13: 8469152 | H13: 223 | I13: 111 | J13: 74 | K13: 89 | L13: 44 | N13: 223
D14: ITBISA-BLUETOOTH-MODULE-HC05 | E14: 46196 | F14: 21771.152 | G14: 4288916.8 | H14: 197 | I14: 98 | J14: 65 | K14: 78 | L14: 39 | N14: 197
D15: ITBISA-BUBBLE-WRAP | E15: 46134 | G15: 0 | H15: 12 | I15: 6 | J15: 4 | K15: 4 | L15: 2 | N15: 12
D16: ITBISA-BUZZER-ACTIVE-5V | E16: 46198 | F16: 1250.5138 | G16: 3372635.7 | H16: 2697 | I16: 1348 | J16: 899 | K16: 1078 | L16: 539 | N16: 2697
D17: ITBISA-CHIP-ESP8266-ESP12F | E17: 46077 | F17: 12783.5 | G17: 485773 | H17: 38 | I17: 19 | J17: 12 | K17: 15 | L17: 7 | N17: 38
D18: ITBISA-DC-TO-DC-STEPDOWN-XL4005 | E18: 46198 | F18: 8461.03 | G18: 126915.45 | H18: 15 | I18: 7 | J18: 5 | K18: 6 | L18: 3 | N18: 15
D19: ITBISA-DC-TO-DC-STEPUP-XL6009 | E19: 46197 | F19: 7240.2871 | G19: 202728.04 | H19: 28 | I19: 14 | J19: 9 | K19: 11 | L19: 5 | N19: 28
D20: ITBISA-DIODA-1N4007-DO41 | E20: 46185 | F20: 78.561407 | G20: 154765.97 | H20: 1970 | I20: 985 | J20: 656 | K20: 788 | L20: 394 | N20: 1970
D21: ITBISA-I2C-IIC-LCD | E21: 46198 | F21: 5806.3269 | G21: 168383.48 | H21: 29 | I21: 14 | J21: 9 | K21: 11 | L21: 5 | N21: 29
D22: ITBISA-IC-74HC245N-DIP20 | E22: 46195 | F22: 1425.7829 | G22: 4030688.3 | H22: 2827 | I22: 1413 | J22: 942 | K22: 1130 | L22: 565 | N22: 2827
D23: ITBISA-IC-74HC595N-DIP16 | E23: 46185 | F23: 768.24276 | G23: 768.24276 | H23: 1 | I23: 0 | J23: 0 | K23: 0 | L23: 0 | N23: 1
D24: ITBISA-IC-ATMEGA328P-DIP28 | E24: 46197 | F24: 27318.46 | G24: 4125087.5 | H24: 151 | I24: 75 | J24: 50 | K24: 60 | L24: 30 | N24: 151
D25: ITBISA-IC-CD4017BE-DIP16 | E25: 46195 | F25: 684.887 | G25: 4794.209 | H25: 7 | I25: 3 | J25: 2 | K25: 2 | L25: 1 | N25: 7
D26: ITBISA-IC-CD4094BE-DIP16 | E26: 46198 | F26: 779.54 | G26: 6587113 | H26: 8450 | I26: 4225 | J26: 2816 | K26: 3380 | L26: 1690 | N26: 8450
D27: ITBISA-IC-CD4094BM-SMD-SOP16 | E27: 46195 | F27: 747.90909 | G27: 3343153.6 | H27: 4470 | I27: 2235 | J27: 1490 | K27: 1788 | L27: 894 | N27: 4470
... D30: ITBISA-IC-L7812CV-TO220 | E30: 46197 | F30: 1057 | G30: 1057 | H30: 1 | I30: 0 | J30: 0 | K30: 0 | L30: 0 | N30: 1
D31: ITBISA-IC-LM741CN-DIP8 | F31: 1291.1 | G31: 1291.1 | H31: 1 | I31: 0 | J31: 0 | K31: 0 | L31: 0 | N31: 1
D32: ITBISA-IC-NE555P-DIP8 | E32: 46197 | F32: 476.82927 | G32: 185486.59 | H32: 389 | I32: 194 | J32: 129 | K32: 155 | L32: 77 | N32: 389
D33: ITBISA-IC-PC817-DIP4 | E33: 46198 | F33: 340.065 | G33: 1305509.5 | H33: 3839 | I33: 1919 | J33: 1279 | K33: 1535 | L33: 767 | N33: 3839
D34: ITBISA-IC-UA741CN-DIP8 | E34: 46198 | F34: 572 | G34: 787644 | H34: 1377 | I34: 688 | J34: 459 | K34: 550 | L34: 275 | N34: 1377
D35: ITBISA-IC-ULN2003AN-DIP16 | E35: 46196 | F35: 855.5 | G35: 1255018.5 | H35: 1467 | I35: 733 | J35: 489 | K35: 586 | L35: 293 | N35: 1467
D36: ITBISA-IC-ULN2803APG-DIP18 | E36: 46191 | F36: 1018 | G36: 1018 | H36: 1 | I36: 0 | J36: 0 | K36: 0 | L36: 0 | N36: 1
D37: ITBISA-IDC-2X5-AMPHENOL-FEMALE | E37: 46179 | F37: 369.94038 | G37: 723603.38 | H37: 1956 | I37: 978 | J37: 652 | K37: 782 | L37: 391 | N37: 1956
D38: ITBISA-IDC-2X5-AMPHENOL-MALE | E38: 46158 | F38: 585.4 | G38: 440220.8 | H38: 752 | I38: 376 | J38: 250 | K38: 300 | L38: 150 | N38: 752
D39: ITBISA-JACK-DC-005-FEMALE | E39: 46198 | F39: 248.68687 | G39: 438186.26 | H39: 1762 | I39: 881 | J39: 587 | K39: 704 | L39: 352 | N39: 1762
D40: ITBISA-JUMPER-FF-10CM | E40: 46196 | F40: 90.005507 | G40: 500430.62 | H40: 5560 | I40: 2780 | J40: 1853 | K40: 2224 | L40: 1112 | N40: 5560
D41: ITBISA-JUMPER-FF-20CM | E41: 46196 | F41: 165.06 | G41: 1023372 | H41: 6200 | I41: 3100 | J41: 2066 | K41: 2480 | L41: 1240 | N41: 6200
D42: ITBISA-JUMPER-MF-10CM | E42: 46197 | F42: 165.05 | G42: 1089330 | H42: 6600 | I42: 3300 | J42: 2200 | K42: 2640 | L42: 1320 | N42: 6600
D43: ITBISA-JUMPER-MF-20CM | E43: 46196 | F43: 119.7 | G43: 545832 | H43: 4560 | I43: 2280 | J43: 1520 | K43: 1824 | L43: 912 | N43: 4560
... D47: ITBISA-KAPASITOR-ELCO-2200UF-25V | E47: 46190 | F47: 662.92581 | G47: 384496.97 | H47: 580 | I47: 290 | J47: 193 | K47: 232 | L47: 116 | N47: 580
D48: ITBISA-KAPASITOR-ELCO-47UF-50V | F48: 110.16657 | G48: 220333.14 | H48: 2000 | I48: 1000 | J48: 666 | K48: 800 | L48: 400 | N48: 2000
D49: ITBISA-LCD-16X2-BLUE | E49: 46181 | F49: 9482.48 | G49: 246544.48 | H49: 26 | I49: 13 | J49: 8 | K49: 10 | L49: 5 | N49: 26
D50: ITBISA-LCD-16X2-GREEN | E50: 46181 | F50: 11611 | G50: 46444 | H50: 4 | I50: 2 | J50: 1 | K50: 1 | L50: 0 | N50: 4
D51: ITBISA-LDR-GL5516 | E51: 46192 | F51: 285.14 | G51: 20815.22 | H51: 73 | I51: 36 | J51: 24 | K51: 29 | L51: 14 | N51: 73
D52: ITBISA-LED-MAX7219-4IN1-GAP | F52: 36500 | G52: 182500 | H52: 5 | I52: 2 | J52: 1 | K52: 2 | L52: 1 | N52: 5
D53: ITBISA-LED-MAX7219-4IN1-TIGHT | E53: 46196 | F53: 35799.38 | G53: 2720752.9 | H53: 76 | I53: 38 | J53: 25 | K53: 30 | L53: 15 | N53: 76
D54: ITBISA-LED-SUPERBRIGHT-5MM-BLUE | E54: 46177 | F54: 58.82 | G54: 293041.24 | H54: 4982 | I54: 2491 | J54: 1660 | K54: 1992 | L54: 996 | N54: 4982
D55: ITBISA-LED-SUPERBRIGHT-5MM-GREEN | E55: 46196 | F55: 69.350746 | G55: 680261.47 | H55: 9809 | I55: 4904 | J55: 3269 | K55: 3923 | L55: 1961 | N55: 9809
D56: ITBISA-LED-SUPERBRIGHT-5MM-RED | E56: 46196 | F56: 52.64 | G56: 214771.2 | H56: 4080 | I56: 2040 | J56: 1360 | K56: 1632 | L56: 816 | N56: 4080
D57: ITBISA-LED-SUPERBRIGHT-5MM-WHITE | E57: 46188 | F57: 76.63 | G57: 132340.01 | H57: 1727 | I57: 863 | J57: 575 | K57: 690 | L57: 345 | N57: 1727
D58: ITBISA-LED-SUPERBRIGHT-5MM-YELLOW | E58: 46196 | F58: 66.67 | G58: 24467.89 | H58: 367 | I58: 183 | J58: 122 | K58: 146 | L58: 73 | N58: 367
D59: ITBISA-NODEMCU-V3-CH340G-ESP8266-MICRO | E59: 46193 | F59: 23261.03 | G59: 23261.03 | H59: 1 | I59: 0 | J59: 0 | K59: 0 | L59: 0 | N59: 1
D60: ITBISA-NPN-2N2222-TO92 | E60: 46193 | F60: 106.37 | G60: 1042106.9 | H60: 9797 | I60: 4898 | J60: 3265 | K60: 3918 | L60: 1959 | N60: 9797
D61: ITBISA-NPN-2N3904-TO92 | E61: 46193 | F61: 106.34 | G61: 235117.74 | H61: 2211 | I61: 1105 | J61: 737 | K61: 884 | L61: 442 | N61: 2211
D62: ITBISA-NPN-2N5551-TO92 | E62: 46193 | F62: 106.43 | G62: 126651.7 | H62: 1190 | I62: 595 | J62: 396 | K62: 476 | L62: 238 | N62: 1190
D63: ITBISA-NPN-BC337-TO92 | E63: 46193 | F63: 106.44 | G63: 232358.52 | H63: 2183 | I63: 1091 | J63: 727 | K63: 873 | L63: 436 | N63: 2183
D64: ITBISA-NPN-BC547-TO92 | E64: 46194 | F64: 106.34 | G64: 349645.92 | H64: 3288 | I64: 1644 | J64: 1096 | K64: 1315 | L64: 657 | N64: 3288
... D100: ITBISA-RESISTOR-33K-1/4W | E100: 46195 | F100: 21.75 | G100: 34800 | H100: 1600 | I100: 800 | J100: 533 | K100: 640 | L100: 320 | N100: 1600
D101: ITBISA-RESISTOR-390-1/4W | F101: 15.59 | G101: 29465.1 | H101: 1890 | I101: 945 | J101: 630 | K101: 756 | L101: 378 | N101: 1890
D102: ITBISA-RESISTOR-39K-1/4W | E102: 46190 | F102: 19.96 | G102: 58283.2 | H102: 2920 | I102: 1460 | J102: 973 | K102: 1168 | L102: 584 | N102: 2920
D103: ITBISA-RESISTOR-3K3-1/4W | E103: 46195 | F103: 17.73 | G103: 40140.72 | H103: 2264 | I103: 1132 | J103: 754 | K103: 905 | L103: 452 | N103: 2264
D104: ITBISA-RESISTOR-470K-1/4W | E104: 46191 | F104: 22.43 | G104: 17831.85 | H104: 795 | I104: 397 | J104: 265 | K104: 318 | L104: 159 | N104: 795
D105: ITBISA-RESISTOR-47K-1/4W | E105: 46195 | F105: 17.63 | G105: 61705 | H105: 3500 | I105: 1750 | J105: 1166 | K105: 1400 | L105: 700 | N105: 3500
D106: ITBISA-RESISTOR-4K7-1/4W | E106: 46196 | F106: 21.7 | G106: 58438.1 | H106: 2693 | I106: 1346 | J106: 897 | K106: 1077 | L106: 538 | N106: 2693
D107: ITBISA-RESISTOR-560-1/4W | E107: 46195 | F107: 19.96 | G107: 88762.12 | H107: 4447 | I107: 2223 | J107: 1482 | K107: 1778 | L107: 889 | N107: 4447
D108: ITBISA-RESISTOR-56K-1/4W | E108: 46190 | F108: 20 | G108: 11600 | H108: 580 | I108: 290 | J108: 193 | K108: 232 | L108: 116 | N108: 580
D109: ITBISA-RESISTOR-5K6-1/4W | E109: 46190 | F109: 19.96 | G109: 136167.12 | H109: 6822 | I109: 3411 | J109: 2274 | K109: 2728 | L109: 1364 | N109: 6822
D110: ITBISA-RESISTOR-680K-1/4W | E110: 46124 | F110: 17.44 | G110: 32525.6 | H110: 1865 | I110: 932 | J110: 621 | K110: 746 | L110: 373 | N110: 1865
D111: ITBISA-RESISTOR-6K8-1/4W | E111: 46190 | F111: 17.63 | G111: 68051.8 | H111: 3860 | I111: 1930 | J111: 1286 | K111: 1544 | L111: 772 | N111: 3860
D112: ITBISA-RFID-RC522-KIT | E112: 46194 | F112: 13200 | G112: 1927200 | H112: 146 | I112: 73 | J112: 48 | K112: 58 | L112: 29 | N112: 146
D113: ITBISA-SENSOR-SUHU-DHT11 | E113: 46127 | F113: 8283.86 | G113: 248515.8 | H113: 30 | I113: 15 | J113: 10 | K113: 12 | L113: 6 | N113: 30
... D121: ITBISA-TERMINAL-BLOCK-KF301-2P-BLUE | E121: 46145 | F121: 395.08727 | G121: 437756.7 | H121: 1108 | I121: 554 | J121: 369 | K121: 443 | L121: 221 | N121: 1108
D122: ITBISA-TIGERHEAD-SENTER-KUNING-FT300 | F122: 10607.58 | G122: 10607.58 | H122: 1 | I122: 0 | J122: 0 | K122: 0 | L122: 0 | N122: 1
D123: ITBISA-USB-A-TO-B-30CM | E123: 46193 | F123: 1714.37 | G123: 533169.07 | H123: 311 | I123: 155 | J123: 103 | K123: 124 | L123: 62 | N123: 311

Sheet BisaPindahBarang
A1: Tanggal | C1: Lokasi Penambahan Barang | D1: Lokasi Pengurangan Barang | E1: Banyak Barang | F1: Keterangan
A3: 46023 | B3: ITBISA-7SEGMENT-ANODE-RED-0.56-1BIT | C3: KERTASARI CIAMIS | D3: KYAI KONTONG | E3: 255
A4: 46023 | B4: ITBISA-7SEGMENT-ANODE-RED-1.00-1BIT | C4: KERTASARI CIAMIS | D4: KYAI KONTONG | E4: 519
A5: 46023 | B5: ITBISA-7SEGMENT-ANODE-RED-1.20-1BIT | C5: KERTASARI CIAMIS | D5: KYAI KONTONG | E5: 782
A6: 46023 | B6: ITBISA-7SEGMENT-CATHODE-RED-0.56-1BIT | C6: KERTASARI CIAMIS | D6: KYAI KONTONG | E6: 1752
A7: 46023 | B7: ITBISA-7SEGMENT-CATHODE-RED-1.20-1BIT | C7: KERTASARI CIAMIS | D7: KYAI KONTONG | E7: 87
A8: 46023 | B8: ITBISA-7SEGMENT-CATHODE-RED-2.30-1BIT | C8: KERTASARI CIAMIS | D8: KYAI KONTONG | E8: 8
A9: 46023 | B9: ITBISA-ABC-BATERAI-9V-POWER | C9: KERTASARI CIAMIS | D9: KYAI KONTONG | E9: 8
A10: 46023 | B10: ITBISA-ABC-BATERAI-AA-ALKALINE | C10: KERTASARI CIAMIS | D10: KYAI KONTONG | E10: 250
A11: 46023 | B11: ITBISA-ABC-BATERAI-AAA-ALKALINE | C11: KERTASARI CIAMIS | D11: KYAI KONTONG | E11: 35
A12: 46023 | B12: ITBISA-ABC-BATERAI-D-POWER | C12: KERTASARI CIAMIS | D12: KYAI KONTONG
A13: 46023 | B13: ITBISA-ARDUINO-UNO-R3-328P-SMD | C13: KERTASARI CIAMIS | D13: KYAI KONTONG | E13: 221
A14: 46023 | B14: ITBISA-BLUETOOTH-MODULE-HC05 | C14: KERTASARI CIAMIS | D14: KYAI KONTONG | E14: 6
A15: 46023 | B15: ITBISA-BREADBOARD-830HOLE-MB102 | C15: KERTASARI CIAMIS | D15: KYAI KONTONG | E15: 24
A16: 46023 | B16: ITBISA-BUBBLE-WRAP | C16: KERTASARI CIAMIS | D16: KYAI KONTONG | E16: -11
A17: 46023 | B17: ITBISA-BUZZER-ACTIVE-5V | C17: KERTASARI CIAMIS | D17: KYAI KONTONG | E17: 1037
A18: 46023 | B18: ITBISA-CHIP-ESP32-WROOM | C18: KERTASARI CIAMIS | D18: KYAI KONTONG | E18: 22
A19: 46023 | B19: ITBISA-CHIP-ESP32-WROOM-ANTENNA | C19: KERTASARI CIAMIS | D19: KYAI KONTONG
A20: 46023 | B20: ITBISA-SOCKET-IC-DIP28-NARROW | C20: KERTASARI CIAMIS | D20: KYAI KONTONG | E20: 20
A21: 46023 | B21: ITBISA-DC-TO-DC-STEPDOWN-LM2596 | C21: KERTASARI CIAMIS | D21: KYAI KONTONG | E21: 101
A22: 46023 | B22: ITBISA-DC-TO-DC-STEPDOWN-XL4005 | C22: KERTASARI CIAMIS | D22: KYAI KONTONG | E22: 67
A23: 46023 | B23: ITBISA-DC-TO-DC-STEPDOWN-XL4015 | C23: KERTASARI CIAMIS | D23: KYAI KONTONG | E23: 119
A24: 46023 | B24: ITBISA-DC-TO-DC-STEPUP-XL6009 | C24: KERTASARI CIAMIS | D24: KYAI KONTONG | E24: 191
A25: 46023 | B25: ITBISA-I2C-IIC-LCD | C25: KERTASARI CIAMIS | D25: KYAI KONTONG | E25: 31
A26: 46023 | B26: ITBISA-IC-74HC595N-DIP16 | C26: KERTASARI CIAMIS | D26: KYAI KONTONG | E26: 14
A27: 46023 | B27: ITBISA-IC-ATMEGA328P-DIP28 | C27: KERTASARI CIAMIS | D27: KYAI KONTONG | E27: 159
A28: 46023 | B28: ITBISA-IC-CD4017BE-DIP16 | C28: KERTASARI CIAMIS | D28: KYAI KONTONG
A29: 46023 | B29: ITBISA-IC-CD4094BE-DIP16 | C29: KERTASARI CIAMIS | D29: KYAI KONTONG
A30: 46023 | B30: ITBISA-IC-CD4094BM-SMD-SOP16 | C30: KERTASARI CIAMIS | D30: KYAI KONTONG | E30: 494
A31: 46023 | B31: ITBISA-IC-JRC4558D-DIP8 | C31: KERTASARI CIAMIS | D31: KYAI KONTONG | E31: 1000
A32: 46023 | B32: ITBISA-IC-L7805CV-TO220 | C32: KERTASARI CIAMIS | D32: KYAI KONTONG | E32: 932
A33: 46023 | B33: ITBISA-IC-L7812CV-TO220 | C33: KERTASARI CIAMIS | D33: KYAI KONTONG | E33: 802
A34: 46023 | B34: ITBISA-IC-LM741CN-DIP8 | C34: KERTASARI CIAMIS | D34: KYAI KONTONG
A35: 46023 | B35: ITBISA-IC-NE555P-DIP8 | C35: KERTASARI CIAMIS | D35: KYAI KONTONG | E35: 2992
A36: 46023 | B36: ITBISA-IC-PC817-DIP4 | C36: KERTASARI CIAMIS | D36: KYAI KONTONG | E36: 1748
A37: 46023 | B37: ITBISA-IC-UA741CN-DIP8 | C37: KERTASARI CIAMIS | D37: KYAI KONTONG | E37: 4619
A38: 46023 | B38: ITBISA-IC-ULN2003AN-DIP16 | C38: KERTASARI CIAMIS | D38: KYAI KONTONG | E38: 1214
A39: 46023 | B39: ITBISA-IC-ULN2803APG-DIP18 | C39: KERTASARI CIAMIS | D39: KYAI KONTONG | E39: 423
A40: 46023 | B40: ITBISA-IDC-2X5-AMPHENOL-FEMALE | C40: KERTASARI CIAMIS | D40: KYAI KONTONG | E40: 1021
A41: 46023 | B41: ITBISA-IDC-2X5-AMPHENOL-MALE | C41: KERTASARI CIAMIS | D41: KYAI KONTONG | E41: 412
A42: 46023 | B42: ITBISA-INFRARED-1838 | C42: KERTASARI CIAMIS | D42: KYAI KONTONG | E42: 552
A43: 46023 | B43: ITBISA-JACK-DC-005-FEMALE | C43: KERTASARI CIAMIS | D43: KYAI KONTONG | E43: 344
A44: 46023 | B44: ITBISA-JUMPER-FF-10CM | C44: KERTASARI CIAMIS | D44: KYAI KONTONG | E44: 5600
A45: 46023 | B45: ITBISA-JUMPER-FF-20CM | C45: KERTASARI CIAMIS | D45: KYAI KONTONG | E45: 3120
A46: 46023 | B46: ITBISA-JUMPER-MF-10CM | C46: KERTASARI CIAMIS | D46: KYAI KONTONG | E46: 5240
... A49: 46023 | B49: ITBISA-JUMPER-MM-20CM | C49: KERTASARI CIAMIS | D49: KYAI KONTONG | E49: 2600
A50: 46023 | B50: ITBISA-KAPASITOR-ELCO-2200UF-25V | C50: KERTASARI CIAMIS | D50: KYAI KONTONG
A51: 46023 | B51: ITBISA-LCD-16X2-BLUE | C51: KERTASARI CIAMIS | D51: KYAI KONTONG | E51: 23
A52: 46023 | B52: ITBISA-LCD-16X2-GREEN | C52: KERTASARI CIAMIS | D52: KYAI KONTONG | E52: 24
A53: 46023 | B53: ITBISA-LDR-GL5516 | C53: KERTASARI CIAMIS | D53: KYAI KONTONG | E53: 109
A54: 46023 | B54: ITBISA-LED-MAX7219-4IN1-GAP | C54: KERTASARI CIAMIS | D54: KYAI KONTONG | E54: 5
A55: 46023 | B55: ITBISA-LED-MAX7219-4IN1-TIGHT | C55: KERTASARI CIAMIS | D55: KYAI KONTONG | E55: 62
A56: 46023 | B56: ITBISA-LED-SUPERBRIGHT-5MM-BLUE | C56: KERTASARI CIAMIS | D56: KYAI KONTONG | E56: 2690
A57: 46023 | B57: ITBISA-LED-SUPERBRIGHT-5MM-GREEN | C57: KERTASARI CIAMIS | D57: KYAI KONTONG | E57: 964
A58: 46023 | B58: ITBISA-LED-SUPERBRIGHT-5MM-RED | C58: KERTASARI CIAMIS | D58: KYAI KONTONG | E58: 983
A59: 46023 | B59: ITBISA-LED-SUPERBRIGHT-5MM-WHITE | C59: KERTASARI CIAMIS | D59: KYAI KONTONG | E59: 2525
A60: 46023 | B60: ITBISA-LED-SUPERBRIGHT-5MM-YELLOW | C60: KERTASARI CIAMIS | D60: KYAI KONTONG | E60: 490
A61: 46023 | B61: ITBISA-NODEMCU-V3-CH340G-ESP8266-MICRO | C61: KERTASARI CIAMIS | D61: KYAI KONTONG | E61: 119
A62: 46023 | B62: ITBISA-NPN-2N2222-TO92 | C62: KERTASARI CIAMIS | D62: KYAI KONTONG | E62: 1825
... A67: 46023 | B67: ITBISA-NPN-BC548-TO92 | C67: KERTASARI CIAMIS | D67: KYAI KONTONG | E67: 1080
A68: 46023 | B68: ITBISA-NPN-S9013-TO92 | C68: KERTASARI CIAMIS | D68: KYAI KONTONG
A69: 46023 | B69: ITBISA-PCB-5X7-COPPER-SINGLE-SIDE | C69: KERTASARI CIAMIS | D69: KYAI KONTONG | E69: 75
A70: 46023 | B70: ITBISA-PIN-HEADER-MALE-1X40PIN-L-SAMA | C70: KERTASARI CIAMIS | D70: KYAI KONTONG | E70: 17
A71: 46023 | B71: ITBISA-PIN-HEADER-MALE-1X40PIN-LURUS | C71: KERTASARI CIAMIS | D71: KYAI KONTONG | E71: 794
A72: 46023 | B72: ITBISA-PNP-2N3906-TO92 | C72: KERTASARI CIAMIS | D72: KYAI KONTONG | E72: 90
A73: 46023 | B73: ITBISA-PNP-2N5401-TO92 | C73: KERTASARI CIAMIS | D73: KYAI KONTONG | E73: 1000
A74: 46023 | B74: ITBISA-PNP-A1015-TO92 | C74: KERTASARI CIAMIS | D74: KYAI KONTONG | E74: 1000
A75: 46023 | B75: ITBISA-PNP-BC557-TO92 | C75: KERTASARI CIAMIS | D75: KYAI KONTONG | E75: 1000
A76: 46023 | B76: ITBISA-PNP-BC558-TO92 | C76: KERTASARI CIAMIS | D76: KYAI KONTONG | E76: 480
A77: 46023 | B77: ITBISA-PNP-S8550-TO92 | C77: KERTASARI CIAMIS | D77: KYAI KONTONG | E77: 400
A78: 46023 | B78: ITBISA-PNP-S9012-TO92 | C78: KERTASARI CIAMIS | D78: KYAI KONTONG
A79: 46023 | B79: ITBISA-RAPID-BOHLAM-E10-2.5V-SCREW | C79: KERTASARI CIAMIS | D79: KYAI KONTONG | E79: 103
A80: 46023 | B80: ITBISA-RAPID-BOHLAM-E10-3.8V-SCREW | C80: KERTASARI CIAMIS | D80: KYAI KONTONG
A81: 46023 | B81: ITBISA-RELAY-12V-4PIN-BLUE | C81: KERTASARI CIAMIS | D81: KYAI KONTONG | E81: 295
A82: 46023 | B82: ITBISA-RELAY-12V-5PIN-BLUE | C82: KERTASARI CIAMIS | D82: KYAI KONTONG | E82: 171
A83: 46023 | B83: ITBISA-RELAY-5V-1CHANNEL-BLUE-LOW-TRIGGER | C83: KERTASARI CIAMIS | D83: KYAI KONTONG | E83: 47
A84: 46023 | B84: ITBISA-RELAY-5V-4PIN-BLUE | C84: KERTASARI CIAMIS | D84: KYAI KONTONG | E84: 1254
A85: 46023 | B85: ITBISA-RELAY-5V-5PIN-BLUE | C85: KERTASARI CIAMIS | D85: KYAI KONTONG | E85: 930
A86: 46023 | B86: ITBISA-RESISTOR-100K-1/4W | C86: KERTASARI CIAMIS | D86: KYAI KONTONG | E86: 900
A87: 46023 | B87: ITBISA-RESISTOR-10K-1/4W | C87: KERTASARI CIAMIS | D87: KYAI KONTONG | E87: 1585
A88: 46023 | B88: ITBISA-RESISTOR-120K-1/4W | C88: KERTASARI CIAMIS | D88: KYAI KONTONG | E88: 1000
A89: 46023 | B89: ITBISA-RESISTOR-12K-1/4W | C89: KERTASARI CIAMIS | D89: KYAI KONTONG | E89: 1000
A90: 46023 | B90: ITBISA-RESISTOR-150K-1/4W | C90: KERTASARI CIAMIS | D90: KYAI KONTONG | E90: 1000
A91: 46023 | B91: ITBISA-RESISTOR-15K-1/4W | C91: KERTASARI CIAMIS | D91: KYAI KONTONG | E91: 1890
A92: 46023 | B92: ITBISA-RESISTOR-18K-1/4W | C92: KERTASARI CIAMIS | D92: KYAI KONTONG | E92: 1000
... A104: 46023 | B104: ITBISA-RESISTOR-390-1/4W | C104: KERTASARI CIAMIS | D104: KYAI KONTONG | E104: 1890
A105: 46023 | B105: ITBISA-RESISTOR-39K-1/4W | C105: KERTASARI CIAMIS | D105: KYAI KONTONG
A106: 46023 | B106: ITBISA-RESISTOR-3K3-1/4W | C106: KERTASARI CIAMIS | D106: KYAI KONTONG | E106: 900
A107: 46023 | B107: ITBISA-RESISTOR-470K-1/4W | C107: KERTASARI CIAMIS | D107: KYAI KONTONG
A108: 46023 | B108: ITBISA-RESISTOR-47K-1/4W | C108: KERTASARI CIAMIS | D108: KYAI KONTONG
A109: 46023 | B109: ITBISA-RESISTOR-4K7-1/4W | C109: KERTASARI CIAMIS | D109: KYAI KONTONG | E109: 1960
A110: 46023 | B110: ITBISA-RESISTOR-560-1/4W | C110: KERTASARI CIAMIS | D110: KYAI KONTONG | E110: 990
A111: 46023 | B111: ITBISA-RESISTOR-56K-1/4W | C111: KERTASARI CIAMIS | D111: KYAI KONTONG
A112: 46023 | B112: ITBISA-RESISTOR-5K6-1/4W | C112: KERTASARI CIAMIS | D112: KYAI KONTONG | E112: 4000
A113: 46023 | B113: ITBISA-RESISTOR-680K-1/4W | C113: KERTASARI CIAMIS | D113: KYAI KONTONG | E113: 1000
A114: 46023 | B114: ITBISA-RESISTOR-6K8-1/4W | C114: KERTASARI CIAMIS | D114: KYAI KONTONG
A115: 46023 | B115: ITBISA-RFID-RC522-KIT | C115: KERTASARI CIAMIS | D115: KYAI KONTONG | E115: 66
A116: 46023 | B116: ITBISA-RTC-DS3231M | C116: KERTASARI CIAMIS | D116: KYAI KONTONG | E116: 174
A117: 46023 | B117: ITBISA-RTC-DS3231SN | C117: KERTASARI CIAMIS | D117: KYAI KONTONG | E117: 96
A118: 46023 | B118: ITBISA-SENSOR-SUHU-DHT11 | C118: KERTASARI CIAMIS | D118: KYAI KONTONG
...

Sheet BisaSEO
A1: SKU | B1: Kata Kunci Utama | C1: Jenis Barang | D1: Keterangan Barang (Ukuran, Warna) | E1: Fungsi Barang (Opsional) | F1: Typo | G1: BisaDivisi | H1: Massa (g) | I1: Tagar | J1: {={"Hitung Tagar";IF(I2:I978="",,LEN(I2:I978)-LEN(SUBSTITUTE(I2:I978,"#","")))}} -> Hitung Tagar | K1: {={"Nama Lengkap";IF(G2:G978="",, TRIM("ITBisa - "&IF(B2:B978="",,B2:B978)&" "&IF(C2:C978="",,C2:C978 )&" "&IF(D2:D978="",,D2:D978)& " "&IF(E2:E978="",,E2:E978)&" "&IF(F2:F978="",,F2:F978)))}} -> Nama Lengkap | L1: {={"Nama Tokopedia (70 Karakter)";IF(K2:K978="",,LEFT(TRIM(K2:K978),70))}} -> Nama Tokopedia (70 Karakter) | M1: {={"Nama Bukalapak (150 Karakter)";IF(K2:K978="",,LEFT(TRIM(K2:K978),150))}} -> Nama Bukalapak (150 Karakter) | N1: {={"Nama Shopee (255 Karakter)";IF(K2:K978="",,LEFT(TRIM(K2:K978),255))}} -> Nama Shopee (255 Karakter) | O1: Link Bukalapak | P1: Link Tokopedia | Q1: Link Shopee
A2: ITBISA-7SEGMENT-ANODE-RED-0.56-1BIT | B2: Seven 7 Segment | C2: CA Common Anode | D2: 0.56 Inch Red 1BIT | E2: LED Merah Display Jam Digital Nilai Sensor | F2: 7-Segment Anoda 0,56" Inci 0.56" 0.56inch 1 BIT | G2: BisaElektronika - BisaSegment | H2: 3 | I2: #ITBisa #BisaElektronika #BisaSegment #7Segment #Segment #CA #CC #Anode #Cathode #0.56 #LED #1BIT #Red #Arduino #Counter #Digital #IC #Mikrokontroler #Timer #Clock | J2: 20 | K2: ITBisa - Seven 7 Segment CA Common Anode 0.56 Inch Red 1BIT LED Merah Display Jam Digital Nilai Sensor 7-Segment Anoda 0,56" Inci 0.56" 0.56inch 1 BIT | L2: ITBisa - Seven 7 Segment CA Common Anode 0.56 Inch Red 1BIT LED Merah | M2: ITBisa - Seven 7 Segment CA Common Anode 0.56 Inch Red 1BIT LED Merah Display Jam Digital Nilai Sensor 7-Segment Anoda 0,56" Inci 0.56" 0.56inch 1 BIT | N2: ITBisa - Seven 7 Segment CA Common Anode 0.56 Inch Red 1BIT LED Merah Display Jam Digital Nilai Sensor 7-Segment Anoda 0,56" Inci 0.56" 0.56inch 1 BIT | O2: https://www.bukalapak.com/p/elektronik/komponen-elektronik/12cm7sr-jual-itbisa-7-segment-cc-common-katoda-0-56-inci-merah-1-bit-led-display-jam-digital-nilai-sensor-7-segment-seven-red-cathode-0-56inch-inch-1bit | P2: https://tokopedia.com/itbisa/itbisa-seven-7-segment-cc-common-cathode-0-56-inch-red-1bit-merah
A3: ITBISA-7SEGMENT-ANODE-RED-1.00-1BIT | B3: Seven 7 Segment | C3: CA Common Anode | D3: 1 Inch Red 1BIT | E3: LED Merah Display Jam Digital Nilai Sensor | F3: 7-Segment Anoda 1" Inch 1inch BIT | G3: BisaElektronika - BisaSegment | H3: 3 | K3: ITBisa - Seven 7 Segment CA Common Anode 1 Inch Red 1BIT LED Merah Display Jam Digital Nilai Sensor 7-Segment Anoda 1" Inch 1inch BIT | L3: ITBisa - Seven 7 Segment CA Common Anode 1 Inch Red 1BIT LED Merah Dis | M3: ITBisa - Seven 7 Segment CA Common Anode 1 Inch Red 1BIT LED Merah Display Jam Digital Nilai Sensor 7-Segment Anoda 1" Inch 1inch BIT | N3: ITBisa - Seven 7 Segment CA Common Anode 1 Inch Red 1BIT LED Merah Display Jam Digital Nilai Sensor 7-Segment Anoda 1" Inch 1inch BIT | O3: https://www.bukalapak.com/p/elektronik/komponen-elektronik/12cn11o-jual-itbisa-ic-ua741cn-dip-8-op-amp-filter-penguat-lpf-hpf-bpf-integrated-circuit-ua-741-ua741-op-amp-opamp-8-pin-kaki-dip8-8dip
A4: ITBISA-7SEGMENT-ANODE-RED-1.20-1BIT | B4: Seven 7 Segment | C4: CA Common Anode | D4: 1.2 Inch Red 1BIT | E4: LED Merah Display Jam Digital Nilai Sensor | F4: 7-Segment Anoda 1,2" Inci 1.2" 1.2inch 1 BIT | G4: BisaElektronika - BisaSegment | H4: 3 | I4: #ITBisa #BisaElektronika #BisaSegment #7Segment #Segment #CA #CC #Anode #Cathode #0.56 #LED #1BIT #Red #Arduino #Counter #Digital #IC #Mikrokontroler #Timer #Clock | J4: 20 | K4: ITBisa - Seven 7 Segment CA Common Anode 1.2 Inch Red 1BIT LED Merah Display Jam Digital Nilai Sensor 7-Segment Anoda 1,2" Inci 1.2" 1.2inch 1 BIT | L4: ITBisa - Seven 7 Segment CA Common Anode 1.2 Inch Red 1BIT LED Merah D | M4: ITBisa - Seven 7 Segment CA Common Anode 1.2 Inch Red 1BIT LED Merah Display Jam Digital Nilai Sensor 7-Segment Anoda 1,2" Inci 1.2" 1.2inch 1 BIT | N4: ITBisa - Seven 7 Segment CA Common Anode 1.2 Inch Red 1BIT LED Merah Display Jam Digital Nilai Sensor 7-Segment Anoda 1,2" Inci 1.2" 1.2inch 1 BIT
A5: ITBISA-7SEGMENT-ANODE-RED-2.30-1BIT | B5: Seven 7 Segment | C5: HS 23101 BS CA Anode Jam Masjid | D5: 2.30 Inch Red 1BIT | E5: LED Display Digital | F5: 7-Segment Anoda 2,3" Inci 2.3" 2.3inch 1 BIT | G5: BisaElektronika - BisaSegment | I5: #ITBisa #BisaElektronika #BisaSegment #7Segment #Segment #CA #CC #Anode #Cathode #0.56 #LED #1BIT #Red #Arduino #Counter #Digital #IC #Mikrokontroler #Timer #Clock | J5: 20 | K5: ITBisa - Seven 7 Segment HS 23101 BS CA Anode Jam Masjid 2.30 Inch Red 1BIT LED Display Digital 7-Segment Anoda 2,3" Inci 2.3" 2.3inch 1 BIT | L5: ITBisa - Seven 7 Segment HS 23101 BS CA Anode Jam Masjid 2.30 Inch Red | M5: ITBisa - Seven 7 Segment HS 23101 BS CA Anode Jam Masjid 2.30 Inch Red 1BIT LED Display Digital 7-Segment Anoda 2,3" Inci 2.3" 2.3inch 1 BIT | N5: ITBisa - Seven 7 Segment HS 23101 BS CA Anode Jam Masjid 2.30 Inch Red 1BIT LED Display Digital 7-Segment Anoda 2,3" Inci 2.3" 2.3inch 1 BIT
A6: ITBISA-7SEGMENT-CATHODE-RED-0.56-1BIT | B6: Seven 7 Segment | C6: CC Common Cathode | D6: 0.56 Inch Red 1BIT | E6: LED Merah Display Jam Digital Nilai Sensor | F6: 7-Segment Katoda 0,56" Inci 0.56" 0.56inch 1 BIT | G6: BisaElektronika - BisaSegment | H6: 3 | I6: #ITBisa #BisaElektronika #BisaSegment #7Segment #Segment #CA #CC #Anode #Cathode #0.56 #LED #1BIT #Red #Arduino #Counter #Digital #IC #Mikrokontroler #Timer #Clock | J6: 20 | K6: ITBisa - Seven 7 Segment CC Common Cathode 0.56 Inch Red 1BIT LED Merah Display Jam Digital Nilai Sensor 7-Segment Katoda 0,56" Inci 0.56" 0.56inch 1 BIT | L6: ITBisa - Seven 7 Segment CC Common Cathode 0.56 Inch Red 1BIT LED Mera | M6: ITBisa - Seven 7 Segment CC Common Cathode 0.56 Inch Red 1BIT LED Merah Display Jam Digital Nilai Sensor 7-Segment Katoda 0,56" Inci 0.56" 0.56inch 1 | N6: ITBisa - Seven 7 Segment CC Common Cathode 0.56 Inch Red 1BIT LED Merah Display Jam Digital Nilai Sensor 7-Segment Katoda 0,56" Inci 0.56" 0.56inch 1 BIT
A7: ITBISA-7SEGMENT-CATHODE-RED-1.00-1BIT | B7: Seven 7 Segment | C7: CC Common Cathode | D7: 1 Inch Red 1BIT | E7: LED Merah Display Jam Digital Nilai Sensor | F7: 7-Segment Katoda 1" Inch 1inch BIT | G7: BisaElektronika - BisaSegment | H7: 3 | K7: ITBisa - Seven 7 Segment CC Common Cathode 1 Inch Red 1BIT LED Merah Display Jam Digital Nilai Sensor 7-Segment Katoda 1" Inch 1inch BIT | L7: ITBisa - Seven 7 Segment CC Common Cathode 1 Inch Red 1BIT LED Merah D | M7: ITBisa - Seven 7 Segment CC Common Cathode 1 Inch Red 1BIT LED Merah Display Jam Digital Nilai Sensor 7-Segment Katoda 1" Inch 1inch BIT | N7: ITBisa - Seven 7 Segment CC Common Cathode 1 Inch Red 1BIT LED Merah Display Jam Digital Nilai Sensor 7-Segment Katoda 1" Inch 1inch BIT
A8: ITBISA-7SEGMENT-CATHODE-RED-1.20-1BIT | B8: Seven 7 Segment | C8: CC Common Cathode | D8: 1.2 Inch Red 1BIT | E8: LED Merah Display Jam Digital Nilai Sensor | F8: 7-Segment Katoda 1,2" Inci 1.2" 1.2inch 1 BIT | G8: BisaElektronika - BisaSegment | H8: 3 | I8: #ITBisa #BisaElektronika #BisaSegment #7Segment #Segment #CA #CC #Anode #Cathode #0.56 #LED #1BIT #Red #Arduino #Counter #Digital #IC #Mikrokontroler #Timer #Clock | J8: 20 | K8: ITBisa - Seven 7 Segment CC Common Cathode 1.2 Inch Red 1BIT LED Merah Display Jam Digital Nilai Sensor 7-Segment Katoda 1,2" Inci 1.2" 1.2inch 1 BIT | L8: ITBisa - Seven 7 Segment CC Common Cathode 1.2 Inch Red 1BIT LED Merah | M8: ITBisa - Seven 7 Segment CC Common Cathode 1.2 Inch Red 1BIT LED Merah Display Jam Digital Nilai Sensor 7-Segment Katoda 1,2" Inci 1.2" 1.2inch 1 BIT | N8: ITBisa - Seven 7 Segment CC Common Cathode 1.2 Inch Red 1BIT LED Merah Display Jam Digital Nilai Sensor 7-Segment Katoda 1,2" Inci 1.2" 1.2inch 1 BIT
A9: ITBISA-7SEGMENT-CATHODE-RED-2.30-1BIT
A10: ITBISA-ABC-BATERAI-9V-ALKALINE
A11: ITBISA-ABC-BATERAI-9V-POWER
A12: ITBISA-ABC-BATERAI-AA-ALKALINE
A13: ITBISA-ABC-BATERAI-AAA-ALKALINE
A14: ITBISA-ABC-BATERAI-D-ALKALINE
A15: ITBISA-ABC-BATERAI-D-BIRU | B15: Baterai ABC | C15: Standar 1,5 V | D15: Size D Biru | F15: Batre Biasa 1,5V 1.5V 1.5 Volt Ukuran D Warna Blue | G15: BisaOspek | H15: 100 | I15: #ITBisa #BisaOspek #BisaBaterai #Ospek #Baterai #ABC #D #Size #1.5V #Volt #Senter #Big #Jumbo #Power #Alkaline #Carbon #Zinc #Karbon #Galon #Jumbo | J15: 20 | K15: ITBisa - Baterai ABC Standar 1,5 V Size D Biru Batre Biasa 1,5V 1.5V 1.5 Volt Ukuran D Warna Blue | L15: ITBisa - Baterai ABC Standar 1,5 V Size D Biru Batre Biasa 1,5V 1.5V 1 | M15: ITBisa - Baterai ABC Standar 1,5 V Size D Biru Batre Biasa 1,5V 1.5V 1.5 Volt Ukuran D Warna Blue | N15: ITBisa - Baterai ABC Standar 1,5 V Size D Biru Batre Biasa 1,5V 1.5V 1.5 Volt Ukuran D Warna Blue
A16: ITBISA-ABC-BATERAI-D-POWER | B16: Baterai ABC Size D | C16: Super Power Heavy Duty DR20P | D16: 1.5V Jumbo Carbon Zinc Hitam | E16: Senter Pompa Galon | F16: Batre Jumbo Karbon Tipe D R20P Besar 1,5V 1.5V 1.5 Volt Type Ukuran D Warna Black | G16: BisaOspek | H16: 100 | I16: #ITBisa #BisaOspek #BisaBaterai #Ospek #Baterai #ABC #D #Size #1.5V #Volt #Senter #Big #Jumbo #Power #Alkaline #Carbon #Zinc #Karbon #Galon #Jumbo | J16: 20 | K16: ITBisa - Baterai ABC Size D Super Power Heavy Duty DR20P 1.5V Jumbo Carbon Zinc Hitam Senter Pompa Galon Batre Jumbo Karbon Tipe D R20P Besar 1,5V 1.5V 1.5 Volt Type Ukuran D Warna Black | L16: ITBisa - Baterai ABC Size D Super Power Heavy Duty DR20P 1.5V Jumbo Ca | M16: ITBisa - Baterai ABC Size D Super Power Heavy Duty DR20P 1.5V Jumbo Carbon Zinc Hitam Senter Pompa Galon Batre Jumbo Karbon Tipe D R20P Besar 1,5V 1.5 | N16: ITBisa - Baterai ABC Size D Super Power Heavy Duty DR20P 1.5V Jumbo Carbon Zinc Hitam Senter Pompa Galon Batre Jumbo Karbon Tipe D R20P Besar 1,5V 1.5V 1.5 Volt Type Ukuran D Warna Black
A17: ITBISA-ABC-SENTER-LED-ALKALINE | B17: Senter ABC Alkaline | C17: LED Multifungsi | E17: Emergency Light | F17: Multifunction LED Lights | G17: BisaSenter | H17: 300 | I17: #ITBisa #BisaOspek #BisaSenter #Ospek #Baterai #ABC #AAA | J17: 7 | K17: ITBisa - Senter ABC Alkaline LED Multifungsi Emergency Light Multifunction LED Lights | L17: ITBisa - Senter ABC Alkaline LED Multifungsi Emergency Light Multifunc | M17: ITBisa - Senter ABC Alkaline LED Multifungsi Emergency Light Multifunction LED Lights | N17: ITBisa - Senter ABC Alkaline LED Multifungsi Emergency Light Multifunction LED Lights | O17: https://www.bukalapak.com/p/elektronik/komponen-elektronik/163beu6-jual-itbisa-40pcs-kabel-jumper-10-cm-male-to-female-m-f-2-54-mm-merk-dupont-arduino-breadboard-40-pcs-buah-mf-m-f-pin-2-54mm-10cm-cable | P17: https://www.tokopedia.com/itbisa/itbisa-40pcs-kabel-jumper-10-cm-male-to-female-m-f-2-54-mm-mf-10cm | Q17: https://shopee.co.id/product/80492423/2291036855/
A18: ITBISA-ARDUINO-UNO-R3-328P-SMD | B18: Arduino | C18: UNO R3 CH340G SMD ATMega328P | D18: Clone Only No Cable | E18: Mikrokontroler | F18: Tanpa Kabel USB ATMega328 AT Mega Kloning Duplikat Microcontroller | G18: BisaElektronika | K18: ITBisa - Arduino UNO R3 CH340G SMD ATMega328P Clone Only No Cable Mikrokontroler Tanpa Kabel USB ATMega328 AT Mega Kloning Duplikat Microcontroller | L18: ITBisa - Arduino UNO R3 CH340G SMD ATMega328P Clone Only No Cable Mikr | M18: ITBisa - Arduino UNO R3 CH340G SMD ATMega328P Clone Only No Cable Mikrokontroler Tanpa Kabel USB ATMega328 AT Mega Kloning Duplikat Microcontroller | N18: ITBisa - Arduino UNO R3 CH340G SMD ATMega328P Clone Only No Cable Mikrokontroler Tanpa Kabel USB ATMega328 AT Mega Kloning Duplikat Microcontroller | O18: https://www.bukalapak.com/p/elektronik/komponen-elektronik/1b2qbb9-jual-itbisa-transistor-bjt-npn-2n2222a-h331-to92-0-6a-30v-penguat-switch-transistors-2n2222-2n-2222-a-to-92-h-331-0-6-op-amp-switching-30-v-30volt | P18: https://www.tokopedia.com/itbisa/itbisa-transistor-bjt-npn-2n2222-a-2n2222a-h331-penguat-switch-to92 | Q18: https://shopee.co.id/product/80492423/2291143520/
A19: ITBISA-ARDUINO-UNO-R3-CLONE-CABLE30CM | B19: Arduino | C19: UNO R3 CH340G SMD | D19: Clone Plus + USB Kabel 30CM Cable 30 CM ATMega328P | E19: Mikrokontroler | F19: ATMega328 AT Mega 328 P + Cable Kloning Duplikat Microcontroller | G19: BisaElektronika | K19: ITBisa - Arduino UNO R3 CH340G SMD Clone Plus + USB Kabel 30CM Cable 30 CM ATMega328P Mikrokontroler ATMega328 AT Mega 328 P + Cable Kloning Duplikat Microcontroller | L19: ITBisa - Arduino UNO R3 CH340G SMD Clone Plus + USB Kabel 30CM Cable 3 | M19: ITBisa - Arduino UNO R3 CH340G SMD Clone Plus + USB Kabel 30CM Cable 30 CM ATMega328P Mikrokontroler ATMega328 AT Mega 328 P + Cable Kloning Duplikat | N19: ITBisa - Arduino UNO R3 CH340G SMD Clone Plus + USB Kabel 30CM Cable 30 CM ATMega328P Mikrokontroler ATMega328 AT Mega 328 P + Cable Kloning Duplikat Microcontroller
A20: ITBISA-ARDUINO-UNO-R3-CLONE-CABLE50CM | B20: Arduino | C20: UNO R3 CH340G ATMega328P SMD | D20: Clone Plus USB Kabel 50CM | E20: Mikrokontroler | F20: ATMega328 AT Mega 328 P + Cable 50 cm Kloning Duplikat Microcontroller | G20: BisaElektronika | K20: ITBisa - Arduino UNO R3 CH340G ATMega328P SMD Clone Plus USB Kabel 50CM Mikrokontroler ATMega328 AT Mega 328 P + Cable 50 cm Kloning Duplikat Microcontroller | L20: ITBisa - Arduino UNO R3 CH340G ATMega328P SMD Clone Plus USB Kabel 50C | M20: ITBisa - Arduino UNO R3 CH340G ATMega328P SMD Clone Plus USB Kabel 50CM Mikrokontroler ATMega328 AT Mega 328 P + Cable 50 cm Kloning Duplikat Microcon | N20: ITBisa - Arduino UNO R3 CH340G ATMega328P SMD Clone Plus USB Kabel 50CM Mikrokontroler ATMega328 AT Mega 328 P + Cable 50 cm Kloning Duplikat Microcontroller
A21: ITBISA-BLUETOOTH-MODULE-HC05
A22: ITBISA-BREADBOARD-830HOLE-MB102
A23: ITBISA-BUBBLE-WRAP
A24: ITBISA-BUKAEMAS
A25: ITBISA-BUKAREKSA-BAHANA-MES-SYARIAH | O25: https://www.bukalapak.com/p/elektronik/komponen-elektronik/1p5d40c-jual-itbisa-40pcs-kabel-jumper-10-cm-female-to-female-f-f-2-54-mm-merk-dupont-arduino-breadboard-40-pcs-buah-ff-f-f-pin-2-54mm-10cm-cable | P25: https://www.tokopedia.com/itbisa/itbisa-40pcs-kabel-jumper-10-cm-female-to-female-f-f-2-54-mm-ff-10cm | Q25: https://shopee.co.id/product/80492423/2287703561/
A26: ITBISA-BUKAREKSA-CIMB-PRINCIPAL-PASAR-UANG | O26: https://www.bukalapak.com/p/elektronik/komponen-elektronik/2aposh9-jual-itbisa-socket-ic-dip-8-2x4-narrow-soket-integrated-circuit-8-pin-kaki-lubang-datar-dip8-8dip | P26: https://tokopedia.com/itbisa/itbisa-socket-ic-dip-8-2x4-narrow-soket-dip8-8dip-8-dip-pin-kaki | Q26: https://shopee.co.id/product/80492423/2287659492/
A27: ITBISA-BUKAREKSA-CIPTA-SYARIAH-BALANCE
A28: ITBISA-BUKAREKSA-MANDIRI-INVESTA-DANA-SYARIAH
A29: ITBISA-BUKAREKSA-MANDIRI-INVESTA-PASAR-UANG
A30: ITBISA-BUKAREKSA-SUCORINVEST-SHARIA-EQUITY-FUND | O30: https://www.bukalapak.com/p/elektronik/komponen-elektronik/3ge7cl1-jual-itbisa-socket-ic-dip16-2x8-narrow-dip-16-pin-16p-soket-dip-16-2-54mm-2-54-mm-dudukan-16-lubang-16-dip-integrated-integrate-circuit-2-x-8-8x2-8-x-2 | P30: https://tokopedia.com/itbisa/itbisa-socket-ic-dip16-2x8-narrow-dip-16-pin-16p-soket-dip-16-2-54mm
A31: ITBISA-BUKAREKSA-SYARIAH-MANDIRI-PASAR-UANG | O31: https://www.bukalapak.com/p/elektronik/komponen-elektronik/3t18497-jual-itbisa-40pcs-kabel-jumper-20-cm-male-to-male-m-m-mm-m-m-2-54mm-arduino-breadboard-40-pcs-20cm-buah-pin-2-54-mm-wire-cable-rainbow-pelangi-sensor | P31: https://tokopedia.com/itbisa/itbisa-40pcs-kabel-jumper-20-cm-male-to-male-m-m-2-54-mm-mm-m-m-20cm | Q31: https://shopee.co.id/product/80492423/4855244491/
A32: ITBISA-BUZZER-ACTIVE-5V | O32: https://www.bukalapak.com/p/elektronik/komponen-elektronik/3t187p8-jual-itbisa-40pcs-kabel-jumper-20-cm-female-to-female-f-f-ff-f-f-2-54mm-arduino-breadboard-40-pcs-20cm-buah-pin-2-54-mm-wire-cable-rainbow-pelangi-sensor | P32: https://www.tokopedia.com/itbisa/itbisa-40pcs-kabel-jumper-20-cm-female-to-female-f-f-2-54-mm-ff-20cm | Q32: https://shopee.co.id/product/80492423/5655241072/
A33: ITBISA-CHIP-ESP32-WROOM | O33: https://www.bukalapak.com/p/elektronik/komponen-elektronik/vbuzpu-jual-itbisa-40pcs-kabel-jumper-10-cm-male-to-male-m-m-2-54-mm-merk-dupont-arduino-breadboard-40-pcs-buah-mm-m-m-pin-2-54mm-10cm-cable | P33: https://www.tokopedia.com/itbisa/itbisa-40pcs-kabel-jumper-10-cm-male-to-male-m-m-2-54-mm-mm-m-m-10cm | Q33: https://shopee.co.id/product/80492423/2291050648/
A34: ITBISA-CHIP-ESP32-WROOM-ANTENNA
A35: ITBISA-CHIP-ESP8266-ESP12F
A36: ITBISA-CORSAIR-VENGEANCE-K66
A37: ITBISA-DC-TO-DC-STEPDOWN-LM2596
A38: ITBISA-DC-TO-DC-STEPDOWN-XL4005
A39: ITBISA-DC-TO-DC-STEPDOWN-XL4015 | P39: https://www.tokopedia.com/itbisa/itbisa-seven-7-segment-ca-common-anode-0-56-inch-red-1bit-led-merah
A40: ITBISA-DC-TO-DC-STEPUP-XL6009
A41: ITBISA-DIODA-1N4007-DO41
A42: ITBISA-EMLOCK-ACM-Y180 | P42: https://tokopedia.com/itbisa/itbisa-baterai-abc-super-power-1-5-v-volt-size-d-hitam-carbon-zinc
A43: ITBISA-EPSON-L310
A44: ITBISA-I2C-IIC-LCD
A45: ITBISA-IC-4N35-DIP6-BLACK | B45: IC 4N35 | C45: DIP-6 | D45: Black | E45: Optocoupler Photocoupler | F45: Phototransistor Optotransistor Putih DIP6 6DIP 6 Pin Kaki | G45: BisaElektronika - BisaIC | H45: 1 | I45: #ITBisa #BisaElektronika #BisaIC #Socket #IC #Switch #Transistor #LED #Sensor #Timer #Osilator #FlipFlop #DIP6 #DIP8 #DIP16 #Arduino #Breadboard #Mikrokontroler #Sensor #PCB | J45: 20 | K45: ITBisa - IC 4N35 DIP-6 Black Optocoupler Photocoupler Phototransistor Optotransistor Putih DIP6 6DIP 6 Pin Kaki | L45: ITBisa - IC 4N35 DIP-6 Black Optocoupler Photocoupler Phototransistor | M45: ITBisa - IC 4N35 DIP-6 Black Optocoupler Photocoupler Phototransistor Optotransistor Putih DIP6 6DIP 6 Pin Kaki | N45: ITBisa - IC 4N35 DIP-6 Black Optocoupler Photocoupler Phototransistor Optotransistor Putih DIP6 6DIP 6 Pin Kaki
A46: ITBISA-IC-4N35-DIP6-WHITE | B46: IC 4N35 | C46: DIP-6 | D46: White | E46: Optocoupler Photocoupler | F46: Phototransistor Optotransistor DIP6 6DIP 6 Pin Kaki | G46: BisaElektronika - BisaIC | H46: 1 | I46: #ITBisa #BisaElektronika #BisaIC #Socket #IC #Switch #Transistor #LED #Sensor #Timer #Osilator #FlipFlop #DIP6 #DIP8 #DIP16 #Arduino #Breadboard #Mikrokontroler #Sensor #PCB | J46: 20 | K46: ITBisa - IC 4N35 DIP-6 White Optocoupler Photocoupler Phototransistor Optotransistor DIP6 6DIP 6 Pin Kaki | L46: ITBisa - IC 4N35 DIP-6 White Optocoupler Photocoupler Phototransistor | M46: ITBisa - IC 4N35 DIP-6 White Optocoupler Photocoupler Phototransistor Optotransistor DIP6 6DIP 6 Pin Kaki | N46: ITBisa - IC 4N35 DIP-6 White Optocoupler Photocoupler Phototransistor Optotransistor DIP6 6DIP 6 Pin Kaki
A47: ITBISA-IC-74HC245N-DIP20 | B47: IC HC245N | C47: SN74HC245N | D47: DIP-20 | E47: Octal Bus Transceiver | F47: SN 74HC245N 74HC245 DIP20 20P 20 Pin Kaki Digital Buffer Parallel Data Transfer Transmission | G47: BisaElektronika - BisaIC | H47: 2 | I47: #ITBisa #BisaElektronika #BisaIC #Socket #IC #Shifter #Shift #Register #7Segment #Segment #LED #Counter #DIP6 #DIP8 #DIP16 #Arduino #Breadboard #Mikrokontroler #Sensor #PCB | J47: 20 | K47: ITBisa - IC HC245N SN74HC245N DIP-20 Octal Bus Transceiver SN 74HC245N 74HC245 DIP20 20P 20 Pin Kaki Digital Buffer Parallel Data Transfer Transmission | L47: ITBisa - IC HC245N SN74HC245N DIP-20 Octal Bus Transceiver SN 74HC245N | M47: ITBisa - IC HC245N SN74HC245N DIP-20 Octal Bus Transceiver SN 74HC245N 74HC245 DIP20 20P 20 Pin Kaki Digital Buffer Parallel Data Transfer Transmissio | N47: ITBisa - IC HC245N SN74HC245N DIP-20 Octal Bus Transceiver SN 74HC245N 74HC245 DIP20 20P 20 Pin Kaki Digital Buffer Parallel Data Transfer Transmission
A48: ITBISA-IC-74HC595N-DIP16 | B48: IC HC595N | C48: SN74HC595N | D48: DIP-16 | E48: 8 Stage Serial Shift Register | F48: SN 74HC595N 74HC595 DIP16 16P 16 Pin Kaki Serial to Parallel Paralel Conversion Output Latch | G48: BisaElektronika - BisaIC | H48: 2 | K48: ITBisa - IC HC595N SN74HC595N DIP-16 8 Stage Serial Shift Register SN 74HC595N 74HC595 DIP16 16P 16 Pin Kaki Serial to Parallel Paralel Conversion Output Latch | L48: ITBisa - IC HC595N SN74HC595N DIP-16 8 Stage Serial Shift Register SN | M48: ITBisa - IC HC595N SN74HC595N DIP-16 8 Stage Serial Shift Register SN 74HC595N 74HC595 DIP16 16P 16 Pin Kaki Serial to Parallel Paralel Conversion Out | N48: ITBisa - IC HC595N SN74HC595N DIP-16 8 Stage Serial Shift Register SN 74HC595N 74HC595 DIP16 16P 16 Pin Kaki Serial to Parallel Paralel Conversion Output Latch
A49: ITBISA-IC-78L05-TO92 | B49: IC 78L05 | C49: 7805 | D49: TO92 | E49: Positive Voltage Regulator 5V 0.1A | F49: L78L05 Positif 100mA TO 92 TO-92 5V 0.1 A 3 Terminal | G49: BisaElektronika - BisaIC | H49: 1 | I49: #ITBisa #BisaElektronika #BisaIC #Regulator #Voltage | J49: 5 | K49: ITBisa - IC 78L05 7805 TO92 Positive Voltage Regulator 5V 0.1A L78L05 Positif 100mA TO 92 TO-92 5V 0.1 A 3 Terminal | L49: ITBisa - IC 78L05 7805 TO92 Positive Voltage Regulator 5V 0.1A L78L05 | M49: ITBisa - IC 78L05 7805 TO92 Positive Voltage Regulator 5V 0.1A L78L05 Positif 100mA TO 92 TO-92 5V 0.1 A 3 Terminal | N49: ITBisa - IC 78L05 7805 TO92 Positive Voltage Regulator 5V 0.1A L78L05 Positif 100mA TO 92 TO-92 5V 0.1 A 3 Terminal
A50: ITBISA-IC-ATMEGA328P-DIP28
A51: ITBISA-IC-CD4017BE-DIP16 | B51: IC 4017 | C51: CD4017 CD4017BE | D51: DIP-16 | E51: Decade Counter Divider Digital | F51: DIP16 16P 16 Pin Kaki CMOS Latch CD 4017 BE Shifter Switch Clock Running LED Text | G51: BisaElektronika - BisaIC | H51: 2 | I51: #ITBisa #BisaElektronika #BisaIC #Socket #IC #Decade #Counter #Divider #Digital #Shifter #LED #CMOS #DIP6 #DIP8 #DIP16 #Arduino #Breadboard #Mikrokontroler #Sensor #PCB | J51: 20 | K51: ITBisa - IC 4017 CD4017 CD4017BE DIP-16 Decade Counter Divider Digital DIP16 16P 16 Pin Kaki CMOS Latch CD 4017 BE Shifter Switch Clock Running LED Text | L51: ITBisa - IC 4017 CD4017 CD4017BE DIP-16 Decade Counter Divider Digital | M51: ITBisa - IC 4017 CD4017 CD4017BE DIP-16 Decade Counter Divider Digital DIP16 16P 16 Pin Kaki CMOS Latch CD 4017 BE Shifter Switch Clock Running LED Te | N51: ITBisa - IC 4017 CD4017 CD4017BE DIP-16 Decade Counter Divider Digital DIP16 16P 16 Pin Kaki CMOS Latch CD 4017 BE Shifter Switch Clock Running LED Text
A52: ITBISA-IC-CD4094BE-DIP16 | B52: IC 4094 | C52: CD4094 BE CD4094BE | D52: DIP-16 | E52: Shift Register | F52: DIP16 16P 16 Pin Kaki 7 Segment 8 BIT 8BIT CD 4094 BE LED 7-Segment Latch CMOS 3 State Counter Output | G52: BisaElektronika - BisaIC | H52: 2 | I52: #ITBisa #BisaElektronika #BisaIC #Socket #IC #Shifter #Shift #Register #7Segment #Segment #LED #Counter #DIP6 #DIP8 #DIP16 #Arduino #Breadboard #Mikrokontroler #Sensor #PCB | J52: 20 | K52: ITBisa - IC 4094 CD4094 BE CD4094BE DIP-16 Shift Register DIP16 16P 16 Pin Kaki 7 Segment 8 BIT 8BIT CD 4094 BE LED 7-Segment Latch CMOS 3 State Counter Output | L52: ITBisa - IC 4094 CD4094 BE CD4094BE DIP-16 Shift Register DIP16 16P 16 | M52: ITBisa - IC 4094 CD4094 BE CD4094BE DIP-16 Shift Register DIP16 16P 16 Pin Kaki 7 Segment 8 BIT 8BIT CD 4094 BE LED 7-Segment Latch CMOS 3 State Count | N52: ITBisa - IC 4094 CD4094 BE CD4094BE DIP-16 Shift Register DIP16 16P 16 Pin Kaki 7 Segment 8 BIT 8BIT CD 4094 BE LED 7-Segment Latch CMOS 3 State Counter Output
A53: ITBISA-IC-CD4094BM-SMD-SOP16 | B53: IC 4094 | C53: SMD CD4094 BM CD4094BM | D53: SOP-16 | E53: Shift Register | F53: SOP16 16P 16 Pin Kaki 7 Segment 8 BIT 8BIT CD 4094 BM LED 7-Segment Latch CMOS 3 State Counter Output | G53: BisaElektronika - BisaIC | H53: 2 | I53: #ITBisa #BisaElektronika #BisaIC #Socket #IC #Shifter #Shift #Register #7Segment #Segment #LED #Counter #SOP6 #SOP8 #SOP16 #Arduino #Breadboard #Mikrokontroler #Sensor #PCB | J53: 20 | K53: ITBisa - IC 4094 SMD CD4094 BM CD4094BM SOP-16 Shift Register SOP16 16P 16 Pin Kaki 7 Segment 8 BIT 8BIT CD 4094 BM LED 7-Segment Latch CMOS 3 State Counter Output | L53: ITBisa - IC 4094 SMD CD4094 BM CD4094BM SOP-16 Shift Register SOP16 16 | M53: ITBisa - IC 4094 SMD CD4094 BM CD4094BM SOP-16 Shift Register SOP16 16P 16 Pin Kaki 7 Segment 8 BIT 8BIT CD 4094 BM LED 7-Segment Latch CMOS 3 State C | N53: ITBisa - IC 4094 SMD CD4094 BM CD4094BM SOP-16 Shift Register SOP16 16P 16 Pin Kaki 7 Segment 8 BIT 8BIT CD 4094 BM LED 7-Segment Latch CMOS 3 State Counter Output
A54: ITBISA-IC-CD4511BE-DIP16
A55: ITBISA-IC-JRC4558D-DIP8
A56: ITBISA-IC-L7805CV-TO220 | B56: IC L7805CV | C56: L7805 7805 CV 7805CV | D56: 3 Terminal TO-220 | E56: Linear Voltage Regulator 5V | F56: 5Volt 5 Volt Linier IC Power Supply Stabilizer TO220 TO 220 | G56: BisaElektronika - BisaIC | H56: 2 | I56: #ITBisa #BisaElektronika #BisaIC #Socket #IC #Shifter #Shift #Register #7Segment #Segment #LED #Counter #DIP6 #DIP8 #DIP16 #Arduino #Breadboard #Mikrokontroler #Sensor #PCB | J56: 20 | K56: ITBisa - IC L7805CV L7805 7805 CV 7805CV 3 Terminal TO-220 Linear Voltage Regulator 5V 5Volt 5 Volt Linier IC Power Supply Stabilizer TO220 TO 220 | L56: ITBisa - IC L7805CV L7805 7805 CV 7805CV 3 Terminal TO-220 Linear Volt | M56: ITBisa - IC L7805CV L7805 7805 CV 7805CV 3 Terminal TO-220 Linear Voltage Regulator 5V 5Volt 5 Volt Linier IC Power Supply Stabilizer TO220 TO 220 | N56: ITBisa - IC L7805CV L7805 7805 CV 7805CV 3 Terminal TO-220 Linear Voltage Regulator 5V 5Volt 5 Volt Linier IC Power Supply Stabilizer TO220 TO 220
A57: ITBISA-IC-L7809CV-TO220 | B57: IC L7809CV | C57: L7809 7809 CV 7809CV | D57: 3 Terminal TO-220 | E57: Linear Voltage Regulator 5V | F57: 5Volt 5 Volt Linier IC Power Supply Stabilizer TO220 TO 220 | G57: BisaElektronika - BisaIC | H57: 2 | I57: #ITBisa #BisaElektronika #BisaIC #Socket #IC #Shifter #Shift #Register #7Segment #Segment #LED #Counter #DIP6 #DIP8 #DIP16 #Arduino #Breadboard #Mikrokontroler #Sensor #PCB | J57: 20 | K57: ITBisa - IC L7809CV L7809 7809 CV 7809CV 3 Terminal TO-220 Linear Voltage Regulator 5V 5Volt 5 Volt Linier IC Power Supply Stabilizer TO220 TO 220 | L57: ITBisa - IC L7809CV L7809 7809 CV 7809CV 3 Terminal TO-220 Linear Volt | M57: ITBisa - IC L7809CV L7809 7809 CV 7809CV 3 Terminal TO-220 Linear Voltage Regulator 5V 5Volt 5 Volt Linier IC Power Supply Stabilizer TO220 TO 220 | N57: ITBisa - IC L7809CV L7809 7809 CV 7809CV 3 Terminal TO-220 Linear Voltage Regulator 5V 5Volt 5 Volt Linier IC Power Supply Stabilizer TO220 TO 220
A58: ITBISA-IC-L7812CV-TO220 | B58: IC L7812CV | C58: L7812 7812 CV 7812CV | D58: 3 Terminal TO-220 | E58: Linear Voltage Regulator 12V | F58: 12Volt 12 Volt Linier IC Power Supply Stabilizer TO220 TO 220 | G58: BisaElektronika - BisaIC | H58: 2 | I58: #ITBisa #BisaElektronika #BisaIC #Socket #IC #Shifter #Shift #Register #7Segment #Segment #LED #Counter #DIP6 #DIP8 #DIP16 #Arduino #Breadboard #Mikrokontroler #Sensor #PCB | J58: 20 | K58: ITBisa - IC L7812CV L7812 7812 CV 7812CV 3 Terminal TO-220 Linear Voltage Regulator 12V 12Volt 12 Volt Linier IC Power Supply Stabilizer TO220 TO 220 | L58: ITBisa - IC L7812CV L7812 7812 CV 7812CV 3 Terminal TO-220 Linear Volt | M58: ITBisa - IC L7812CV L7812 7812 CV 7812CV 3 Terminal TO-220 Linear Voltage Regulator 12V 12Volt 12 Volt Linier IC Power Supply Stabilizer TO220 TO 220 | N58: ITBisa - IC L7812CV L7812 7812 CV 7812CV 3 Terminal TO-220 Linear Voltage Regulator 12V 12Volt 12 Volt Linier IC Power Supply Stabilizer TO220 TO 220
A59: ITBISA-IC-L7815CV-TO220 | B59: IC L7815CV | C59: L7815 7815 CV 7815CV | D59: 3 Terminal TO-220 | E59: Linear Voltage Regulator 15V | F59: 15Volt 15 Volt Linier IC Power Supply Stabilizer TO220 TO 220 | G59: BisaElektronika - BisaIC | H59: 2 | I59: #ITBisa #BisaElektronika #BisaIC #Socket #IC #Shifter #Shift #Register #7Segment #Segment #LED #Counter #DIP6 #DIP8 #DIP16 #Arduino #Breadboard #Mikrokontroler #Sensor #PCB | J59: 20 | K59: ITBisa - IC L7815CV L7815 7815 CV 7815CV 3 Terminal TO-220 Linear Voltage Regulator 15V 15Volt 15 Volt Linier IC Power Supply Stabilizer TO220 TO 220 | L59: ITBisa - IC L7815CV L7815 7815 CV 7815CV 3 Terminal TO-220 Linear Volt | M59: ITBisa - IC L7815CV L7815 7815 CV 7815CV 3 Terminal TO-220 Linear Voltage Regulator 15V 15Volt 15 Volt Linier IC Power Supply Stabilizer TO220 TO 220 | N59: ITBisa - IC L7815CV L7815 7815 CV 7815CV 3 Terminal TO-220 Linear Voltage Regulator 15V 15Volt 15 Volt Linier IC Power Supply Stabilizer TO220 TO 220
A60: ITBISA-IC-LM741CN-DIP8 | B60: IC 741 | C60: LM741CN | D60: DIP-8 | E60: Op-Amp Filter Penguat LPF HPF BPF | F60: Integrated Circuit LM 741 LM741 Op Amp OpAmp 8 Pin Kaki DIP8 8DIP | G60: BisaElektronika - BisaIC | H60: 1 | I60: #ITBisa #BisaElektronika #BisaIC #Socket #IC #OpAmp #HPF #LPF #BPF #Filter #Amplifier #Inverting #DIP6 #DIP8 #DIP16 #Arduino #Breadboard #Mikrokontroler #Sensor #PCB | J60: 20 | K60: ITBisa - IC 741 LM741CN DIP-8 Op-Amp Filter Penguat LPF HPF BPF Integrated Circuit LM 741 LM741 Op Amp OpAmp 8 Pin Kaki DIP8 8DIP | L60: ITBisa - IC 741 LM741CN DIP-8 Op-Amp Filter Penguat LPF HPF BPF Integr | M60: ITBisa - IC 741 LM741CN DIP-8 Op-Amp Filter Penguat LPF HPF BPF Integrated Circuit LM 741 LM741 Op Amp OpAmp 8 Pin Kaki DIP8 8DIP | N60: ITBisa - IC 741 LM741CN DIP-8 Op-Amp Filter Penguat LPF HPF BPF Integrated Circuit LM 741 LM741 Op Amp OpAmp 8 Pin Kaki DIP8 8DIP
A61: ITBISA-IC-NE555P-DIP8 | B61: IC NE 555 | C61: NE555P | D61: DIP 8 Pin Kaki DIP-8 DIP8 8DIP | E61: Timer Osilator Flip Flop DIP-8 | F61: Oscillator Flip-Flop Integrated Circuit 8 Kaki | G61: BisaElektronika - BisaIC | H61: 1 | I61: #ITBisa #BisaElektronika #BisaIC #Socket #IC #Switch #Transistor #LED #Sensor #Timer #Osilator #FlipFlop #DIP6 #DIP8 #DIP16 #Arduino #Breadboard #Mikrokontroler #Sensor #PCB | J61: 20 | K61: ITBisa - IC NE 555 NE555P DIP 8 Pin Kaki DIP-8 DIP8 8DIP Timer Osilator Flip Flop DIP-8 Oscillator Flip-Flop Integrated Circuit 8 Kaki | L61: ITBisa - IC NE 555 NE555P DIP 8 Pin Kaki DIP-8 DIP8 8DIP Timer Osilato | M61: ITBisa - IC NE 555 NE555P DIP 8 Pin Kaki DIP-8 DIP8 8DIP Timer Osilator Flip Flop DIP-8 Oscillator Flip-Flop Integrated Circuit 8 Kaki | N61: ITBisa - IC NE 555 NE555P DIP 8 Pin Kaki DIP-8 DIP8 8DIP Timer Osilator Flip Flop DIP-8 Oscillator Flip-Flop Integrated Circuit 8 Kaki
A62: ITBISA-IC-PC817-DIP4
A63: ITBISA-IC-UA741CN-DIP8 | B63: IC UA 741 CN | C63: UA741CN | D63: 8 Pin DIP8 | E63: Op Amp Filter Penguat LPF HPF BPF DIP-8 | F63: 8 Kaki UA741 OpAmp Op-Amp Integrated Circuit | G63: BisaElektronika - BisaIC | H63: 1 | I63: #ITBisa #BisaElektronika #BisaIC #Socket #IC #OpAmp #HPF #LPF #BPF #Filter #Amplifier #Inverting #DIP6 #DIP8 #DIP16 #Arduino #Breadboard #Mikrokontroler #Sensor #PCB | J63: 20 | K63: ITBisa - IC UA 741 CN UA741CN 8 Pin DIP8 Op Amp Filter Penguat LPF HPF BPF DIP-8 8 Kaki UA741 OpAmp Op-Amp Integrated Circuit | L63: ITBisa - IC UA 741 CN UA741CN 8 Pin DIP8 Op Amp Filter Penguat LPF HPF | M63: ITBisa - IC UA 741 CN UA741CN 8 Pin DIP8 Op Amp Filter Penguat LPF HPF BPF DIP-8 8 Kaki UA741 OpAmp Op-Amp Integrated Circuit | N63: ITBisa - IC UA 741 CN UA741CN 8 Pin DIP8 Op Amp Filter Penguat LPF HPF BPF DIP-8 8 Kaki UA741 OpAmp Op-Amp Integrated Circuit
A64: ITBISA-IC-ULN2003AN-DIP16 | B64: IC 2003 | C64: ULN2003AN | D64: DIP16 DIP-16 16 Pin 16P | E64: Kanal Channel Darlington Driver Motor Stepper Control Kontrol | F64: ULN2003 | G64: BisaElektronika - BisaIC | I64: #ITBisa #BisaElektronika #BisaIC #Socket #IC #OpAmp #HPF #LPF #BPF #Filter #Amplifier #Inverting #DIP6 #DIP8 #DIP16 #Arduino #Breadboard #Mikrokontroler #Sensor #PCB | J64: 20 | K64: ITBisa - IC 2003 ULN2003AN DIP16 DIP-16 16 Pin 16P Kanal Channel Darlington Driver Motor Stepper Control Kontrol ULN2003 | L64: ITBisa - IC 2003 ULN2003AN DIP16 DIP-16 16 Pin 16P Kanal Channel Darli | M64: ITBisa - IC 2003 ULN2003AN DIP16 DIP-16 16 Pin 16P Kanal Channel Darlington Driver Motor Stepper Control Kontrol ULN2003 | N64: ITBisa - IC 2003 ULN2003AN DIP16 DIP-16 16 Pin 16P Kanal Channel Darlington Driver Motor Stepper Control Kontrol ULN2003
A65: ITBISA-IC-ULN2803APG-DIP18 | B65: IC 2803 | C65: ULN2803APG | D65: DIP18 DIP-18 18 Pin 18P | E65: Kanal Channel Darlington Driver Motor Stepper Control Kontrol | F65: ULN2803 | G65: BisaElektronika - BisaIC | I65: #ITBisa #BisaElektronika #BisaIC #Socket #IC #OpAmp #HPF #LPF #BPF #Filter #Amplifier #Inverting #DIP6 #DIP8 #DIP16 #DIP18 #Arduino #Breadboard #Mikrokontroler #Sensor #PCB | J65: 21 | K65: ITBisa - IC 2803 ULN2803APG DIP18 DIP-18 18 Pin 18P Kanal Channel Darlington Driver Motor Stepper Control Kontrol ULN2803 | L65: ITBisa - IC 2803 ULN2803APG DIP18 DIP-18 18 Pin 18P Kanal Channel Darl | M65: ITBisa - IC 2803 ULN2803APG DIP18 DIP-18 18 Pin 18P Kanal Channel Darlington Driver Motor Stepper Control Kontrol ULN2803 | N65: ITBisa - IC 2803 ULN2803APG DIP18 DIP-18 18 Pin 18P Kanal Channel Darlington Driver Motor Stepper Control Kontrol ULN2803
A66: ITBISA-IDC-2X5-AMPHENOL-FEMALE
A67: ITBISA-IDC-2X5-AMPHENOL-MALE
A68: ITBISA-IGAME-GTX-1070-8GB-DDR5-X-TOP-TRIPLE-FAN
A69: ITBISA-INFRARED-1838
A70: ITBISA-JACK-DC-005-FEMALE
A71: ITBISA-JUMPER-FF-10CM | B71: 40PCS Kabel Jumper | C71: 10 cm Female to Female F-F FF F F 2.54mm | E71: Arduino Breadboard | F71: 40 PCS 10cm Buah Pin 2.54 mm 2,54 mm 2,54mm Cable Rainbow Pelangi Sensor | G71: BisaElektronika - BisaKabel | H71: 25 | I71: #ITBisa #BisaElektronika #BisaKabel #Kabel #Jumper #40PCS #Male #Female #FF #10cm #20cm #30cm #Arduino #Breadboard #2.54mm #Mikrokontroler #Sensor #Socket #IC #PCB | J71: 20 | K71: ITBisa - 40PCS Kabel Jumper 10 cm Female to Female F-F FF F F 2.54mm Arduino Breadboard 40 PCS 10cm Buah Pin 2.54 mm 2,54 mm 2,54mm Cable Rainbow Pelangi Sensor | L71: ITBisa - 40PCS Kabel Jumper 10 cm Female to Female F-F FF F F 2.54mm A | M71: ITBisa - 40PCS Kabel Jumper 10 cm Female to Female F-F FF F F 2.54mm Arduino Breadboard 40 PCS 10cm Buah Pin 2.54 mm 2,54 mm 2,54mm Cable Rainbow Pela | N71: ITBisa - 40PCS Kabel Jumper 10 cm Female to Female F-F FF F F 2.54mm Arduino Breadboard 40 PCS 10cm Buah Pin 2.54 mm 2,54 mm 2,54mm Cable Rainbow Pelangi Sensor
A72: ITBISA-JUMPER-FF-20CM | B72: 40PCS Kabel Jumper | C72: 20 cm Female to Female F-F FF F F 2.54mm | E72: Arduino Breadboard | F72: 40 PCS 20cm Buah Pin 2.54 mm 2,54 mm 2,54mm Cable Rainbow Pelangi Sensor | G72: BisaElektronika - BisaKabel | H72: 35 | I72: #ITBisa #BisaElektronika #BisaKabel #Kabel #Jumper #40PCS #Male #Female #FF #10cm #20cm #30cm #Arduino #Breadboard #2.54mm #Mikrokontroler #Sensor #Socket #IC #PCB | J72: 20 | K72: ITBisa - 40PCS Kabel Jumper 20 cm Female to Female F-F FF F F 2.54mm Arduino Breadboard 40 PCS 20cm Buah Pin 2.54 mm 2,54 mm 2,54mm Cable Rainbow Pelangi Sensor | L72: ITBisa - 40PCS Kabel Jumper 20 cm Female to Female F-F FF F F 2.54mm A | M72: ITBisa - 40PCS Kabel Jumper 20 cm Female to Female F-F FF F F 2.54mm Arduino Breadboard 40 PCS 20cm Buah Pin 2.54 mm 2,54 mm 2,54mm Cable Rainbow Pela | N72: ITBisa - 40PCS Kabel Jumper 20 cm Female to Female F-F FF F F 2.54mm Arduino Breadboard 40 PCS 20cm Buah Pin 2.54 mm 2,54 mm 2,54mm Cable Rainbow Pelangi Sensor
A73: ITBISA-JUMPER-MF-10CM | B73: 40PCS Kabel Jumper | C73: 10 cm Male to Female M-F MF M F 2.54mm | E73: Arduino Breadboard | F73: 40 PCS 10cm Buah Pin 2.54 mm 2,54 mm 2,54mm Cable Rainbow Pelangi Sensor | G73: BisaElektronika - BisaKabel | H73: 25 | I73: #ITBisa #BisaElektronika #BisaKabel #Kabel #Jumper #40PCS #Male #Female #MF #10cm #20cm #30cm #Arduino #Breadboard #2.54mm #Mikrokontroler #Sensor #Socket #IC #PCB | J73: 20 | K73: ITBisa - 40PCS Kabel Jumper 10 cm Male to Female M-F MF M F 2.54mm Arduino Breadboard 40 PCS 10cm Buah Pin 2.54 mm 2,54 mm 2,54mm Cable Rainbow Pelangi Sensor | L73: ITBisa - 40PCS Kabel Jumper 10 cm Male to Female M-F MF M F 2.54mm Ard | M73: ITBisa - 40PCS Kabel Jumper 10 cm Male to Female M-F MF M F 2.54mm Arduino Breadboard 40 PCS 10cm Buah Pin 2.54 mm 2,54 mm 2,54mm Cable Rainbow Pelang | N73: ITBisa - 40PCS Kabel Jumper 10 cm Male to Female M-F MF M F 2.54mm Arduino Breadboard 40 PCS 10cm Buah Pin 2.54 mm 2,54 mm 2,54mm Cable Rainbow Pelangi Sensor
A74: ITBISA-JUMPER-MF-20CM | B74: 40PCS Kabel Jumper | C74: 20 cm Male to Female M-F MF M F 2.54mm | E74: Arduino Breadboard | F74: 40 PCS 20cm Buah Pin 2.54 mm 2,54 mm 2,54mm Cable Rainbow Pelangi Sensor | G74: BisaElektronika - BisaKabel | H74: 35 | I74: #ITBisa #BisaElektronika #BisaKabel #Kabel #Jumper #40PCS #Male #Female #MF #10cm #20cm #30cm #Arduino #Breadboard #2.54mm #Mikrokontroler #Sensor #Socket #IC #PCB | J74: 20 | K74: ITBisa - 40PCS Kabel Jumper 20 cm Male to Female M-F MF M F 2.54mm Arduino Breadboard 40 PCS 20cm Buah Pin 2.54 mm 2,54 mm 2,54mm Cable Rainbow Pelangi Sensor | L74: ITBisa - 40PCS Kabel Jumper 20 cm Male to Female M-F MF M F 2.54mm Ard | M74: ITBisa - 40PCS Kabel Jumper 20 cm Male to Female M-F MF M F 2.54mm Arduino Breadboard 40 PCS 20cm Buah Pin 2.54 mm 2,54 mm 2,54mm Cable Rainbow Pelang | N74: ITBisa - 40PCS Kabel Jumper 20 cm Male to Female M-F MF M F 2.54mm Arduino Breadboard 40 PCS 20cm Buah Pin 2.54 mm 2,54 mm 2,54mm Cable Rainbow Pelangi Sensor
A75: ITBISA-JUMPER-MM-10CM | B75: 40PCS Kabel Jumper | C75: 10 cm Male to Male M-M MM M M 2.54mm | E75: Arduino Breadboard | F75: 40 PCS 10cm Buah Pin 2.54 mm 2,54 mm 2,54mm Cable Rainbow Pelangi Sensor | G75: BisaElektronika - BisaKabel | H75: 25 | I75: #ITBisa #BisaElektronika #BisaKabel #Kabel #Jumper #40PCS #Male #Female #MM #10cm #20cm #30cm #Arduino #Breadboard #2.54mm #Mikrokontroler #Sensor #Socket #IC #PCB | J75: 20 | K75: ITBisa - 40PCS Kabel Jumper 10 cm Male to Male M-M MM M M 2.54mm Arduino Breadboard 40 PCS 10cm Buah Pin 2.54 mm 2,54 mm 2,54mm Cable Rainbow Pelangi Sensor | L75: ITBisa - 40PCS Kabel Jumper 10 cm Male to Male M-M MM M M 2.54mm Ardui | M75: ITBisa - 40PCS Kabel Jumper 10 cm Male to Male M-M MM M M 2.54mm Arduino Breadboard 40 PCS 10cm Buah Pin 2.54 mm 2,54 mm 2,54mm Cable Rainbow Pelangi | N75: ITBisa - 40PCS Kabel Jumper 10 cm Male to Male M-M MM M M 2.54mm Arduino Breadboard 40 PCS 10cm Buah Pin 2.54 mm 2,54 mm 2,54mm Cable Rainbow Pelangi Sensor | P75: https://tokopedia.com/itbisa/itbisa-ic-4n35-optocoupler-phototransistor-photocoupler-dip6-6-pin
A76: ITBISA-JUMPER-MM-20CM | B76: 40PCS Kabel Jumper | C76: 20 cm Male to Male M-M MM M M 2.54mm | E76: Arduino Breadboard | F76: 40 PCS 20cm Buah Pin 2.54 mm 2,54 mm 2,54mm Cable Rainbow Pelangi Sensor | G76: BisaElektronika - BisaKabel | H76: 35 | I76: #ITBisa #BisaElektronika #BisaKabel #Kabel #Jumper #40PCS #Male #Female #MM #10cm #20cm #30cm #Arduino #Breadboard #2.54mm #Mikrokontroler #Sensor #Socket #IC #PCB | J76: 20 | K76: ITBisa - 40PCS Kabel Jumper 20 cm Male to Male M-M MM M M 2.54mm Arduino Breadboard 40 PCS 20cm Buah Pin 2.54 mm 2,54 mm 2,54mm Cable Rainbow Pelangi Sensor | L76: ITBisa - 40PCS Kabel Jumper 20 cm Male to Male M-M MM M M 2.54mm Ardui | M76: ITBisa - 40PCS Kabel Jumper 20 cm Male to Male M-M MM M M 2.54mm Arduino Breadboard 40 PCS 20cm Buah Pin 2.54 mm 2,54 mm 2,54mm Cable Rainbow Pelangi | N76: ITBisa - 40PCS Kabel Jumper 20 cm Male to Male M-M MM M M 2.54mm Arduino Breadboard 40 PCS 20cm Buah Pin 2.54 mm 2,54 mm 2,54mm Cable Rainbow Pelangi Sensor
A77: ITBISA-KAPASITOR-ELCO-100UF-25V
A78: ITBISA-KAPASITOR-ELCO-2200UF-25V
A79: ITBISA-KAPASITOR-ELCO-47UF-50V
A80: ITBISA-KODE-UNIK
A81: ITBISA-KUPLUK-HITAM
A82: ITBISA-LCD-16X2-BLUE
A83: ITBISA-LCD-16X2-GREEN
A84: ITBISA-LDR-GL5516
A85: ITBISA-LED-MAX7219-4IN1-GAP
A86: ITBISA-LED-MAX7219-4IN1-TIGHT
A87: ITBISA-LED-SUPERBRIGHT-5MM-BLUE
A88: ITBISA-LED-SUPERBRIGHT-5MM-GREEN
... A93: ITBISA-MICRO-SD-READER-MINI
A94: ITBISA-MOTORDRIVER-L298N-WITH-HEATSINK | B94: Motor Driver Stepper DC | C94: L298N Dual H Bridge | D94: With Heatsink | E94: Module Control Robot Car Arduino | F94: L 298 N Modul Kontrol High Power | G94: BisaElektronika | K94: ITBisa - Motor Driver Stepper DC L298N Dual H Bridge With Heatsink Module Control Robot Car Arduino L 298 N Modul Kontrol High Power | L94: ITBisa - Motor Driver Stepper DC L298N Dual H Bridge With Heatsink Mod | M94: ITBisa - Motor Driver Stepper DC L298N Dual H Bridge With Heatsink Module Control Robot Car Arduino L 298 N Modul Kontrol High Power | N94: ITBisa - Motor Driver Stepper DC L298N Dual H Bridge With Heatsink Module Control Robot Car Arduino L 298 N Modul Kontrol High Power
A95: ITBISA-NODEMCU-ESP32-MICRO
A96: ITBISA-NODEMCU-ESP32-MICRO-30PIN
A97: ITBISA-NODEMCU-ESP32-MICRO-38PIN
A98: ITBISA-NODEMCU-V3-CH340G-ESP8266-MICRO | B98: NodeMCU | C98: V3 CH340G
A99: ITBISA-NPN-2N2222-TO92 | B99: Transistor | C99: BJT NPN 2N2222 A 2N2222A | D99: TO92 0.6A 30V | E99: Penguat Switch | F99: Transistors 2N 2222 TO 92 TO-92 0.6 Ampere 0,6A Op-Amp Op Amp Switching 30 V 30Volt Volt | G99: BisaElektronika - BisaTransistor | H99: 1 | I99: #ITBisa #BisaElektronika #BisaTransistor #IC #Socket #Switch #Penguat #OpAmp #Op-Amp #Amplifier #BJT #MOSFET #NPN #PNP #TO-92 #TO92 #PCB #Arduino #Breadboard #Mikrokontroler | J99: 20 | K99: ITBisa - Transistor BJT NPN 2N2222 A 2N2222A TO92 0.6A 30V Penguat Switch Transistors 2N 2222 TO 92 TO-92 0.6 Ampere 0,6A Op-Amp Op Amp Switching 30 V 30Volt Volt | L99: ITBisa - Transistor BJT NPN 2N2222 A 2N2222A TO92 0.6A 30V Penguat Swi | M99: ITBisa - Transistor BJT NPN 2N2222 A 2N2222A TO92 0.6A 30V Penguat Switch Transistors 2N 2222 TO 92 TO-92 0.6 Ampere 0,6A Op-Amp Op Amp Switching 30 V | N99: ITBisa - Transistor BJT NPN 2N2222 A 2N2222A TO92 0.6A 30V Penguat Switch Transistors 2N 2222 TO 92 TO-92 0.6 Ampere 0,6A Op-Amp Op Amp Switching 30 V 30Volt Volt
A100: ITBISA-NPN-2N3904-TO92
A101: ITBISA-NPN-2N5551-TO92
A102: ITBISA-NPN-BC337-TO92
A103: ITBISA-NPN-BC547-TO92 | B103: Transistor | C103: BJT NPN BC547 | D103: TO-92 TO92 | E103: Penguat Switch Amplifier | G103: BisaElektronika - BisaTransistor | H103: 1 | I103: #ITBisa #BisaElektronika #BisaTransistor #IC #Socket #Switch #Penguat #OpAmp #Op-Amp #Amplifier #BJT #MOSFET #NPN #PNP #TO-92 #TO92 #PCB #Arduino #Breadboard #Mikrokontroler | J103: 20 | K103: ITBisa - Transistor BJT NPN BC547 TO-92 TO92 Penguat Switch Amplifier | L103: ITBisa - Transistor BJT NPN BC547 TO-92 TO92 Penguat Switch Amplifier | M103: ITBisa - Transistor BJT NPN BC547 TO-92 TO92 Penguat Switch Amplifier | N103: ITBisa - Transistor BJT NPN BC547 TO-92 TO92 Penguat Switch Amplifier
A104: ITBISA-NPN-BC547A-TO92 | B104: Transistor | C104: BJT NPN BC547 | D104: TO-92 TO92 | E104: Penguat Switch Amplifier | G104: BisaElektronika - BisaTransistor | H104: 1 | I104: #ITBisa #BisaElektronika #BisaTransistor #IC #Socket #Switch #Penguat #OpAmp #Op-Amp #Amplifier #BJT #MOSFET #NPN #PNP #TO-92 #TO92 #PCB #Arduino #Breadboard #Mikrokontroler | J104: 20 | K104: ITBisa - Transistor BJT NPN BC547 TO-92 TO92 Penguat Switch Amplifier | L104: ITBisa - Transistor BJT NPN BC547 TO-92 TO92 Penguat Switch Amplifier | M104: ITBisa - Transistor BJT NPN BC547 TO-92 TO92 Penguat Switch Amplifier | N104: ITBisa - Transistor BJT NPN BC547 TO-92 TO92 Penguat Switch Amplifier
...

Sheet BisaEtalase
A1: Level 1 | B1: Level 2
A2: Elektronika
B3: IC
B4: Induktor
B5: Kabel
B6: Kapasitor
B7: Lampu
B8: Mikrokontroler
B9: PCB
B10: Resistor
B11: Segment
B12: Socket
B13: Transistor
A14: Ospek
B15: Lampu
B16: Sarung Tangan
B17: Senter
B18: Syal
B19: Baterai

Sheet BisaPerlengkapan
A1: Tanggal Beli | B1: Jenis Transaksi Debit | C1: Jenis Transaksi Kredit | D1: Nominal | E1: Keterangan
A3: 46023.008 | B3: Perlengkapan Kardus | C3: Kas ITBisa | D3: =80*250 - 4000 + 1000 -> 17000 | E3: 80 x Kardus 12x6x6 - KARDUS MOUD Shopee
A4: 46048.586 | B4: Perlengkapan Tinta | C4: Kas ITBisa | D4: =(98000 + 3100 - 10000 + 1000) -> 92100 | E4: 1 x Tinta EPSON Hitam L3110
A6: 46128.061 | B6: Perlengkapan Selotip | C6: Kas ITBisa | D6: =(2*48600 + 1*48600 + 56000 - 55000 - 29160 + 2200) -> 119840 | E6: Lakban 48mm x 90 yard (2 x 6 Cokelat BAGUS + 2 x 1 Bening JELEK)
A7: 46142.66 | B7: Perlengkapan Bubble Wrap | C7: Kas ITBisa | D7: =(129900 + 14000 - 14000 - 15000 + 2200) -> 117100 | E7: Bubble Wrap Hitam 3 kg Non Core
A9: 45782.901 | B9: Perlengkapan Gunting | C9: Kas ITBisa | D9: =(14500 + 8000 - 8000 - 5000 + 1500) -> 11000 | E9: 1 x Gunting Joyko Besar - JURAGAN ATK Official Shopee
A10: 46147.75 | B10: Perlengkapan Plastik Klip | C10: Kas ITBisa | D10: =(56250 + 6500 - 6500 - 4000 + 2000) -> 54250 | E10: 1 x 1000 Plastik Klip - majuplastic Shopee
A11: 46152.705 | B11: Perlengkapan Selotip | C11: Kas ITBisa | D11: =(28500 + 8000 - 8000 - 4000 + 2000) -> 26500 | E11: 6 x Lakban Cokelat 45mm x 90 yard - SUPER LIGHTING Shopee
A12: 46152.697 | B12: Perlengkapan Selotip | C12: Kas ITBisa | D12: =(583200 + 48900 - 48900 - 58320 + 3000) -> 527880 | E12: 72 x Lakban Cokelat 45mm x 90 yard - kilatpacking Shopee
A14: 46158.592 | B14: Perlengkapan Tape Cutter | C14: Kas ITBisa | D14: =(3*7200) - 2160 + 66 -> 19506 | E14: 3 x Tape Cutter 2 Inch - Andalan Packing Shopee
A15: 46159.726 | B15: Perlengkapan Kardus | C15: Kas ITBisa | D15: =54426+21999-21999+10000-10885+435 -> 53976 | E15: 193 x Kardus/Karton Box Packing 12x6x6 - ID karton Shopee
A16: 46159.726 | B16: Perlengkapan Kardus | C16: Kas ITBisa | D16: =95550+28000-28000+5000-19111+765 -> 82204 | E16: 390 x Karton Packing 12x6x6 - i Box Shopee
A17: 46168.515 | B17: Perlengkapan Kardus | C17: Kas ITBisa | D17: =21999+25200-25200-4000+1000 -> 18999 | E17: 1 x Kardus 1-5 kg bekas Ale Ale 3Kg - PUSAT OLEH-OLEH BREBES.ID Shopee
A18: 46168.518 | B18: Perlengkapan Bubble Wrap | C18: Kas ITBisa | D18: =127000+39000-39000-10795-19050+2000 -> 99155 | E18: 1 x Bubble Wrap Hitam Standard 125cm x 50M - sipacking Shopee
A20: 46193.699 | B20: Perlengkapan Kardus | C20: Kas ITBisa | D20: =21999+25200-25200-4399+323 -> 17923 | E20: 1 x Kardus 1-5 Kg bekas Ale Ale 3Kg - PUSAT OLEH-OLEH BREBES.ID - 260620JUFJQBW4
A21: 46193.699 | B21: Perlengkapan Selotip | C21: Kas ITBisa | D21: =127800+22500-22500-25561+1877 -> 104116 | E21: 2 x Lakban Solasi Cortape Plakban Selotip Cokelat 48mm x 90yard + 1 x Lakban Solasi Cortape Plakban Selotip Bening 48mm x 90yard - kilatpacking - 260620JUFJQBW3
A22: 46190.592 | B22: Perlengkapan Tinta | C22: Kas ITBisa | D22: =588000+6300-2000-58800+3000 -> 536500 | E22: 1 x Epson Tinta 003 1 set (Paket 4 warna) + 2 x Tinta Epson 003 Black Original - Epson Official Store Indonesia - 260617B1GDURYV

Sheet BisaJurnal
A1: {={"Tanggal Akun","Akun","Referensi (Kode Transaksi)","Debit","Kredit","Keterangan"; SORT({ IF((BisaStok!B3:B5017<2),,{BisaStok!B3:B5017+0.00001*MOD(ROW(BisaStok!B3:B5017),100), "Piutang "&BisaStok!F3:F5017,IF(BisaStok!B3:B5017<2,,"PIU-BisaStok-"&TEXT(ROW(BisaStok!B3:B5017),"00000")),BisaStok!AB3:AB5017,SUBSTITUTE(BisaStok!B3:B5017,BisaStok!B3:B5017,),BisaStok!H3:H5017}); IF((BisaStok!B3:B5017<2),,{BisaStok!B3:B5017+0.00001*MOD(ROW(BisaStok!B3:B5017),100), " Kas ITBisa"&SUBSTITUTE(BisaStok!B3:B5017,BisaStok!B3:B5017,),IF(BisaStok!B3:B5017<2,,"KAS-BisaStok-"&TEXT(ROW(BisaStok!B3:B5017),"00000")),SUBSTITUTE(BisaStok!B3:B5017,BisaStok!B3:B5017,),BisaStok!AB3:AB5017,BisaStok!H3:H5017}); IF((BisaStok!C3:C5017<2),,{BisaStok!C3:C5017+0.00001*MOD(ROW(BisaStok!C3:C5017),100), "Persediaan "&BisaStok!A3:A5017,IF(BisaStok!B3:B5017<2,,"INV-BisaStok-"&TEXT(ROW(BisaStok!B3:B5017),"00000")),BisaStok!AB3:AB5017,SUBSTITUTE(BisaStok!B3:B5017,BisaStok!B3:B5017,),BisaStok!H3:H5017}); IF((BisaStok!C3:C5017<2),,{BisaStok!C3:C5017+0.00001*MOD(ROW(BisaStok!C3:C5017),100), " Piutang "&BisaStok!F3:F5017,IF(BisaStok!B3:B5017<2,,"PIU-BisaStok-"&TEXT(ROW(BisaStok!B3:B5017),"00000")),SUBSTITUTE(BisaStok!B3:B5017,BisaStok!B3:B5017,),BisaStok!AB3:AB5017,BisaStok!H3:H5017}); "","","","","",""; IF((BisaPerlengkapan!A2:A5017<2),,{BisaPerlengkapan!A2:A5017+0.00001*MOD(ROW(BisaPerlengkapan!A2:A5017),100),BisaPerlengkapan!B2:B5017,"DBT-BisaPerlengkapan-"&TEXT(ROW(BisaPerlengkapan!A2:A5017),"00000"),BisaPerlengkapan!D2:D5017,SUBSTITUTE(BisaPerlengkapan!A2:A5017,BisaPerlengkapan!A2:A5017,),BisaPerlengkapan!E2:E5017}); IF((BisaPerlengkapan!A2:A5017<2),,{BisaPerlengkapan!A2:A5017+0.00001*MOD(ROW(BisaPerlengkapan!A2:A5017),100), " "&BisaPerlengkapan!C2:C5017,"CRT-BisaPerlengkapan-"&TEXT(ROW(BisaPerlengkapan!A2:A5017),"00000"),SUBSTITUTE(BisaPerlengkapan!A2:A5017,BisaPerlengkapan!A2:A5017,),BisaPerlengkapan!D2:D5017,BisaPerlengkapan!E2:E5017}); "","","","","",""; IF((BisaHilang!A2:A5017<2)+(BisaHilang!C2:C5017<1)+(BisaHilang!D2:D5017<1),,{BisaHilang!A2:A5017+0.00001*MOD(ROW(BisaHilang!A2:A5017),100),"Persediaan "&BisaHilang!B2:B5017,"INV-BisaHilang-"&TEXT(ROW(BisaHilang!A2:A5017),"00000"),BisaHilang!D2:D5017,SUBSTITUTE(BisaHilang!A2:A5017,BisaHilang!A2:A5017,),SUBSTITUTE(BisaHilang!A2:A5017,BisaHilang!A2:A5017,)}); IF((BisaHilang!A2:A5017<2)+(BisaHilang!C2:C5017<1)+(BisaHilang!D2:D5017<1),,{BisaHilang!A2:A5017+0.00001*MOD(ROW(BisaHilang!A2:A5017),100)," Bonus "&BisaHilang!B2:B5017,"BNS-BisaHilang-"&TEXT(ROW(BisaHilang!A2:A5017),"00000"),SUBSTITUTE(BisaHilang!A2:A5017,BisaHilang!A2:A5017,),BisaHilang!D2:D5017,SUBSTITUTE(BisaHilang!A2:A5017,BisaHilang!A2:A5017,)}); "","","","","",""; IF((BisaHilang!A2:A5017<2)+(BisaHilang!E2:E5017<1)+(BisaHilang!F2:F5017<1),,{BisaHilang!A2:A5017+0.00001*MOD(ROW(BisaHilang!A2:A5017),100),"Beban Hilang "&BisaHilang!B2:B5017,"BBN-BisaHilang-"&TEXT(ROW(BisaHilang!A2:A5017),"00000"),BisaHilang!F2:F5017,SUBSTITUTE(BisaHilang!A2:A5017,BisaHilang!A2:A5017,),SUBSTITUTE(BisaHilang!A2:A5017,BisaHilang!A2:A5017,)}); IF((BisaHilang!A2:A5017<2)+(BisaHilang!E2:E5017<1)+(BisaHilang!F2:F5017<1),,{BisaHilang!A2:A5017+0.00001*MOD(ROW(BisaHilang!A2:A5017),100)," Persediaan "&BisaHilang!B2:B5017,"INV-BisaHilang-"&TEXT(ROW(BisaHilang!A2:A5017),"00000"),SUBSTITUTE(BisaHilang!A2:A5017,BisaHilang!A2:A5017,),BisaHilang!F2:F5017,SUBSTITUTE(BisaHilang!A2:A5017,BisaHilang!A2:A5017,)}); "","","","","",""},1,TRUE)}} -> Tanggal Akun | B1: Akun | C1: Referensi (Kode Transaksi) | D1: Debit | E1: Kredit | F1: Keterangan
A2: 43590.408 | B2: Piutang Migrasi - Shopee | C2: PIU-BisaStok-00004 | D2: 27113.1 | F2: Shopee Furqonajiy 19050510476HUJK ( - ) Mahal ( + ) Untuk Testing Darurat Pesan (?) setiap 10 buah diberi strefoam
A3: 43590.408 | B3: Kas ITBisa | C3: KAS-BisaStok-00004 | E3: 27113.1 | F3: Shopee Furqonajiy 19050510476HUJK ( - ) Mahal ( + ) Untuk Testing Darurat Pesan (?) setiap 10 buah diberi strefoam
A4: 43596 | B4: Persediaan ITBISA-IC-LM741CN-DIP8 | C4: INV-BisaStok-00004 | D4: 27113.1 | F4: Shopee Furqonajiy 19050510476HUJK ( - ) Mahal ( + ) Untuk Testing Darurat Pesan (?) setiap 10 buah diberi strefoam
A5: 43596 | B5: Piutang Migrasi - Shopee | C5: PIU-BisaStok-00004 | E5: 27113.1 | F5: Shopee Furqonajiy 19050510476HUJK ( - ) Mahal ( + ) Untuk Testing Darurat Pesan (?) setiap 10 buah diberi strefoam
A6: 44032 | B6: Piutang Migrasi - Tokopedia | C6: PIU-BisaStok-00005 | D6: 21981.4 | F6: Tokopedia Furqonajiy
A7: 44032 | B7: Kas ITBisa | C7: KAS-BisaStok-00005 | E7: 21981.4 | F7: Tokopedia Furqonajiy
A8: 44039 | B8: Persediaan ITBISA-RESISTOR-470K-1/4W | C8: INV-BisaStok-00005 | D8: 21981.4 | F8: Tokopedia Furqonajiy
A9: 44039 | B9: Piutang Migrasi - Tokopedia | C9: PIU-BisaStok-00005 | E9: 21981.4 | F9: Tokopedia Furqonajiy
A10: 44039 | B10: Piutang Migrasi - Tokopedia | C10: PIU-BisaStok-00006 | D10: 13000 | F10: Tokopedia Furqonajiy
A11: 44039 | B11: Kas ITBisa | C11: KAS-BisaStok-00006 | E11: 13000 | F11: Tokopedia Furqonajiy
A12: 44041 | B12: Persediaan ITBISA-RESISTOR-56K-1/4W | C12: INV-BisaStok-00006 | D12: 13000 | F12: Tokopedia Furqonajiy
A13: 44041 | B13: Piutang Migrasi - Tokopedia | C13: PIU-BisaStok-00006 | E13: 13000 | F13: Tokopedia Furqonajiy
A14: 44871 | B14: Piutang Migrasi - Tokopedia | C14: PIU-BisaStok-00007 | D14: 461407.04 | F14: Tokopedia Furqonajiy
A15: 44871 | B15: Kas ITBisa | C15: KAS-BisaStok-00007 | E15: 461407.04 | F15: Tokopedia Furqonajiy
A16: 44873 | B16: Persediaan ITBISA-RAPID-BOHLAM-E10-3.8V-SCREW | C16: INV-BisaStok-00007 | D16: 461407.04 | F16: Tokopedia Furqonajiy
A17: 44873 | B17: Piutang Migrasi - Tokopedia | C17: PIU-BisaStok-00007 | E17: 461407.04 | F17: Tokopedia Furqonajiy
A18: 45013 | B18: Piutang Migrasi - Jasa Impor Tiongkok | C18: PIU-BisaStok-00008 | D18: 2095046
A19: 45013 | B19: Kas ITBisa | C19: KAS-BisaStok-00008 | E19: 2095046
A20: 45061 | B20: Persediaan ITBISA-7SEGMENT-CATHODE-RED-0.56-1BIT | C20: INV-BisaStok-00008 | D20: 2095046
A21: 45061 | B21: Piutang Migrasi - Jasa Impor Tiongkok | C21: PIU-BisaStok-00008 | E21: 2095046
A22: 45085 | B22: Piutang Migrasi - Jasa Impor Tiongkok | C22: PIU-BisaStok-00009 | D22: 2864004 | F22: Tokopedia Furqonajiy 1x Invoice
A23: 45085 | B23: Kas ITBisa | C23: KAS-BisaStok-00009 | E23: 2864004 | F23: Tokopedia Furqonajiy 1x Invoice
A24: 45129 | B24: Persediaan ITBISA-IC-UA741CN-DIP8 | C24: INV-BisaStok-00009 | D24: 2864004 | F24: Tokopedia Furqonajiy 1x Invoice
A25: 45129 | B25: Piutang Migrasi - Jasa Impor Tiongkok | C25: PIU-BisaStok-00009 | E25: 2864004 | F25: Tokopedia Furqonajiy 1x Invoice
A26: 45202.354 | B26: Piutang Migrasi - Jasa Impor Tiongkok | C26: PIU-BisaStok-00010 | D26: 1113424
A27: 45202.354 | B27: Kas ITBisa | C27: KAS-BisaStok-00010 | E27: 1113424
A28: 45232.639 | B28: Persediaan ITBISA-7SEGMENT-CATHODE-RED-1.20-1BIT | C28: INV-BisaStok-00010 | D28: 1113424
A29: 45232.639 | B29: Piutang Migrasi - Jasa Impor Tiongkok | C29: PIU-BisaStok-00010 | E29: 1113424
A30: 45265.69 | B30: Piutang Migrasi - Ocistok/Martkita | C30: PIU-BisaStok-00011 | D30: 361680
A31: 45265.69 | B31: Kas ITBisa | C31: KAS-BisaStok-00011 | E31: 361680
A32: 45313.25 | B32: Persediaan ITBISA-TIGERHEAD-SENTER-KUNING-FT300 | C32: INV-BisaStok-00012 | D32: 10607.58 | F32: Shopee Aji
A33: 45313.25 | B33: Piutang Migrasi - Shopee | C33: PIU-BisaStok-00012 | E33: 10607.58 | F33: Shopee Aji
A34: 45336.461 | B34: Piutang Migrasi - Shopee | C34: PIU-BisaStok-00012 | D34: 10607.58 | F34: Shopee Aji
A35: 45336.461 | B35: Kas ITBisa | C35: KAS-BisaStok-00012 | E35: 10607.58 | F35: Shopee Aji
A36: 45341.64 | B36: Persediaan ITBISA-7SEGMENT-CATHODE-RED-2.30-1BIT | C36: INV-BisaStok-00011 | D36: 361680
A37: 45341.64 | B37: Piutang Migrasi - Ocistok/Martkita | C37: PIU-BisaStok-00011 | E37: 361680
A38: 45361.604 | B38: Piutang Migrasi - Art Techno | C38: PIU-BisaStok-00013 | D38: 182500 | F38: Art Techno
A39: 45361.604 | B39: Kas ITBisa | C39: KAS-BisaStok-00013 | E39: 182500 | F39: Art Techno
A40: 45365.484 | B40: Persediaan ITBISA-LED-MAX7219-4IN1-GAP | C40: INV-BisaStok-00013 | D40: 182500 | F40: Art Techno
A41: 45365.484 | B41: Piutang Migrasi - Art Techno | C41: PIU-BisaStok-00013 | E41: 182500 | F41: Art Techno
A42: 45374.679 | B42: Piutang Migrasi - Ocistok/Martkita | C42: PIU-BisaStok-00014 | D42: 4318000 | F42: MKT-63258 / 187963 (0.85 RMB)
A43: 45374.679 | B43: Kas ITBisa | C43: KAS-BisaStok-00014 | E43: 4318000 | F43: MKT-63258 / 187963 (0.85 RMB)
A44: 45381.201 | B44: Piutang Migrasi - Shopee | C44: PIU-BisaStok-00015 | D44: 38280 | F44: Shopee Aji GTGD
A45: 45381.201 | B45: Kas ITBisa | C45: KAS-BisaStok-00015 | E45: 38280 | F45: Shopee Aji GTGD
A46: 45384.568 | B46: Persediaan ITBISA-RESISTOR-33K-1/4W | C46: INV-BisaStok-00015 | D46: 38280 | F46: Shopee Aji GTGD
A47: 45384.568 | B47: Piutang Migrasi - Shopee | C47: PIU-BisaStok-00015 | E47: 38280 | F47: Shopee Aji GTGD
A48: 45409.658 | B48: Piutang Migrasi - Tokopedia | C48: PIU-BisaStok-00016 | D48: 7210919.3 | F48: Tokopedia Hendang
A49: 45409.658 | B49: Kas ITBisa | C49: KAS-BisaStok-00016 | E49: 7210919.3 | F49: Tokopedia Hendang
A50: 45410.559 | B50: Persediaan ITBISA-LED-MAX7219-4IN1-TIGHT | C50: INV-BisaStok-00053 | D50: 3257743.6 | F50: Shopee Aji J0CP
A51: 45410.559 | B51: Piutang Migrasi - Shopee | C51: PIU-BisaStok-00053 | E51: 3257743.6 | F51: Shopee Aji J0CP
A52: 45411.511 | B52: Piutang Migrasi - Shopee | C52: PIU-BisaStok-00017 | D52: 784180.08 | F52: Shopee Aji 5E6M
A53: 45411.511 | B53: Kas ITBisa | C53: KAS-BisaStok-00017 | E53: 784180.08 | F53: Shopee Aji 5E6M
A54: 45411.659 | B54: Persediaan ITBISA-NODEMCU-V3-CH340G-ESP8266-MICRO | C54: INV-BisaStok-00016 | D54: 7210919.3 | F54: Tokopedia Hendang
A55: 45411.659 | B55: Piutang Migrasi - Tokopedia | C55: PIU-BisaStok-00016 | E55: 7210919.3 | F55: Tokopedia Hendang
A56: 45414.417 | B56: Persediaan ITBISA-RAPID-BOHLAM-E10-2.5V-SCREW | C56: INV-BisaStok-00017 | D56: 784180.08 | F56: Shopee Aji 5E6M
A57: 45414.417 | B57: Piutang Migrasi - Shopee | C57: PIU-BisaStok-00017 | E57: 784180.08 | F57: Shopee Aji 5E6M
A58: 45414.907 | B58: Piutang Migrasi - Tokopedia | C58: PIU-BisaStok-00018 | D58: 5166.67 | F58: SmartBrain Tokopedia
A59: 45414.907 | B59: Kas ITBisa | C59: KAS-BisaStok-00018 | E59: 5166.67 | F59: SmartBrain Tokopedia
A60: 45415.655 | B60: Persediaan ITBISA-ABC-BATERAI-D-POWER | C60: INV-BisaStok-00018 | D60: 5166.67 | F60: SmartBrain Tokopedia
A61: 45415.655 | B61: Piutang Migrasi - Tokopedia | C61: PIU-BisaStok-00018 | E61: 5166.67 | F61: SmartBrain Tokopedia
A62: 45417.981 | B62: Piutang Migrasi - Shopee | C62: PIU-BisaStok-00019 | D62: 298218.96 | F62: Shopee Anggi VMGV
A63: 45417.981 | B63: Kas ITBisa | C63: KAS-BisaStok-00019 | E63: 298218.96 | F63: Shopee Anggi VMGV
A64: 45421.205 | B64: Piutang Migrasi - Shopee | C64: PIU-BisaStok-00020 | D64: 62344.1 | F64: Shopee Aji QK45
A65: 45421.205 | B65: Kas ITBisa | C65: KAS-BisaStok-00020 | E65: 62344.1 | F65: Shopee Aji QK45
A66: 45421.605 | B66: Persediaan ITBISA-SENSOR-SUHU-DHT11 | C66: INV-BisaStok-00019 | D66: 298218.96 | F66: Shopee Anggi VMGV
A67: 45421.605 | B67: Piutang Migrasi - Shopee | C67: PIU-BisaStok-00019 | E67: 298218.96 | F67: Shopee Anggi VMGV
A68: 45423.626 | B68: Persediaan ITBISA-RESISTOR-4K7-1/4W | C68: INV-BisaStok-00020 | D68: 62344.1 | F68: Shopee Aji QK45
A69: 45423.626 | B69: Piutang Migrasi - Shopee | C69: PIU-BisaStok-00020 | E69: 62344.1 | F69: Shopee Aji QK45
A70: 45426.593 | B70: Piutang Migrasi - Ocistok/Martkita | C70: PIU-BisaStok-00021 | D70: 1344778 | F70: Ocistok 205883
A71: 45426.593 | B71: Kas ITBisa | C71: KAS-BisaStok-00021 | E71: 1344778 | F71: Ocistok 205883
A72: 45426.999 | B72: Piutang Migrasi - Shopee | C72: PIU-BisaStok-00022 | D72: 5168602.3 | F72: Shopee Aji F1PM
A73: 45426.999 | B73: Kas ITBisa | C73: KAS-BisaStok-00022 | E73: 5168602.3 | F73: Shopee Aji F1PM
A74: 45429.457 | B74: Persediaan ITBISA-IC-L7805CV-TO220 | C74: INV-BisaStok-00022 | D74: 5168602.3 | F74: Shopee Aji F1PM
A75: 45429.457 | B75: Piutang Migrasi - Shopee | C75: PIU-BisaStok-00022 | E75: 5168602.3 | F75: Shopee Aji F1PM
A76: 45452.716 | B76: Piutang Migrasi - Shopee | C76: PIU-BisaStok-00023 | D76: 1144731 | F76: Shopee Aji F9QB
A77: 45452.716 | B77: Kas ITBisa | C77: KAS-BisaStok-00023 | E77: 1144731 | F77: Shopee Aji F9QB
A78: 45453.541 | B78: Piutang Migrasi - Tokopedia | C78: PIU-BisaStok-00024 | D78: 5808.14 | F78: Tokopedia Anggi 3524
A79: 45453.541 | B79: Kas ITBisa | C79: KAS-BisaStok-00024 | E79: 5808.14 | F79: Tokopedia Anggi 3524
A80: 45455.61 | B80: Piutang Migrasi - Ocistok/Martkita | C80: PIU-BisaStok-00025 | D80: 482915 | F80: MKT-62468 / 217289 (0.58 RMB)
A81: 45455.61 | B81: Kas ITBisa | C81: KAS-BisaStok-00025 | E81: 482915 | F81: MKT-62468 / 217289 (0.58 RMB)
A82: 45455.61 | B82: Piutang Migrasi - Ocistok/Martkita | C82: PIU-BisaStok-00026 | D82: 2617563 | F82: MKT-62469 / 217290 (0.58 RMB)
A83: 45455.61 | B83: Kas ITBisa | C83: KAS-BisaStok-00026 | E83: 2617563 | F83: MKT-62469 / 217290 (0.58 RMB)
A84: 45456.542 | B84: Persediaan ITBISA-SOCKET-BATERAI-AA-4SLOT | C84: INV-BisaStok-00024 | D84: 5808.14 | F84: Tokopedia Anggi 3524
A85: 45456.542 | B85: Piutang Migrasi - Tokopedia | C85: PIU-BisaStok-00024 | E85: 5808.14 | F85: Tokopedia Anggi 3524
A86: 45456.595 | B86: Persediaan ITBISA-IC-L7812CV-TO220 | C86: INV-BisaStok-00023 | D86: 1144731 | F86: Shopee Aji F9QB
A87: 45456.595 | B87: Piutang Migrasi - Shopee | C87: PIU-BisaStok-00023 | E87: 1144731 | F87: Shopee Aji F9QB
A88: 45477.917 | B88: Persediaan ITBISA-7SEGMENT-ANODE-RED-1.00-1BIT | C88: INV-BisaStok-00014 | D88: 4318000 | F88: MKT-63258 / 187963 (0.85 RMB)
A89: 45477.917 | B89: Piutang Migrasi - Ocistok/Martkita | C89: PIU-BisaStok-00014 | E89: 4318000 | F89: MKT-63258 / 187963 (0.85 RMB)
A90: 45486.573 | B90: Piutang Migrasi - Shopee | C90: PIU-BisaStok-00027 | D90: 348820 | F90: Shopee Aji 3XK4
A91: 45486.573 | B91: Kas ITBisa | C91: KAS-BisaStok-00027 | E91: 348820 | F91: Shopee Aji 3XK4
A92: 45488.834 | B92: Persediaan ITBISA-SOCKET-IC-DIP20-NARROW | C92: INV-BisaStok-00027 | D92: 348820 | F92: Shopee Aji 3XK4
A93: 45488.834 | B93: Piutang Migrasi - Shopee | C93: PIU-BisaStok-00027 | E93: 348820 | F93: Shopee Aji 3XK4
A94: 45493.667 | B94: Persediaan ITBISA-IC-ULN2803APG-DIP18 | C94: INV-BisaStok-00021 | D94: 1344778 | F94: Ocistok 205883
A95: 45493.667 | B95: Piutang Migrasi - Ocistok/Martkita | C95: PIU-BisaStok-00021 | E95: 1344778 | F95: Ocistok 205883
A96: 45512.035 | B96: Piutang Migrasi - Shopee | C96: PIU-BisaStok-00028 | D96: 12343.53 | F96: Shopee Aji 1TPY
A97: 45512.035 | B97: Kas ITBisa | C97: KAS-BisaStok-00028 | E97: 12343.53 | F97: Shopee Aji 1TPY
A98: 45513 | B98: Piutang Migrasi - Tokopedia | C98: PIU-BisaStok-00029 | D98: 460845 | F98: Tokopedia Anggi 9419
A99: 45513 | B99: Kas ITBisa | C99: KAS-BisaStok-00029 | E99: 460845 | F99: Tokopedia Anggi 9419
A100: 45514.667 | B100: Persediaan ITBISA-PIN-HEADER-MALE-1X40PIN-LURUS | C100: INV-BisaStok-00029 | D100: 460845 | F100: Tokopedia Anggi 9419
...

Sheet BisaRekapBarangBackend
A1: {={"Alamat Penerima"; SORT(IF(UNIQUE(TRIM(UPPER({BisaStok!D3:D1745;BisaPindahBarang!C2:C1745;BisaPindahBarang!D2:D1745;BisaHilang!G2:G1745})))="",,UNIQUE(TRIM(UPPER({BisaStok!D3:D1745;BisaPindahBarang!C2:C1745;BisaPindahBarang!D2:D1745;BisaHilang!G2:G1745})))))}} -> Alamat Penerima | B1: {={"Harga Impor Barang (Rupiah)";IF(A2:A1745="",,IF(SUMIF(BisaStok!D3:D1745&BisaStok!E3:E1745&IF(BisaStok!C3:C1745<2,FALSE,TRUE),A2:A1745&TRUE&FALSE,BisaStok!X3:X1745)<1,,SUMIF(BisaStok!D3:D1745&BisaStok!E3:E1745&IF(BisaStok!C3:C1745<2,FALSE,TRUE),A2:A1745&TRUE&FALSE,BisaStok!X3:X1745)))}} -> Harga Impor Barang (Rupiah) | C1: =IFERROR(__xludf.DUMMYFUNCTION("ARRAYFORMULA({""Harga Impor Barang (USD)"";If(B2:B1745="""",,B2:B1745/GOOGLEFINANCE(""CURRENCY:USDIDR""))})"),"Harga Impor Barang (USD)") -> Harga Impor Barang (USD) | D1: {={"SKU","Tanggal Pesan Terakhir","HPP Terakhir"; SORT({ SORT(UNIQUE(BisaSEO!A2:A1745)),IFERROR(IF(SORT(UNIQUE(BisaSEO!A2:A1745))="",,{ VLOOKUP(SORT(BisaSEO!A2:A1745),SORT({'Import-BisaJual'!A2:A1745,'Import-BisaJual'!B2:B1745},1,TRUE,2,FALSE),2,FALSE), VLOOKUP(SORT(BisaSEO!A2:A1745),SORT({BisaStok!A3:A1745,BisaStok!B3:B1745,BisaStok!AC3:AC1745},1,TRUE,2,FALSE),3,FALSE)}),"") },1,TRUE)}} -> SKU | E1: Tanggal Pesan Terakhir | F1: HPP Terakhir | G1: {={"HPP Belum Terjual";IF(D2:D1745="",,F2:F1745*H2:H1745)}} -> HPP Belum Terjual | H1: {={"Total Stok"; IF(D2:D1745="",,IF(SUMIF(IF(COLUMN(M2:O1745),ROW(M2:O1745)),ROW(M2:O1745),M2:O1745)=0,,SUMIF(IF(COLUMN(M2:O1745),ROW(M2:O1745)),ROW(M2:O1745),M2:O1745)))}} -> Total Stok | I1: {={"1/2 Total Stok"; IF(H2:H1745="",,ROUNDDOWN(H2:H1745/2,0))}} -> 1/2 Total Stok | J1: {={"1/3 Total Stok"; IF(H2:H1745="",,ROUNDDOWN(H2:H1745/3,0))}} -> 1/3 Total Stok | K1: {={"40% Total Stok"; IF(H2:H1745="",,ROUNDDOWN(H2:H1745*40%,0))}} -> 40% Total Stok | L1: {={"20% Total Stok"; IF(H2:H1745="",,ROUNDDOWN(H2:H1745*20%,0))}} -> 20% Total Stok | M1: {=TRANSPOSE(SORT(TRANSPOSE(IF( ABS(BisaRekapGudangBackend!A1:AE1)<0.5 + (BisaRekapGudangBackend!A2:AE2="BCA ITBISA") + (BisaRekapGudangBackend!A2:AE2="BLIBLI ITBISA") + (BisaRekapGudangBackend!A2:AE2="BNI SYARIAH ITBISA") + (BisaRekapGudangBackend!A2:AE2="BRI ITBISA") + (BisaRekapGudangBackend!A2:AE2="MANDIRI ITBISA") ,,{BisaRekapGudangBackend!A2:M2;IF(ABS(BisaRekapGudangBackend!A3:M1745)<1,,BisaRekapGudangBackend!A3:M1745)}))))} -> KERTASARI CIAMIS | N1: KYAI KONTONG
A2: KERTASARI CIAMIS | D2: ITBISA-7SEGMENT-ANODE-RED-0.56-1BIT | E2: 46197 | F2: 675.92 | G2: 2867252.6 | H2: 4242 | I2: 2121 | J2: 1414 | K2: 1696 | L2: 848 | N2: 4242
A3: KYAI KONTONG | B3: 100503000 | C3: =IFERROR(__xludf.DUMMYFUNCTION("""COMPUTED_VALUE"""),5600.300902708124) -> 5600.3009 | D3: ITBISA-7SEGMENT-ANODE-RED-1.00-1BIT | E3: 46197 | F3: 2000 | G3: 4016000 | H3: 2008 | I3: 1004 | J3: 669 | K3: 803 | L3: 401 | N3: 2008
D4: ITBISA-7SEGMENT-ANODE-RED-1.20-1BIT | E4: 46193 | F4: 3611.73 | G4: 2235660.9 | H4: 619 | I4: 309 | J4: 206 | K4: 247 | L4: 123 | N4: 619
D5: ITBISA-7SEGMENT-ANODE-RED-2.30-1BIT | F5: 6462.2939 | G5: 0
D6: ITBISA-7SEGMENT-CATHODE-RED-0.56-1BIT | E6: 46196 | F6: 731 | G6: 3655 | H6: 5 | I6: 2 | J6: 1 | K6: 2 | L6: 1 | N6: 5
D7: ITBISA-7SEGMENT-CATHODE-RED-1.00-1BIT | G7: 0
D8: ITBISA-7SEGMENT-CATHODE-RED-1.20-1BIT | E8: 46176 | F8: 2756 | G8: 55120 | H8: 20 | I8: 10 | J8: 6 | K8: 8 | L8: 4 | N8: 20
D9: ITBISA-7SEGMENT-CATHODE-RED-2.30-1BIT | E9: 46179 | F9: 6462.2939 | G9: 38773.763 | H9: 6 | I9: 3 | J9: 2 | K9: 2 | L9: 1 | N9: 6
D10: ITBISA-ABC-BATERAI-9V-ALKALINE | G10: 0
D11: ITBISA-ABC-BATERAI-9V-POWER | E11: 46192 | F11: 11210.938 | G11: 1244414.1 | H11: 111 | I11: 55 | J11: 37 | K11: 44 | L11: 22 | N11: 111
D12: ITBISA-ABC-BATERAI-AA-ALKALINE | E12: 46198 | F12: 3987.5 | G12: 1375687.5 | H12: 345 | I12: 172 | J12: 115 | K12: 138 | L12: 69 | N12: 345
D13: ITBISA-ABC-BATERAI-AAA-ALKALINE | E13: 46198 | F13: 3117.1667 | G13: 1362201.8 | H13: 437 | I13: 218 | J13: 145 | K13: 174 | L13: 87 | N13: 437
D14: ITBISA-ABC-BATERAI-D-ALKALINE | G14: 0
D15: ITBISA-ABC-BATERAI-D-BIRU | G15: 0
D16: ITBISA-ABC-BATERAI-D-POWER | F16: 5166.67 | G16: 5166.67 | H16: 1 | I16: 0 | J16: 0 | K16: 0 | L16: 0 | N16: 1
D17: ITBISA-ABC-SENTER-LED-ALKALINE | G17: 0
D18: ITBISA-ARDUINO-UNO-R3-328P-SMD | E18: 46196 | F18: 37978.26 | G18: 8469152 | H18: 223 | I18: 111 | J18: 74 | K18: 89 | L18: 44 | N18: 223
D19: ITBISA-ARDUINO-UNO-R3-CLONE-CABLE30CM | G19: 0
D20: ITBISA-ARDUINO-UNO-R3-CLONE-CABLE50CM | G20: 0
D21: ITBISA-BLUETOOTH-MODULE-HC05 | E21: 46196 | F21: 21771.152 | G21: 4288916.8 | H21: 197 | I21: 98 | J21: 65 | K21: 78 | L21: 39 | N21: 197
D22: ITBISA-BREADBOARD-830HOLE-MB102 | E22: 46196 | F22: 6809.6 | G22: 0
D23: ITBISA-BUBBLE-WRAP | E23: 46134 | G23: 0 | H23: 12 | I23: 6 | J23: 4 | K23: 4 | L23: 2 | N23: 12
D24: ITBISA-BUKAEMAS | G24: 0
D25: ITBISA-BUKAREKSA-BAHANA-MES-SYARIAH | G25: 0
D26: ITBISA-BUKAREKSA-CIMB-PRINCIPAL-PASAR-UANG | G26: 0
D27: ITBISA-BUKAREKSA-CIPTA-SYARIAH-BALANCE | G27: 0
D28: ITBISA-BUKAREKSA-MANDIRI-INVESTA-DANA-SYARIAH | G28: 0
D29: ITBISA-BUKAREKSA-MANDIRI-INVESTA-PASAR-UANG | G29: 0
D30: ITBISA-BUKAREKSA-SUCORINVEST-SHARIA-EQUITY-FUND | G30: 0
D31: ITBISA-BUKAREKSA-SYARIAH-MANDIRI-PASAR-UANG | G31: 0
D32: ITBISA-BUZZER-ACTIVE-5V | E32: 46198 | F32: 1250.5138 | G32: 3372635.7 | H32: 2697 | I32: 1348 | J32: 899 | K32: 1078 | L32: 539 | N32: 2697
D33: ITBISA-CHIP-ESP32-WROOM | E33: 46063 | F33: 23076 | G33: 0
D34: ITBISA-CHIP-ESP32-WROOM-ANTENNA | E34: 46192 | F34: 24820 | G34: 0
D35: ITBISA-CHIP-ESP8266-ESP12F | E35: 46077 | F35: 12783.5 | G35: 485773 | H35: 38 | I35: 19 | J35: 12 | K35: 15 | L35: 7 | N35: 38
D36: ITBISA-CORSAIR-VENGEANCE-K66 | G36: 0
D37: ITBISA-DC-TO-DC-STEPDOWN-LM2596 | E37: 46196 | F37: 4973.93 | G37: 0
D38: ITBISA-DC-TO-DC-STEPDOWN-XL4005 | E38: 46198 | F38: 8461.03 | G38: 126915.45 | H38: 15 | I38: 7 | J38: 5 | K38: 6 | L38: 3 | N38: 15
D39: ITBISA-DC-TO-DC-STEPDOWN-XL4015 | E39: 46144 | F39: 8384.98 | G39: 0
D40: ITBISA-DC-TO-DC-STEPUP-XL6009 | E40: 46197 | F40: 7240.2871 | G40: 202728.04 | H40: 28 | I40: 14 | J40: 9 | K40: 11 | L40: 5 | N40: 28
D41: ITBISA-DIODA-1N4007-DO41 | E41: 46185 | F41: 78.561407 | G41: 154765.97 | H41: 1970 | I41: 985 | J41: 656 | K41: 788 | L41: 394 | N41: 1970
D42: ITBISA-EMLOCK-ACM-Y180 | G42: 0
D43: ITBISA-EPSON-L310 | G43: 0
D44: ITBISA-I2C-IIC-LCD | E44: 46198 | F44: 5806.3269 | G44: 168383.48 | H44: 29 | I44: 14 | J44: 9 | K44: 11 | L44: 5 | N44: 29
D45: ITBISA-IC-4N35-DIP6-BLACK | G45: 0
D46: ITBISA-IC-4N35-DIP6-WHITE | G46: 0
D47: ITBISA-IC-74HC245N-DIP20 | E47: 46195 | F47: 1425.7829 | G47: 4030688.3 | H47: 2827 | I47: 1413 | J47: 942 | K47: 1130 | L47: 565 | N47: 2827
D48: ITBISA-IC-74HC595N-DIP16 | E48: 46185 | F48: 768.24276 | G48: 768.24276 | H48: 1 | I48: 0 | J48: 0 | K48: 0 | L48: 0 | N48: 1
D49: ITBISA-IC-78L05-TO92 | G49: 0
D50: ITBISA-IC-ATMEGA328P-DIP28 | E50: 46197 | F50: 27318.46 | G50: 4125087.5 | H50: 151 | I50: 75 | J50: 50 | K50: 60 | L50: 30 | N50: 151
D51: ITBISA-IC-CD4017BE-DIP16 | E51: 46195 | F51: 684.887 | G51: 4794.209 | H51: 7 | I51: 3 | J51: 2 | K51: 2 | L51: 1 | N51: 7
D52: ITBISA-IC-CD4094BE-DIP16 | E52: 46198 | F52: 779.54 | G52: 6587113 | H52: 8450 | I52: 4225 | J52: 2816 | K52: 3380 | L52: 1690 | N52: 8450
D53: ITBISA-IC-CD4094BM-SMD-SOP16 | E53: 46195 | F53: 747.90909 | G53: 3343153.6 | H53: 4470 | I53: 2235 | J53: 1490 | K53: 1788 | L53: 894 | N53: 4470
D54: ITBISA-IC-CD4511BE-DIP16 | G54: 0
D55: ITBISA-IC-JRC4558D-DIP8 | E55: 46192 | F55: 552.99 | G55: 1373074.2 | H55: 2483 | I55: 1241 | J55: 827 | K55: 993 | L55: 496 | N55: 2483
D56: ITBISA-IC-L7805CV-TO220 | E56: 46195 | F56: 1140.72 | G56: 1140.72 | H56: 1 | I56: 0 | J56: 0 | K56: 0 | L56: 0 | N56: 1
D57: ITBISA-IC-L7809CV-TO220 | G57: 0
D58: ITBISA-IC-L7812CV-TO220 | E58: 46197 | F58: 1057 | G58: 1057 | H58: 1 | I58: 0 | J58: 0 | K58: 0 | L58: 0 | N58: 1
D59: ITBISA-IC-L7815CV-TO220 | G59: 0
D60: ITBISA-IC-LM741CN-DIP8 | F60: 1291.1 | G60: 1291.1 | H60: 1 | I60: 0 | J60: 0 | K60: 0 | L60: 0 | N60: 1
D61: ITBISA-IC-NE555P-DIP8 | E61: 46197 | F61: 476.82927 | G61: 185486.59 | H61: 389 | I61: 194 | J61: 129 | K61: 155 | L61: 77 | N61: 389
D62: ITBISA-IC-PC817-DIP4 | E62: 46198 | F62: 340.065 | G62: 1305509.5 | H62: 3839 | I62: 1919 | J62: 1279 | K62: 1535 | L62: 767 | N62: 3839
D63: ITBISA-IC-UA741CN-DIP8 | E63: 46198 | F63: 572 | G63: 787644 | H63: 1377 | I63: 688 | J63: 459 | K63: 550 | L63: 275 | N63: 1377
D64: ITBISA-IC-ULN2003AN-DIP16 | E64: 46196 | F64: 855.5 | G64: 1255018.5 | H64: 1467 | I64: 733 | J64: 489 | K64: 586 | L64: 293 | N64: 1467
D65: ITBISA-IC-ULN2803APG-DIP18 | E65: 46191 | F65: 1018 | G65: 1018 | H65: 1 | I65: 0 | J65: 0 | K65: 0 | L65: 0 | N65: 1
D66: ITBISA-IDC-2X5-AMPHENOL-FEMALE | E66: 46179 | F66: 369.94038 | G66: 723603.38 | H66: 1956 | I66: 978 | J66: 652 | K66: 782 | L66: 391 | N66: 1956
D67: ITBISA-IDC-2X5-AMPHENOL-MALE | E67: 46158 | F67: 585.4 | G67: 440220.8 | H67: 752 | I67: 376 | J67: 250 | K67: 300 | L67: 150 | N67: 752
D68: ITBISA-IGAME-GTX-1070-8GB-DDR5-X-TOP-TRIPLE-FAN | G68: 0
D69: ITBISA-INFRARED-1838 | E69: 46197 | F69: 607.75 | G69: 0
D70: ITBISA-JACK-DC-005-FEMALE | E70: 46198 | F70: 248.68687 | G70: 438186.26 | H70: 1762 | I70: 881 | J70: 587 | K70: 704 | L70: 352 | N70: 1762
D71: ITBISA-JUMPER-FF-10CM | E71: 46196 | F71: 90.005507 | G71: 500430.62 | H71: 5560 | I71: 2780 | J71: 1853 | K71: 2224 | L71: 1112 | N71: 5560
D72: ITBISA-JUMPER-FF-20CM | E72: 46196 | F72: 165.06 | G72: 1023372 | H72: 6200 | I72: 3100 | J72: 2066 | K72: 2480 | L72: 1240 | N72: 6200
D73: ITBISA-JUMPER-MF-10CM | E73: 46197 | F73: 165.05 | G73: 1089330 | H73: 6600 | I73: 3300 | J73: 2200 | K73: 2640 | L73: 1320 | N73: 6600
D74: ITBISA-JUMPER-MF-20CM | E74: 46196 | F74: 119.7 | G74: 545832 | H74: 4560 | I74: 2280 | J74: 1520 | K74: 1824 | L74: 912 | N74: 4560
D75: ITBISA-JUMPER-MM-10CM | E75: 46197 | F75: 110.87764 | G75: 385854.2 | H75: 3480 | I75: 1740 | J75: 1160 | K75: 1392 | L75: 696 | N75: 3480
D76: ITBISA-JUMPER-MM-20CM | E76: 46196 | F76: 187.38 | G76: 652082.4 | H76: 3480 | I76: 1740 | J76: 1160 | K76: 1392 | L76: 696 | N76: 3480
D77: ITBISA-KAPASITOR-ELCO-100UF-25V | E77: 46167 | F77: 101.13652 | G77: 201261.68 | H77: 1990 | I77: 995 | J77: 663 | K77: 796 | L77: 398 | N77: 1990
D78: ITBISA-KAPASITOR-ELCO-2200UF-25V | E78: 46190 | F78: 662.92581 | G78: 384496.97 | H78: 580 | I78: 290 | J78: 193 | K78: 232 | L78: 116 | N78: 580
D79: ITBISA-KAPASITOR-ELCO-47UF-50V | F79: 110.16657 | G79: 220333.14 | H79: 2000 | I79: 1000 | J79: 666 | K79: 800 | L79: 400 | N79: 2000
D80: ITBISA-KODE-UNIK | G80: 0
D81: ITBISA-KUPLUK-HITAM | G81: 0
D82: ITBISA-LCD-16X2-BLUE | E82: 46181 | F82: 9482.48 | G82: 246544.48 | H82: 26 | I82: 13 | J82: 8 | K82: 10 | L82: 5 | N82: 26
D83: ITBISA-LCD-16X2-GREEN | E83: 46181 | F83: 11611 | G83: 46444 | H83: 4 | I83: 2 | J83: 1 | K83: 1 | L83: 0 | N83: 4
D84: ITBISA-LDR-GL5516 | E84: 46192 | F84: 285.14 | G84: 20815.22 | H84: 73 | I84: 36 | J84: 24 | K84: 29 | L84: 14 | N84: 73
D85: ITBISA-LED-MAX7219-4IN1-GAP | F85: 36500 | G85: 182500 | H85: 5 | I85: 2 | J85: 1 | K85: 2 | L85: 1 | N85: 5
D86: ITBISA-LED-MAX7219-4IN1-TIGHT | E86: 46196 | F86: 35799.38 | G86: 2720752.9 | H86: 76 | I86: 38 | J86: 25 | K86: 30 | L86: 15 | N86: 76
D87: ITBISA-LED-SUPERBRIGHT-5MM-BLUE | E87: 46177 | F87: 58.82 | G87: 293041.24 | H87: 4982 | I87: 2491 | J87: 1660 | K87: 1992 | L87: 996 | N87: 4982
D88: ITBISA-LED-SUPERBRIGHT-5MM-GREEN | E88: 46196 | F88: 69.350746 | G88: 680261.47 | H88: 9809 | I88: 4904 | J88: 3269 | K88: 3923 | L88: 1961 | N88: 9809
D89: ITBISA-LED-SUPERBRIGHT-5MM-RED | E89: 46196 | F89: 52.64 | G89: 214771.2 | H89: 4080 | I89: 2040 | J89: 1360 | K89: 1632 | L89: 816 | N89: 4080
D90: ITBISA-LED-SUPERBRIGHT-5MM-WHITE | E90: 46188 | F90: 76.63 | G90: 132340.01 | H90: 1727 | I90: 863 | J90: 575 | K90: 690 | L90: 345 | N90: 1727
D91: ITBISA-LED-SUPERBRIGHT-5MM-YELLOW | E91: 46196 | F91: 66.67 | G91: 24467.89 | H91: 367 | I91: 183 | J91: 122 | K91: 146 | L91: 73 | N91: 367
D92: ITBISA-LOGITECH-F710 | G92: 0
D93: ITBISA-MICRO-SD-READER-MINI | G93: 0
D94: ITBISA-MOTORDRIVER-L298N-WITH-HEATSINK | G94: 0
D95: ITBISA-NODEMCU-ESP32-MICRO | G95: 0
D96: ITBISA-NODEMCU-ESP32-MICRO-30PIN | G96: 0
D97: ITBISA-NODEMCU-ESP32-MICRO-38PIN | G97: 0
D98: ITBISA-NODEMCU-V3-CH340G-ESP8266-MICRO | E98: 46193 | F98: 23261.03 | G98: 23261.03 | H98: 1 | I98: 0 | J98: 0 | K98: 0 | L98: 0 | N98: 1
D99: ITBISA-NPN-2N2222-TO92 | E99: 46193 | F99: 106.37 | G99: 1042106.9 | H99: 9797 | I99: 4898 | J99: 3265 | K99: 3918 | L99: 1959 | N99: 9797
D100: ITBISA-NPN-2N3904-TO92 | E100: 46193 | F100: 106.34 | G100: 235117.74 | H100: 2211 | I100: 1105 | J100: 737 | K100: 884 | L100: 442 | N100: 2211
...

Sheet BisaRekapGudangBackend
A1: {=SUMIF(IF(ROW(A3:B624),COLUMN(A3:B624)),COLUMN(A3:B624),A3:B624)} -> 7 | B1: 241714
A2: {={TRANSPOSE(UNIQUE(BisaRekapBarangBackend!A2:A624)); IF(BisaRekapBarangBackend!D2:D624="",,0 + SUMIF(BisaStok!A3:A624&BisaStok!D3:D624&(BisaStok!C3:C624>0),BisaRekapBarangBackend!D2:D624&TRANSPOSE(UNIQUE(BisaRekapBarangBackend!A2:A624))&TRUE,BisaStok!Q3:Q624) + SUMIF(BisaPindahBarang!B2:B624&BisaPindahBarang!C2:C624,BisaRekapBarangBackend!D2:D624&TRANSPOSE(UNIQUE(BisaRekapBarangBackend!A2:A624)),BisaPindahBarang!E2:E624) - SUMIF(BisaPindahBarang!B2:B624&BisaPindahBarang!D2:D624,BisaRekapBarangBackend!D2:D624&TRANSPOSE(UNIQUE(BisaRekapBarangBackend!A2:A624)),BisaPindahBarang!E2:E624) - SUMIF('Import-BisaJual'!A2:A624&'Import-BisaJual'!C2:C624,BisaRekapBarangBackend!D2:D624&TRANSPOSE(UNIQUE(BisaRekapBarangBackend!A2:A624)),'Import-BisaJual'!D2:D624) + SUMIF(BisaHilang!B2:B624&BisaHilang!G2:G624,BisaRekapBarangBackend!D2:D624&TRANSPOSE(UNIQUE(BisaRekapBarangBackend!A2:A624)),BisaHilang!C2:C624) - SUMIF(BisaHilang!B2:B624&BisaHilang!G2:G624,BisaRekapBarangBackend!D2:D624&TRANSPOSE(UNIQUE(BisaRekapBarangBackend!A2:A624)),BisaHilang!E2:E624) )}} -> KERTASARI CIAMIS | B2: KYAI KONTONG
A3: 0 | B3: 4242 | C3: 0
A4: 0 | B4: 2008 | C4: 0
A5: 0 | B5: 619 | C5: 0
A6: 0 | B6: 0 | C6: 0
A7: 0 | B7: 5 | C7: 0
A8: 0 | B8: 0 | C8: 0
A9: 0 | B9: 20 | C9: 0
A10: 0 | B10: 6 | C10: 0
A11: 0 | B11: 0 | C11: 0
A12: 0 | B12: 111 | C12: 0
A13: 0 | B13: 345 | C13: 0
A14: 0 | B14: 437 | C14: 0
... A218: 0 | B218: 0 | C218: 0

Sheet Import-BisaJual
A1: =IFERROR(__xludf.DUMMYFUNCTION("ARRAYFORMULA({IF(IMPORTRANGE(""https://docs.google.com/spreadsheets/d/1t2pimo7Ih4U-zR6WGfj6GlQekm62EvrCvE7VaN8UNxA"",""Ekspor-BisaJual-BisaStok!A1:H1"")="""",, IMPORTRANGE(""https://docs.google.com/spreadsheets/d/1t2pimo7Ih4U-zR6WGfj6GlQekm62EvrCvE7VaN8UN"&"xA"",""Ekspor-BisaJual-BisaStok!A1:H1"")); SORT(IF(IMPORTRANGE(""https://docs.google.com/spreadsheets/d/1t2pimo7Ih4U-zR6WGfj6GlQekm62EvrCvE7VaN8UNxA"",""Ekspor-BisaJual-BisaStok!A2:H"")="""",, IMPORTRANGE(""https://docs.google.com/spreadsheets/d/1t2pimo7I"&"h4U-zR6WGfj6GlQekm62EvrCvE7VaN8UNxA"",""Ekspor-BisaJual-BisaStok!A2:H"")))})"),"SKU") -> SKU | B1: =IFERROR(__xludf.DUMMYFUNCTION("""COMPUTED_VALUE"""),"Tanggal") -> Tanggal | C1: =IFERROR(__xludf.DUMMYFUNCTION("""COMPUTED_VALUE"""),"Lokasi Gudang") -> Lokasi Gudang | D1: =IFERROR(__xludf.DUMMYFUNCTION("""COMPUTED_VALUE"""),"Banyak Terjual (Buah)") -> Banyak Terjual (Buah)
A2: =IFERROR(__xludf.DUMMYFUNCTION("""COMPUTED_VALUE"""),"ITBISA-7SEGMENT-ANODE-RED-0.56-1BIT") -> ITBISA-7SEGMENT-ANODE-RED-0.56-1BIT | B2: =IFERROR(__xludf.DUMMYFUNCTION("""COMPUTED_VALUE"""),45871.0) -> 45871 | C2: =IFERROR(__xludf.DUMMYFUNCTION("""COMPUTED_VALUE"""),"KERTASARI CIAMIS") -> KERTASARI CIAMIS | D2: =IFERROR(__xludf.DUMMYFUNCTION("""COMPUTED_VALUE"""),60.0) -> 60
A3: =IFERROR(__xludf.DUMMYFUNCTION("""COMPUTED_VALUE"""),"ITBISA-7SEGMENT-ANODE-RED-0.56-1BIT") -> ITBISA-7SEGMENT-ANODE-RED-0.56-1BIT | B3: =IFERROR(__xludf.DUMMYFUNCTION("""COMPUTED_VALUE"""),46026.0) -> 46026 | C3: =IFERROR(__xludf.DUMMYFUNCTION("""COMPUTED_VALUE"""),"KYAI KONTONG") -> KYAI KONTONG | D3: =IFERROR(__xludf.DUMMYFUNCTION("""COMPUTED_VALUE"""),10.0) -> 10
A4: =IFERROR(__xludf.DUMMYFUNCTION("""COMPUTED_VALUE"""),"ITBISA-7SEGMENT-ANODE-RED-0.56-1BIT") -> ITBISA-7SEGMENT-ANODE-RED-0.56-1BIT | B4: =IFERROR(__xludf.DUMMYFUNCTION("""COMPUTED_VALUE"""),46028.0) -> 46028 | C4: =IFERROR(__xludf.DUMMYFUNCTION("""COMPUTED_VALUE"""),"KYAI KONTONG") -> KYAI KONTONG | D4: =IFERROR(__xludf.DUMMYFUNCTION("""COMPUTED_VALUE"""),20.0) -> 20
A5: =IFERROR(__xludf.DUMMYFUNCTION("""COMPUTED_VALUE"""),"ITBISA-7SEGMENT-ANODE-RED-0.56-1BIT") -> ITBISA-7SEGMENT-ANODE-RED-0.56-1BIT | B5: =IFERROR(__xludf.DUMMYFUNCTION("""COMPUTED_VALUE"""),46034.0) -> 46034 | C5: =IFERROR(__xludf.DUMMYFUNCTION("""COMPUTED_VALUE"""),"KYAI KONTONG") -> KYAI KONTONG | D5: =IFERROR(__xludf.DUMMYFUNCTION("""COMPUTED_VALUE"""),50.0) -> 50
A6: =IFERROR(__xludf.DUMMYFUNCTION("""COMPUTED_VALUE"""),"ITBISA-7SEGMENT-ANODE-RED-0.56-1BIT") -> ITBISA-7SEGMENT-ANODE-RED-0.56-1BIT | B6: =IFERROR(__xludf.DUMMYFUNCTION("""COMPUTED_VALUE"""),46036.0) -> 46036 | C6: =IFERROR(__xludf.DUMMYFUNCTION("""COMPUTED_VALUE"""),"KYAI KONTONG") -> KYAI KONTONG | D6: =IFERROR(__xludf.DUMMYFUNCTION("""COMPUTED_VALUE"""),30.0) -> 30
A7: =IFERROR(__xludf.DUMMYFUNCTION("""COMPUTED_VALUE"""),"ITBISA-7SEGMENT-ANODE-RED-0.56-1BIT") -> ITBISA-7SEGMENT-ANODE-RED-0.56-1BIT | B7: =IFERROR(__xludf.DUMMYFUNCTION("""COMPUTED_VALUE"""),46036.0) -> 46036 | C7: =IFERROR(__xludf.DUMMYFUNCTION("""COMPUTED_VALUE"""),"KYAI KONTONG") -> KYAI KONTONG | D7: =IFERROR(__xludf.DUMMYFUNCTION("""COMPUTED_VALUE"""),30.0) -> 30
A8: =IFERROR(__xludf.DUMMYFUNCTION("""COMPUTED_VALUE"""),"ITBISA-7SEGMENT-ANODE-RED-0.56-1BIT") -> ITBISA-7SEGMENT-ANODE-RED-0.56-1BIT | B8: =IFERROR(__xludf.DUMMYFUNCTION("""COMPUTED_VALUE"""),46042.0) -> 46042 | C8: =IFERROR(__xludf.DUMMYFUNCTION("""COMPUTED_VALUE"""),"KYAI KONTONG") -> KYAI KONTONG | D8: =IFERROR(__xludf.DUMMYFUNCTION("""COMPUTED_VALUE"""),200.0) -> 200
A9: =IFERROR(__xludf.DUMMYFUNCTION("""COMPUTED_VALUE"""),"ITBISA-7SEGMENT-ANODE-RED-0.56-1BIT") -> ITBISA-7SEGMENT-ANODE-RED-0.56-1BIT | B9: =IFERROR(__xludf.DUMMYFUNCTION("""COMPUTED_VALUE"""),46043.0) -> 46043 | C9: =IFERROR(__xludf.DUMMYFUNCTION("""COMPUTED_VALUE"""),"KYAI KONTONG") -> KYAI KONTONG | D9: =IFERROR(__xludf.DUMMYFUNCTION("""COMPUTED_VALUE"""),10.0) -> 10
A10: =IFERROR(__xludf.DUMMYFUNCTION("""COMPUTED_VALUE"""),"ITBISA-7SEGMENT-ANODE-RED-0.56-1BIT") -> ITBISA-7SEGMENT-ANODE-RED-0.56-1BIT | B10: =IFERROR(__xludf.DUMMYFUNCTION("""COMPUTED_VALUE"""),46044.0) -> 46044 | C10: =IFERROR(__xludf.DUMMYFUNCTION("""COMPUTED_VALUE"""),"KYAI KONTONG") -> KYAI KONTONG | D10: =IFERROR(__xludf.DUMMYFUNCTION("""COMPUTED_VALUE"""),10.0) -> 10
A11: =IFERROR(__xludf.DUMMYFUNCTION("""COMPUTED_VALUE"""),"ITBISA-7SEGMENT-ANODE-RED-0.56-1BIT") -> ITBISA-7SEGMENT-ANODE-RED-0.56-1BIT | B11: =IFERROR(__xludf.DUMMYFUNCTION("""COMPUTED_VALUE"""),46044.0) -> 46044 | C11: =IFERROR(__xludf.DUMMYFUNCTION("""COMPUTED_VALUE"""),"KYAI KONTONG") -> KYAI KONTONG | D11: =IFERROR(__xludf.DUMMYFUNCTION("""COMPUTED_VALUE"""),80.0) -> 80
A12: =IFERROR(__xludf.DUMMYFUNCTION("""COMPUTED_VALUE"""),"ITBISA-7SEGMENT-ANODE-RED-0.56-1BIT") -> ITBISA-7SEGMENT-ANODE-RED-0.56-1BIT | B12: =IFERROR(__xludf.DUMMYFUNCTION("""COMPUTED_VALUE"""),46044.0) -> 46044 | C12: =IFERROR(__xludf.DUMMYFUNCTION("""COMPUTED_VALUE"""),"KYAI KONTONG") -> KYAI KONTONG | D12: =IFERROR(__xludf.DUMMYFUNCTION("""COMPUTED_VALUE"""),150.0) -> 150
A13: =IFERROR(__xludf.DUMMYFUNCTION("""COMPUTED_VALUE"""),"ITBISA-7SEGMENT-ANODE-RED-0.56-1BIT") -> ITBISA-7SEGMENT-ANODE-RED-0.56-1BIT | B13: =IFERROR(__xludf.DUMMYFUNCTION("""COMPUTED_VALUE"""),46060.0) -> 46060 | C13: =IFERROR(__xludf.DUMMYFUNCTION("""COMPUTED_VALUE"""),"KYAI KONTONG") -> KYAI KONTONG | D13: =IFERROR(__xludf.DUMMYFUNCTION("""COMPUTED_VALUE"""),60.0) -> 60
A14: =IFERROR(__xludf.DUMMYFUNCTION("""COMPUTED_VALUE"""),"ITBISA-7SEGMENT-ANODE-RED-0.56-1BIT") -> ITBISA-7SEGMENT-ANODE-RED-0.56-1BIT | B14: =IFERROR(__xludf.DUMMYFUNCTION("""COMPUTED_VALUE"""),46063.0) -> 46063 | C14: =IFERROR(__xludf.DUMMYFUNCTION("""COMPUTED_VALUE"""),"KYAI KONTONG") -> KYAI KONTONG | D14: =IFERROR(__xludf.DUMMYFUNCTION("""COMPUTED_VALUE"""),10.0) -> 10
A15: =IFERROR(__xludf.DUMMYFUNCTION("""COMPUTED_VALUE"""),"ITBISA-7SEGMENT-ANODE-RED-0.56-1BIT") -> ITBISA-7SEGMENT-ANODE-RED-0.56-1BIT | B15: =IFERROR(__xludf.DUMMYFUNCTION("""COMPUTED_VALUE"""),46065.0) -> 46065 | C15: =IFERROR(__xludf.DUMMYFUNCTION("""COMPUTED_VALUE"""),"KYAI KONTONG") -> KYAI KONTONG | D15: =IFERROR(__xludf.DUMMYFUNCTION("""COMPUTED_VALUE"""),60.0) -> 60
A16: =IFERROR(__xludf.DUMMYFUNCTION("""COMPUTED_VALUE"""),"ITBISA-7SEGMENT-ANODE-RED-0.56-1BIT") -> ITBISA-7SEGMENT-ANODE-RED-0.56-1BIT | B16: =IFERROR(__xludf.DUMMYFUNCTION("""COMPUTED_VALUE"""),46065.0) -> 46065 | C16: =IFERROR(__xludf.DUMMYFUNCTION("""COMPUTED_VALUE"""),"KYAI KONTONG") -> KYAI KONTONG | D16: =IFERROR(__xludf.DUMMYFUNCTION("""COMPUTED_VALUE"""),300.0) -> 300
A17: =IFERROR(__xludf.DUMMYFUNCTION("""COMPUTED_VALUE"""),"ITBISA-7SEGMENT-ANODE-RED-0.56-1BIT") -> ITBISA-7SEGMENT-ANODE-RED-0.56-1BIT | B17: =IFERROR(__xludf.DUMMYFUNCTION("""COMPUTED_VALUE"""),46067.0) -> 46067 | C17: =IFERROR(__xludf.DUMMYFUNCTION("""COMPUTED_VALUE"""),"KYAI KONTONG") -> KYAI KONTONG | D17: =IFERROR(__xludf.DUMMYFUNCTION("""COMPUTED_VALUE"""),12.0) -> 12
A18: =IFERROR(__xludf.DUMMYFUNCTION("""COMPUTED_VALUE"""),"ITBISA-7SEGMENT-ANODE-RED-0.56-1BIT") -> ITBISA-7SEGMENT-ANODE-RED-0.56-1BIT | B18: =IFERROR(__xludf.DUMMYFUNCTION("""COMPUTED_VALUE"""),46068.0) -> 46068 | C18: =IFERROR(__xludf.DUMMYFUNCTION("""COMPUTED_VALUE"""),"KYAI KONTONG") -> KYAI KONTONG | D18: =IFERROR(__xludf.DUMMYFUNCTION("""COMPUTED_VALUE"""),30.0) -> 30
A19: =IFERROR(__xludf.DUMMYFUNCTION("""COMPUTED_VALUE"""),"ITBISA-7SEGMENT-ANODE-RED-0.56-1BIT") -> ITBISA-7SEGMENT-ANODE-RED-0.56-1BIT | B19: =IFERROR(__xludf.DUMMYFUNCTION("""COMPUTED_VALUE"""),46077.0) -> 46077 | C19: =IFERROR(__xludf.DUMMYFUNCTION("""COMPUTED_VALUE"""),"KERTASARI CIAMIS") -> KERTASARI CIAMIS | D19: =IFERROR(__xludf.DUMMYFUNCTION("""COMPUTED_VALUE"""),272.0) -> 272
A20: =IFERROR(__xludf.DUMMYFUNCTION("""COMPUTED_VALUE"""),"ITBISA-7SEGMENT-ANODE-RED-0.56-1BIT") -> ITBISA-7SEGMENT-ANODE-RED-0.56-1BIT | B20: =IFERROR(__xludf.DUMMYFUNCTION("""COMPUTED_VALUE"""),46083.0) -> 46083 | C20: =IFERROR(__xludf.DUMMYFUNCTION("""COMPUTED_VALUE"""),"KYAI KONTONG") -> KYAI KONTONG | D20: =IFERROR(__xludf.DUMMYFUNCTION("""COMPUTED_VALUE"""),10.0) -> 10
A21: =IFERROR(__xludf.DUMMYFUNCTION("""COMPUTED_VALUE"""),"ITBISA-7SEGMENT-ANODE-RED-0.56-1BIT") -> ITBISA-7SEGMENT-ANODE-RED-0.56-1BIT | B21: =IFERROR(__xludf.DUMMYFUNCTION("""COMPUTED_VALUE"""),46115.0) -> 46115 | C21: =IFERROR(__xludf.DUMMYFUNCTION("""COMPUTED_VALUE"""),"KYAI KONTONG") -> KYAI KONTONG | D21: =IFERROR(__xludf.DUMMYFUNCTION("""COMPUTED_VALUE"""),320.0) -> 320
A22: =IFERROR(__xludf.DUMMYFUNCTION("""COMPUTED_VALUE"""),"ITBISA-7SEGMENT-ANODE-RED-0.56-1BIT") -> ITBISA-7SEGMENT-ANODE-RED-0.56-1BIT | B22: =IFERROR(__xludf.DUMMYFUNCTION("""COMPUTED_VALUE"""),46120.0) -> 46120 | C22: =IFERROR(__xludf.DUMMYFUNCTION("""COMPUTED_VALUE"""),"KYAI KONTONG") -> KYAI KONTONG | D22: =IFERROR(__xludf.DUMMYFUNCTION("""COMPUTED_VALUE"""),10.0) -> 10
A23: =IFERROR(__xludf.DUMMYFUNCTION("""COMPUTED_VALUE"""),"ITBISA-7SEGMENT-ANODE-RED-0.56-1BIT") -> ITBISA-7SEGMENT-ANODE-RED-0.56-1BIT | B23: =IFERROR(__xludf.DUMMYFUNCTION("""COMPUTED_VALUE"""),46125.0) -> 46125 | C23: =IFERROR(__xludf.DUMMYFUNCTION("""COMPUTED_VALUE"""),"KYAI KONTONG") -> KYAI KONTONG | D23: =IFERROR(__xludf.DUMMYFUNCTION("""COMPUTED_VALUE"""),10.0) -> 10
A24: =IFERROR(__xludf.DUMMYFUNCTION("""COMPUTED_VALUE"""),"ITBISA-7SEGMENT-ANODE-RED-0.56-1BIT") -> ITBISA-7SEGMENT-ANODE-RED-0.56-1BIT | B24: =IFERROR(__xludf.DUMMYFUNCTION("""COMPUTED_VALUE"""),46128.0) -> 46128 | C24: =IFERROR(__xludf.DUMMYFUNCTION("""COMPUTED_VALUE"""),"KYAI KONTONG") -> KYAI KONTONG | D24: =IFERROR(__xludf.DUMMYFUNCTION("""COMPUTED_VALUE"""),10.0) -> 10
A25: =IFERROR(__xludf.DUMMYFUNCTION("""COMPUTED_VALUE"""),"ITBISA-7SEGMENT-ANODE-RED-0.56-1BIT") -> ITBISA-7SEGMENT-ANODE-RED-0.56-1BIT | B25: =IFERROR(__xludf.DUMMYFUNCTION("""COMPUTED_VALUE"""),46128.0) -> 46128 | C25: =IFERROR(__xludf.DUMMYFUNCTION("""COMPUTED_VALUE"""),"KYAI KONTONG") -> KYAI KONTONG | D25: =IFERROR(__xludf.DUMMYFUNCTION("""COMPUTED_VALUE"""),80.0) -> 80
A26: =IFERROR(__xludf.DUMMYFUNCTION("""COMPUTED_VALUE"""),"ITBISA-7SEGMENT-ANODE-RED-0.56-1BIT") -> ITBISA-7SEGMENT-ANODE-RED-0.56-1BIT | B26: =IFERROR(__xludf.DUMMYFUNCTION("""COMPUTED_VALUE"""),46140.0) -> 46140 | C26: =IFERROR(__xludf.DUMMYFUNCTION("""COMPUTED_VALUE"""),"KYAI KONTONG") -> KYAI KONTONG | D26: =IFERROR(__xludf.DUMMYFUNCTION("""COMPUTED_VALUE"""),40.0) -> 40
A27: =IFERROR(__xludf.DUMMYFUNCTION("""COMPUTED_VALUE"""),"ITBISA-7SEGMENT-ANODE-RED-0.56-1BIT") -> ITBISA-7SEGMENT-ANODE-RED-0.56-1BIT | B27: =IFERROR(__xludf.DUMMYFUNCTION("""COMPUTED_VALUE"""),46144.0) -> 46144 | C27: =IFERROR(__xludf.DUMMYFUNCTION("""COMPUTED_VALUE"""),"KYAI KONTONG") -> KYAI KONTONG | D27: =IFERROR(__xludf.DUMMYFUNCTION("""COMPUTED_VALUE"""),10.0) -> 10
A28: =IFERROR(__xludf.DUMMYFUNCTION("""COMPUTED_VALUE"""),"ITBISA-7SEGMENT-ANODE-RED-0.56-1BIT") -> ITBISA-7SEGMENT-ANODE-RED-0.56-1BIT | B28: =IFERROR(__xludf.DUMMYFUNCTION("""COMPUTED_VALUE"""),46147.0) -> 46147 | C28: =IFERROR(__xludf.DUMMYFUNCTION("""COMPUTED_VALUE"""),"KYAI KONTONG") -> KYAI KONTONG | D28: =IFERROR(__xludf.DUMMYFUNCTION("""COMPUTED_VALUE"""),10.0) -> 10
A29: =IFERROR(__xludf.DUMMYFUNCTION("""COMPUTED_VALUE"""),"ITBISA-7SEGMENT-ANODE-RED-0.56-1BIT") -> ITBISA-7SEGMENT-ANODE-RED-0.56-1BIT | B29: =IFERROR(__xludf.DUMMYFUNCTION("""COMPUTED_VALUE"""),46156.0) -> 46156 | C29: =IFERROR(__xludf.DUMMYFUNCTION("""COMPUTED_VALUE"""),"KYAI KONTONG") -> KYAI KONTONG | D29: =IFERROR(__xludf.DUMMYFUNCTION("""COMPUTED_VALUE"""),10.0) -> 10
A30: =IFERROR(__xludf.DUMMYFUNCTION("""COMPUTED_VALUE"""),"ITBISA-7SEGMENT-ANODE-RED-0.56-1BIT") -> ITBISA-7SEGMENT-ANODE-RED-0.56-1BIT | B30: =IFERROR(__xludf.DUMMYFUNCTION("""COMPUTED_VALUE"""),46157.0) -> 46157 | C30: =IFERROR(__xludf.DUMMYFUNCTION("""COMPUTED_VALUE"""),"KYAI KONTONG") -> KYAI KONTONG | D30: =IFERROR(__xludf.DUMMYFUNCTION("""COMPUTED_VALUE"""),50.0) -> 50
A31: =IFERROR(__xludf.DUMMYFUNCTION("""COMPUTED_VALUE"""),"ITBISA-7SEGMENT-ANODE-RED-0.56-1BIT") -> ITBISA-7SEGMENT-ANODE-RED-0.56-1BIT | B31: =IFERROR(__xludf.DUMMYFUNCTION("""COMPUTED_VALUE"""),46158.0) -> 46158 | C31: =IFERROR(__xludf.DUMMYFUNCTION("""COMPUTED_VALUE"""),"KYAI KONTONG") -> KYAI KONTONG | D31: =IFERROR(__xludf.DUMMYFUNCTION("""COMPUTED_VALUE"""),20.0) -> 20
A32: =IFERROR(__xludf.DUMMYFUNCTION("""COMPUTED_VALUE"""),"ITBISA-7SEGMENT-ANODE-RED-0.56-1BIT") -> ITBISA-7SEGMENT-ANODE-RED-0.56-1BIT | B32: =IFERROR(__xludf.DUMMYFUNCTION("""COMPUTED_VALUE"""),46160.0) -> 46160 | C32: =IFERROR(__xludf.DUMMYFUNCTION("""COMPUTED_VALUE"""),"KYAI KONTONG") -> KYAI KONTONG | D32: =IFERROR(__xludf.DUMMYFUNCTION("""COMPUTED_VALUE"""),10.0) -> 10
A33: =IFERROR(__xludf.DUMMYFUNCTION("""COMPUTED_VALUE"""),"ITBISA-7SEGMENT-ANODE-RED-0.56-1BIT") -> ITBISA-7SEGMENT-ANODE-RED-0.56-1BIT | B33: =IFERROR(__xludf.DUMMYFUNCTION("""COMPUTED_VALUE"""),46163.0) -> 46163 | C33: =IFERROR(__xludf.DUMMYFUNCTION("""COMPUTED_VALUE"""),"KYAI KONTONG") -> KYAI KONTONG | D33: =IFERROR(__xludf.DUMMYFUNCTION("""COMPUTED_VALUE"""),10.0) -> 10
A34: =IFERROR(__xludf.DUMMYFUNCTION("""COMPUTED_VALUE"""),"ITBISA-7SEGMENT-ANODE-RED-0.56-1BIT") -> ITBISA-7SEGMENT-ANODE-RED-0.56-1BIT | B34: =IFERROR(__xludf.DUMMYFUNCTION("""COMPUTED_VALUE"""),46170.0) -> 46170 | C34: =IFERROR(__xludf.DUMMYFUNCTION("""COMPUTED_VALUE"""),"KYAI KONTONG") -> KYAI KONTONG | D34: =IFERROR(__xludf.DUMMYFUNCTION("""COMPUTED_VALUE"""),20.0) -> 20
A35: =IFERROR(__xludf.DUMMYFUNCTION("""COMPUTED_VALUE"""),"ITBISA-7SEGMENT-ANODE-RED-0.56-1BIT") -> ITBISA-7SEGMENT-ANODE-RED-0.56-1BIT | B35: =IFERROR(__xludf.DUMMYFUNCTION("""COMPUTED_VALUE"""),46172.0) -> 46172 | C35: =IFERROR(__xludf.DUMMYFUNCTION("""COMPUTED_VALUE"""),"KYAI KONTONG") -> KYAI KONTONG | D35: =IFERROR(__xludf.DUMMYFUNCTION("""COMPUTED_VALUE"""),500.0) -> 500
A36: =IFERROR(__xludf.DUMMYFUNCTION("""COMPUTED_VALUE"""),"ITBISA-7SEGMENT-ANODE-RED-0.56-1BIT") -> ITBISA-7SEGMENT-ANODE-RED-0.56-1BIT | B36: =IFERROR(__xludf.DUMMYFUNCTION("""COMPUTED_VALUE"""),46175.0) -> 46175 | C36: =IFERROR(__xludf.DUMMYFUNCTION("""COMPUTED_VALUE"""),"KYAI KONTONG") -> KYAI KONTONG | D36: =IFERROR(__xludf.DUMMYFUNCTION("""COMPUTED_VALUE"""),6.0) -> 6
A37: =IFERROR(__xludf.DUMMYFUNCTION("""COMPUTED_VALUE"""),"ITBISA-7SEGMENT-ANODE-RED-0.56-1BIT") -> ITBISA-7SEGMENT-ANODE-RED-0.56-1BIT | B37: =IFERROR(__xludf.DUMMYFUNCTION("""COMPUTED_VALUE"""),46177.0) -> 46177 | C37: =IFERROR(__xludf.DUMMYFUNCTION("""COMPUTED_VALUE"""),"KYAI KONTONG") -> KYAI KONTONG | D37: =IFERROR(__xludf.DUMMYFUNCTION("""COMPUTED_VALUE"""),7.0) -> 7
A38: =IFERROR(__xludf.DUMMYFUNCTION("""COMPUTED_VALUE"""),"ITBISA-7SEGMENT-ANODE-RED-0.56-1BIT") -> ITBISA-7SEGMENT-ANODE-RED-0.56-1BIT | B38: =IFERROR(__xludf.DUMMYFUNCTION("""COMPUTED_VALUE"""),46178.0) -> 46178 | C38: =IFERROR(__xludf.DUMMYFUNCTION("""COMPUTED_VALUE"""),"KYAI KONTONG") -> KYAI KONTONG | D38: =IFERROR(__xludf.DUMMYFUNCTION("""COMPUTED_VALUE"""),7.0) -> 7
A39: =IFERROR(__xludf.DUMMYFUNCTION("""COMPUTED_VALUE"""),"ITBISA-7SEGMENT-ANODE-RED-0.56-1BIT") -> ITBISA-7SEGMENT-ANODE-RED-0.56-1BIT | B39: =IFERROR(__xludf.DUMMYFUNCTION("""COMPUTED_VALUE"""),46178.0) -> 46178 | C39: =IFERROR(__xludf.DUMMYFUNCTION("""COMPUTED_VALUE"""),"KYAI KONTONG") -> KYAI KONTONG | D39: =IFERROR(__xludf.DUMMYFUNCTION("""COMPUTED_VALUE"""),10.0) -> 10
A40: =IFERROR(__xludf.DUMMYFUNCTION("""COMPUTED_VALUE"""),"ITBISA-7SEGMENT-ANODE-RED-0.56-1BIT") -> ITBISA-7SEGMENT-ANODE-RED-0.56-1BIT | B40: =IFERROR(__xludf.DUMMYFUNCTION("""COMPUTED_VALUE"""),46182.0) -> 46182 | C40: =IFERROR(__xludf.DUMMYFUNCTION("""COMPUTED_VALUE"""),"KYAI KONTONG") -> KYAI KONTONG | D40: =IFERROR(__xludf.DUMMYFUNCTION("""COMPUTED_VALUE"""),7.0) -> 7
A41: =IFERROR(__xludf.DUMMYFUNCTION("""COMPUTED_VALUE"""),"ITBISA-7SEGMENT-ANODE-RED-0.56-1BIT") -> ITBISA-7SEGMENT-ANODE-RED-0.56-1BIT | B41: =IFERROR(__xludf.DUMMYFUNCTION("""COMPUTED_VALUE"""),46183.0) -> 46183 | C41: =IFERROR(__xludf.DUMMYFUNCTION("""COMPUTED_VALUE"""),"KYAI KONTONG") -> KYAI KONTONG | D41: =IFERROR(__xludf.DUMMYFUNCTION("""COMPUTED_VALUE"""),100.0) -> 100
A42: =IFERROR(__xludf.DUMMYFUNCTION("""COMPUTED_VALUE"""),"ITBISA-7SEGMENT-ANODE-RED-0.56-1BIT") -> ITBISA-7SEGMENT-ANODE-RED-0.56-1BIT | B42: =IFERROR(__xludf.DUMMYFUNCTION("""COMPUTED_VALUE"""),46184.0) -> 46184 | C42: =IFERROR(__xludf.DUMMYFUNCTION("""COMPUTED_VALUE"""),"KYAI KONTONG") -> KYAI KONTONG | D42: =IFERROR(__xludf.DUMMYFUNCTION("""COMPUTED_VALUE"""),20.0) -> 20
A43: =IFERROR(__xludf.DUMMYFUNCTION("""COMPUTED_VALUE"""),"ITBISA-7SEGMENT-ANODE-RED-0.56-1BIT") -> ITBISA-7SEGMENT-ANODE-RED-0.56-1BIT | B43: =IFERROR(__xludf.DUMMYFUNCTION("""COMPUTED_VALUE"""),46184.0) -> 46184 | C43: =IFERROR(__xludf.DUMMYFUNCTION("""COMPUTED_VALUE"""),"KYAI KONTONG") -> KYAI KONTONG | D43: =IFERROR(__xludf.DUMMYFUNCTION("""COMPUTED_VALUE"""),30.0) -> 30
A44: =IFERROR(__xludf.DUMMYFUNCTION("""COMPUTED_VALUE"""),"ITBISA-7SEGMENT-ANODE-RED-0.56-1BIT") -> ITBISA-7SEGMENT-ANODE-RED-0.56-1BIT | B44: =IFERROR(__xludf.DUMMYFUNCTION("""COMPUTED_VALUE"""),46187.0) -> 46187 | C44: =IFERROR(__xludf.DUMMYFUNCTION("""COMPUTED_VALUE"""),"KYAI KONTONG") -> KYAI KONTONG | D44: =IFERROR(__xludf.DUMMYFUNCTION("""COMPUTED_VALUE"""),7.0) -> 7
A45: =IFERROR(__xludf.DUMMYFUNCTION("""COMPUTED_VALUE"""),"ITBISA-7SEGMENT-ANODE-RED-0.56-1BIT") -> ITBISA-7SEGMENT-ANODE-RED-0.56-1BIT | B45: =IFERROR(__xludf.DUMMYFUNCTION("""COMPUTED_VALUE"""),46188.0) -> 46188 | C45: =IFERROR(__xludf.DUMMYFUNCTION("""COMPUTED_VALUE"""),"KYAI KONTONG") -> KYAI KONTONG | D45: =IFERROR(__xludf.DUMMYFUNCTION("""COMPUTED_VALUE"""),7.0) -> 7
A46: =IFERROR(__xludf.DUMMYFUNCTION("""COMPUTED_VALUE"""),"ITBISA-7SEGMENT-ANODE-RED-0.56-1BIT") -> ITBISA-7SEGMENT-ANODE-RED-0.56-1BIT | B46: =IFERROR(__xludf.DUMMYFUNCTION("""COMPUTED_VALUE"""),46189.0) -> 46189 | C46: =IFERROR(__xludf.DUMMYFUNCTION("""COMPUTED_VALUE"""),"KYAI KONTONG") -> KYAI KONTONG | D46: =IFERROR(__xludf.DUMMYFUNCTION("""COMPUTED_VALUE"""),40.0) -> 40
A47: =IFERROR(__xludf.DUMMYFUNCTION("""COMPUTED_VALUE"""),"ITBISA-7SEGMENT-ANODE-RED-0.56-1BIT") -> ITBISA-7SEGMENT-ANODE-RED-0.56-1BIT | B47: =IFERROR(__xludf.DUMMYFUNCTION("""COMPUTED_VALUE"""),46193.0) -> 46193 | C47: =IFERROR(__xludf.DUMMYFUNCTION("""COMPUTED_VALUE"""),"KYAI KONTONG") -> KYAI KONTONG | D47: =IFERROR(__xludf.DUMMYFUNCTION("""COMPUTED_VALUE"""),50.0) -> 50
A48: =IFERROR(__xludf.DUMMYFUNCTION("""COMPUTED_VALUE"""),"ITBISA-7SEGMENT-ANODE-RED-0.56-1BIT") -> ITBISA-7SEGMENT-ANODE-RED-0.56-1BIT | B48: =IFERROR(__xludf.DUMMYFUNCTION("""COMPUTED_VALUE"""),46194.0) -> 46194 | C48: =IFERROR(__xludf.DUMMYFUNCTION("""COMPUTED_VALUE"""),"KYAI KONTONG") -> KYAI KONTONG | D48: =IFERROR(__xludf.DUMMYFUNCTION("""COMPUTED_VALUE"""),30.0) -> 30
A49: =IFERROR(__xludf.DUMMYFUNCTION("""COMPUTED_VALUE"""),"ITBISA-7SEGMENT-ANODE-RED-0.56-1BIT") -> ITBISA-7SEGMENT-ANODE-RED-0.56-1BIT | B49: =IFERROR(__xludf.DUMMYFUNCTION("""COMPUTED_VALUE"""),46196.0) -> 46196 | C49: =IFERROR(__xludf.DUMMYFUNCTION("""COMPUTED_VALUE"""),"KYAI KONTONG") -> KYAI KONTONG | D49: =IFERROR(__xludf.DUMMYFUNCTION("""COMPUTED_VALUE"""),40.0) -> 40
A50: =IFERROR(__xludf.DUMMYFUNCTION("""COMPUTED_VALUE"""),"ITBISA-7SEGMENT-ANODE-RED-0.56-1BIT") -> ITBISA-7SEGMENT-ANODE-RED-0.56-1BIT | B50: =IFERROR(__xludf.DUMMYFUNCTION("""COMPUTED_VALUE"""),46197.0) -> 46197 | C50: =IFERROR(__xludf.DUMMYFUNCTION("""COMPUTED_VALUE"""),"KYAI KONTONG") -> KYAI KONTONG | D50: =IFERROR(__xludf.DUMMYFUNCTION("""COMPUTED_VALUE"""),10.0) -> 10
A51: =IFERROR(__xludf.DUMMYFUNCTION("""COMPUTED_VALUE"""),"ITBISA-7SEGMENT-ANODE-RED-0.56-1BIT") -> ITBISA-7SEGMENT-ANODE-RED-0.56-1BIT | B51: =IFERROR(__xludf.DUMMYFUNCTION("""COMPUTED_VALUE"""),46197.0) -> 46197 | C51: =IFERROR(__xludf.DUMMYFUNCTION("""COMPUTED_VALUE"""),"KYAI KONTONG") -> KYAI KONTONG | D51: =IFERROR(__xludf.DUMMYFUNCTION("""COMPUTED_VALUE"""),18.0) -> 18
A52: =IFERROR(__xludf.DUMMYFUNCTION("""COMPUTED_VALUE"""),"ITBISA-7SEGMENT-ANODE-RED-1.00-1BIT") -> ITBISA-7SEGMENT-ANODE-RED-1.00-1BIT | B52: =IFERROR(__xludf.DUMMYFUNCTION("""COMPUTED_VALUE"""),45871.0) -> 45871 | C52: =IFERROR(__xludf.DUMMYFUNCTION("""COMPUTED_VALUE"""),"KERTASARI CIAMIS") -> KERTASARI CIAMIS | D52: =IFERROR(__xludf.DUMMYFUNCTION("""COMPUTED_VALUE"""),30.0) -> 30
A53: =IFERROR(__xludf.DUMMYFUNCTION("""COMPUTED_VALUE"""),"ITBISA-7SEGMENT-ANODE-RED-1.00-1BIT") -> ITBISA-7SEGMENT-ANODE-RED-1.00-1BIT | B53: =IFERROR(__xludf.DUMMYFUNCTION("""COMPUTED_VALUE"""),46034.0) -> 46034 | C53: =IFERROR(__xludf.DUMMYFUNCTION("""COMPUTED_VALUE"""),"KYAI KONTONG") -> KYAI KONTONG | D53: =IFERROR(__xludf.DUMMYFUNCTION("""COMPUTED_VALUE"""),10.0) -> 10
A54: =IFERROR(__xludf.DUMMYFUNCTION("""COMPUTED_VALUE"""),"ITBISA-7SEGMENT-ANODE-RED-1.00-1BIT") -> ITBISA-7SEGMENT-ANODE-RED-1.00-1BIT | B54: =IFERROR(__xludf.DUMMYFUNCTION("""COMPUTED_VALUE"""),46036.0) -> 46036 | C54: =IFERROR(__xludf.DUMMYFUNCTION("""COMPUTED_VALUE"""),"KYAI KONTONG") -> KYAI KONTONG | D54: =IFERROR(__xludf.DUMMYFUNCTION("""COMPUTED_VALUE"""),10.0) -> 10
A55: =IFERROR(__xludf.DUMMYFUNCTION("""COMPUTED_VALUE"""),"ITBISA-7SEGMENT-ANODE-RED-1.00-1BIT") -> ITBISA-7SEGMENT-ANODE-RED-1.00-1BIT | B55: =IFERROR(__xludf.DUMMYFUNCTION("""COMPUTED_VALUE"""),46057.0) -> 46057 | C55: =IFERROR(__xludf.DUMMYFUNCTION("""COMPUTED_VALUE"""),"KERTASARI CIAMIS") -> KERTASARI CIAMIS | D55: =IFERROR(__xludf.DUMMYFUNCTION("""COMPUTED_VALUE"""),10.0) -> 10
A56: =IFERROR(__xludf.DUMMYFUNCTION("""COMPUTED_VALUE"""),"ITBISA-7SEGMENT-ANODE-RED-1.00-1BIT") -> ITBISA-7SEGMENT-ANODE-RED-1.00-1BIT | B56: =IFERROR(__xludf.DUMMYFUNCTION("""COMPUTED_VALUE"""),46066.0) -> 46066 | C56: =IFERROR(__xludf.DUMMYFUNCTION("""COMPUTED_VALUE"""),"KERTASARI CIAMIS") -> KERTASARI CIAMIS | D56: =IFERROR(__xludf.DUMMYFUNCTION("""COMPUTED_VALUE"""),10.0) -> 10
A57: =IFERROR(__xludf.DUMMYFUNCTION("""COMPUTED_VALUE"""),"ITBISA-7SEGMENT-ANODE-RED-1.00-1BIT") -> ITBISA-7SEGMENT-ANODE-RED-1.00-1BIT | B57: =IFERROR(__xludf.DUMMYFUNCTION("""COMPUTED_VALUE"""),46078.0) -> 46078 | C57: =IFERROR(__xludf.DUMMYFUNCTION("""COMPUTED_VALUE"""),"KYAI KONTONG") -> KYAI KONTONG | D57: =IFERROR(__xludf.DUMMYFUNCTION("""COMPUTED_VALUE"""),6.0) -> 6
A58: =IFERROR(__xludf.DUMMYFUNCTION("""COMPUTED_VALUE"""),"ITBISA-7SEGMENT-ANODE-RED-1.00-1BIT") -> ITBISA-7SEGMENT-ANODE-RED-1.00-1BIT | B58: =IFERROR(__xludf.DUMMYFUNCTION("""COMPUTED_VALUE"""),46118.0) -> 46118 | C58: =IFERROR(__xludf.DUMMYFUNCTION("""COMPUTED_VALUE"""),"KYAI KONTONG") -> KYAI KONTONG | D58: =IFERROR(__xludf.DUMMYFUNCTION("""COMPUTED_VALUE"""),5.0) -> 5
A59: =IFERROR(__xludf.DUMMYFUNCTION("""COMPUTED_VALUE"""),"ITBISA-7SEGMENT-ANODE-RED-1.00-1BIT") -> ITBISA-7SEGMENT-ANODE-RED-1.00-1BIT | B59: =IFERROR(__xludf.DUMMYFUNCTION("""COMPUTED_VALUE"""),46147.0) -> 46147 | C59: =IFERROR(__xludf.DUMMYFUNCTION("""COMPUTED_VALUE"""),"KYAI KONTONG") -> KYAI KONTONG | D59: =IFERROR(__xludf.DUMMYFUNCTION("""COMPUTED_VALUE"""),5.0) -> 5
A60: =IFERROR(__xludf.DUMMYFUNCTION("""COMPUTED_VALUE"""),"ITBISA-7SEGMENT-ANODE-RED-1.00-1BIT") -> ITBISA-7SEGMENT-ANODE-RED-1.00-1BIT | B60: =IFERROR(__xludf.DUMMYFUNCTION("""COMPUTED_VALUE"""),46159.0) -> 46159 | C60: =IFERROR(__xludf.DUMMYFUNCTION("""COMPUTED_VALUE"""),"KYAI KONTONG") -> KYAI KONTONG | D60: =IFERROR(__xludf.DUMMYFUNCTION("""COMPUTED_VALUE"""),2.0) -> 2
A61: =IFERROR(__xludf.DUMMYFUNCTION("""COMPUTED_VALUE"""),"ITBISA-7SEGMENT-ANODE-RED-1.00-1BIT") -> ITBISA-7SEGMENT-ANODE-RED-1.00-1BIT | B61: =IFERROR(__xludf.DUMMYFUNCTION("""COMPUTED_VALUE"""),46160.0) -> 46160 | C61: =IFERROR(__xludf.DUMMYFUNCTION("""COMPUTED_VALUE"""),"KYAI KONTONG") -> KYAI KONTONG | D61: =IFERROR(__xludf.DUMMYFUNCTION("""COMPUTED_VALUE"""),5.0) -> 5
A62: =IFERROR(__xludf.DUMMYFUNCTION("""COMPUTED_VALUE"""),"ITBISA-7SEGMENT-ANODE-RED-1.00-1BIT") -> ITBISA-7SEGMENT-ANODE-RED-1.00-1BIT | B62: =IFERROR(__xludf.DUMMYFUNCTION("""COMPUTED_VALUE"""),46172.0) -> 46172 | C62: =IFERROR(__xludf.DUMMYFUNCTION("""COMPUTED_VALUE"""),"KYAI KONTONG") -> KYAI KONTONG | D62: =IFERROR(__xludf.DUMMYFUNCTION("""COMPUTED_VALUE"""),6.0) -> 6
A63: =IFERROR(__xludf.DUMMYFUNCTION("""COMPUTED_VALUE"""),"ITBISA-7SEGMENT-ANODE-RED-1.00-1BIT") -> ITBISA-7SEGMENT-ANODE-RED-1.00-1BIT | B63: =IFERROR(__xludf.DUMMYFUNCTION("""COMPUTED_VALUE"""),46192.0) -> 46192 | C63: =IFERROR(__xludf.DUMMYFUNCTION("""COMPUTED_VALUE"""),"KYAI KONTONG") -> KYAI KONTONG | D63: =IFERROR(__xludf.DUMMYFUNCTION("""COMPUTED_VALUE"""),4.0) -> 4
A64: =IFERROR(__xludf.DUMMYFUNCTION("""COMPUTED_VALUE"""),"ITBISA-7SEGMENT-ANODE-RED-1.00-1BIT") -> ITBISA-7SEGMENT-ANODE-RED-1.00-1BIT | B64: =IFERROR(__xludf.DUMMYFUNCTION("""COMPUTED_VALUE"""),46195.0) -> 46195 | C64: =IFERROR(__xludf.DUMMYFUNCTION("""COMPUTED_VALUE"""),"KYAI KONTONG") -> KYAI KONTONG | D64: =IFERROR(__xludf.DUMMYFUNCTION("""COMPUTED_VALUE"""),10.0) -> 10
A65: =IFERROR(__xludf.DUMMYFUNCTION("""COMPUTED_VALUE"""),"ITBISA-7SEGMENT-ANODE-RED-1.00-1BIT") -> ITBISA-7SEGMENT-ANODE-RED-1.00-1BIT | B65: =IFERROR(__xludf.DUMMYFUNCTION("""COMPUTED_VALUE"""),46196.0) -> 46196 | C65: =IFERROR(__xludf.DUMMYFUNCTION("""COMPUTED_VALUE"""),"KYAI KONTONG") -> KYAI KONTONG | D65: =IFERROR(__xludf.DUMMYFUNCTION("""COMPUTED_VALUE"""),30.0) -> 30
A66: =IFERROR(__xludf.DUMMYFUNCTION("""COMPUTED_VALUE"""),"ITBISA-7SEGMENT-ANODE-RED-1.00-1BIT") -> ITBISA-7SEGMENT-ANODE-RED-1.00-1BIT | B66: =IFERROR(__xludf.DUMMYFUNCTION("""COMPUTED_VALUE"""),46197.0) -> 46197 | C66: =IFERROR(__xludf.DUMMYFUNCTION("""COMPUTED_VALUE"""),"KYAI KONTONG") -> KYAI KONTONG | D66: =IFERROR(__xludf.DUMMYFUNCTION("""COMPUTED_VALUE"""),8.0) -> 8
A67: =IFERROR(__xludf.DUMMYFUNCTION("""COMPUTED_VALUE"""),"ITBISA-7SEGMENT-ANODE-RED-1.20-1BIT") -> ITBISA-7SEGMENT-ANODE-RED-1.20-1BIT | B67: =IFERROR(__xludf.DUMMYFUNCTION("""COMPUTED_VALUE"""),45871.0) -> 45871 | C67: =IFERROR(__xludf.DUMMYFUNCTION("""COMPUTED_VALUE"""),"KERTASARI CIAMIS") -> KERTASARI CIAMIS | D67: =IFERROR(__xludf.DUMMYFUNCTION("""COMPUTED_VALUE"""),12.0) -> 12
A68: =IFERROR(__xludf.DUMMYFUNCTION("""COMPUTED_VALUE"""),"ITBISA-7SEGMENT-ANODE-RED-1.20-1BIT") -> ITBISA-7SEGMENT-ANODE-RED-1.20-1BIT | B68: =IFERROR(__xludf.DUMMYFUNCTION("""COMPUTED_VALUE"""),46023.0) -> 46023 | C68: =IFERROR(__xludf.DUMMYFUNCTION("""COMPUTED_VALUE"""),"KYAI KONTONG") -> KYAI KONTONG | D68: =IFERROR(__xludf.DUMMYFUNCTION("""COMPUTED_VALUE"""),45.0) -> 45
A69: =IFERROR(__xludf.DUMMYFUNCTION("""COMPUTED_VALUE"""),"ITBISA-7SEGMENT-ANODE-RED-1.20-1BIT") -> ITBISA-7SEGMENT-ANODE-RED-1.20-1BIT | B69: =IFERROR(__xludf.DUMMYFUNCTION("""COMPUTED_VALUE"""),46027.0) -> 46027 | C69: =IFERROR(__xludf.DUMMYFUNCTION("""COMPUTED_VALUE"""),"KYAI KONTONG") -> KYAI KONTONG | D69: =IFERROR(__xludf.DUMMYFUNCTION("""COMPUTED_VALUE"""),100.0) -> 100
A70: =IFERROR(__xludf.DUMMYFUNCTION("""COMPUTED_VALUE"""),"ITBISA-7SEGMENT-ANODE-RED-1.20-1BIT") -> ITBISA-7SEGMENT-ANODE-RED-1.20-1BIT | B70: =IFERROR(__xludf.DUMMYFUNCTION("""COMPUTED_VALUE"""),46035.0) -> 46035 | C70: =IFERROR(__xludf.DUMMYFUNCTION("""COMPUTED_VALUE"""),"KERTASARI CIAMIS") -> KERTASARI CIAMIS | D70: =IFERROR(__xludf.DUMMYFUNCTION("""COMPUTED_VALUE"""),90.0) -> 90
A71: =IFERROR(__xludf.DUMMYFUNCTION("""COMPUTED_VALUE"""),"ITBISA-7SEGMENT-ANODE-RED-1.20-1BIT") -> ITBISA-7SEGMENT-ANODE-RED-1.20-1BIT | B71: =IFERROR(__xludf.DUMMYFUNCTION("""COMPUTED_VALUE"""),46044.0) -> 46044 | C71: =IFERROR(__xludf.DUMMYFUNCTION("""COMPUTED_VALUE"""),"KYAI KONTONG") -> KYAI KONTONG | D71: =IFERROR(__xludf.DUMMYFUNCTION("""COMPUTED_VALUE"""),10.0) -> 10
A72: =IFERROR(__xludf.DUMMYFUNCTION("""COMPUTED_VALUE"""),"ITBISA-7SEGMENT-ANODE-RED-1.20-1BIT") -> ITBISA-7SEGMENT-ANODE-RED-1.20-1BIT | B72: =IFERROR(__xludf.DUMMYFUNCTION("""COMPUTED_VALUE"""),46044.0) -> 46044 | C72: =IFERROR(__xludf.DUMMYFUNCTION("""COMPUTED_VALUE"""),"KYAI KONTONG") -> KYAI KONTONG | D72: =IFERROR(__xludf.DUMMYFUNCTION("""COMPUTED_VALUE"""),12.0) -> 12
A73: =IFERROR(__xludf.DUMMYFUNCTION("""COMPUTED_VALUE"""),"ITBISA-7SEGMENT-ANODE-RED-1.20-1BIT") -> ITBISA-7SEGMENT-ANODE-RED-1.20-1BIT | B73: =IFERROR(__xludf.DUMMYFUNCTION("""COMPUTED_VALUE"""),46064.0) -> 46064 | C73: =IFERROR(__xludf.DUMMYFUNCTION("""COMPUTED_VALUE"""),"KERTASARI CIAMIS") -> KERTASARI CIAMIS | D73: =IFERROR(__xludf.DUMMYFUNCTION("""COMPUTED_VALUE"""),304.0) -> 304
A74: =IFERROR(__xludf.DUMMYFUNCTION("""COMPUTED_VALUE"""),"ITBISA-7SEGMENT-ANODE-RED-1.20-1BIT") -> ITBISA-7SEGMENT-ANODE-RED-1.20-1BIT | B74: =IFERROR(__xludf.DUMMYFUNCTION("""COMPUTED_VALUE"""),46077.0) -> 46077 | C74: =IFERROR(__xludf.DUMMYFUNCTION("""COMPUTED_VALUE"""),"KERTASARI CIAMIS") -> KERTASARI CIAMIS | D74: =IFERROR(__xludf.DUMMYFUNCTION("""COMPUTED_VALUE"""),18.0) -> 18
A75: =IFERROR(__xludf.DUMMYFUNCTION("""COMPUTED_VALUE"""),"ITBISA-7SEGMENT-ANODE-RED-1.20-1BIT") -> ITBISA-7SEGMENT-ANODE-RED-1.20-1BIT | B75: =IFERROR(__xludf.DUMMYFUNCTION("""COMPUTED_VALUE"""),46094.0) -> 46094 | C75: =IFERROR(__xludf.DUMMYFUNCTION("""COMPUTED_VALUE"""),"KYAI KONTONG") -> KYAI KONTONG | D75: =IFERROR(__xludf.DUMMYFUNCTION("""COMPUTED_VALUE"""),5.0) -> 5
A76: =IFERROR(__xludf.DUMMYFUNCTION("""COMPUTED_VALUE"""),"ITBISA-7SEGMENT-ANODE-RED-1.20-1BIT") -> ITBISA-7SEGMENT-ANODE-RED-1.20-1BIT | B76: =IFERROR(__xludf.DUMMYFUNCTION("""COMPUTED_VALUE"""),46114.0) -> 46114 | C76: =IFERROR(__xludf.DUMMYFUNCTION("""COMPUTED_VALUE"""),"KYAI KONTONG") -> KYAI KONTONG | D76: =IFERROR(__xludf.DUMMYFUNCTION("""COMPUTED_VALUE"""),90.0) -> 90
A77: =IFERROR(__xludf.DUMMYFUNCTION("""COMPUTED_VALUE"""),"ITBISA-7SEGMENT-ANODE-RED-1.20-1BIT") -> ITBISA-7SEGMENT-ANODE-RED-1.20-1BIT | B77: =IFERROR(__xludf.DUMMYFUNCTION("""COMPUTED_VALUE"""),46116.0) -> 46116 | C77: =IFERROR(__xludf.DUMMYFUNCTION("""COMPUTED_VALUE"""),"KYAI KONTONG") -> KYAI KONTONG | D77: =IFERROR(__xludf.DUMMYFUNCTION("""COMPUTED_VALUE"""),10.0) -> 10
A78: =IFERROR(__xludf.DUMMYFUNCTION("""COMPUTED_VALUE"""),"ITBISA-7SEGMENT-ANODE-RED-1.20-1BIT") -> ITBISA-7SEGMENT-ANODE-RED-1.20-1BIT | B78: =IFERROR(__xludf.DUMMYFUNCTION("""COMPUTED_VALUE"""),46123.0) -> 46123 | C78: =IFERROR(__xludf.DUMMYFUNCTION("""COMPUTED_VALUE"""),"KYAI KONTONG") -> KYAI KONTONG | D78: =IFERROR(__xludf.DUMMYFUNCTION("""COMPUTED_VALUE"""),30.0) -> 30
A79: =IFERROR(__xludf.DUMMYFUNCTION("""COMPUTED_VALUE"""),"ITBISA-7SEGMENT-ANODE-RED-1.20-1BIT") -> ITBISA-7SEGMENT-ANODE-RED-1.20-1BIT | B79: =IFERROR(__xludf.DUMMYFUNCTION("""COMPUTED_VALUE"""),46131.0) -> 46131 | C79: =IFERROR(__xludf.DUMMYFUNCTION("""COMPUTED_VALUE"""),"KYAI KONTONG") -> KYAI KONTONG | D79: =IFERROR(__xludf.DUMMYFUNCTION("""COMPUTED_VALUE"""),5.0) -> 5
A80: =IFERROR(__xludf.DUMMYFUNCTION("""COMPUTED_VALUE"""),"ITBISA-7SEGMENT-ANODE-RED-1.20-1BIT") -> ITBISA-7SEGMENT-ANODE-RED-1.20-1BIT | B80: =IFERROR(__xludf.DUMMYFUNCTION("""COMPUTED_VALUE"""),46140.0) -> 46140 | C80: =IFERROR(__xludf.DUMMYFUNCTION("""COMPUTED_VALUE"""),"KYAI KONTONG") -> KYAI KONTONG | D80: =IFERROR(__xludf.DUMMYFUNCTION("""COMPUTED_VALUE"""),27.0) -> 27
A81: =IFERROR(__xludf.DUMMYFUNCTION("""COMPUTED_VALUE"""),"ITBISA-7SEGMENT-ANODE-RED-1.20-1BIT") -> ITBISA-7SEGMENT-ANODE-RED-1.20-1BIT | B81: =IFERROR(__xludf.DUMMYFUNCTION("""COMPUTED_VALUE"""),46144.0) -> 46144 | C81: =IFERROR(__xludf.DUMMYFUNCTION("""COMPUTED_VALUE"""),"KYAI KONTONG") -> KYAI KONTONG | D81: =IFERROR(__xludf.DUMMYFUNCTION("""COMPUTED_VALUE"""),5.0) -> 5
A82: =IFERROR(__xludf.DUMMYFUNCTION("""COMPUTED_VALUE"""),"ITBISA-7SEGMENT-ANODE-RED-1.20-1BIT") -> ITBISA-7SEGMENT-ANODE-RED-1.20-1BIT | B82: =IFERROR(__xludf.DUMMYFUNCTION("""COMPUTED_VALUE"""),46146.0) -> 46146 | C82: =IFERROR(__xludf.DUMMYFUNCTION("""COMPUTED_VALUE"""),"KYAI KONTONG") -> KYAI KONTONG | D82: =IFERROR(__xludf.DUMMYFUNCTION("""COMPUTED_VALUE"""),15.0) -> 15
A83: =IFERROR(__xludf.DUMMYFUNCTION("""COMPUTED_VALUE"""),"ITBISA-7SEGMENT-ANODE-RED-1.20-1BIT") -> ITBISA-7SEGMENT-ANODE-RED-1.20-1BIT | B83: =IFERROR(__xludf.DUMMYFUNCTION("""COMPUTED_VALUE"""),46148.0) -> 46148 | C83: =IFERROR(__xludf.DUMMYFUNCTION("""COMPUTED_VALUE"""),"KYAI KONTONG") -> KYAI KONTONG | D83: =IFERROR(__xludf.DUMMYFUNCTION("""COMPUTED_VALUE"""),2.0) -> 2
A84: =IFERROR(__xludf.DUMMYFUNCTION("""COMPUTED_VALUE"""),"ITBISA-7SEGMENT-ANODE-RED-1.20-1BIT") -> ITBISA-7SEGMENT-ANODE-RED-1.20-1BIT | B84: =IFERROR(__xludf.DUMMYFUNCTION("""COMPUTED_VALUE"""),46151.0) -> 46151 | C84: =IFERROR(__xludf.DUMMYFUNCTION("""COMPUTED_VALUE"""),"KYAI KONTONG") -> KYAI KONTONG | D84: =IFERROR(__xludf.DUMMYFUNCTION("""COMPUTED_VALUE"""),75.0) -> 75
A85: =IFERROR(__xludf.DUMMYFUNCTION("""COMPUTED_VALUE"""),"ITBISA-7SEGMENT-ANODE-RED-1.20-1BIT") -> ITBISA-7SEGMENT-ANODE-RED-1.20-1BIT | B85: =IFERROR(__xludf.DUMMYFUNCTION("""COMPUTED_VALUE"""),46155.0) -> 46155 | C85: =IFERROR(__xludf.DUMMYFUNCTION("""COMPUTED_VALUE"""),"KYAI KONTONG") -> KYAI KONTONG | D85: =IFERROR(__xludf.DUMMYFUNCTION("""COMPUTED_VALUE"""),5.0) -> 5
A86: =IFERROR(__xludf.DUMMYFUNCTION("""COMPUTED_VALUE"""),"ITBISA-7SEGMENT-ANODE-RED-1.20-1BIT") -> ITBISA-7SEGMENT-ANODE-RED-1.20-1BIT | B86: =IFERROR(__xludf.DUMMYFUNCTION("""COMPUTED_VALUE"""),46155.0) -> 46155 | C86: =IFERROR(__xludf.DUMMYFUNCTION("""COMPUTED_VALUE"""),"KYAI KONTONG") -> KYAI KONTONG | D86: =IFERROR(__xludf.DUMMYFUNCTION("""COMPUTED_VALUE"""),90.0) -> 90
A87: =IFERROR(__xludf.DUMMYFUNCTION("""COMPUTED_VALUE"""),"ITBISA-7SEGMENT-ANODE-RED-1.20-1BIT") -> ITBISA-7SEGMENT-ANODE-RED-1.20-1BIT | B87: =IFERROR(__xludf.DUMMYFUNCTION("""COMPUTED_VALUE"""),46156.0) -> 46156 | C87: =IFERROR(__xludf.DUMMYFUNCTION("""COMPUTED_VALUE"""),"KYAI KONTONG") -> KYAI KONTONG | D87: =IFERROR(__xludf.DUMMYFUNCTION("""COMPUTED_VALUE"""),5.0) -> 5
A88: =IFERROR(__xludf.DUMMYFUNCTION("""COMPUTED_VALUE"""),"ITBISA-7SEGMENT-ANODE-RED-1.20-1BIT") -> ITBISA-7SEGMENT-ANODE-RED-1.20-1BIT | B88: =IFERROR(__xludf.DUMMYFUNCTION("""COMPUTED_VALUE"""),46158.0) -> 46158 | C88: =IFERROR(__xludf.DUMMYFUNCTION("""COMPUTED_VALUE"""),"KYAI KONTONG") -> KYAI KONTONG | D88: =IFERROR(__xludf.DUMMYFUNCTION("""COMPUTED_VALUE"""),10.0) -> 10
A89: =IFERROR(__xludf.DUMMYFUNCTION("""COMPUTED_VALUE"""),"ITBISA-7SEGMENT-ANODE-RED-1.20-1BIT") -> ITBISA-7SEGMENT-ANODE-RED-1.20-1BIT | B89: =IFERROR(__xludf.DUMMYFUNCTION("""COMPUTED_VALUE"""),46161.0) -> 46161 | C89: =IFERROR(__xludf.DUMMYFUNCTION("""COMPUTED_VALUE"""),"KYAI KONTONG") -> KYAI KONTONG | D89: =IFERROR(__xludf.DUMMYFUNCTION("""COMPUTED_VALUE"""),5.0) -> 5
A90: =IFERROR(__xludf.DUMMYFUNCTION("""COMPUTED_VALUE"""),"ITBISA-7SEGMENT-ANODE-RED-1.20-1BIT") -> ITBISA-7SEGMENT-ANODE-RED-1.20-1BIT | B90: =IFERROR(__xludf.DUMMYFUNCTION("""COMPUTED_VALUE"""),46161.0) -> 46161 | C90: =IFERROR(__xludf.DUMMYFUNCTION("""COMPUTED_VALUE"""),"KYAI KONTONG") -> KYAI KONTONG | D90: =IFERROR(__xludf.DUMMYFUNCTION("""COMPUTED_VALUE"""),7.0) -> 7
A91: =IFERROR(__xludf.DUMMYFUNCTION("""COMPUTED_VALUE"""),"ITBISA-7SEGMENT-ANODE-RED-1.20-1BIT") -> ITBISA-7SEGMENT-ANODE-RED-1.20-1BIT | B91: =IFERROR(__xludf.DUMMYFUNCTION("""COMPUTED_VALUE"""),46162.0) -> 46162 | C91: =IFERROR(__xludf.DUMMYFUNCTION("""COMPUTED_VALUE"""),"KYAI KONTONG") -> KYAI KONTONG | D91: =IFERROR(__xludf.DUMMYFUNCTION("""COMPUTED_VALUE"""),75.0) -> 75
A92: =IFERROR(__xludf.DUMMYFUNCTION("""COMPUTED_VALUE"""),"ITBISA-7SEGMENT-ANODE-RED-1.20-1BIT") -> ITBISA-7SEGMENT-ANODE-RED-1.20-1BIT | B92: =IFERROR(__xludf.DUMMYFUNCTION("""COMPUTED_VALUE"""),46163.0) -> 46163 | C92: =IFERROR(__xludf.DUMMYFUNCTION("""COMPUTED_VALUE"""),"KYAI KONTONG") -> KYAI KONTONG | D92: =IFERROR(__xludf.DUMMYFUNCTION("""COMPUTED_VALUE"""),11.0) -> 11
A93: =IFERROR(__xludf.DUMMYFUNCTION("""COMPUTED_VALUE"""),"ITBISA-7SEGMENT-ANODE-RED-1.20-1BIT") -> ITBISA-7SEGMENT-ANODE-RED-1.20-1BIT | B93: =IFERROR(__xludf.DUMMYFUNCTION("""COMPUTED_VALUE"""),46166.0) -> 46166 | C93: =IFERROR(__xludf.DUMMYFUNCTION("""COMPUTED_VALUE"""),"KYAI KONTONG") -> KYAI KONTONG | D93: =IFERROR(__xludf.DUMMYFUNCTION("""COMPUTED_VALUE"""),75.0) -> 75
A94: =IFERROR(__xludf.DUMMYFUNCTION("""COMPUTED_VALUE"""),"ITBISA-7SEGMENT-ANODE-RED-1.20-1BIT") -> ITBISA-7SEGMENT-ANODE-RED-1.20-1BIT | B94: =IFERROR(__xludf.DUMMYFUNCTION("""COMPUTED_VALUE"""),46167.0) -> 46167 | C94: =IFERROR(__xludf.DUMMYFUNCTION("""COMPUTED_VALUE"""),"KYAI KONTONG") -> KYAI KONTONG | D94: =IFERROR(__xludf.DUMMYFUNCTION("""COMPUTED_VALUE"""),5.0) -> 5
A95: =IFERROR(__xludf.DUMMYFUNCTION("""COMPUTED_VALUE"""),"ITBISA-7SEGMENT-ANODE-RED-1.20-1BIT") -> ITBISA-7SEGMENT-ANODE-RED-1.20-1BIT | B95: =IFERROR(__xludf.DUMMYFUNCTION("""COMPUTED_VALUE"""),46167.0) -> 46167 | C95: =IFERROR(__xludf.DUMMYFUNCTION("""COMPUTED_VALUE"""),"KYAI KONTONG") -> KYAI KONTONG | D95: =IFERROR(__xludf.DUMMYFUNCTION("""COMPUTED_VALUE"""),75.0) -> 75
A96: =IFERROR(__xludf.DUMMYFUNCTION("""COMPUTED_VALUE"""),"ITBISA-7SEGMENT-ANODE-RED-1.20-1BIT") -> ITBISA-7SEGMENT-ANODE-RED-1.20-1BIT | B96: =IFERROR(__xludf.DUMMYFUNCTION("""COMPUTED_VALUE"""),46175.0) -> 46175 | C96: =IFERROR(__xludf.DUMMYFUNCTION("""COMPUTED_VALUE"""),"KYAI KONTONG") -> KYAI KONTONG | D96: =IFERROR(__xludf.DUMMYFUNCTION("""COMPUTED_VALUE"""),15.0) -> 15
A97: =IFERROR(__xludf.DUMMYFUNCTION("""COMPUTED_VALUE"""),"ITBISA-7SEGMENT-ANODE-RED-1.20-1BIT") -> ITBISA-7SEGMENT-ANODE-RED-1.20-1BIT | B97: =IFERROR(__xludf.DUMMYFUNCTION("""COMPUTED_VALUE"""),46181.0) -> 46181 | C97: =IFERROR(__xludf.DUMMYFUNCTION("""COMPUTED_VALUE"""),"KYAI KONTONG") -> KYAI KONTONG | D97: =IFERROR(__xludf.DUMMYFUNCTION("""COMPUTED_VALUE"""),5.0) -> 5
A98: =IFERROR(__xludf.DUMMYFUNCTION("""COMPUTED_VALUE"""),"ITBISA-7SEGMENT-ANODE-RED-1.20-1BIT") -> ITBISA-7SEGMENT-ANODE-RED-1.20-1BIT | B98: =IFERROR(__xludf.DUMMYFUNCTION("""COMPUTED_VALUE"""),46181.0) -> 46181 | C98: =IFERROR(__xludf.DUMMYFUNCTION("""COMPUTED_VALUE"""),"KYAI KONTONG") -> KYAI KONTONG | D98: =IFERROR(__xludf.DUMMYFUNCTION("""COMPUTED_VALUE"""),45.0) -> 45
A99: =IFERROR(__xludf.DUMMYFUNCTION("""COMPUTED_VALUE"""),"ITBISA-7SEGMENT-ANODE-RED-1.20-1BIT") -> ITBISA-7SEGMENT-ANODE-RED-1.20-1BIT | B99: =IFERROR(__xludf.DUMMYFUNCTION("""COMPUTED_VALUE"""),46182.0) -> 46182 | C99: =IFERROR(__xludf.DUMMYFUNCTION("""COMPUTED_VALUE"""),"KYAI KONTONG") -> KYAI KONTONG | D99: =IFERROR(__xludf.DUMMYFUNCTION("""COMPUTED_VALUE"""),5.0) -> 5
A100: =IFERROR(__xludf.DUMMYFUNCTION("""COMPUTED_VALUE"""),"ITBISA-7SEGMENT-ANODE-RED-1.20-1BIT") -> ITBISA-7SEGMENT-ANODE-RED-1.20-1BIT | B100: =IFERROR(__xludf.DUMMYFUNCTION("""COMPUTED_VALUE"""),46188.0) -> 46188 | C100: =IFERROR(__xludf.DUMMYFUNCTION("""COMPUTED_VALUE"""),"KYAI KONTONG") -> KYAI KONTONG | D100: =IFERROR(__xludf.DUMMYFUNCTION("""COMPUTED_VALUE"""),150.0) -> 150
...

Sheet Import-BisaJurnal
A1: =IFERROR(__xludf.DUMMYFUNCTION("IMPORTRANGE(""https://docs.google.com/spreadsheets/d/10nrArtKFHLIJKC2sUfDzfj4Ejf-FxrJ-NY954fXdMD0/edit#gid=778135825"",""BisaEksporBisaJurnal!A:A"")"),"")
A2: =IFERROR(__xludf.DUMMYFUNCTION("""COMPUTED_VALUE"""),"Adjustment") -> Adjustment
A3: =IFERROR(__xludf.DUMMYFUNCTION("""COMPUTED_VALUE"""),"Beban Gaji Mbak Dwi") -> Beban Gaji Mbak Dwi
A4: =IFERROR(__xludf.DUMMYFUNCTION("""COMPUTED_VALUE"""),"Beban Gaji Ujreng") -> Beban Gaji Ujreng
A5: =IFERROR(__xludf.DUMMYFUNCTION("""COMPUTED_VALUE"""),"Beban Hilang ITBISA-7SEGMENT-ANODE-RED-0.56-1BIT") -> Beban Hilang ITBISA-7SEGMENT-ANODE-RED-0.56-1BIT
A6: =IFERROR(__xludf.DUMMYFUNCTION("""COMPUTED_VALUE"""),"Beban Hilang ITBISA-7SEGMENT-CATHODE-RED-0.56-1BIT") -> Beban Hilang ITBISA-7SEGMENT-CATHODE-RED-0.56-1BIT
A7: =IFERROR(__xludf.DUMMYFUNCTION("""COMPUTED_VALUE"""),"Beban Hilang ITBISA-7SEGMENT-CATHODE-RED-1.20-1BIT") -> Beban Hilang ITBISA-7SEGMENT-CATHODE-RED-1.20-1BIT
A8: =IFERROR(__xludf.DUMMYFUNCTION("""COMPUTED_VALUE"""),"Beban Hilang ITBISA-ABC-BATERAI-AA-ALKALINE") -> Beban Hilang ITBISA-ABC-BATERAI-AA-ALKALINE
A9: =IFERROR(__xludf.DUMMYFUNCTION("""COMPUTED_VALUE"""),"Beban Hilang ITBISA-BLUETOOTH-MODULE-HC05") -> Beban Hilang ITBISA-BLUETOOTH-MODULE-HC05
A10: =IFERROR(__xludf.DUMMYFUNCTION("""COMPUTED_VALUE"""),"Beban Hilang ITBISA-BREADBOARD-830HOLE-MB102") -> Beban Hilang ITBISA-BREADBOARD-830HOLE-MB102
A11: =IFERROR(__xludf.DUMMYFUNCTION("""COMPUTED_VALUE"""),"Beban Hilang ITBISA-BUBBLE-WRAP") -> Beban Hilang ITBISA-BUBBLE-WRAP
A12: =IFERROR(__xludf.DUMMYFUNCTION("""COMPUTED_VALUE"""),"Beban Hilang ITBISA-CHIP-ESP32-WROOM-ANTENNA") -> Beban Hilang ITBISA-CHIP-ESP32-WROOM-ANTENNA
A13: =IFERROR(__xludf.DUMMYFUNCTION("""COMPUTED_VALUE"""),"Beban Hilang ITBISA-CHIP-ESP8266-ESP12F") -> Beban Hilang ITBISA-CHIP-ESP8266-ESP12F
A14: =IFERROR(__xludf.DUMMYFUNCTION("""COMPUTED_VALUE"""),"Beban Hilang ITBISA-DC-TO-DC-STEPDOWN-LM2596") -> Beban Hilang ITBISA-DC-TO-DC-STEPDOWN-LM2596
A15: =IFERROR(__xludf.DUMMYFUNCTION("""COMPUTED_VALUE"""),"Beban Hilang ITBISA-DC-TO-DC-STEPDOWN-XL4005") -> Beban Hilang ITBISA-DC-TO-DC-STEPDOWN-XL4005
A16: =IFERROR(__xludf.DUMMYFUNCTION("""COMPUTED_VALUE"""),"Beban Hilang ITBISA-DC-TO-DC-STEPDOWN-XL4015") -> Beban Hilang ITBISA-DC-TO-DC-STEPDOWN-XL4015
A17: =IFERROR(__xludf.DUMMYFUNCTION("""COMPUTED_VALUE"""),"Beban Hilang ITBISA-DC-TO-DC-STEPUP-XL6009") -> Beban Hilang ITBISA-DC-TO-DC-STEPUP-XL6009
A18: =IFERROR(__xludf.DUMMYFUNCTION("""COMPUTED_VALUE"""),"Beban Hilang ITBISA-IC-CD4017BE-DIP16") -> Beban Hilang ITBISA-IC-CD4017BE-DIP16
A19: =IFERROR(__xludf.DUMMYFUNCTION("""COMPUTED_VALUE"""),"Beban Hilang ITBISA-IC-CD4094BM-SMD-SOP16") -> Beban Hilang ITBISA-IC-CD4094BM-SMD-SOP16
A20: =IFERROR(__xludf.DUMMYFUNCTION("""COMPUTED_VALUE"""),"Beban Hilang ITBISA-IC-L7805CV-TO220") -> Beban Hilang ITBISA-IC-L7805CV-TO220
A21: =IFERROR(__xludf.DUMMYFUNCTION("""COMPUTED_VALUE"""),"Beban Hilang ITBISA-IC-L7812CV-TO220") -> Beban Hilang ITBISA-IC-L7812CV-TO220
A22: =IFERROR(__xludf.DUMMYFUNCTION("""COMPUTED_VALUE"""),"Beban Hilang ITBISA-IC-LM741CN-DIP8") -> Beban Hilang ITBISA-IC-LM741CN-DIP8
A23: =IFERROR(__xludf.DUMMYFUNCTION("""COMPUTED_VALUE"""),"Beban Hilang ITBISA-IC-NE555P-DIP8") -> Beban Hilang ITBISA-IC-NE555P-DIP8
A24: =IFERROR(__xludf.DUMMYFUNCTION("""COMPUTED_VALUE"""),"Beban Hilang ITBISA-IC-PC817-DIP4") -> Beban Hilang ITBISA-IC-PC817-DIP4
A25: =IFERROR(__xludf.DUMMYFUNCTION("""COMPUTED_VALUE"""),"Beban Hilang ITBISA-IC-ULN2803APG-DIP18") -> Beban Hilang ITBISA-IC-ULN2803APG-DIP18
A26: =IFERROR(__xludf.DUMMYFUNCTION("""COMPUTED_VALUE"""),"Beban Hilang ITBISA-INFRARED-1838") -> Beban Hilang ITBISA-INFRARED-1838
A27: =IFERROR(__xludf.DUMMYFUNCTION("""COMPUTED_VALUE"""),"Beban Hilang ITBISA-LDR-GL5516") -> Beban Hilang ITBISA-LDR-GL5516
A28: =IFERROR(__xludf.DUMMYFUNCTION("""COMPUTED_VALUE"""),"Beban Hilang ITBISA-LED-MAX7219-4IN1-TIGHT") -> Beban Hilang ITBISA-LED-MAX7219-4IN1-TIGHT
A29: =IFERROR(__xludf.DUMMYFUNCTION("""COMPUTED_VALUE"""),"Beban Hilang ITBISA-NODEMCU-V3-CH340G-ESP8266-MICRO") -> Beban Hilang ITBISA-NODEMCU-V3-CH340G-ESP8266-MICRO
A30: =IFERROR(__xludf.DUMMYFUNCTION("""COMPUTED_VALUE"""),"Beban Hilang ITBISA-PIN-HEADER-MALE-1X40PIN-L-SAMA") -> Beban Hilang ITBISA-PIN-HEADER-MALE-1X40PIN-L-SAMA
A31: =IFERROR(__xludf.DUMMYFUNCTION("""COMPUTED_VALUE"""),"Beban Hilang ITBISA-RELAY-12V-5PIN-BLUE") -> Beban Hilang ITBISA-RELAY-12V-5PIN-BLUE
A32: =IFERROR(__xludf.DUMMYFUNCTION("""COMPUTED_VALUE"""),"Beban Hilang ITBISA-RELAY-5V-1CHANNEL-BLUE-LOW-TRIGGER") -> Beban Hilang ITBISA-RELAY-5V-1CHANNEL-BLUE-LOW-TRIGGER
A33: =IFERROR(__xludf.DUMMYFUNCTION("""COMPUTED_VALUE"""),"Beban Hilang ITBISA-RTC-DS3231M") -> Beban Hilang ITBISA-RTC-DS3231M
A34: =IFERROR(__xludf.DUMMYFUNCTION("""COMPUTED_VALUE"""),"Beban Hilang ITBISA-RTC-DS3231SN") -> Beban Hilang ITBISA-RTC-DS3231SN
A35: =IFERROR(__xludf.DUMMYFUNCTION("""COMPUTED_VALUE"""),"Beban Hilang ITBISA-SERVO-SG90-180DEG") -> Beban Hilang ITBISA-SERVO-SG90-180DEG
A36: =IFERROR(__xludf.DUMMYFUNCTION("""COMPUTED_VALUE"""),"Beban Hilang ITBISA-SERVO-SG90-360DEG") -> Beban Hilang ITBISA-SERVO-SG90-360DEG
A37: =IFERROR(__xludf.DUMMYFUNCTION("""COMPUTED_VALUE"""),"Beban Hilang ITBISA-SOCKET-IC-DIP8-NARROW") -> Beban Hilang ITBISA-SOCKET-IC-DIP8-NARROW
A38: =IFERROR(__xludf.DUMMYFUNCTION("""COMPUTED_VALUE"""),"Beban Hilang ITBISA-WEMOS-D1-MINI-ESP8266") -> Beban Hilang ITBISA-WEMOS-D1-MINI-ESP8266
A39: =IFERROR(__xludf.DUMMYFUNCTION("""COMPUTED_VALUE"""),"Bonus ITBISA-7SEGMENT-CATHODE-RED-1.20-1BIT") -> Bonus ITBISA-7SEGMENT-CATHODE-RED-1.20-1BIT
A40: =IFERROR(__xludf.DUMMYFUNCTION("""COMPUTED_VALUE"""),"Bonus ITBISA-7SEGMENT-CATHODE-RED-2.30-1BIT") -> Bonus ITBISA-7SEGMENT-CATHODE-RED-2.30-1BIT
A41: =IFERROR(__xludf.DUMMYFUNCTION("""COMPUTED_VALUE"""),"Bonus ITBISA-ABC-BATERAI-AAA-ALKALINE") -> Bonus ITBISA-ABC-BATERAI-AAA-ALKALINE
A42: =IFERROR(__xludf.DUMMYFUNCTION("""COMPUTED_VALUE"""),"Bonus ITBISA-BREADBOARD-830HOLE-MB102") -> Bonus ITBISA-BREADBOARD-830HOLE-MB102
A43: =IFERROR(__xludf.DUMMYFUNCTION("""COMPUTED_VALUE"""),"Bonus ITBISA-BUBBLE-WRAP") -> Bonus ITBISA-BUBBLE-WRAP
A44: =IFERROR(__xludf.DUMMYFUNCTION("""COMPUTED_VALUE"""),"Bonus ITBISA-CHIP-ESP32-WROOM") -> Bonus ITBISA-CHIP-ESP32-WROOM
A45: =IFERROR(__xludf.DUMMYFUNCTION("""COMPUTED_VALUE"""),"Bonus ITBISA-CHIP-ESP8266-ESP12F") -> Bonus ITBISA-CHIP-ESP8266-ESP12F
